{
  "type": "Feature",
  "properties": {
    "gn:admin1_code":"37",
    "gn:asciiname":"Tayifli",
    "gn:country_code":"AZ",
    "gn:dem":479,
    "gn:feature_class":"P",
    "gn:feature_code":"PPL",
    "gn:name":"Tay\u0131fl\u0131",
    "gn:population":0,
    "gn:timezone":"Asia/Baku",
    "iso:country":"AZ",
    "name:azb_x_preferred":[
        "\u062a\u0627\u06cc\u06cc\u0641\u200c\u0644\u06cc"
    ],
    "name:aze_x_preferred":[
        "Tay\u0131fl\u0131"
    ],
    "name:ceb_x_preferred":[
        "Tay\u0131fl\u0131"
    ],
    "name:ita_x_preferred":[
        "Tay\u0131fl\u0131"
    ],
    "name:msa_x_preferred":[
        "Tay\u0131fl\u0131"
    ],
    "name:swe_x_preferred":[
        "Tay\u0131fl\u0131"
    ],
    "name:und_x_variant":[
        "Tayfliy",
        "Taifly",
        "Tayfly",
        "Tay\u0131fl\u0131"
    ],
    "wof:name":"Tayifli",
    "wof:placetype":"locality"
},
  "geometry": {"coordinates":[47.51131,41.00574],"type":"Point"}
}