{
  "type": "Feature",
  "properties": {
    "gn:admin1_code":"58",
    "gn:asciiname":"Khakhollar",
    "gn:country_code":"AZ",
    "gn:dem":1622,
    "gn:feature_class":"P",
    "gn:feature_code":"PPL",
    "gn:name":"Khakhollar",
    "gn:population":0,
    "gn:timezone":"Asia/Baku",
    "iso:country":"AZ",
    "name:und_x_variant":[
        "N\u0259sibli",
        "Nasibli"
    ],
    "wof:name":"Khakhollar",
    "wof:placetype":"locality"
},
  "geometry": {"coordinates":[45.50965,40.69244000000001],"type":"Point"}
}