{
  "type": "Feature",
  "properties": {
    "gn:admin1_code":"60",
    "gn:asciiname":"Gyuneshli",
    "gn:country_code":"AZ",
    "gn:dem":-17,
    "gn:feature_class":"P",
    "gn:feature_code":"PPL",
    "gn:name":"Gyuneshli",
    "gn:population":0,
    "gn:timezone":"Asia/Baku",
    "iso:country":"AZ",
    "name:aze_x_preferred":[
        "Gun\u0259\u015fli"
    ],
    "name:aze_x_variant":[
        "G\u00fcn\u0259\u015fli"
    ],
    "wof:name":"Gyuneshli",
    "wof:placetype":"locality"
},
  "geometry": {"coordinates":[48.67033,41.78415],"type":"Point"}
}