{
  "type": "Feature",
  "properties": {
    "gn:admin1_code":"67",
    "gn:asciiname":"Mironabad",
    "gn:country_code":"AZ",
    "gn:dem":32,
    "gn:feature_class":"P",
    "gn:feature_code":"PPL",
    "gn:name":"Mironabad",
    "gn:population":0,
    "gn:timezone":"Asia/Baku",
    "iso:country":"AZ",
    "name:aze_x_preferred":[
        "Mironabad"
    ],
    "wof:name":"Mironabad",
    "wof:placetype":"locality"
},
  "geometry": {"coordinates":[47.05733,40.60704000000001],"type":"Point"}
}