{
  "type": "Feature",
  "properties": {
    "gn:admin1_code":"42",
    "gn:asciiname":"Syukhyub",
    "gn:country_code":"AZ",
    "gn:dem":1670,
    "gn:feature_class":"P",
    "gn:feature_code":"PPL",
    "gn:name":"Syukhyub",
    "gn:population":0,
    "gn:timezone":"Asia/Baku",
    "iso:country":"AZ",
    "name:azb_x_preferred":[
        "\u0633\u0624\u0647\u0648\u0628"
    ],
    "name:aze_x_preferred":[
        "S\u00f6h\u00fcb"
    ],
    "name:ceb_x_preferred":[
        "Syukhyub"
    ],
    "name:ell_x_preferred":[
        "\u03a3\u03b9\u03bf\u03c7\u03bf\u03cd\u03bc\u03c0"
    ],
    "name:eng_x_preferred":[
        "S\u00f6h\u00fcb"
    ],
    "name:ita_x_preferred":[
        "S\u00f6h\u00fcb"
    ],
    "name:msa_x_preferred":[
        "S\u00f6h\u00fcb"
    ],
    "name:rus_x_preferred":[
        "\u0421\u044e\u0445\u044e\u0431"
    ],
    "name:swe_x_preferred":[
        "Syukhyub"
    ],
    "name:und_x_variant":[
        "Sukhyub",
        "Syugyub"
    ],
    "wof:name":"Syukhyub",
    "wof:placetype":"locality"
},
  "geometry": {"coordinates":[48.39707,41.1505],"type":"Point"}
}