{
  "type": "Feature",
  "properties": {
    "gn:admin1_code":"06",
    "gn:asciiname":"Sanqalan",
    "gn:country_code":"AZ",
    "gn:dem":795,
    "gn:feature_class":"P",
    "gn:feature_code":"PPL",
    "gn:name":"Sanqalan",
    "gn:population":0,
    "gn:timezone":"Asia/Baku",
    "iso:country":"AZ",
    "name:azb_x_preferred":[
        "\u0633\u0627\u0646\u0642\u0627\u0644\u0627\u0646"
    ],
    "name:aze_x_preferred":[
        "Sanqalan"
    ],
    "name:fas_x_preferred":[
        "\u0633\u0646\u06af\u0644\u0627\u0646"
    ],
    "name:ita_x_preferred":[
        "Sanqalan"
    ],
    "name:kat_x_preferred":[
        "\u10e1\u10d0\u10dc\u10e5\u10d0\u10da\u10d0\u10dc\u10d8"
    ],
    "name:msa_x_preferred":[
        "Sanqalan"
    ],
    "name:und_x_variant":[
        "Leninabad"
    ],
    "wof:name":"Sanqalan",
    "wof:placetype":"locality"
},
  "geometry": {"coordinates":[48.4401,40.68881],"type":"Point"}
}