{
  "type": "Feature",
  "properties": {
    "gn:admin1_code":"18",
    "gn:asciiname":"Qacar",
    "gn:country_code":"AZ",
    "gn:dem":508,
    "gn:feature_class":"P",
    "gn:feature_code":"PPL",
    "gn:name":"Qacar",
    "gn:population":0,
    "gn:timezone":"Asia/Baku",
    "iso:country":"AZ",
    "name:aze_x_preferred":[
        "Qacar"
    ],
    "name:hye_x_preferred":[
        "K\u2019ajar"
    ],
    "name:hye_x_variant":[
        "\u0554\u0561\u057b\u0561\u0580",
        "Jivani",
        "\u054b\u056b\u057e\u0561\u0576\u056b"
    ],
    "name:rus_x_preferred":[
        "\u041a\u0430\u0434\u0436\u0430\u0440"
    ],
    "name:und_x_variant":[
        "Ghajar",
        "Ghadgar",
        "Kadzhar"
    ],
    "wof:name":"Qacar",
    "wof:placetype":"locality"
},
  "geometry": {"coordinates":[47.05671,39.64937000000001],"type":"Point"}
}