{
  "type": "Feature",
  "properties": {
    "gn:admin1_code":"26",
    "gn:asciiname":"Ikkinci Milli",
    "gn:country_code":"AZ",
    "gn:dem":1971,
    "gn:feature_class":"P",
    "gn:feature_code":"PPL",
    "gn:name":"\u0130kkinci Milli",
    "gn:population":0,
    "gn:timezone":"Asia/Baku",
    "iso:country":"AZ",
    "name:aze_x_preferred":[
        "\u0130kkinci Milli"
    ],
    "name:aze_x_variant":[
        "\u0130kinci Milli"
    ],
    "name:rus_x_preferred":[
        "\u041c\u0438\u043b\u043b\u0438 \u0412\u0442\u043e\u0440\u043e\u0435"
    ],
    "name:und_x_variant":[
        "Milli Vtoroye"
    ],
    "wof:name":"Ikkinci Milli",
    "wof:placetype":"locality"
},
  "geometry": {"coordinates":[46.08674,40.12275],"type":"Point"}
}