{
  "type": "Feature",
  "properties": {
    "gn:admin1_code":"67",
    "gn:asciiname":"Meyveli",
    "gn:country_code":"AZ",
    "gn:dem":70,
    "gn:feature_class":"P",
    "gn:feature_code":"PPL",
    "gn:name":"Meyveli",
    "gn:population":0,
    "gn:timezone":"Asia/Baku",
    "iso:country":"AZ",
    "name:und_x_variant":[
        "Meyv\u0259li",
        "Meyveli"
    ],
    "wof:name":"Meyveli",
    "wof:placetype":"locality"
},
  "geometry": {"coordinates":[47.27259,40.75623],"type":"Point"}
}