{
  "type": "Feature",
  "properties": {
    "gn:admin1_code":"32",
    "gn:asciiname":"Boiady",
    "gn:country_code":"AZ",
    "gn:dem":-22,
    "gn:feature_class":"P",
    "gn:feature_code":"PPL",
    "gn:name":"Boiady",
    "gn:population":0,
    "gn:timezone":"Asia/Baku",
    "iso:country":"AZ",
    "wof:name":"Boiady",
    "wof:placetype":"locality"
},
  "geometry": {"coordinates":[48.76444,38.89083],"type":"Point"}
}