{
  "type": "Feature",
  "properties": {
    "gn:admin1_code":"08",
    "gn:asciiname":"Kapchimakhla",
    "gn:country_code":"AZ",
    "gn:dem":-13,
    "gn:feature_class":"P",
    "gn:feature_code":"PPL",
    "gn:name":"Kapchimakhla",
    "gn:population":0,
    "gn:timezone":"Asia/Baku",
    "iso:country":"AZ",
    "name:aze_x_preferred":[
        "Gap\u0131\u00e7\u0131m\u0259hl\u0259"
    ],
    "name:aze_x_variant":[
        "Qap\u0131\u00e7\u0131m\u0259h\u0259ll\u0259"
    ],
    "wof:name":"Kapchimakhla",
    "wof:placetype":"locality"
},
  "geometry": {"coordinates":[48.82706,38.45365],"type":"Point"}
}