{
  "type": "Feature",
  "properties": {
    "gn:admin1_code":"26",
    "gn:asciiname":"Gasanlar",
    "gn:country_code":"AZ",
    "gn:dem":1910,
    "gn:feature_class":"P",
    "gn:feature_code":"PPL",
    "gn:name":"Gasanlar",
    "gn:population":0,
    "gn:timezone":"Asia/Baku",
    "iso:country":"AZ",
    "name:aze_x_preferred":[
        "H\u0259s\u0259nl\u0259r"
    ],
    "name:rus_x_preferred":[
        "\u0413\u0430\u0441\u0430\u043d\u043b\u0430\u0440"
    ],
    "wof:name":"Gasanlar",
    "wof:placetype":"locality"
},
  "geometry": {"coordinates":[45.97023,40.09897],"type":"Point"}
}