{
  "type": "Feature",
  "properties": {
    "gn:admin1_code":"35",
    "gn:admin2_code":"7669114.0",
    "gn:asciiname":"Araz",
    "gn:country_code":"AZ",
    "gn:dem":787,
    "gn:feature_class":"P",
    "gn:feature_code":"PPL",
    "gn:name":"Araz",
    "gn:population":0,
    "gn:timezone":"Asia/Baku",
    "iso:country":"AZ",
    "name:aze_x_preferred":[
        "Araz"
    ],
    "wof:name":"Araz",
    "wof:placetype":"locality"
},
  "geometry": {"coordinates":[45.42377000000001,39.11126],"type":"Point"}
}