{
  "type": "Feature",
  "properties": {
    "gn:admin1_code":"63",
    "gn:asciiname":"Tazakend",
    "gn:country_code":"AZ",
    "gn:dem":249,
    "gn:feature_class":"P",
    "gn:feature_code":"PPL",
    "gn:name":"Tazakend",
    "gn:population":0,
    "gn:timezone":"Asia/Baku",
    "iso:country":"AZ",
    "name:ceb_x_preferred":[
        "Tazakend"
    ],
    "name:swe_x_preferred":[
        "Tazakend"
    ],
    "name:und_x_variant":[
        "T\u0259z\u0259k\u0259nd"
    ],
    "wof:name":"Tazakend",
    "wof:placetype":"locality"
},
  "geometry": {"coordinates":[49.17081,40.88623],"type":"Point"}
}