{
  "type": "Feature",
  "properties": {
    "gn:admin1_code":"35",
    "gn:admin2_code":"8014931.0",
    "gn:asciiname":"Sust",
    "gn:country_code":"AZ",
    "gn:dem":1023,
    "gn:feature_class":"P",
    "gn:feature_code":"PPL",
    "gn:name":"Sust",
    "gn:population":0,
    "gn:timezone":"Asia/Baku",
    "iso:country":"AZ",
    "name:aze_x_preferred":[
        "S\u00fcst"
    ],
    "name:hye_x_preferred":[
        "\u054d\u0578\u0582\u057d\u057f"
    ],
    "wof:name":"Sust",
    "wof:placetype":"locality"
},
  "geometry": {"coordinates":[45.30422,39.36401],"type":"Point"}
}