{
  "type": "Feature",
  "properties": {
    "gn:admin1_code":"06",
    "gn:asciiname":"Caparli",
    "gn:country_code":"AZ",
    "gn:dem":83,
    "gn:feature_class":"P",
    "gn:feature_code":"PPL",
    "gn:name":"\u00c7aparl\u0131",
    "gn:population":0,
    "gn:timezone":"Asia/Baku",
    "iso:country":"AZ",
    "name:azb_x_preferred":[
        "\u0686\u0627\u067e\u0627\u0631\u0644\u06cc"
    ],
    "name:aze_x_preferred":[
        "\u00c7aparl\u0131"
    ],
    "name:ceb_x_preferred":[
        "\u00c7aparl\u0131"
    ],
    "name:ell_x_preferred":[
        "\u03a4\u03c3\u03b1\u03c0\u03b1\u03c1\u03bb\u03af"
    ],
    "name:ita_x_preferred":[
        "\u00c7aparl\u0131"
    ],
    "name:kat_x_preferred":[
        "\u10e9\u10d0\u10e4\u10d0\u10e0\u10da\u10d8"
    ],
    "name:msa_x_preferred":[
        "\u00c7aparl\u0131"
    ],
    "name:swe_x_preferred":[
        "\u00c7aparl\u0131"
    ],
    "name:und_x_variant":[
        "Chaparly",
        "\u00c7aparl\u0131"
    ],
    "wof:name":"Caparli",
    "wof:placetype":"locality"
},
  "geometry": {"coordinates":[48.45384,40.50964000000001],"type":"Point"}
}