{
  "type": "Feature",
  "properties": {
    "gn:admin1_code":"06",
    "gn:asciiname":"Caparli",
    "gn:country_code":"AZ",
    "gn:dem":83,
    "gn:feature_class":"P",
    "gn:feature_code":"PPL",
    "gn:name":"\u00c7aparl\u0131",
    "gn:population":0,
    "gn:timezone":"Asia/Baku",
    "iso:country":"AZ",
    "name:und_x_variant":[
        "Chaparly",
        "\u00c7aparl\u0131"
    ],
    "wof:name":"Caparli",
    "wof:placetype":"locality"
},
  "geometry": {"coordinates":[48.45384,40.50964000000001],"type":"Point"}
}