{
  "type": "Feature",
  "properties": {
    "gn:admin1_code":"69",
    "gn:asciiname":"Baharli",
    "gn:country_code":"AZ",
    "gn:dem":365,
    "gn:feature_class":"P",
    "gn:feature_code":"PPL",
    "gn:name":"Baharl\u0131",
    "gn:population":0,
    "gn:timezone":"Asia/Baku",
    "iso:country":"AZ",
    "name:aze_x_preferred":[
        "Baharl\u0131"
    ],
    "name:rus_x_preferred":[
        "\u0411\u0430\u0445\u0430\u0440\u043b\u044b"
    ],
    "name:und_x_variant":[
        "Bakharly",
        "Bagarly"
    ],
    "wof:name":"Baharli",
    "wof:placetype":"locality"
},
  "geometry": {"coordinates":[46.6748,39.01899],"type":"Point"}
}