{
  "type": "Feature",
  "properties": {
    "gn:admin1_code":"31",
    "gn:asciiname":"Dzhango-Miran",
    "gn:country_code":"AZ",
    "gn:dem":1105,
    "gn:feature_class":"P",
    "gn:feature_code":"PPL",
    "gn:name":"Dzhango-Miran",
    "gn:population":0,
    "gn:timezone":"Asia/Baku",
    "iso:country":"AZ",
    "name:und_x_variant":[
        "Dzhangemiran",
        "Dzhango-Miran",
        "C\u0259ng\u0259miran"
    ],
    "wof:name":"Dzhango-Miran",
    "wof:placetype":"locality"
},
  "geometry": {"coordinates":[48.43607,38.75931],"type":"Point"}
}