{
  "type": "Feature",
  "properties": {
    "gn:admin1_code":"31",
    "gn:asciiname":"Dzhango-Miran",
    "gn:country_code":"AZ",
    "gn:dem":1105,
    "gn:feature_class":"P",
    "gn:feature_code":"PPL",
    "gn:name":"Dzhango-Miran",
    "gn:population":0,
    "gn:timezone":"Asia/Baku",
    "iso:country":"AZ",
    "name:azb_x_preferred":[
        "\u062c\u0646\u06af\u0647 \u0645\u06cc\u0631\u0627\u0646"
    ],
    "name:aze_x_preferred":[
        "C\u0259ng\u0259miran"
    ],
    "name:ceb_x_preferred":[
        "Dzhango-Miran"
    ],
    "name:fas_x_preferred":[
        "\u062c\u0646\u06af\u0647\u200c\u0645\u06cc\u0631\u0627\u0646"
    ],
    "name:ita_x_preferred":[
        "C\u0259ng\u0259miran"
    ],
    "name:msa_x_preferred":[
        "C\u0259ng\u0259miran"
    ],
    "name:swe_x_preferred":[
        "Dzhango-Miran"
    ],
    "name:und_x_variant":[
        "Dzhangemiran",
        "Dzhango-Miran",
        "C\u0259ng\u0259miran"
    ],
    "wof:name":"Dzhango-Miran",
    "wof:placetype":"locality"
},
  "geometry": {"coordinates":[48.43607,38.75931],"type":"Point"}
}