{
  "type": "Feature",
  "properties": {
    "gn:admin1_code":"35",
    "gn:admin2_code":"147365.0",
    "gn:asciiname":"Kilit",
    "gn:country_code":"AZ",
    "gn:dem":1030,
    "gn:feature_class":"P",
    "gn:feature_code":"PPL",
    "gn:name":"Kilit",
    "gn:population":0,
    "gn:timezone":"Asia/Baku",
    "iso:country":"AZ",
    "name:aze_x_preferred":[
        "Kilit"
    ],
    "wof:name":"Kilit",
    "wof:placetype":"locality"
},
  "geometry": {"coordinates":[46.12805,38.87907],"type":"Point"}
}