{
  "type": "Feature",
  "properties": {
    "gn:admin1_code":"63",
    "gn:asciiname":"Tudar",
    "gn:country_code":"AZ",
    "gn:dem":730,
    "gn:feature_class":"P",
    "gn:feature_code":"PPL",
    "gn:name":"Tudar",
    "gn:population":0,
    "gn:timezone":"Asia/Baku",
    "iso:country":"AZ",
    "name:eng_x_preferred":[
        "Tudar"
    ],
    "name:rus_x_preferred":[
        "\u0422\u0443\u0434\u0430\u0440"
    ],
    "wof:name":"Tudar",
    "wof:placetype":"locality"
},
  "geometry": {"coordinates":[49.0702,40.73539],"type":"Point"}
}