{
  "type": "Feature",
  "properties": {
    "gn:admin1_code":"41",
    "gn:asciiname":"Dzheyrankechmaz",
    "gn:country_code":"AZ",
    "gn:dem":458,
    "gn:feature_class":"P",
    "gn:feature_code":"PPL",
    "gn:name":"Dzheyrankechmaz",
    "gn:population":0,
    "gn:timezone":"Asia/Baku",
    "iso:country":"AZ",
    "name:und_x_variant":[
        "Dzheiran-Kechmas",
        "Dzheyran-Kechmas",
        "Ceyranke\u00e7m\u0259z"
    ],
    "wof:name":"Dzheyrankechmaz",
    "wof:placetype":"locality"
},
  "geometry": {"coordinates":[49.05956,40.48295],"type":"Point"}
}