{
  "type": "Feature",
  "properties": {
    "gn:admin1_code":"41",
    "gn:asciiname":"Dzheyrankechmaz",
    "gn:country_code":"AZ",
    "gn:dem":458,
    "gn:feature_class":"P",
    "gn:feature_code":"PPL",
    "gn:name":"Dzheyrankechmaz",
    "gn:population":0,
    "gn:timezone":"Asia/Baku",
    "iso:country":"AZ",
    "name:azb_x_preferred":[
        "\u062c\u0626\u06cc\u0631\u0627\u0646 \u06a9\u0626\u0686\u0645\u0632"
    ],
    "name:aze_x_preferred":[
        "Ceyranke\u00e7m\u0259z"
    ],
    "name:ell_x_preferred":[
        "\u03a4\u03c3\u03b5\u03ca\u03c1\u03b1\u03bd\u03ba\u03b5\u03c4\u03c3\u03bc\u03ad\u03b6"
    ],
    "name:fas_x_preferred":[
        "\u062c\u06cc\u0631\u0627\u0646\u200c\u06a9\u0686\u0645\u0632"
    ],
    "name:ita_x_preferred":[
        "Ceyranke\u00e7m\u0259z"
    ],
    "name:kat_x_preferred":[
        "\u10ef\u10d4\u10d8\u10e0\u10d0\u10dc\u10e5\u10d4\u10e9\u10db\u10d0\u10d6\u10d8"
    ],
    "name:msa_x_preferred":[
        "Ceyranke\u00e7m\u0259z"
    ],
    "name:und_x_variant":[
        "Dzheiran-Kechmas",
        "Dzheyran-Kechmas"
    ],
    "wof:name":"Dzheyrankechmaz",
    "wof:placetype":"locality"
},
  "geometry": {"coordinates":[49.05956,40.48295],"type":"Point"}
}