{
  "type": "Feature",
  "properties": {
    "gn:admin1_code":"44",
    "gn:asciiname":"Boyuk Muruq",
    "gn:country_code":"AZ",
    "gn:dem":1110,
    "gn:feature_class":"P",
    "gn:feature_code":"PPL",
    "gn:name":"B\u00f6y\u00fck Muruq",
    "gn:population":0,
    "gn:timezone":"Asia/Baku",
    "iso:country":"AZ",
    "name:und_x_variant":[
        "B\u00ebyuk Murug",
        "Beyuk-Murukh",
        "B\u00f6y\u00fck Muruq"
    ],
    "wof:name":"Boyuk Muruq",
    "wof:placetype":"locality"
},
  "geometry": {"coordinates":[48.17733,41.43168],"type":"Point"}
}