{
  "type": "Feature",
  "properties": {
    "gn:admin1_code":"44",
    "gn:asciiname":"Boyuk Muruq",
    "gn:country_code":"AZ",
    "gn:dem":1110,
    "gn:feature_class":"P",
    "gn:feature_code":"PPL",
    "gn:name":"B\u00f6y\u00fck Muruq",
    "gn:population":0,
    "gn:timezone":"Asia/Baku",
    "iso:country":"AZ",
    "name:aze_x_preferred":[
        "B\u00f6y\u00fck Muruq"
    ],
    "name:ceb_x_preferred":[
        "B\u00f6y\u00fck Muruq"
    ],
    "name:ell_x_preferred":[
        "\u039c\u03c0\u03bf\u03b3\u03b9\u03bf\u03cd\u03ba \u039c\u03bf\u03c5\u03c1\u03bf\u03cd\u03ba"
    ],
    "name:ita_x_preferred":[
        "B\u00f6y\u00fck Muruq"
    ],
    "name:kat_x_preferred":[
        "\u10d1\u10d8\u10dd\u10d8\u10d8\u10e3\u10e5\u10d8-\u10db\u10e3\u10e0\u10e3\u10d2\u10d8"
    ],
    "name:lez_x_preferred":[
        "\u0427I\u0435\u0445\u0438 \u041c\u0443\u0440\u0443\u0433\u044a"
    ],
    "name:msa_x_preferred":[
        "B\u00f6y\u00fck Muruq"
    ],
    "name:swe_x_preferred":[
        "B\u00f6y\u00fck Muruq"
    ],
    "name:und_x_variant":[
        "B\u00ebyuk Murug",
        "Beyuk-Murukh"
    ],
    "wof:name":"Boyuk Muruq",
    "wof:placetype":"locality"
},
  "geometry": {"coordinates":[48.17733,41.43168],"type":"Point"}
}