{
  "type": "Feature",
  "properties": {
    "gn:admin1_code":"62",
    "gn:asciiname":"Yolqulular",
    "gn:country_code":"AZ",
    "gn:dem":443,
    "gn:feature_class":"P",
    "gn:feature_code":"PPL",
    "gn:name":"Yolqulular",
    "gn:population":0,
    "gn:timezone":"Asia/Baku",
    "iso:country":"AZ",
    "name:azb_x_preferred":[
        "\u06cc\u0648\u0644\u0642\u0648\u0644\u0648\u0644\u0627\u0631"
    ],
    "name:aze_x_preferred":[
        "Yolqulular"
    ],
    "name:ceb_x_preferred":[
        "Yolqulular"
    ],
    "name:ell_x_preferred":[
        "\u0393\u03b9\u03bf\u03bb\u03ba\u03bf\u03c5\u03bb\u03bf\u03c5\u03bb\u03ac\u03c1"
    ],
    "name:ita_x_preferred":[
        "Yolqulular"
    ],
    "name:kat_x_preferred":[
        "\u10d8\u10dd\u10da\u10e7\u10e3\u10da\u10e3\u10da\u10d0\u10e0\u10d8"
    ],
    "name:msa_x_preferred":[
        "Yolqulular"
    ],
    "name:rus_x_preferred":[
        "\u0401\u043b\u043a\u0443\u043b\u0443\u043b\u0430\u0440"
    ],
    "name:swe_x_preferred":[
        "Yolqulular"
    ],
    "name:und_x_variant":[
        "Y\u00eblkulular",
        "Yolqulular"
    ],
    "name:urd_x_preferred":[
        "\u06cc\u0648\u0644\u0642\u0644\u0648\u0644\u0631"
    ],
    "wof:name":"Yolqulular",
    "wof:placetype":"locality"
},
  "geometry": {"coordinates":[46.51592,40.62424],"type":"Point"}
}