{
  "type": "Feature",
  "properties": {
    "gn:admin1_code":"51",
    "gn:asciiname":"Tatarli",
    "gn:country_code":"AZ",
    "gn:dem":589,
    "gn:feature_class":"P",
    "gn:feature_code":"PPL",
    "gn:name":"Tatarl\u0131",
    "gn:population":0,
    "gn:timezone":"Asia/Baku",
    "iso:country":"AZ",
    "name:und_x_variant":[
        "Tatarly",
        "Tatarl\u0131"
    ],
    "wof:name":"Tatarli",
    "wof:placetype":"locality"
},
  "geometry": {"coordinates":[45.73914,40.8552],"type":"Point"}
}