{
  "type": "Feature",
  "properties": {
    "gn:admin1_code":"51",
    "gn:asciiname":"Yeniabad",
    "gn:country_code":"AZ",
    "gn:dem":210,
    "gn:feature_class":"P",
    "gn:feature_code":"PPL",
    "gn:name":"Yeniabad",
    "gn:population":0,
    "gn:timezone":"Asia/Baku",
    "iso:country":"AZ",
    "name:azb_x_preferred":[
        "\u06cc\u0626\u0646\u06cc\u200c\u0622\u0628\u0627\u062f"
    ],
    "name:aze_x_preferred":[
        "Yeniabad"
    ],
    "name:ceb_x_preferred":[
        "Yeniabad"
    ],
    "name:ell_x_preferred":[
        "\u0393\u03b9\u03b5\u03bd\u03b9\u03b1\u03bc\u03c0\u03ac\u03bd\u03c4"
    ],
    "name:fas_x_preferred":[
        "\u06cc\u0646\u06cc\u200c\u0622\u0628\u0627\u062f"
    ],
    "name:ita_x_preferred":[
        "Yeniabad"
    ],
    "name:msa_x_preferred":[
        "Yeniabad"
    ],
    "name:swe_x_preferred":[
        "Yeniabad"
    ],
    "name:und_x_variant":[
        "Bitdili",
        "Bittili"
    ],
    "name:urd_x_preferred":[
        "\u06cc\u0646 \u0622\u0628\u0627\u062f"
    ],
    "wof:name":"Yeniabad",
    "wof:placetype":"locality"
},
  "geometry": {"coordinates":[46.17025,40.8911],"type":"Point"}
}