{
  "type": "Feature",
  "properties": {
    "gn:admin1_code":"51",
    "gn:asciiname":"Yeniabad",
    "gn:country_code":"AZ",
    "gn:dem":210,
    "gn:feature_class":"P",
    "gn:feature_code":"PPL",
    "gn:name":"Yeniabad",
    "gn:population":0,
    "gn:timezone":"Asia/Baku",
    "iso:country":"AZ",
    "name:und_x_variant":[
        "Bitdili",
        "Bittili",
        "Yeniabad"
    ],
    "wof:name":"Yeniabad",
    "wof:placetype":"locality"
},
  "geometry": {"coordinates":[46.17025,40.8911],"type":"Point"}
}