{
  "type": "Feature",
  "properties": {
    "gn:admin1_code":"69",
    "gn:asciiname":"Birinci Agali",
    "gn:country_code":"AZ",
    "gn:dem":337,
    "gn:feature_class":"P",
    "gn:feature_code":"PPL",
    "gn:name":"Birinci A\u011fal\u0131",
    "gn:population":0,
    "gn:timezone":"Asia/Baku",
    "iso:country":"AZ",
    "name:azb_x_preferred":[
        "\u0628\u06cc\u0631\u06cc\u0646\u062c\u06cc \u0622\u063a\u0627\u0644\u06cc"
    ],
    "name:aze_x_preferred":[
        "Birinci A\u011fal\u0131"
    ],
    "name:kat_x_preferred":[
        "\u10d1\u10d8\u10e0\u10d8\u10dc\u10ef\u10d8-\u10d0\u10e6\u10d0\u10da\u10d8"
    ],
    "name:msa_x_preferred":[
        "Birinci A\u011fal\u0131"
    ],
    "name:rus_x_preferred":[
        "\u0410\u0433\u0430\u043b\u044b \u041f\u0435\u0440\u0432\u043e\u0435"
    ],
    "name:und_x_variant":[
        "Yukhary Agaly",
        "Agaly Pervyye",
        "Agaly",
        "Agaly Pervoye"
    ],
    "wof:name":"Birinci Agali",
    "wof:placetype":"locality"
},
  "geometry": {"coordinates":[46.75161,39.18614],"type":"Point"}
}