{
  "type": "Feature",
  "properties": {
    "iso:country":"AZ",
    "name:azb_x_preferred":[
        "\u0634\u0648\u0631\u0627\u0622\u0628\u0627\u062f"
    ],
    "name:aze_x_preferred":[
        "\u015euraabad"
    ],
    "name:eng_x_preferred":[
        "\u015euraabad"
    ],
    "name:fas_x_preferred":[
        "\u0634\u0648\u0631\u0627\u0622\u0628\u0627\u062f"
    ],
    "name:ita_x_preferred":[
        "\u015euraabad"
    ],
    "name:kat_x_preferred":[
        "\u10e8\u10e3\u10e0\u10d0\u10d0\u10d1\u10d0\u10d3\u10d8"
    ],
    "name:msa_x_preferred":[
        "\u015euraabad"
    ],
    "name:nld_x_preferred":[
        "\u015euraabad"
    ],
    "name:rus_x_preferred":[
        "\u0428\u0443\u0440\u0430\u0430\u0431\u0430\u0434"
    ],
    "name:unk_x_variant":[
        "Soviet Abad"
    ],
    "qs:gn_country":"AZ",
    "qs:gn_fcode":"PPL",
    "qs:gn_pop":1945,
    "qs:name":"\u015euraabad",
    "qs:name_adm0":"Azerbaijan",
    "qs:name_adm1":"Xizi",
    "qs:photos":0,
    "qs:photos_1k":0,
    "qs:photos_9k":0,
    "qs:photos_9r":0,
    "qs:photos_all":0,
    "qs:photos_sr":0,
    "qs:placetype":"Town",
    "qs:pop_sr":"3",
    "qs:woe_adm0":23424741,
    "wd:wordcount":103,
    "wof:name":"\u015euraabad",
    "wof:placetype":"locality",
    "wof:population":1945
},
  "geometry": {"coordinates":[49.46874,40.81924],"type":"Point"}
}