{
  "type": "Feature",
  "properties": {
    "gn:admin1_code":"42",
    "gn:asciiname":"Khashy",
    "gn:country_code":"AZ",
    "gn:dem":1377,
    "gn:feature_class":"P",
    "gn:feature_code":"PPL",
    "gn:name":"Khashy",
    "gn:population":0,
    "gn:timezone":"Asia/Baku",
    "iso:country":"AZ",
    "name:und_x_variant":[
        "Khashi",
        "Xa\u015f\u0131"
    ],
    "wof:name":"Khashy",
    "wof:placetype":"locality"
},
  "geometry": {"coordinates":[48.66536,41.0281],"type":"Point"}
}