{
  "type": "Feature",
  "properties": {
    "gn:admin1_code":"44",
    "gn:asciiname":"Kazioba",
    "gn:country_code":"AZ",
    "gn:dem":333,
    "gn:feature_class":"P",
    "gn:feature_code":"PPL",
    "gn:name":"Kazioba",
    "gn:population":0,
    "gn:timezone":"Asia/Baku",
    "iso:country":"AZ",
    "name:azb_x_preferred":[
        "\u06a9\u0627\u0632\u06cc \u0627\u0648\u0628\u0627"
    ],
    "name:ell_x_preferred":[
        "\u039a\u03b1\u03b6\u03b9\u03cc\u03bc\u03c0\u03b1"
    ],
    "name:ita_x_preferred":[
        "Kazioba"
    ],
    "name:kat_x_preferred":[
        "\u10e5\u10d0\u10d6\u10d8\u10dd\u10d1\u10d0"
    ],
    "name:msa_x_preferred":[
        "Kazioba"
    ],
    "wof:name":"Kazioba",
    "wof:placetype":"locality"
},
  "geometry": {"coordinates":[48.58333,41.48333],"type":"Point"}
}