{
  "type": "Feature",
  "properties": {
    "gn:admin1_code":"44",
    "gn:asciiname":"Kazioba",
    "gn:country_code":"AZ",
    "gn:dem":333,
    "gn:feature_class":"P",
    "gn:feature_code":"PPL",
    "gn:name":"Kazioba",
    "gn:population":0,
    "gn:timezone":"Asia/Baku",
    "iso:country":"AZ",
    "wof:name":"Kazioba",
    "wof:placetype":"locality"
},
  "geometry": {"coordinates":[48.58333,41.48333],"type":"Point"}
}