{
  "type": "Feature",
  "properties": {
    "gn:admin1_code":"57",
    "gn:asciiname":"Qapanli",
    "gn:country_code":"AZ",
    "gn:dem":130,
    "gn:feature_class":"P",
    "gn:feature_code":"PPL",
    "gn:name":"Qapanl\u0131",
    "gn:population":0,
    "gn:timezone":"Asia/Baku",
    "iso:country":"AZ",
    "name:aze_x_preferred":[
        "Qapanl\u0131"
    ],
    "name:und_x_variant":[
        "Kapanly"
    ],
    "wof:name":"Qapanli",
    "wof:placetype":"locality"
},
  "geometry": {"coordinates":[47.05127,40.33858],"type":"Point"}
}