{
  "type": "Feature",
  "properties": {
    "gn:admin1_code":"11",
    "gn:asciiname":"Mollalar",
    "gn:country_code":"AZ",
    "gn:dem":-1,
    "gn:feature_class":"P",
    "gn:feature_code":"PPL",
    "gn:name":"Mollalar",
    "gn:population":0,
    "gn:timezone":"Asia/Baku",
    "iso:country":"AZ",
    "wof:name":"Mollalar",
    "wof:placetype":"locality"
},
  "geometry": {"coordinates":[47.48333,40.25],"type":"Point"}
}