{
  "type": "Feature",
  "properties": {
    "gn:admin1_code":"46",
    "gn:asciiname":"Quruzma",
    "gn:country_code":"AZ",
    "gn:dem":-17,
    "gn:feature_class":"P",
    "gn:feature_code":"PPL",
    "gn:name":"Quruzma",
    "gn:population":0,
    "gn:timezone":"Asia/Baku",
    "iso:country":"AZ",
    "name:azb_x_preferred":[
        "\u0642\u0648\u0631\u0648\u0632\u0645\u0627"
    ],
    "name:aze_x_preferred":[
        "Quruzma"
    ],
    "name:ceb_x_preferred":[
        "Quruzma"
    ],
    "name:eng_x_preferred":[
        "Quruzmaq"
    ],
    "name:ita_x_preferred":[
        "Quruzma"
    ],
    "name:msa_x_preferred":[
        "Quruzma"
    ],
    "name:rus_x_preferred":[
        "\u041a\u0443\u0440\u0443\u0437\u043c\u0430"
    ],
    "name:swe_x_preferred":[
        "Quruzma"
    ],
    "name:und_x_variant":[
        "Kuruzma"
    ],
    "wof:name":"Quruzma",
    "wof:placetype":"locality"
},
  "geometry": {"coordinates":[48.6096,40.08965],"type":"Point"}
}