{
  "type": "Feature",
  "properties": {
    "gn:admin1_code":"11",
    "gn:asciiname":"Emirli",
    "gn:country_code":"AZ",
    "gn:dem":88,
    "gn:feature_class":"P",
    "gn:feature_code":"PPL",
    "gn:name":"Emirli",
    "gn:population":0,
    "gn:timezone":"Asia/Baku",
    "iso:country":"AZ",
    "name:azb_x_preferred":[
        "\u0627\u0645\u06cc\u0631\u0644\u06cc"
    ],
    "name:aze_x_preferred":[
        "\u018fmirli"
    ],
    "name:ceb_x_preferred":[
        "Emirli"
    ],
    "name:ita_x_preferred":[
        "\u018fmirli"
    ],
    "name:kat_x_preferred":[
        "\u10d0\u10db\u10d8\u10e0\u10da\u10d8"
    ],
    "name:msa_x_preferred":[
        "\u018fmirli"
    ],
    "name:swe_x_preferred":[
        "Emirli"
    ],
    "name:und_x_variant":[
        "Naibly"
    ],
    "wof:name":"Emirli",
    "wof:placetype":"locality"
},
  "geometry": {"coordinates":[47.14823,40.21908],"type":"Point"}
}