{
  "type": "Feature",
  "properties": {
    "gn:admin1_code":"19",
    "gn:asciiname":"Sarikoynak",
    "gn:country_code":"AZ",
    "gn:dem":1469,
    "gn:feature_class":"P",
    "gn:feature_code":"PPL",
    "gn:name":"Sar\u0131k\u00f6yn\u0259k",
    "gn:population":0,
    "gn:timezone":"Asia/Baku",
    "iso:country":"AZ",
    "name:und_x_variant":[
        "Saryk\u00ebynak",
        "Sar\u0131k\u00f6yn\u0259k"
    ],
    "wof:name":"Sarikoynak",
    "wof:placetype":"locality"
},
  "geometry": {"coordinates":[45.71673,40.55074000000001],"type":"Point"}
}