{
  "type": "Feature",
  "properties": {
    "gn:admin1_code":"19",
    "gn:asciiname":"Sarikoynak",
    "gn:country_code":"AZ",
    "gn:dem":1469,
    "gn:feature_class":"P",
    "gn:feature_code":"PPL",
    "gn:name":"Sar\u0131k\u00f6yn\u0259k",
    "gn:population":0,
    "gn:timezone":"Asia/Baku",
    "iso:country":"AZ",
    "name:aze_x_preferred":[
        "Sar\u0131k\u00f6yn\u0259k"
    ],
    "name:ita_x_preferred":[
        "Sar\u0131k\u00f6yn\u0259k"
    ],
    "name:kat_x_preferred":[
        "\u10e1\u10d0\u10e0\u10d8\u10e5\u10d8\u10dd\u10d8\u10dc\u10d0\u10e5\u10d8"
    ],
    "name:msa_x_preferred":[
        "Sar\u0131k\u00f6yn\u0259k"
    ],
    "name:und_x_variant":[
        "Saryk\u00ebynak",
        "Sar\u0131k\u00f6yn\u0259k"
    ],
    "wof:name":"Sarikoynak",
    "wof:placetype":"locality"
},
  "geometry": {"coordinates":[45.71673,40.55074000000001],"type":"Point"}
}