{
  "type": "Feature",
  "properties": {
    "gn:admin1_code":"17",
    "gn:asciiname":"Tazakand",
    "gn:country_code":"AZ",
    "gn:dem":31,
    "gn:feature_class":"P",
    "gn:feature_code":"PPL",
    "gn:name":"T\u0259z\u0259k\u0259nd",
    "gn:population":0,
    "gn:timezone":"Asia/Baku",
    "iso:country":"AZ",
    "name:aze_x_preferred":[
        "T\u0259z\u0259k\u0259nd"
    ],
    "wof:name":"Tazakand",
    "wof:placetype":"locality"
},
  "geometry": {"coordinates":[48.937,41.23763],"type":"Point"}
}