{
  "type": "Feature",
  "properties": {
    "gn:admin1_code":"46",
    "gn:asciiname":"Zalqaraagac",
    "gn:country_code":"AZ",
    "gn:dem":-22,
    "gn:feature_class":"P",
    "gn:feature_code":"PPL",
    "gn:name":"Zalqaraa\u011fac",
    "gn:population":0,
    "gn:timezone":"Asia/Baku",
    "iso:country":"AZ",
    "name:azb_x_preferred":[
        "\u0632\u0627\u0644\u0642\u0627\u0631\u0627 \u0622\u063a\u0627\u062c"
    ],
    "name:aze_x_preferred":[
        "Zalqaraa\u011fac"
    ],
    "name:ceb_x_preferred":[
        "Zalqaraa\u011fac"
    ],
    "name:ita_x_preferred":[
        "Zalqaraa\u011fac"
    ],
    "name:msa_x_preferred":[
        "Zalqaraa\u011fac"
    ],
    "name:swe_x_preferred":[
        "Zalqaraa\u011fac"
    ],
    "name:und_x_variant":[
        "Zalkaraagach"
    ],
    "wof:name":"Zalqaraagac",
    "wof:placetype":"locality"
},
  "geometry": {"coordinates":[48.80278,39.90913],"type":"Point"}
}