{
  "type": "Feature",
  "properties": {
    "gn:admin1_code":"67",
    "gn:asciiname":"Varvara",
    "gn:country_code":"AZ",
    "gn:dem":21,
    "gn:feature_class":"P",
    "gn:feature_code":"PPL",
    "gn:name":"Varvara",
    "gn:population":0,
    "gn:timezone":"Asia/Baku",
    "iso:country":"AZ",
    "name:aze_x_preferred":[
        "Varvara"
    ],
    "name:eng_x_preferred":[
        "Varvara"
    ],
    "name:rus_x_preferred":[
        "\u0412\u0430\u0440\u0432\u0430\u0440\u0430"
    ],
    "wof:name":"Varvara",
    "wof:placetype":"locality"
},
  "geometry": {"coordinates":[47.09318,40.67742],"type":"Point"}
}