{
  "type": "Feature",
  "properties": {
    "gn:admin1_code":"60",
    "gn:asciiname":"Mukhtadir",
    "gn:country_code":"AZ",
    "gn:dem":-18,
    "gn:feature_class":"P",
    "gn:feature_code":"PPL",
    "gn:name":"Mukhtadir",
    "gn:population":0,
    "gn:timezone":"Asia/Baku",
    "iso:country":"AZ",
    "name:azb_x_preferred":[
        "\u0627\u06cc\u0633\u062a\u06cc\u0633\u0648 \u0642\u0635\u0628\u0647\u200c\u0633\u06cc"
    ],
    "name:aze_x_preferred":[
        "\u0130stisu q\u0259s\u0259b\u0259si"
    ],
    "name:ceb_x_preferred":[
        "Mukhtadir"
    ],
    "name:eng_x_preferred":[
        "M\u00fcqt\u01dddir"
    ],
    "name:ita_x_preferred":[
        "M\u00fcqt\u0259dir"
    ],
    "name:lez_x_preferred":[
        "\u041c\u0443\u043a\u044c\u0442\u0430\u0434\u0438\u0440"
    ],
    "name:msa_x_preferred":[
        "M\u00fcqt\u0259dir"
    ],
    "name:rus_x_preferred":[
        "\u041c\u0443\u0445\u0442\u0430\u0434\u0438\u0440"
    ],
    "name:rus_x_variant":[
        "\u0418\u0441\u0442\u0438\u0441\u0443"
    ],
    "name:swe_x_preferred":[
        "Mukhtadir"
    ],
    "name:und_x_variant":[
        "M\u00fcqt\u0259dir"
    ],
    "wof:name":"Mukhtadir",
    "wof:placetype":"locality"
},
  "geometry": {"coordinates":[48.77603,41.66692000000001],"type":"Point"}
}