{
  "type": "Feature",
  "properties": {
    "gn:admin1_code":"63",
    "gn:asciiname":"Yeni Yasma",
    "gn:country_code":"AZ",
    "gn:dem":-22,
    "gn:feature_class":"P",
    "gn:feature_code":"PPL",
    "gn:name":"Yeni Ya\u015fma",
    "gn:population":0,
    "gn:timezone":"Asia/Baku",
    "iso:country":"AZ",
    "name:aze_x_preferred":[
        "Yeni Ya\u015fma"
    ],
    "wof:name":"Yeni Yasma",
    "wof:placetype":"locality"
},
  "geometry": {"coordinates":[49.47062,40.75559000000001],"type":"Point"}
}