{
  "type": "Feature",
  "properties": {
    "gn:admin1_code":"70",
    "gn:asciiname":"Mudzhakhbina",
    "gn:country_code":"AZ",
    "gn:dem":246,
    "gn:feature_class":"P",
    "gn:feature_code":"PPL",
    "gn:name":"Mudzhakhbina",
    "gn:population":0,
    "gn:timezone":"Asia/Baku",
    "iso:country":"AZ",
    "name:ava_x_preferred":[
        "\u041c\u0443\u0447\u0430\u043a\u0438\u0431"
    ],
    "name:azb_x_preferred":[
        "\u0645\u0648\u062c\u06a9 \u0628\u06cc\u0646\u0647"
    ],
    "name:aze_x_preferred":[
        "M\u00fcc\u0259kbin\u0259"
    ],
    "name:ita_x_preferred":[
        "M\u00fcc\u0259kbin\u0259"
    ],
    "name:kat_x_preferred":[
        "\u10db\u10d8\u10e3\u10ef\u10d0\u10e5\u10d1\u10d8\u10dc\u10d0"
    ],
    "name:msa_x_preferred":[
        "M\u00fcc\u0259kbin\u0259"
    ],
    "name:und_x_variant":[
        "M\u00fcc\u0259kbin\u0259"
    ],
    "wof:name":"Mudzhakhbina",
    "wof:placetype":"locality"
},
  "geometry": {"coordinates":[46.52591,41.55194],"type":"Point"}
}