{
  "type": "Feature",
  "properties": {
    "gn:admin1_code":"70",
    "gn:asciiname":"Mudzhakhbina",
    "gn:country_code":"AZ",
    "gn:dem":246,
    "gn:feature_class":"P",
    "gn:feature_code":"PPL",
    "gn:name":"Mudzhakhbina",
    "gn:population":0,
    "gn:timezone":"Asia/Baku",
    "iso:country":"AZ",
    "name:und_x_variant":[
        "M\u00fcc\u0259kbin\u0259"
    ],
    "wof:name":"Mudzhakhbina",
    "wof:placetype":"locality"
},
  "geometry": {"coordinates":[46.52591,41.55194],"type":"Point"}
}