{
  "type": "Feature",
  "properties": {
    "gn:admin1_code":"17",
    "gn:asciiname":"Ledzhedy",
    "gn:country_code":"AZ",
    "gn:dem":417,
    "gn:feature_class":"P",
    "gn:feature_code":"PPL",
    "gn:name":"Ledzhedy",
    "gn:population":0,
    "gn:timezone":"Asia/Baku",
    "iso:country":"AZ",
    "name:und_x_variant":[
        "Ledzhedi",
        "Ledzhedy",
        "L\u0259c\u0259di"
    ],
    "wof:name":"Ledzhedy",
    "wof:placetype":"locality"
},
  "geometry": {"coordinates":[48.86114,41.2268],"type":"Point"}
}