{
  "type": "Feature",
  "properties": {
    "gn:admin1_code":"19",
    "gn:asciiname":"Kesaman",
    "gn:country_code":"AZ",
    "gn:dem":1247,
    "gn:feature_class":"P",
    "gn:feature_code":"PPL",
    "gn:name":"Kesaman",
    "gn:population":0,
    "gn:timezone":"Asia/Baku",
    "iso:country":"AZ",
    "name:und_x_variant":[
        "K\u0259s\u0259m\u0259n"
    ],
    "wof:name":"Kesaman",
    "wof:placetype":"locality"
},
  "geometry": {"coordinates":[45.65647,40.604],"type":"Point"}
}