{
  "type": "Feature",
  "properties": {
    "gn:admin1_code":"70",
    "gn:asciiname":"Bozbina",
    "gn:country_code":"AZ",
    "gn:dem":261,
    "gn:feature_class":"P",
    "gn:feature_code":"PPL",
    "gn:name":"Bozbina",
    "gn:population":0,
    "gn:timezone":"Asia/Baku",
    "iso:country":"AZ",
    "name:azb_x_preferred":[
        "\u0628\u0648\u0632 \u0628\u06cc\u0646\u0647"
    ],
    "name:aze_x_preferred":[
        "Bozbin\u0259"
    ],
    "name:fas_x_preferred":[
        "\u0628\u0632\u0628\u06cc\u0646\u0647"
    ],
    "name:ita_x_preferred":[
        "Bozbin\u0259"
    ],
    "name:kat_x_preferred":[
        "\u10d1\u10dd\u10d6\u10d1\u10d8\u10dc\u10d0"
    ],
    "name:msa_x_preferred":[
        "Bozbin\u0259"
    ],
    "name:und_x_variant":[
        "Bozbina"
    ],
    "wof:name":"Bozbina",
    "wof:placetype":"locality"
},
  "geometry": {"coordinates":[46.52786,41.57181],"type":"Point"}
}