{
  "type": "Feature",
  "properties": {
    "gn:admin1_code":"12",
    "gn:asciiname":"Bulutlu",
    "gn:country_code":"AZ",
    "gn:dem":31,
    "gn:feature_class":"P",
    "gn:feature_code":"PPL",
    "gn:name":"Bulutlu",
    "gn:population":0,
    "gn:timezone":"Asia/Baku",
    "iso:country":"AZ",
    "wof:name":"Bulutlu",
    "wof:placetype":"locality"
},
  "geometry": {"coordinates":[47.75349,39.75044000000001],"type":"Point"}
}