{
  "type": "Feature",
  "properties": {
    "gn:admin1_code":"11",
    "gn:asciiname":"Dargalar",
    "gn:country_code":"AZ",
    "gn:dem":89,
    "gn:feature_class":"P",
    "gn:feature_code":"PPL",
    "gn:name":"Dar\u011falar",
    "gn:population":0,
    "gn:timezone":"Asia/Baku",
    "iso:country":"AZ",
    "name:aze_x_preferred":[
        "Dar\u011falar"
    ],
    "wof:name":"Dargalar",
    "wof:placetype":"locality"
},
  "geometry": {"coordinates":[47.10937,40.33609000000001],"type":"Point"}
}