{
  "type": "Feature",
  "properties": {
    "gn:admin1_code":"39",
    "gn:asciiname":"Tasmali",
    "gn:country_code":"AZ",
    "gn:dem":220,
    "gn:feature_class":"P",
    "gn:feature_code":"PPL",
    "gn:name":"Tasmal\u0131",
    "gn:population":0,
    "gn:timezone":"Asia/Baku",
    "iso:country":"AZ",
    "name:ava_x_preferred":[
        "\u0422\u0430\u0441\u043c\u0430\u043b\u0443\u0431"
    ],
    "name:azb_x_preferred":[
        "\u062a\u0627\u0633\u0645\u0627\u0644\u06cc"
    ],
    "name:aze_x_preferred":[
        "Tasmal\u0131"
    ],
    "name:ceb_x_preferred":[
        "Tasmal\u0131"
    ],
    "name:eng_x_preferred":[
        "Tasmal\u0131"
    ],
    "name:ita_x_preferred":[
        "Tasmal\u0131"
    ],
    "name:kat_x_preferred":[
        "\u10d7\u10d0\u10e1\u10db\u10d0\u10da\u10d8"
    ],
    "name:msa_x_preferred":[
        "Tasmal\u0131"
    ],
    "name:rus_x_preferred":[
        "\u0422\u0430\u0441\u043c\u0430\u043b\u044b"
    ],
    "name:swe_x_preferred":[
        "Tasmal\u0131"
    ],
    "name:und_x_variant":[
        "Tasmanly",
        "Tasmaly"
    ],
    "wof:name":"Tasmali",
    "wof:placetype":"locality"
},
  "geometry": {"coordinates":[46.70265,41.43149],"type":"Point"}
}