{
  "type": "Feature",
  "properties": {
    "gn:admin1_code":"39",
    "gn:asciiname":"Tasmali",
    "gn:country_code":"AZ",
    "gn:dem":220,
    "gn:feature_class":"P",
    "gn:feature_code":"PPL",
    "gn:name":"Tasmal\u0131",
    "gn:population":0,
    "gn:timezone":"Asia/Baku",
    "iso:country":"AZ",
    "name:eng_x_preferred":[
        "Tasmal\u0131"
    ],
    "name:rus_x_preferred":[
        "\u0422\u0430\u0441\u043c\u0430\u043b\u044b"
    ],
    "name:und_x_variant":[
        "Tasmanly",
        "Tasmaly",
        "Tasmal\u0131"
    ],
    "wof:name":"Tasmali",
    "wof:placetype":"locality"
},
  "geometry": {"coordinates":[46.70265,41.43149],"type":"Point"}
}