{
  "type": "Feature",
  "properties": {
    "gn:admin1_code":"18",
    "gn:asciiname":"Hacili",
    "gn:country_code":"AZ",
    "gn:dem":116,
    "gn:feature_class":"P",
    "gn:feature_code":"PPL",
    "gn:name":"Hac\u0131l\u0131",
    "gn:population":0,
    "gn:timezone":"Asia/Baku",
    "iso:country":"AZ",
    "name:rus_x_preferred":[
        "\u0413\u0430\u0434\u0436\u0438\u043b\u0443"
    ],
    "name:und_x_variant":[
        "Gadzhilu",
        "Hac\u0131l\u0131"
    ],
    "wof:name":"Hacili",
    "wof:placetype":"locality"
},
  "geometry": {"coordinates":[47.46428,39.50236],"type":"Point"}
}