{
  "type": "Feature",
  "properties": {
    "gn:admin1_code":"21",
    "gn:asciiname":"Shafibeyli",
    "gn:country_code":"AZ",
    "gn:dem":489,
    "gn:feature_class":"P",
    "gn:feature_code":"PPL",
    "gn:name":"Shafibeyli",
    "gn:population":0,
    "gn:timezone":"Asia/Baku",
    "iso:country":"AZ",
    "name:aze_x_preferred":[
        "\u015e\u0259fib\u0259yli"
    ],
    "name:hye_x_preferred":[
        "\u0547\u0561\u0586\u056b\u0562\u0565\u0575\u056c\u056b"
    ],
    "name:rus_x_preferred":[
        "\u0428\u0430\u0444\u0438\u0431\u0435\u0439\u043b\u0438"
    ],
    "name:und_x_variant":[
        "Shafibeili"
    ],
    "wof:name":"Shafibeyli",
    "wof:placetype":"locality"
},
  "geometry": {"coordinates":[46.71098,40.47925],"type":"Point"}
}