{
  "type": "Feature",
  "properties": {
    "gn:admin1_code":"65",
    "gn:asciiname":"Mioulkoudara",
    "gn:country_code":"AZ",
    "gn:dem":1227,
    "gn:feature_class":"P",
    "gn:feature_code":"PPL",
    "gn:name":"Mioulkoudara",
    "gn:population":0,
    "gn:timezone":"Asia/Baku",
    "iso:country":"AZ",
    "name:azb_x_preferred":[
        "\u0645\u0648\u0644\u06a9\u0648\u062f\u0631\u0647"
    ],
    "name:aze_x_preferred":[
        "M\u00fclk\u00fcd\u0259r\u0259"
    ],
    "name:bel_x_preferred":[
        "\u0414\u0436\u0440\u0430\u0431\u0435\u0440\u0434"
    ],
    "name:ell_x_preferred":[
        "\u039c\u03b9\u03bf\u03c5\u03bb\u03ba\u03b9\u03bf\u03c5\u03bd\u03c4\u03b5\u03c1\u03ad"
    ],
    "name:fas_x_preferred":[
        "\u062c\u0631\u0627\u0628\u0631\u062f"
    ],
    "name:hye_x_preferred":[
        "Mulk\u2019idara"
    ],
    "name:hye_x_variant":[
        "\u0544\u0578\u0582\u056c\u0584\u056b\u0564\u0561\u0580\u0561",
        "Jraberd",
        "\u054b\u0580\u0561\u0562\u0565\u0580\u0564"
    ],
    "name:msa_x_preferred":[
        "M\u00fclk\u00fcd\u0259r\u0259"
    ],
    "name:rus_x_preferred":[
        "Myul\u2019kyudere"
    ],
    "name:rus_x_variant":[
        "\u041c\u044e\u043b\u044c\u043a\u044e\u0434\u0435\u0440\u0435"
    ],
    "name:ukr_x_preferred":[
        "\u0414\u0436\u0440\u0430\u0431\u0435\u0440\u0434"
    ],
    "name:und_x_variant":[
        "Myul\u2019kudara",
        "Hayrenater"
    ],
    "wof:name":"Mioulkoudara",
    "wof:placetype":"locality"
},
  "geometry": {"coordinates":[46.93138,39.47384],"type":"Point"}
}