{
  "type": "Feature",
  "properties": {
    "gn:admin1_code":"65",
    "gn:asciiname":"Mioulkoudara",
    "gn:country_code":"AZ",
    "gn:dem":1227,
    "gn:feature_class":"P",
    "gn:feature_code":"PPL",
    "gn:name":"Mioulkoudara",
    "gn:population":0,
    "gn:timezone":"Asia/Baku",
    "iso:country":"AZ",
    "name:aze_x_preferred":[
        "M\u00fclk\u00fcd\u0259r\u0259"
    ],
    "name:hye_x_preferred":[
        "Mulk\u2019idara"
    ],
    "name:hye_x_variant":[
        "\u0544\u0578\u0582\u056c\u0584\u056b\u0564\u0561\u0580\u0561",
        "Jraberd",
        "\u054b\u0580\u0561\u0562\u0565\u0580\u0564"
    ],
    "name:rus_x_preferred":[
        "Myul\u2019kyudere"
    ],
    "name:rus_x_variant":[
        "\u041c\u044e\u043b\u044c\u043a\u044e\u0434\u0435\u0440\u0435"
    ],
    "name:und_x_variant":[
        "Myul\u2019kudara",
        "Hayrenater"
    ],
    "wof:name":"Mioulkoudara",
    "wof:placetype":"locality"
},
  "geometry": {"coordinates":[46.93138,39.47384],"type":"Point"}
}