{
  "type": "Feature",
  "properties": {
    "gn:admin1_code":"62",
    "gn:asciiname":"Panakhlyar",
    "gn:country_code":"AZ",
    "gn:dem":587,
    "gn:feature_class":"P",
    "gn:feature_code":"PPL",
    "gn:name":"Panakhlyar",
    "gn:population":0,
    "gn:timezone":"Asia/Baku",
    "iso:country":"AZ",
    "name:aze_x_preferred":[
        "P\u0259nahlar"
    ],
    "name:hye_x_preferred":[
        "P\u2019anakhlar"
    ],
    "name:hye_x_variant":[
        "\u0553\u0561\u0576\u0561\u056d\u056c\u0561\u0580"
    ],
    "wof:name":"Panakhlyar",
    "wof:placetype":"locality"
},
  "geometry": {"coordinates":[46.4977,40.55689],"type":"Point"}
}