{
  "type": "Feature",
  "properties": {
    "gn:admin1_code":"58",
    "gn:asciiname":"Kozdere",
    "gn:country_code":"AZ",
    "gn:dem":672,
    "gn:feature_class":"P",
    "gn:feature_code":"PPL",
    "gn:name":"Kozdere",
    "gn:population":0,
    "gn:timezone":"Asia/Baku",
    "iso:country":"AZ",
    "name:und_x_variant":[
        "Qozd\u0259r\u0259"
    ],
    "wof:name":"Kozdere",
    "wof:placetype":"locality"
},
  "geometry": {"coordinates":[45.68463,40.83762],"type":"Point"}
}