{
  "type": "Feature",
  "properties": {
    "gn:admin1_code":"35",
    "gn:admin2_code":"147997.0",
    "gn:asciiname":"Charchibogan",
    "gn:country_code":"AZ",
    "gn:dem":804,
    "gn:feature_class":"P",
    "gn:feature_code":"PPL",
    "gn:name":"Charchibogan",
    "gn:population":0,
    "gn:timezone":"Asia/Baku",
    "iso:country":"AZ",
    "name:aze_x_preferred":[
        "\u00c7\u0259r\u00e7ibo\u011fan"
    ],
    "wof:name":"Charchibogan",
    "wof:placetype":"locality"
},
  "geometry": {"coordinates":[44.9806,39.53101],"type":"Point"}
}