{
  "type": "Feature",
  "properties": {
    "gn:admin1_code":"17",
    "gn:asciiname":"Adakar",
    "gn:country_code":"AZ",
    "gn:dem":-25,
    "gn:feature_class":"P",
    "gn:feature_code":"PPL",
    "gn:name":"Adakar",
    "gn:population":0,
    "gn:timezone":"Asia/Baku",
    "iso:country":"AZ",
    "wof:name":"Adakar",
    "wof:placetype":"locality"
},
  "geometry": {"coordinates":[49.07278,41.33306],"type":"Point"}
}