{
  "type": "Feature",
  "properties": {
    "gn:admin1_code":"28",
    "gn:asciiname":"Novruzlu",
    "gn:cc2":"AZ",
    "gn:country_code":"AZ",
    "gn:dem":1208,
    "gn:feature_class":"P",
    "gn:feature_code":"PPL",
    "gn:name":"Novruzlu",
    "gn:population":0,
    "gn:timezone":"Asia/Baku",
    "iso:country":"AZ",
    "name:aze_x_preferred":[
        "Novruzlu"
    ],
    "name:hye_x_preferred":[
        "Dziasar"
    ],
    "name:hye_x_variant":[
        "\u0541\u056b\u0561\u057d\u0561\u0580"
    ],
    "name:und_x_variant":[
        "Novruzglylar"
    ],
    "wof:name":"Novruzlu",
    "wof:placetype":"locality"
},
  "geometry": {"coordinates":[46.48111,39.60194],"type":"Point"}
}