{
  "type": "Feature",
  "properties": {
    "gn:admin1_code":"03",
    "gn:asciiname":"Khydyrly",
    "gn:country_code":"AZ",
    "gn:dem":435,
    "gn:feature_class":"P",
    "gn:feature_code":"PPL",
    "gn:name":"Khydyrly",
    "gn:population":0,
    "gn:timezone":"Asia/Baku",
    "iso:country":"AZ",
    "name:aze_x_preferred":[
        "X\u0131d\u0131rl\u0131"
    ],
    "name:hye_x_preferred":[
        "Khdrly"
    ],
    "name:hye_x_variant":[
        "\u053d\u0564\u0580\u056c\u0568"
    ],
    "name:rus_x_preferred":[
        "\u0425\u044b\u0434\u044b\u0440\u043b\u044b"
    ],
    "name:und_x_variant":[
        "Khidirly",
        "Khydyrly"
    ],
    "wof:name":"Khydyrly",
    "wof:placetype":"locality"
},
  "geometry": {"coordinates":[46.89111,40.00987],"type":"Point"}
}