{
  "type": "Feature",
  "properties": {
    "gn:admin1_code":"26",
    "gn:asciiname":"Xallanli",
    "gn:country_code":"AZ",
    "gn:dem":1762,
    "gn:feature_class":"P",
    "gn:feature_code":"PPL",
    "gn:name":"Xallanl\u0131",
    "gn:population":0,
    "gn:timezone":"Asia/Baku",
    "iso:country":"AZ",
    "name:aze_x_preferred":[
        "Xallanl\u0131"
    ],
    "name:hye_x_preferred":[
        "Ishkhanik"
    ],
    "name:hye_x_variant":[
        "\u053b\u0577\u056d\u0561\u0576\u056b\u056f"
    ],
    "name:msa_x_preferred":[
        "Xallanl\u0131"
    ],
    "name:rus_x_preferred":[
        "\u0425\u0430\u043b\u043b\u0430\u043d\u043b\u044b"
    ],
    "name:und_x_variant":[
        "Khallanly",
        "Khailanly",
        "Khanlanly"
    ],
    "wof:name":"Xallanli",
    "wof:placetype":"locality"
},
  "geometry": {"coordinates":[46.17642,39.97128],"type":"Point"}
}