{
  "type": "Feature",
  "properties": {
    "gn:admin1_code":"44",
    "gn:asciiname":"Qaratoba",
    "gn:country_code":"AZ",
    "gn:dem":117,
    "gn:feature_class":"P",
    "gn:feature_code":"PPL",
    "gn:name":"Qaratoba",
    "gn:population":0,
    "gn:timezone":"Asia/Baku",
    "iso:country":"AZ",
    "name:azb_x_preferred":[
        "\u0642\u0627\u0631\u0627\u062a \u0627\u0648\u0628\u0627"
    ],
    "name:aze_x_preferred":[
        "Qaratoba"
    ],
    "name:ceb_x_preferred":[
        "Qaratoba"
    ],
    "name:ell_x_preferred":[
        "\u039a\u03b1\u03c1\u03b1\u03c4\u03cc\u03bc\u03c0\u03b1"
    ],
    "name:fas_x_preferred":[
        "\u06a9\u0627\u0631\u0627\u062a\u0648\u0628\u0627"
    ],
    "name:ita_x_preferred":[
        "Qaratoba"
    ],
    "name:kat_x_preferred":[
        "\u10e7\u10d0\u10e0\u10d0\u10d7\u10dd\u10d1\u10d0"
    ],
    "name:lez_x_preferred":[
        "\u041a\u044a\u0430\u0440\u0430\u0442\u0443\u0431\u0430"
    ],
    "name:msa_x_preferred":[
        "Qaratoba"
    ],
    "name:swe_x_preferred":[
        "Qaratoba"
    ],
    "name:und_x_variant":[
        "Karatoba",
        "Qaratoba"
    ],
    "wof:name":"Qaratoba",
    "wof:placetype":"locality"
},
  "geometry": {"coordinates":[48.55974000000001,41.71279000000001],"type":"Point"}
}