{
  "type": "Feature",
  "properties": {
    "gn:admin1_code":"44",
    "gn:asciiname":"Qaratoba",
    "gn:country_code":"AZ",
    "gn:dem":117,
    "gn:feature_class":"P",
    "gn:feature_code":"PPL",
    "gn:name":"Qaratoba",
    "gn:population":0,
    "gn:timezone":"Asia/Baku",
    "iso:country":"AZ",
    "name:und_x_variant":[
        "Karatoba",
        "Qaratoba"
    ],
    "wof:name":"Qaratoba",
    "wof:placetype":"locality"
},
  "geometry": {"coordinates":[48.55974000000001,41.71279000000001],"type":"Point"}
}