{
  "type": "Feature",
  "properties": {
    "gn:admin1_code":"32",
    "gn:asciiname":"Meshakenar",
    "gn:country_code":"AZ",
    "gn:dem":14,
    "gn:feature_class":"P",
    "gn:feature_code":"PPL",
    "gn:name":"Meshakenar",
    "gn:population":0,
    "gn:timezone":"Asia/Baku",
    "iso:country":"AZ",
    "name:aze_x_preferred":[
        "Me\u015f\u0259k\u0259nar\u0131"
    ],
    "wof:name":"Meshakenar",
    "wof:placetype":"locality"
},
  "geometry": {"coordinates":[48.61203,39.06819],"type":"Point"}
}