{
  "type": "Feature",
  "properties": {
    "gn:admin1_code":"17",
    "gn:asciiname":"Chukhur-Zami",
    "gn:country_code":"AZ",
    "gn:dem":1003,
    "gn:feature_class":"P",
    "gn:feature_code":"PPL",
    "gn:name":"Chukhur-Zami",
    "gn:population":0,
    "gn:timezone":"Asia/Baku",
    "iso:country":"AZ",
    "name:eng_x_preferred":[
        "\u00c7uxur\u01ddz\u01ddmi"
    ],
    "name:rus_x_preferred":[
        "\u0427\u0443\u0445\u0443\u0440\u0430\u0437\u0430\u043c\u0438"
    ],
    "name:und_x_variant":[
        "Chukhurazami",
        "Chukhur-Zami",
        "\u00c7uxur\u0259z\u0259mi"
    ],
    "wof:name":"Chukhur-Zami",
    "wof:placetype":"locality"
},
  "geometry": {"coordinates":[48.80707,40.96714],"type":"Point"}
}