{
  "type": "Feature",
  "properties": {
    "gn:admin1_code":"31",
    "gn:asciiname":"Bobogil",
    "gn:country_code":"AZ",
    "gn:dem":515,
    "gn:feature_class":"P",
    "gn:feature_code":"PPL",
    "gn:name":"Bobogil",
    "gn:population":0,
    "gn:timezone":"Asia/Baku",
    "iso:country":"AZ",
    "name:aze_x_preferred":[
        "Bobogil"
    ],
    "name:aze_x_variant":[
        "Babagil"
    ],
    "name:rus_x_preferred":[
        "Byubogil\u2019"
    ],
    "wof:name":"Bobogil",
    "wof:placetype":"locality"
},
  "geometry": {"coordinates":[48.51378,38.798],"type":"Point"}
}