{
  "type": "Feature",
  "properties": {
    "gn:admin1_code":"38",
    "gn:asciiname":"Hacialili",
    "gn:country_code":"AZ",
    "gn:dem":362,
    "gn:feature_class":"P",
    "gn:feature_code":"PPL",
    "gn:name":"Hac\u0131al\u0131l\u0131",
    "gn:population":0,
    "gn:timezone":"Asia/Baku",
    "iso:country":"AZ",
    "name:aze_x_preferred":[
        "Hacall\u0131"
    ],
    "name:eng_x_preferred":[
        "Hac\u0131al\u0131l\u0131"
    ],
    "name:rus_x_preferred":[
        "\u0413\u0430\u0434\u0436\u044b\u0430\u043b\u044b\u043b\u044b"
    ],
    "name:und_x_variant":[
        "Gadzhally",
        "Gadzhylalyly"
    ],
    "wof:name":"Hacialili",
    "wof:placetype":"locality"
},
  "geometry": {"coordinates":[47.7297,40.84307],"type":"Point"}
}