{
  "type": "Feature",
  "properties": {
    "gn:admin1_code":"28",
    "gn:asciiname":"Chyrakhly",
    "gn:country_code":"AZ",
    "gn:dem":1898,
    "gn:feature_class":"P",
    "gn:feature_code":"PPL",
    "gn:name":"Chyrakhly",
    "gn:population":0,
    "gn:timezone":"Asia/Baku",
    "iso:country":"AZ",
    "name:aze_x_preferred":[
        "\u00c7\u0131raql\u0131"
    ],
    "name:hye_x_preferred":[
        "Chraghly"
    ],
    "name:hye_x_variant":[
        "\u0549\u0580\u0561\u0572\u056c\u0568",
        "Chragidzor",
        "\u0543\u0580\u0561\u0572\u056b\u0571\u0578\u0580"
    ],
    "name:rus_x_preferred":[
        "\u0427\u044b\u0440\u0430\u0433\u043b\u044b"
    ],
    "name:und_x_variant":[
        "Chyragly",
        "Chyakhly",
        "\u0427\u044b\u0440\u0430\u0433\u043b\u044b"
    ],
    "wof:name":"Chyrakhly",
    "wof:placetype":"locality"
},
  "geometry": {"coordinates":[46.31288,39.73105],"type":"Point"}
}