{
  "type": "Feature",
  "properties": {
    "gn:admin1_code":"26",
    "gn:asciiname":"Charectar",
    "gn:country_code":"AZ",
    "gn:dem":954,
    "gn:feature_class":"P",
    "gn:feature_code":"PPL",
    "gn:name":"Charectar",
    "gn:population":0,
    "gn:timezone":"Asia/Baku",
    "iso:country":"AZ",
    "name:aze_x_preferred":[
        "\u00c7\u0259r\u0259ktar"
    ],
    "name:aze_x_variant":[
        "\u00c7\u0259r\u0259kdar"
    ],
    "name:eng_x_preferred":[
        "\u00c7\u01ddr\u01ddktar"
    ],
    "name:hye_x_preferred":[
        "Charektar"
    ],
    "name:hye_x_variant":[
        "\u0549\u0561\u0580\u0565\u056f\u057f\u0561\u0580",
        "\u0549\u0561\u0580\u0565\u0584\u057f\u0561\u0580"
    ],
    "name:rus_x_preferred":[
        "\u0427\u0430\u0440\u0435\u043a\u0442\u0430\u0440"
    ],
    "name:und_x_variant":[
        "Ch\u2019arek\u2019tar",
        "Charectar"
    ],
    "wof:name":"Charectar",
    "wof:placetype":"locality"
},
  "geometry": {"coordinates":[46.34312,40.14145],"type":"Point"}
}