{
  "type": "Feature",
  "properties": {
    "gn:admin1_code":"08",
    "gn:asciiname":"Takhtakeran",
    "gn:country_code":"AZ",
    "gn:dem":83,
    "gn:feature_class":"P",
    "gn:feature_code":"PPL",
    "gn:name":"Takhtakeran",
    "gn:population":0,
    "gn:timezone":"Asia/Baku",
    "iso:country":"AZ",
    "name:aze_x_preferred":[
        "Taxtak\u0259ran"
    ],
    "name:aze_x_variant":[
        "Taxtan\u0259k\u0259ran"
    ],
    "wof:name":"Takhtakeran",
    "wof:placetype":"locality"
},
  "geometry": {"coordinates":[48.76249,38.58894],"type":"Point"}
}