{
  "type": "Feature",
  "properties": {
    "gn:admin1_code":"15",
    "gn:asciiname":"Dzhafarly",
    "gn:country_code":"AZ",
    "gn:dem":99,
    "gn:feature_class":"P",
    "gn:feature_code":"PPL",
    "gn:name":"Dzhafarly",
    "gn:population":0,
    "gn:timezone":"Asia/Baku",
    "iso:country":"AZ",
    "name:aze_x_preferred":[
        "C\u0259f\u0259rli"
    ],
    "name:und_x_variant":[
        "Dzhafarli"
    ],
    "wof:name":"Dzhafarly",
    "wof:placetype":"locality"
},
  "geometry": {"coordinates":[48.41554,39.18984],"type":"Point"}
}