{
  "type": "Feature",
  "properties": {
    "gn:admin1_code":"37",
    "gn:asciiname":"Yaqublu",
    "gn:country_code":"AZ",
    "gn:dem":451,
    "gn:feature_class":"P",
    "gn:feature_code":"PPL",
    "gn:name":"Yaqublu",
    "gn:population":0,
    "gn:timezone":"Asia/Baku",
    "iso:country":"AZ",
    "name:aze_x_preferred":[
        "Yaqublu"
    ],
    "name:ita_x_preferred":[
        "Yaqublu"
    ],
    "name:kat_x_preferred":[
        "\u10d8\u10d0\u10e7\u10e3\u10d1\u10da\u10e3"
    ],
    "name:msa_x_preferred":[
        "Yaqublu"
    ],
    "name:rus_x_preferred":[
        "\u042f\u0433\u0443\u0431\u043b\u0443"
    ],
    "name:und_x_variant":[
        "Ashaga Yakublu",
        "Yagublu"
    ],
    "wof:name":"Yaqublu",
    "wof:placetype":"locality"
},
  "geometry": {"coordinates":[47.46135,40.92263],"type":"Point"}
}