{
  "type": "Feature",
  "properties": {
    "gn:admin1_code":"37",
    "gn:asciiname":"Yaqublu",
    "gn:country_code":"AZ",
    "gn:dem":451,
    "gn:feature_class":"P",
    "gn:feature_code":"PPL",
    "gn:name":"Yaqublu",
    "gn:population":0,
    "gn:timezone":"Asia/Baku",
    "iso:country":"AZ",
    "name:und_x_variant":[
        "Ashaga Yakublu",
        "Yagublu",
        "Yaqublu"
    ],
    "wof:name":"Yaqublu",
    "wof:placetype":"locality"
},
  "geometry": {"coordinates":[47.46135,40.92263],"type":"Point"}
}