{
  "type": "Feature",
  "properties": {
    "gn:admin1_code":"24",
    "gn:asciiname":"Sarixanli",
    "gn:country_code":"AZ",
    "gn:dem":7,
    "gn:feature_class":"P",
    "gn:feature_code":"PPL",
    "gn:name":"Sar\u0131xanl\u0131",
    "gn:population":0,
    "gn:timezone":"Asia/Baku",
    "iso:country":"AZ",
    "name:aze_x_preferred":[
        "Sar\u0131xanl\u0131"
    ],
    "name:und_x_variant":[
        "Sarykhanly"
    ],
    "wof:name":"Sarixanli",
    "wof:placetype":"locality"
},
  "geometry": {"coordinates":[47.92274000000001,39.82315],"type":"Point"}
}