{
  "type": "Feature",
  "properties": {
    "gn:admin1_code":"24",
    "gn:asciiname":"Sarixanli",
    "gn:country_code":"AZ",
    "gn:dem":7,
    "gn:feature_class":"P",
    "gn:feature_code":"PPL",
    "gn:name":"Sar\u0131xanl\u0131",
    "gn:population":0,
    "gn:timezone":"Asia/Baku",
    "iso:country":"AZ",
    "name:azb_x_preferred":[
        "\u0633\u0627\u0631\u06cc\u062e\u0627\u0646\u0644\u06cc"
    ],
    "name:aze_x_preferred":[
        "Sar\u0131xanl\u0131"
    ],
    "name:ceb_x_preferred":[
        "Sar\u0131xanl\u0131"
    ],
    "name:ell_x_preferred":[
        "\u03a3\u03b1\u03c1\u03b9\u03c7\u03b1\u03bd\u03bb\u03af"
    ],
    "name:ita_x_preferred":[
        "Sar\u0131xanl\u0131"
    ],
    "name:kat_x_preferred":[
        "\u10e1\u10d0\u10e0\u10d8\u10ee\u10d0\u10dc\u10da\u10d8"
    ],
    "name:msa_x_preferred":[
        "Sar\u0131xanl\u0131"
    ],
    "name:swe_x_preferred":[
        "Sar\u0131xanl\u0131"
    ],
    "name:und_x_variant":[
        "Sarykhanly"
    ],
    "wof:name":"Sarixanli",
    "wof:placetype":"locality"
},
  "geometry": {"coordinates":[47.92274000000001,39.82315],"type":"Point"}
}