{
  "type": "Feature",
  "properties": {
    "gn:admin1_code":"19",
    "gn:asciiname":"Leshker",
    "gn:country_code":"AZ",
    "gn:dem":1372,
    "gn:feature_class":"P",
    "gn:feature_code":"PPL",
    "gn:name":"Leshker",
    "gn:population":0,
    "gn:timezone":"Asia/Baku",
    "iso:country":"AZ",
    "name:und_x_variant":[
        "L\u0259\u015fk\u0259r"
    ],
    "wof:name":"Leshker",
    "wof:placetype":"locality"
},
  "geometry": {"coordinates":[45.68252,40.54445],"type":"Point"}
}