{
  "type": "Feature",
  "properties": {
    "gn:admin1_code":"32",
    "gn:asciiname":"Bedelan",
    "gn:country_code":"AZ",
    "gn:dem":-12,
    "gn:feature_class":"P",
    "gn:feature_code":"PPL",
    "gn:name":"Bedelan",
    "gn:population":0,
    "gn:timezone":"Asia/Baku",
    "iso:country":"AZ",
    "name:aze_x_preferred":[
        "B\u0259d\u0259lan"
    ],
    "name:ceb_x_preferred":[
        "Bedelan"
    ],
    "name:ita_x_preferred":[
        "B\u0259d\u0259lan"
    ],
    "name:msa_x_preferred":[
        "B\u0259d\u0259lan"
    ],
    "name:swe_x_preferred":[
        "Bedelan"
    ],
    "name:und_x_variant":[
        "Bedalan",
        "Bedelan",
        "B\u0259d\u0259lan"
    ],
    "wof:name":"Bedelan",
    "wof:placetype":"locality"
},
  "geometry": {"coordinates":[48.6846,38.95242],"type":"Point"}
}