{
  "type": "Feature",
  "properties": {
    "gn:admin1_code":"45",
    "gn:asciiname":"Beylik",
    "gn:country_code":"AZ",
    "gn:dem":-12,
    "gn:feature_class":"P",
    "gn:feature_code":"PPL",
    "gn:name":"Beylik",
    "gn:population":0,
    "gn:timezone":"Asia/Baku",
    "iso:country":"AZ",
    "name:und_x_variant":[
        "Beilyar",
        "Beylik",
        "B\u0259ylik"
    ],
    "wof:name":"Beylik",
    "wof:placetype":"locality"
},
  "geometry": {"coordinates":[48.42891,39.96361],"type":"Point"}
}