{
  "type": "Feature",
  "properties": {
    "gn:admin1_code":"35",
    "gn:admin2_code":"8014931.0",
    "gn:asciiname":"Tazakend",
    "gn:country_code":"AZ",
    "gn:dem":1108,
    "gn:feature_class":"P",
    "gn:feature_code":"PPL",
    "gn:name":"Tazakend",
    "gn:population":0,
    "gn:timezone":"Asia/Baku",
    "iso:country":"AZ",
    "name:aze_x_preferred":[
        "T\u0259z\u0259k\u0259nd"
    ],
    "name:ceb_x_preferred":[
        "Tazakend"
    ],
    "name:swe_x_preferred":[
        "Tazakend"
    ],
    "wof:name":"Tazakend",
    "wof:placetype":"locality"
},
  "geometry": {"coordinates":[45.29906,39.39385],"type":"Point"}
}