{
  "type": "Feature",
  "properties": {
    "gn:admin1_code":"32",
    "gn:asciiname":"Taza Alvady",
    "gn:country_code":"AZ",
    "gn:dem":5,
    "gn:feature_class":"P",
    "gn:feature_code":"PPL",
    "gn:name":"Taza Alvady",
    "gn:population":0,
    "gn:timezone":"Asia/Baku",
    "iso:country":"AZ",
    "name:azb_x_preferred":[
        "\u062a\u0632\u0647 \u0622\u0644\u0648\u0627\u062f\u06cc"
    ],
    "name:aze_x_preferred":[
        "T\u0259z\u0259 Alvad\u0131"
    ],
    "name:ceb_x_preferred":[
        "Taza Alvady"
    ],
    "name:fas_x_preferred":[
        "\u062a\u0632\u0647 \u0622\u0644\u0648\u062f\u06cc"
    ],
    "name:ita_x_preferred":[
        "T\u0259z\u0259 Alvad\u0131"
    ],
    "name:msa_x_preferred":[
        "T\u0259z\u0259 Alvad\u0131"
    ],
    "name:swe_x_preferred":[
        "Taza Alvady"
    ],
    "name:und_x_variant":[
        "Novyye Alvady",
        "Taza Alvady",
        "T\u0259z\u0259 Alvad\u0131\u0259"
    ],
    "wof:name":"Taza Alvady",
    "wof:placetype":"locality"
},
  "geometry": {"coordinates":[48.60463,39.08789],"type":"Point"}
}