{
  "type": "Feature",
  "properties": {
    "gn:admin1_code":"16",
    "gn:asciiname":"Astaf",
    "gn:country_code":"AZ",
    "gn:dem":1624,
    "gn:feature_class":"P",
    "gn:feature_code":"PPL",
    "gn:name":"Astaf",
    "gn:population":0,
    "gn:timezone":"Asia/Baku",
    "iso:country":"AZ",
    "name:azb_x_preferred":[
        "\u0622\u0633\u062a\u0627\u0641"
    ],
    "name:aze_x_preferred":[
        "Astaf"
    ],
    "name:ceb_x_preferred":[
        "Astaf"
    ],
    "name:fas_x_preferred":[
        "\u0627\u0633\u062a\u0627\u0641"
    ],
    "name:hye_x_preferred":[
        "\u0540\u0561\u0581\u057f\u0561\u0583"
    ],
    "name:ita_x_preferred":[
        "Astaf"
    ],
    "name:kat_x_preferred":[
        "\u10d0\u10e1\u10d7\u10d0\u10e4\u10d8"
    ],
    "name:msa_x_preferred":[
        "Astaf"
    ],
    "name:swe_x_preferred":[
        "Astaf"
    ],
    "wof:name":"Astaf",
    "wof:placetype":"locality"
},
  "geometry": {"coordinates":[45.86319,40.46745],"type":"Point"}
}