{
  "type": "Feature",
  "properties": {
    "gn:admin1_code":"29",
    "gn:asciiname":"Kenaramesha",
    "gn:country_code":"AZ",
    "gn:dem":-17,
    "gn:feature_class":"P",
    "gn:feature_code":"PPL",
    "gn:name":"Kenaramesha",
    "gn:population":0,
    "gn:timezone":"Asia/Baku",
    "iso:country":"AZ",
    "name:und_x_variant":[
        "K\u0259nar\u0259me\u015f\u0259"
    ],
    "wof:name":"Kenaramesha",
    "wof:placetype":"locality"
},
  "geometry": {"coordinates":[48.86428,38.70032],"type":"Point"}
}