{
  "type": "Feature",
  "properties": {
    "gn:admin1_code":"69",
    "gn:asciiname":"Mirza Gasanly",
    "gn:country_code":"AZ",
    "gn:dem":488,
    "gn:feature_class":"P",
    "gn:feature_code":"PPL",
    "gn:name":"Mirza Gasanly",
    "gn:population":0,
    "gn:timezone":"Asia/Baku",
    "iso:country":"AZ",
    "name:aze_x_preferred":[
        "Mirz\u0259h\u0259s\u0259nli"
    ],
    "name:hye_x_preferred":[
        "Vanatun"
    ],
    "name:hye_x_variant":[
        "\u054e\u0561\u0576\u0561\u057f\u0578\u0582\u0576"
    ],
    "name:rus_x_preferred":[
        "\u041c\u0438\u0440\u0437\u0430\u0433\u0430\u0441\u0430\u043d\u043b\u0438"
    ],
    "name:und_x_variant":[
        "Mirzagasanli"
    ],
    "wof:name":"Mirza Gasanly",
    "wof:placetype":"locality"
},
  "geometry": {"coordinates":[46.64175,39.15424],"type":"Point"}
}