{
  "type": "Feature",
  "properties": {
    "gn:admin1_code":"12",
    "gn:asciiname":"Milskii",
    "gn:country_code":"AZ",
    "gn:dem":4,
    "gn:feature_class":"P",
    "gn:feature_code":"PPL",
    "gn:name":"Milskii",
    "gn:population":0,
    "gn:timezone":"Asia/Baku",
    "iso:country":"AZ",
    "name:aze_x_preferred":[
        "T\u00fcrkl\u0259r"
    ],
    "name:und_x_variant":[
        "Milskii Sovkhoz Sem\u2019",
        "Mil\u2019skaya Gruppa Sovkhozov",
        "Tyurklyar"
    ],
    "wof:name":"Milskii",
    "wof:placetype":"locality"
},
  "geometry": {"coordinates":[47.79077,39.80469],"type":"Point"}
}