{
  "type": "Feature",
  "properties": {
    "gn:admin1_code":"24",
    "gn:asciiname":"Telisli",
    "gn:country_code":"AZ",
    "gn:dem":-10,
    "gn:feature_class":"P",
    "gn:feature_code":"PPL",
    "gn:name":"Teli\u015fli",
    "gn:population":0,
    "gn:timezone":"Asia/Baku",
    "iso:country":"AZ",
    "name:und_x_variant":[
        "Temishli",
        "Teli\u015fli",
        "Telishli"
    ],
    "wof:name":"Telisli",
    "wof:placetype":"locality"
},
  "geometry": {"coordinates":[48.08235,40.11231],"type":"Point"}
}