{
  "type": "Feature",
  "properties": {
    "gn:admin1_code":"24",
    "gn:asciiname":"Telisli",
    "gn:country_code":"AZ",
    "gn:dem":-10,
    "gn:feature_class":"P",
    "gn:feature_code":"PPL",
    "gn:name":"Teli\u015fli",
    "gn:population":0,
    "gn:timezone":"Asia/Baku",
    "iso:country":"AZ",
    "name:azb_x_preferred":[
        "\u062a\u0644\u06cc\u0634\u200c\u0644\u06cc"
    ],
    "name:aze_x_preferred":[
        "Teli\u015fli"
    ],
    "name:ceb_x_preferred":[
        "Teli\u015fli"
    ],
    "name:ita_x_preferred":[
        "Teli\u015fli"
    ],
    "name:kat_x_preferred":[
        "\u10d7\u10d4\u10da\u10d8\u10e8\u10da\u10d8"
    ],
    "name:msa_x_preferred":[
        "Teli\u015fli"
    ],
    "name:swe_x_preferred":[
        "Teli\u015fli"
    ],
    "name:und_x_variant":[
        "Temishli",
        "Teli\u015fli",
        "Telishli"
    ],
    "wof:name":"Telisli",
    "wof:placetype":"locality"
},
  "geometry": {"coordinates":[48.08235,40.11231],"type":"Point"}
}