{
  "type": "Feature",
  "properties": {
    "gn:admin1_code":"15",
    "gn:asciiname":"Teklya",
    "gn:country_code":"AZ",
    "gn:dem":131,
    "gn:feature_class":"P",
    "gn:feature_code":"PPL",
    "gn:name":"Teklya",
    "gn:population":0,
    "gn:timezone":"Asia/Baku",
    "iso:country":"AZ",
    "name:und_x_variant":[
        "T\u0259kl\u0259"
    ],
    "wof:name":"Teklya",
    "wof:placetype":"locality"
},
  "geometry": {"coordinates":[48.34684,39.25679],"type":"Point"}
}