{
  "type": "Feature",
  "properties": {
    "gn:admin1_code":"21",
    "gn:asciiname":"Qazaxlar",
    "gn:country_code":"AZ",
    "gn:dem":176,
    "gn:feature_class":"P",
    "gn:feature_code":"PPL",
    "gn:name":"Qazaxlar",
    "gn:population":0,
    "gn:timezone":"Asia/Baku",
    "iso:country":"AZ",
    "name:rus_x_preferred":[
        "\u041a\u0430\u0437\u0430\u0445\u043b\u0430\u0440"
    ],
    "name:und_x_variant":[
        "Kazakhyar",
        "Kazakhlar",
        "Qazaxlar"
    ],
    "wof:name":"Qazaxlar",
    "wof:placetype":"locality"
},
  "geometry": {"coordinates":[46.6801,40.66079000000001],"type":"Point"}
}