{
  "type": "Feature",
  "properties": {
    "gn:admin1_code":"57",
    "gn:asciiname":"Qiziloba",
    "gn:country_code":"AZ",
    "gn:dem":218,
    "gn:feature_class":"P",
    "gn:feature_code":"PPL",
    "gn:name":"Q\u0131z\u0131loba",
    "gn:population":0,
    "gn:timezone":"Asia/Baku",
    "iso:country":"AZ",
    "name:aze_x_preferred":[
        "Q\u0131z\u0131loba"
    ],
    "name:aze_x_variant":[
        "Qarmirovan",
        "Q\u0131rm\u0131z\u0131k\u0259nd"
    ],
    "name:hye_x_preferred":[
        "Karmiravan"
    ],
    "name:hye_x_variant":[
        "\u053f\u0561\u0580\u0574\u056b\u0580\u0561\u057e\u0561\u0576"
    ],
    "name:ita_x_preferred":[
        "Kyrmyzykena"
    ],
    "name:msa_x_preferred":[
        "Kyrmyzykena"
    ],
    "name:rus_x_preferred":[
        "\u041a\u0430\u0440\u043c\u0438\u0440\u0430\u0432\u0430\u043d"
    ],
    "wof:name":"Qiziloba",
    "wof:placetype":"locality"
},
  "geometry": {"coordinates":[46.94378,40.26166],"type":"Point"}
}