{
  "type": "Feature",
  "properties": {
    "gn:admin1_code":"23",
    "gn:asciiname":"Khila Mirzali",
    "gn:country_code":"AZ",
    "gn:dem":-22,
    "gn:feature_class":"P",
    "gn:feature_code":"PPL",
    "gn:name":"Khila Mirzali",
    "gn:population":0,
    "gn:timezone":"Asia/Baku",
    "iso:country":"AZ",
    "name:aze_x_preferred":[
        "\u018fl\u0259tli"
    ],
    "name:und_x_variant":[
        "Alyatli"
    ],
    "wof:name":"Khila Mirzali",
    "wof:placetype":"locality"
},
  "geometry": {"coordinates":[48.81733,40.01154],"type":"Point"}
}