{
  "type": "Feature",
  "properties": {
    "gn:admin1_code":"32",
    "gn:asciiname":"Gariblyar",
    "gn:country_code":"AZ",
    "gn:dem":83,
    "gn:feature_class":"P",
    "gn:feature_code":"PPL",
    "gn:name":"Gariblyar",
    "gn:population":0,
    "gn:timezone":"Asia/Baku",
    "iso:country":"AZ",
    "name:und_x_variant":[
        "Gariblar",
        "Q\u0259ribl\u0259r"
    ],
    "wof:name":"Gariblyar",
    "wof:placetype":"locality"
},
  "geometry": {"coordinates":[48.59534,38.99814],"type":"Point"}
}