{
  "type": "Feature",
  "properties": {
    "gn:admin1_code":"32",
    "gn:asciiname":"Gariblyar",
    "gn:country_code":"AZ",
    "gn:dem":83,
    "gn:feature_class":"P",
    "gn:feature_code":"PPL",
    "gn:name":"Gariblyar",
    "gn:population":0,
    "gn:timezone":"Asia/Baku",
    "iso:country":"AZ",
    "name:azb_x_preferred":[
        "\u063a\u0631\u06cc\u0628\u0644\u0631"
    ],
    "name:aze_x_preferred":[
        "Q\u0259ribl\u0259r"
    ],
    "name:ceb_x_preferred":[
        "Gariblyar"
    ],
    "name:fas_x_preferred":[
        "\u063a\u0631\u06cc\u0628\u0644\u0631"
    ],
    "name:ita_x_preferred":[
        "Q\u0259ribl\u0259r"
    ],
    "name:msa_x_preferred":[
        "Q\u0259ribl\u0259r"
    ],
    "name:swe_x_preferred":[
        "Gariblyar"
    ],
    "name:und_x_variant":[
        "Gariblar"
    ],
    "wof:name":"Gariblyar",
    "wof:placetype":"locality"
},
  "geometry": {"coordinates":[48.59534,38.99814],"type":"Point"}
}