{
  "type": "Feature",
  "properties": {
    "gn:admin1_code":"42",
    "gn:asciiname":"Amsar",
    "gn:country_code":"AZ",
    "gn:dem":587,
    "gn:feature_class":"P",
    "gn:feature_code":"PPL",
    "gn:name":"Amsar",
    "gn:population":0,
    "gn:timezone":"Asia/Baku",
    "iso:country":"AZ",
    "name:eng_x_preferred":[
        "Amsar"
    ],
    "name:rus_x_preferred":[
        "\u0410\u043c\u0441\u0430\u0440"
    ],
    "wof:name":"Amsar",
    "wof:placetype":"locality"
},
  "geometry": {"coordinates":[48.5403,41.32892],"type":"Point"}
}