{
  "type": "Feature",
  "properties": {
    "gn:admin1_code":"51",
    "gn:asciiname":"Qaraqocali",
    "gn:country_code":"AZ",
    "gn:dem":563,
    "gn:feature_class":"P",
    "gn:feature_code":"PPL",
    "gn:name":"Qaraqocal\u0131",
    "gn:population":0,
    "gn:timezone":"Asia/Baku",
    "iso:country":"AZ",
    "name:und_x_variant":[
        "Karagodzhaly",
        "Qaraqocal\u0131"
    ],
    "wof:name":"Qaraqocali",
    "wof:placetype":"locality"
},
  "geometry": {"coordinates":[46.04591,40.71641],"type":"Point"}
}