{
  "type": "Feature",
  "properties": {
    "gn:admin1_code":"09",
    "gn:asciiname":"Kitly",
    "gn:country_code":"AZ",
    "gn:dem":10,
    "gn:feature_class":"P",
    "gn:feature_code":"PPL",
    "gn:name":"Kitly",
    "gn:population":0,
    "gn:timezone":"Asia/Baku",
    "iso:country":"AZ",
    "name:aze_x_preferred":[
        "Ke\u015fl\u0259"
    ],
    "name:und_x_variant":[
        "Keshly",
        "Kishly",
        "Kishty",
        "Kishlya",
        "Keshlya",
        "Kitly",
        "K\u0259\u015fl\u0259"
    ],
    "wof:name":"Kitly",
    "wof:placetype":"locality"
},
  "geometry": {"coordinates":[49.89861,40.39778],"type":"Point"}
}