{
  "type": "Feature",
  "properties": {
    "gn:admin1_code":"67",
    "gn:asciiname":"Kebikeru",
    "gn:country_code":"AZ",
    "gn:dem":49,
    "gn:feature_class":"P",
    "gn:feature_code":"PPL",
    "gn:name":"Kebikeru",
    "gn:population":0,
    "gn:timezone":"Asia/Baku",
    "iso:country":"AZ",
    "name:aze_x_preferred":[
        "K\u00f6v\u0259r"
    ],
    "name:ita_x_preferred":[
        "Kebikeru"
    ],
    "name:kat_x_preferred":[
        "\u10e5\u10d4\u10d1\u10d8\u10e5\u10d4\u10e0\u10e3"
    ],
    "name:msa_x_preferred":[
        "Kebikeru"
    ],
    "name:rus_x_preferred":[
        "K\u00ebvar"
    ],
    "wof:name":"Kebikeru",
    "wof:placetype":"locality"
},
  "geometry": {"coordinates":[47.1132,40.50461],"type":"Point"}
}