{
  "type": "Feature",
  "properties": {
    "gn:admin1_code":"50",
    "gn:asciiname":"Zarat-Kheyberi",
    "gn:country_code":"AZ",
    "gn:dem":1711,
    "gn:feature_class":"P",
    "gn:feature_code":"PPL",
    "gn:name":"Zarat-Kheyberi",
    "gn:population":0,
    "gn:timezone":"Asia/Baku",
    "iso:country":"AZ",
    "name:aze_x_preferred":[
        "Zarat Xeyb\u0259ri"
    ],
    "name:eng_x_preferred":[
        "Zarat Xeyt\u01ddri"
    ],
    "name:kat_x_preferred":[
        "\u10d6\u10d0\u10e0\u10d0\u10d7-\u10ee\u10d4\u10d8\u10d1\u10d0\u10e0\u10d8"
    ],
    "name:msa_x_preferred":[
        "Zarat Xeyb\u0259ri"
    ],
    "name:rus_x_preferred":[
        "\u0417\u0430\u0440\u0430\u0442 \u0425\u0435\u0439\u0431\u0435\u0440\u0438"
    ],
    "name:und_x_variant":[
        "Zarat Xeyt\u0259ri"
    ],
    "wof:name":"Zarat-Kheyberi",
    "wof:placetype":"locality"
},
  "geometry": {"coordinates":[48.54397,40.90051],"type":"Point"}
}