{
  "type": "Feature",
  "properties": {
    "gn:admin1_code":"38",
    "gn:asciiname":"Sarihacalli",
    "gn:country_code":"AZ",
    "gn:dem":337,
    "gn:feature_class":"P",
    "gn:feature_code":"PPL",
    "gn:name":"Sar\u0131hacall\u0131",
    "gn:population":0,
    "gn:timezone":"Asia/Baku",
    "iso:country":"AZ",
    "name:aze_x_preferred":[
        "Sar\u0131 Hac\u0131l\u0131"
    ],
    "name:ita_x_preferred":[
        "Sar\u0131hacall\u0131"
    ],
    "name:kat_x_preferred":[
        "\u10e1\u10d0\u10e0\u10d8-\u10f0\u10d0\u10ef\u10d8\u10da\u10d8"
    ],
    "name:lez_x_preferred":[
        "\u0421\u0430\u0440\u044b \u0413\u044c\u0430\u0436\u0438\u043b\u044b"
    ],
    "name:msa_x_preferred":[
        "Sar\u0131hacall\u0131"
    ],
    "name:und_x_variant":[
        "Sargadzhyly",
        "Sari-Gadzhili",
        "Sarygadzhally"
    ],
    "wof:name":"Sarihacalli",
    "wof:placetype":"locality"
},
  "geometry": {"coordinates":[47.65821,40.83798],"type":"Point"}
}