{
  "type": "Feature",
  "properties": {
    "gn:admin1_code":"38",
    "gn:asciiname":"Sarihacalli",
    "gn:country_code":"AZ",
    "gn:dem":337,
    "gn:feature_class":"P",
    "gn:feature_code":"PPL",
    "gn:name":"Sar\u0131hacall\u0131",
    "gn:population":0,
    "gn:timezone":"Asia/Baku",
    "iso:country":"AZ",
    "name:und_x_variant":[
        "Sargadzhyly",
        "Sari-Gadzhili",
        "Sarygadzhally",
        "Sar\u0131hacall\u0131"
    ],
    "wof:name":"Sarihacalli",
    "wof:placetype":"locality"
},
  "geometry": {"coordinates":[47.65821,40.83798],"type":"Point"}
}