{
  "type": "Feature",
  "properties": {
    "gn:admin1_code":"50",
    "gn:asciiname":"Ovculu",
    "gn:country_code":"AZ",
    "gn:dem":156,
    "gn:feature_class":"P",
    "gn:feature_code":"PPL",
    "gn:name":"Ov\u00e7ulu",
    "gn:population":0,
    "gn:timezone":"Asia/Baku",
    "iso:country":"AZ",
    "name:und_x_variant":[
        "Ovchulu",
        "Ov\u00e7ulu"
    ],
    "wof:name":"Ovculu",
    "wof:placetype":"locality"
},
  "geometry": {"coordinates":[48.60232,40.44835],"type":"Point"}
}