{
  "type": "Feature",
  "properties": {
    "gn:admin1_code":"28",
    "gn:asciiname":"Aganus",
    "gn:country_code":"AZ",
    "gn:dem":1310,
    "gn:feature_class":"P",
    "gn:feature_code":"PPL",
    "gn:name":"A\u011fanus",
    "gn:population":0,
    "gn:timezone":"Asia/Baku",
    "iso:country":"AZ",
    "name:aze_x_preferred":[
        "A\u011fanus"
    ],
    "name:hye_x_preferred":[
        "\u0531\u0572\u0561\u0576\u0578\u0582\u057d"
    ],
    "name:hye_x_variant":[
        "Aghanus"
    ],
    "name:rus_x_preferred":[
        "\u0410\u0433\u0430\u043d\u0443\u0441"
    ],
    "name:und_x_variant":[
        "Aghanus",
        "Aganus"
    ],
    "wof:name":"Aganus",
    "wof:placetype":"locality"
},
  "geometry": {"coordinates":[46.58759000000001,39.62834],"type":"Point"}
}