{
  "type": "Feature",
  "properties": {
    "gn:admin1_code":"71",
    "gn:asciiname":"Birinci Alicanli",
    "gn:country_code":"AZ",
    "gn:dem":2,
    "gn:feature_class":"P",
    "gn:feature_code":"PPL",
    "gn:name":"Birinci Al\u0131canl\u0131",
    "gn:population":0,
    "gn:timezone":"Asia/Baku",
    "iso:country":"AZ",
    "name:azb_x_preferred":[
        "\u0628\u06cc\u0631\u06cc\u0646\u062c\u06cc \u0639\u0644\u06cc\u062c\u0627\u0646\u0644\u06cc"
    ],
    "name:aze_x_preferred":[
        "Birinci Al\u0131canl\u0131"
    ],
    "name:aze_x_variant":[
        "Birinci \u018flicanl\u0131"
    ],
    "name:ceb_x_preferred":[
        "Birinci Al\u0131canl\u0131"
    ],
    "name:ita_x_preferred":[
        "Birinci \u018flicanl\u0131"
    ],
    "name:kat_x_preferred":[
        "\u10d1\u10d8\u10e0\u10d8\u10dc\u10ef\u10d8-\u10d0\u10da\u10d8\u10ef\u10d0\u10dc\u10da\u10d8"
    ],
    "name:msa_x_preferred":[
        "Birinci \u018flicanl\u0131"
    ],
    "name:swe_x_preferred":[
        "Birinci Al\u0131canl\u0131"
    ],
    "name:und_x_variant":[
        "Alydzhanly Pervoye",
        "Alidzhanly Pervyye",
        "Birinci Al\u0131ncanl\u0131",
        "Alydzhanly Pervyy",
        "Birinci \u018flicanl\u0131"
    ],
    "wof:name":"Birinci Alicanli",
    "wof:placetype":"locality"
},
  "geometry": {"coordinates":[47.59708,40.33639],"type":"Point"}
}