{
  "type": "Feature",
  "properties": {
    "gn:admin1_code":"05",
    "gn:asciiname":"Boyuk Kasik",
    "gn:country_code":"AZ",
    "gn:dem":268,
    "gn:feature_class":"P",
    "gn:feature_code":"PPL",
    "gn:name":"B\u00f6y\u00fck K\u0259sik",
    "gn:population":0,
    "gn:timezone":"Asia/Baku",
    "iso:country":"AZ",
    "name:azb_x_preferred":[
        "\u0628\u0624\u06cc\u0648\u06a9 \u06a9\u0633\u06cc\u06a9"
    ],
    "name:aze_x_preferred":[
        "B\u00f6y\u00fck K\u0259sik"
    ],
    "name:ceb_x_preferred":[
        "B\u00f6y\u00fck K\u0259sik"
    ],
    "name:hye_x_preferred":[
        "\u0532\u0578\u0575\u0578\u0582\u0584 \u0554\u0561\u057d\u056b\u0584"
    ],
    "name:ita_x_preferred":[
        "B\u00f6y\u00fck K\u0259sik"
    ],
    "name:kat_x_preferred":[
        "\u10d1\u10d8\u10dd\u10d8\u10e3\u10e5\u10d8-\u10e5\u10d0\u10e1\u10d8\u10e5\u10d8"
    ],
    "name:msa_x_preferred":[
        "B\u00f6y\u00fck K\u0259sik"
    ],
    "name:rus_x_preferred":[
        "B\u00ebyuk-Kyasik"
    ],
    "name:swe_x_preferred":[
        "B\u00f6y\u00fck K\u0259sik"
    ],
    "wof:name":"Boyuk Kasik",
    "wof:placetype":"locality"
},
  "geometry": {"coordinates":[45.18762,41.39022],"type":"Point"}
}