{
  "type": "Feature",
  "properties": {
    "gn:admin1_code":"05",
    "gn:asciiname":"Boyuk Kasik",
    "gn:country_code":"AZ",
    "gn:dem":268,
    "gn:feature_class":"P",
    "gn:feature_code":"PPL",
    "gn:name":"B\u00f6y\u00fck K\u0259sik",
    "gn:population":0,
    "gn:timezone":"Asia/Baku",
    "iso:country":"AZ",
    "name:rus_x_preferred":[
        "B\u00ebyuk-Kyasik"
    ],
    "name:und_x_variant":[
        "B\u00f6y\u00fck K\u0259sik"
    ],
    "wof:name":"Boyuk Kasik",
    "wof:placetype":"locality"
},
  "geometry": {"coordinates":[45.18762,41.39022],"type":"Point"}
}