{
  "type": "Feature",
  "properties": {
    "gn:admin1_code":"11",
    "gn:asciiname":"Yerevanly",
    "gn:country_code":"AZ",
    "gn:dem":153,
    "gn:feature_class":"P",
    "gn:feature_code":"PPL",
    "gn:name":"Yerevanly",
    "gn:population":0,
    "gn:timezone":"Asia/Baku",
    "iso:country":"AZ",
    "name:aze_x_preferred":[
        "Yerevanly"
    ],
    "name:aze_x_variant":[
        "Yerevanl\u0131",
        "\u0130r\u0259vanl\u0131"
    ],
    "name:und_x_variant":[
        "Erevanly"
    ],
    "wof:name":"Yerevanly",
    "wof:placetype":"locality"
},
  "geometry": {"coordinates":[47.02627,40.33397],"type":"Point"}
}