{
  "type": "Feature",
  "properties": {
    "gn:admin1_code":"12",
    "gn:asciiname":"Asiqalilar",
    "gn:country_code":"AZ",
    "gn:dem":23,
    "gn:feature_class":"P",
    "gn:feature_code":"PPL",
    "gn:name":"A\u015f\u0131qal\u0131lar",
    "gn:population":0,
    "gn:timezone":"Asia/Baku",
    "iso:country":"AZ",
    "name:aze_x_preferred":[
        "A\u015f\u0131qal\u0131lar"
    ],
    "name:aze_x_variant":[
        "A\u015fqalar"
    ],
    "name:und_x_variant":[
        "Yeddybugukskiy",
        "Gadzhi-Kharrar",
        "Ashkallar",
        "Ashgalar",
        "Ashygalylar"
    ],
    "wof:name":"Asiqalilar",
    "wof:placetype":"locality"
},
  "geometry": {"coordinates":[47.8323,39.70113],"type":"Point"}
}