{
  "type": "Feature",
  "properties": {
    "gn:admin1_code":"12",
    "gn:asciiname":"Asiqalilar",
    "gn:country_code":"AZ",
    "gn:dem":23,
    "gn:feature_class":"P",
    "gn:feature_code":"PPL",
    "gn:name":"A\u015f\u0131qal\u0131lar",
    "gn:population":0,
    "gn:timezone":"Asia/Baku",
    "iso:country":"AZ",
    "name:azb_x_preferred":[
        "\u0622\u0634\u06cc\u0642\u0627\u0644\u06cc\u0644\u0627\u0631"
    ],
    "name:aze_x_preferred":[
        "A\u015f\u0131qal\u0131lar"
    ],
    "name:aze_x_variant":[
        "A\u015fqalar"
    ],
    "name:ceb_x_preferred":[
        "A\u015f\u0131qal\u0131lar"
    ],
    "name:ita_x_preferred":[
        "A\u015f\u0131qal\u0131lar"
    ],
    "name:kat_x_preferred":[
        "\u10d0\u10e8\u10d8\u10d2\u10d0\u10da\u10d8\u10da\u10d0\u10e0\u10d8"
    ],
    "name:msa_x_preferred":[
        "A\u015f\u0131qal\u0131lar"
    ],
    "name:swe_x_preferred":[
        "A\u015f\u0131qal\u0131lar"
    ],
    "name:und_x_variant":[
        "Yeddybugukskiy",
        "Gadzhi-Kharrar",
        "Ashkallar",
        "Ashgalar",
        "Ashygalylar"
    ],
    "wof:name":"Asiqalilar",
    "wof:placetype":"locality"
},
  "geometry": {"coordinates":[47.8323,39.70113],"type":"Point"}
}