{
  "type": "Feature",
  "properties": {
    "gn:admin1_code":"32",
    "gn:asciiname":"Tambalau",
    "gn:country_code":"AZ",
    "gn:dem":393,
    "gn:feature_class":"P",
    "gn:feature_code":"PPL",
    "gn:name":"Tambalau",
    "gn:population":0,
    "gn:timezone":"Asia/Baku",
    "iso:country":"AZ",
    "name:und_x_variant":[
        "D\u0259mb\u0259lov",
        "Dambalov"
    ],
    "wof:name":"Tambalau",
    "wof:placetype":"locality"
},
  "geometry": {"coordinates":[48.53274,38.97843],"type":"Point"}
}