{
  "type": "Feature",
  "properties": {
    "gn:admin1_code":"23",
    "gn:asciiname":"Ikinci Udullu",
    "gn:country_code":"AZ",
    "gn:dem":228,
    "gn:feature_class":"P",
    "gn:feature_code":"PPL",
    "gn:name":"\u0130kinci Udullu",
    "gn:population":0,
    "gn:timezone":"Asia/Baku",
    "iso:country":"AZ",
    "name:aze_x_preferred":[
        "\u0130kinci Udullu"
    ],
    "name:ceb_x_preferred":[
        "\u0130kinci Udullu"
    ],
    "name:ita_x_preferred":[
        "\u0130kinci Udullu"
    ],
    "name:msa_x_preferred":[
        "\u0130kinci Udullu"
    ],
    "name:rus_x_preferred":[
        "\u0423\u0434\u0443\u043b\u043b\u0443 \u0412\u0442\u043e\u0440\u043e\u0435"
    ],
    "name:swe_x_preferred":[
        "\u0130kinci Udullu"
    ],
    "name:und_x_variant":[
        "Dzhangyan-Udulu",
        "Udullu Vtoroye",
        "Dzhankend",
        "Uduli Vtoryye"
    ],
    "wof:name":"Ikinci Udullu",
    "wof:placetype":"locality"
},
  "geometry": {"coordinates":[48.84145,40.30888],"type":"Point"}
}