{
  "type": "Feature",
  "properties": {
    "gn:admin1_code":"23",
    "gn:asciiname":"Ikinci Udullu",
    "gn:country_code":"AZ",
    "gn:dem":228,
    "gn:feature_class":"P",
    "gn:feature_code":"PPL",
    "gn:name":"\u0130kinci Udullu",
    "gn:population":0,
    "gn:timezone":"Asia/Baku",
    "iso:country":"AZ",
    "name:und_x_variant":[
        "Dzhangyan-Udulu",
        "Udullu Vtoroye",
        "Dzhankend",
        "Uduli Vtoryye",
        "\u0130kinci Udullu"
    ],
    "wof:name":"Ikinci Udullu",
    "wof:placetype":"locality"
},
  "geometry": {"coordinates":[48.84145,40.30888],"type":"Point"}
}