{
  "type": "Feature",
  "properties": {
    "gn:admin1_code":"35",
    "gn:admin2_code":"7669114.0",
    "gn:asciiname":"Yeniyol",
    "gn:country_code":"AZ",
    "gn:dem":960,
    "gn:feature_class":"P",
    "gn:feature_code":"PPL",
    "gn:name":"Yeniyol",
    "gn:population":0,
    "gn:timezone":"Asia/Baku",
    "iso:country":"AZ",
    "name:azb_x_preferred":[
        "\u0645\u062d\u0645\u062f\u0631\u0636\u0627\u062f\u06cc\u0632\u0647"
    ],
    "name:aze_x_preferred":[
        "Yeniyol"
    ],
    "name:aze_x_variant":[
        "M\u0259mm\u0259drza Diz\u0259"
    ],
    "name:fas_x_preferred":[
        "\u0645\u062d\u0645\u062f\u0631\u0636\u0627\u062f\u06cc\u0632\u0647"
    ],
    "name:hye_x_preferred":[
        "\u0535\u0576\u056b\u056b\u056c"
    ],
    "name:ita_x_preferred":[
        "M\u0259mm\u0259drza Diz\u0259"
    ],
    "name:kat_x_preferred":[
        "\u10db\u10d0\u10db\u10d4\u10d3\u10e0\u10d6\u10d0-\u10d3\u10d8\u10d6\u10d0"
    ],
    "name:msa_x_preferred":[
        "M\u0259mm\u0259drza Diz\u0259"
    ],
    "name:rus_x_preferred":[
        "Yeniy\u00ebl"
    ],
    "wof:name":"Yeniyol",
    "wof:placetype":"locality"
},
  "geometry": {"coordinates":[45.46037000000001,39.28989],"type":"Point"}
}