{
  "type": "Feature",
  "properties": {
    "gn:admin1_code":"35",
    "gn:admin2_code":"7669114.0",
    "gn:asciiname":"Yeniyol",
    "gn:country_code":"AZ",
    "gn:dem":960,
    "gn:feature_class":"P",
    "gn:feature_code":"PPL",
    "gn:name":"Yeniyol",
    "gn:population":0,
    "gn:timezone":"Asia/Baku",
    "iso:country":"AZ",
    "name:aze_x_preferred":[
        "Yeniyol"
    ],
    "name:aze_x_variant":[
        "M\u0259mm\u0259drza Diz\u0259"
    ],
    "name:rus_x_preferred":[
        "Yeniy\u00ebl"
    ],
    "wof:name":"Yeniyol",
    "wof:placetype":"locality"
},
  "geometry": {"coordinates":[45.46037000000001,39.28989],"type":"Point"}
}