{
  "type": "Feature",
  "properties": {
    "gn:admin1_code":"32",
    "gn:asciiname":"Sarchuvar",
    "gn:country_code":"AZ",
    "gn:dem":-21,
    "gn:feature_class":"P",
    "gn:feature_code":"PPL",
    "gn:name":"Sarchuvar",
    "gn:population":0,
    "gn:timezone":"Asia/Baku",
    "iso:country":"AZ",
    "name:azb_x_preferred":[
        "\u0633\u0631\u0686\u0648\u0648\u0627\u0631"
    ],
    "name:aze_x_preferred":[
        "C\u0259r\u00e7uvar"
    ],
    "name:aze_x_variant":[
        "S\u0259r\u00e7uvar"
    ],
    "name:ceb_x_preferred":[
        "Sarchuvar"
    ],
    "name:fas_x_preferred":[
        "\u0633\u0631\u0686\u0648\u0627\u0631"
    ],
    "name:ita_x_preferred":[
        "S\u0259r\u00e7uvar"
    ],
    "name:msa_x_preferred":[
        "S\u0259r\u00e7uvar"
    ],
    "name:swe_x_preferred":[
        "Sarchuvar"
    ],
    "wof:name":"Sarchuvar",
    "wof:placetype":"locality"
},
  "geometry": {"coordinates":[48.74877,38.96513],"type":"Point"}
}