{
  "type": "Feature",
  "properties": {
    "gn:admin1_code":"32",
    "gn:asciiname":"Sarchuvar",
    "gn:country_code":"AZ",
    "gn:dem":-21,
    "gn:feature_class":"P",
    "gn:feature_code":"PPL",
    "gn:name":"Sarchuvar",
    "gn:population":0,
    "gn:timezone":"Asia/Baku",
    "iso:country":"AZ",
    "name:aze_x_preferred":[
        "C\u0259r\u00e7uvar"
    ],
    "name:und_x_variant":[
        "S\u0259r\u00e7uvar"
    ],
    "wof:name":"Sarchuvar",
    "wof:placetype":"locality"
},
  "geometry": {"coordinates":[48.74877,38.96513],"type":"Point"}
}