{
  "type": "Feature",
  "properties": {
    "gn:admin1_code":"14",
    "gn:asciiname":"Isaqli",
    "gn:country_code":"AZ",
    "gn:dem":967,
    "gn:feature_class":"P",
    "gn:feature_code":"PPL",
    "gn:name":"\u0130saql\u0131",
    "gn:population":0,
    "gn:timezone":"Asia/Baku",
    "iso:country":"AZ",
    "name:azb_x_preferred":[
        "\u0627\u06cc\u0633\u062d\u0627\u0642\u200c\u0644\u06cc"
    ],
    "name:aze_x_preferred":[
        "\u0130saql\u0131"
    ],
    "name:hye_x_preferred":[
        "Isak\u2019ly"
    ],
    "name:hye_x_variant":[
        "\u053b\u057d\u0561\u0584\u056c\u0568",
        "Sahakashen",
        "\u054d\u0561\u0570\u0561\u056f\u0561\u0577\u0565\u0576"
    ],
    "name:min_x_preferred":[
        "Isaql\u0131"
    ],
    "name:msa_x_preferred":[
        "Isaql\u0131"
    ],
    "name:rus_x_preferred":[
        "\u0418\u0441\u0430\u043a\u043b\u044b"
    ],
    "name:und_x_variant":[
        "Isakly",
        "Isak-Kishtak",
        "Isak-Kishlak"
    ],
    "wof:name":"Isaqli",
    "wof:placetype":"locality"
},
  "geometry": {"coordinates":[46.87332,39.42024],"type":"Point"}
}