{
  "type": "Feature",
  "properties": {
    "gn:admin1_code":"70",
    "gn:asciiname":"Hoytala",
    "gn:country_code":"AZ",
    "gn:dem":238,
    "gn:feature_class":"P",
    "gn:feature_code":"PPL",
    "gn:name":"H\u00f6ytala",
    "gn:population":0,
    "gn:timezone":"Asia/Baku",
    "iso:country":"AZ",
    "name:aze_x_preferred":[
        "H\u00f6ytala"
    ],
    "name:ell_x_preferred":[
        "\u03a7\u03b9\u03bf\u03ca\u03c4\u03ac\u03bb\u03b1"
    ],
    "name:ita_x_preferred":[
        "H\u00f6ytala"
    ],
    "name:kat_x_preferred":[
        "\u10f0\u10d8\u10dd\u10d8\u10d7\u10d0\u10da\u10d0"
    ],
    "name:msa_x_preferred":[
        "H\u00f6ytala"
    ],
    "name:und_x_variant":[
        "Oytala",
        "Vo\u0131tala"
    ],
    "wof:name":"Hoytala",
    "wof:placetype":"locality"
},
  "geometry": {"coordinates":[46.48793,41.57753],"type":"Point"}
}