{
  "type": "Feature",
  "properties": {
    "gn:admin1_code":"11",
    "gn:asciiname":"Mirzalybeyli",
    "gn:country_code":"AZ",
    "gn:dem":58,
    "gn:feature_class":"P",
    "gn:feature_code":"PPL",
    "gn:name":"Mirzalybeyli",
    "gn:population":0,
    "gn:timezone":"Asia/Baku",
    "iso:country":"AZ",
    "name:azb_x_preferred":[
        "\u0645\u06cc\u0631\u0632\u0627\u0644\u06cc \u0628\u06cc\u200c\u0644\u06cc"
    ],
    "name:aze_x_preferred":[
        "Mirzal\u0131b\u0259yli"
    ],
    "name:ceb_x_preferred":[
        "Mirzalybeyli"
    ],
    "name:ita_x_preferred":[
        "Mirzal\u0131b\u0259yli"
    ],
    "name:kat_x_preferred":[
        "\u10db\u10d8\u10e0\u10d6\u10d0\u10da\u10d8\u10d1\u10d4\u10d8\u10da\u10d8"
    ],
    "name:msa_x_preferred":[
        "Mirzal\u0131b\u0259yli"
    ],
    "name:swe_x_preferred":[
        "Mirzalybeyli"
    ],
    "wof:name":"Mirzalybeyli",
    "wof:placetype":"locality"
},
  "geometry": {"coordinates":[47.15927,40.39921],"type":"Point"}
}