{
  "type": "Feature",
  "properties": {
    "gn:admin1_code":"11",
    "gn:asciiname":"Mirzalybeyli",
    "gn:country_code":"AZ",
    "gn:dem":58,
    "gn:feature_class":"P",
    "gn:feature_code":"PPL",
    "gn:name":"Mirzalybeyli",
    "gn:population":0,
    "gn:timezone":"Asia/Baku",
    "iso:country":"AZ",
    "name:aze_x_preferred":[
        "Mirzal\u0131b\u0259yli"
    ],
    "wof:name":"Mirzalybeyli",
    "wof:placetype":"locality"
},
  "geometry": {"coordinates":[47.15927,40.39921],"type":"Point"}
}