{
  "type": "Feature",
  "properties": {
    "iso:country":"AZ",
    "name:aze_x_colloquial":[
        "Culfa"
    ],
    "name:aze_x_historical":[
        "Culfa"
    ],
    "name:aze_x_preferred":[
        "Culfa"
    ],
    "name:eng_x_historical":[
        "Julfa"
    ],
    "name:eng_x_preferred":[
        "Julfa"
    ],
    "name:fas_x_preferred":[
        "Jolf\u0101-ye Nakhjav\u0101n"
    ],
    "name:fas_x_variant":[
        "\u062c\u0644\u0641\u0627\u06cc \u0646\u062e\u062c\u0648\u0627\u0646"
    ],
    "name:heb_x_preferred":[
        "\u05e7\u05d5\u05dc\u05e4\u05d4"
    ],
    "name:hun_x_preferred":[
        "Culfa"
    ],
    "name:rus_x_preferred":[
        "\u0414\u0436\u0443\u043b\u044c\u0444\u0430"
    ],
    "name:tur_x_historical":[
        "Culfa"
    ],
    "name:tur_x_preferred":[
        "Culfa"
    ],
    "name:und_x_variant":[
        "Dzhul\u2019fa"
    ],
    "qs:gn_country":"AZ",
    "qs:gn_fcode":"PPLA2",
    "qs:gn_pop":10820,
    "qs:name":"Culfa",
    "qs:name_adm0":"Azerbaijan",
    "qs:name_adm1":"Culfa",
    "qs:photos":28,
    "qs:photos_1k":6,
    "qs:photos_9k":1,
    "qs:photos_9r":2,
    "qs:photos_all":28,
    "qs:photos_sr":2,
    "qs:placetype":"Town",
    "qs:pop_sr":"6",
    "qs:woe_adm0":23424741,
    "wof:name":"Culfa",
    "wof:placetype":"locality",
    "wof:population":10820
},
  "geometry": {"coordinates":[45.6308,38.9558],"type":"Point"}
}