{
  "type": "Feature",
  "properties": {
    "gn:admin1_code":"70",
    "gn:asciiname":"Gasanbina",
    "gn:country_code":"AZ",
    "gn:dem":224,
    "gn:feature_class":"P",
    "gn:feature_code":"PPL",
    "gn:name":"Gasanbina",
    "gn:population":0,
    "gn:timezone":"Asia/Baku",
    "iso:country":"AZ",
    "name:ava_x_preferred":[
        "\u0425I\u0430\u0441\u0430\u043d\u0431\u0438\u043d\u0430"
    ],
    "name:azb_x_preferred":[
        "\u062d\u0633\u0646 \u0628\u06cc\u0646\u0647"
    ],
    "name:aze_x_preferred":[
        "H\u0259s\u0259nbin\u0259"
    ],
    "name:ita_x_preferred":[
        "H\u0259s\u0259nbin\u0259"
    ],
    "name:kat_x_preferred":[
        "\u10f0\u10d0\u10e1\u10d0\u10dc\u10d1\u10d8\u10dc\u10d0"
    ],
    "name:msa_x_preferred":[
        "H\u0259s\u0259nbin\u0259"
    ],
    "wof:name":"Gasanbina",
    "wof:placetype":"locality"
},
  "geometry": {"coordinates":[46.48512,41.54327],"type":"Point"}
}