{
  "type": "Feature",
  "properties": {
    "gn:admin1_code":"47",
    "gn:asciiname":"Baqqal",
    "gn:country_code":"AZ",
    "gn:dem":408,
    "gn:feature_class":"P",
    "gn:feature_code":"PPL",
    "gn:name":"Baqqal",
    "gn:population":0,
    "gn:timezone":"Asia/Baku",
    "iso:country":"AZ",
    "name:azb_x_preferred":[
        "\u0628\u0627\u0642\u0642\u0627\u0644"
    ],
    "name:aze_x_preferred":[
        "Baqqal"
    ],
    "name:ceb_x_preferred":[
        "Baqqal"
    ],
    "name:ita_x_preferred":[
        "Baqqal"
    ],
    "name:msa_x_preferred":[
        "Baqqal"
    ],
    "name:swe_x_preferred":[
        "Baqqal"
    ],
    "name:und_x_variant":[
        "Bakkal"
    ],
    "wof:name":"Baqqal",
    "wof:placetype":"locality"
},
  "geometry": {"coordinates":[46.99338,41.33505],"type":"Point"}
}