{
  "type": "Feature",
  "properties": {
    "gn:admin1_code":"26",
    "gn:asciiname":"Dalqilincli",
    "gn:country_code":"AZ",
    "gn:dem":1671,
    "gn:feature_class":"P",
    "gn:feature_code":"PPL",
    "gn:name":"Dalq\u0131l\u0131ncl\u0131",
    "gn:population":0,
    "gn:timezone":"Asia/Baku",
    "iso:country":"AZ",
    "name:aze_x_preferred":[
        "Q\u0131l\u0131\u00e7l\u0131"
    ],
    "name:aze_x_variant":[
        "Dalq\u0131l\u0131ncl\u0131"
    ],
    "name:msa_x_preferred":[
        "Kylychly"
    ],
    "name:und_x_variant":[
        "Kylychly",
        "Dadychly"
    ],
    "wof:name":"Dalqilincli",
    "wof:placetype":"locality"
},
  "geometry": {"coordinates":[46.02586,40.10837],"type":"Point"}
}