{
  "type": "Feature",
  "properties": {
    "gn:admin1_code":"27",
    "gn:asciiname":"Khynysly",
    "gn:country_code":"AZ",
    "gn:dem":7,
    "gn:feature_class":"P",
    "gn:feature_code":"PPL",
    "gn:name":"Khynysly",
    "gn:population":0,
    "gn:timezone":"Asia/Baku",
    "iso:country":"AZ",
    "name:azb_x_preferred":[
        "\u062e\u06cc\u0646\u06cc\u0633\u200c\u0644\u06cc"
    ],
    "name:aze_x_preferred":[
        "X\u0131n\u0131sl\u0131"
    ],
    "name:ceb_x_preferred":[
        "Khynysly"
    ],
    "name:ita_x_preferred":[
        "X\u0131n\u0131sl\u0131"
    ],
    "name:msa_x_preferred":[
        "X\u0131n\u0131sl\u0131"
    ],
    "name:swe_x_preferred":[
        "Khynysly"
    ],
    "wof:name":"Khynysly",
    "wof:placetype":"locality"
},
  "geometry": {"coordinates":[48.28393,40.32538],"type":"Point"}
}