{
  "type": "Feature",
  "properties": {
    "gn:admin1_code":"27",
    "gn:asciiname":"Khynysly",
    "gn:country_code":"AZ",
    "gn:dem":7,
    "gn:feature_class":"P",
    "gn:feature_code":"PPL",
    "gn:name":"Khynysly",
    "gn:population":0,
    "gn:timezone":"Asia/Baku",
    "iso:country":"AZ",
    "name:und_x_variant":[
        "X\u0131n\u0131sl\u0131"
    ],
    "wof:name":"Khynysly",
    "wof:placetype":"locality"
},
  "geometry": {"coordinates":[48.28393,40.32538],"type":"Point"}
}