{
  "type": "Feature",
  "properties": {
    "gn:admin1_code":"32",
    "gn:asciiname":"Khalfalar",
    "gn:country_code":"AZ",
    "gn:dem":38,
    "gn:feature_class":"P",
    "gn:feature_code":"PPL",
    "gn:name":"Khalfalar",
    "gn:population":0,
    "gn:timezone":"Asia/Baku",
    "iso:country":"AZ",
    "name:aze_x_preferred":[
        "X\u0259lf\u0259l\u0259r"
    ],
    "name:und_x_variant":[
        "Khal\u2019fyalyar",
        "Khalfalar"
    ],
    "wof:name":"Khalfalar",
    "wof:placetype":"locality"
},
  "geometry": {"coordinates":[48.6008,39.01772],"type":"Point"}
}