{
  "type": "Feature",
  "properties": {
    "gn:admin1_code":"35",
    "gn:admin2_code":"147365.0",
    "gn:asciiname":"Bist",
    "gn:country_code":"AZ",
    "gn:dem":1591,
    "gn:feature_class":"P",
    "gn:feature_code":"PPL",
    "gn:name":"Bist",
    "gn:population":0,
    "gn:timezone":"Asia/Baku",
    "iso:country":"AZ",
    "name:aze_x_preferred":[
        "Bist"
    ],
    "name:ceb_x_preferred":[
        "Bist"
    ],
    "name:ita_x_preferred":[
        "Bist"
    ],
    "name:kat_x_preferred":[
        "\u10d1\u10d8\u10e1\u10d7\u10d8"
    ],
    "name:swe_x_preferred":[
        "Bist"
    ],
    "wof:name":"Bist",
    "wof:placetype":"locality"
},
  "geometry": {"coordinates":[45.88056,39.14944000000001],"type":"Point"}
}