{
  "type": "Feature",
  "properties": {
    "iso:country":"AZ",
    "qs:gn_pop":0,
    "qs:name":"Siy\u00e4z\u00e4n",
    "qs:name_adm0":"Azerbaijan",
    "qs:name_adm1":"Siyazan",
    "qs:photos":5,
    "qs:photos_1k":1,
    "qs:photos_9k":1,
    "qs:photos_9r":1,
    "qs:photos_all":5,
    "qs:photos_sr":1,
    "qs:placetype":"Town",
    "qs:pop_sr":"0",
    "qs:woe_adm0":23424741,
    "wof:name":"Siy\u00e4z\u00e4n",
    "wof:placetype":"locality"
},
  "geometry": {"coordinates":[49.238491,40.964474],"type":"Point"}
}