{
  "type": "Feature",
  "properties": {
    "gn:admin1_code":"28",
    "gn:asciiname":"Akhmedli",
    "gn:country_code":"AZ",
    "gn:dem":1617,
    "gn:feature_class":"P",
    "gn:feature_code":"PPL",
    "gn:name":"Akhmedli",
    "gn:population":0,
    "gn:timezone":"Asia/Baku",
    "iso:country":"AZ",
    "name:aze_x_preferred":[
        "\u018fhm\u0259dli"
    ],
    "name:hye_x_preferred":[
        "Ahmedli"
    ],
    "name:hye_x_variant":[
        "\u0531\u0570\u0574\u0565\u0564\u056c\u056b",
        "Herik",
        "\u0540\u0565\u0580\u056b\u056f"
    ],
    "name:rus_x_preferred":[
        "\u0410\u0445\u043c\u0435\u0434\u043b\u0438"
    ],
    "name:und_x_variant":[
        "Akhmedh",
        "Akhmedli"
    ],
    "wof:name":"Akhmedli",
    "wof:placetype":"locality"
},
  "geometry": {"coordinates":[46.28578,39.68659],"type":"Point"}
}