{
  "type": "Feature",
  "properties": {
    "gn:admin1_code":"58",
    "gn:asciiname":"Duz Cirdaxan",
    "gn:country_code":"AZ",
    "gn:dem":398,
    "gn:feature_class":"P",
    "gn:feature_code":"PPL",
    "gn:name":"D\u00fcz C\u0131rdaxan",
    "gn:population":0,
    "gn:timezone":"Asia/Baku",
    "iso:country":"AZ",
    "name:azb_x_preferred":[
        "\u062f\u06c6\u0632 \u062c\u06cc\u0631\u062f\u0627\u062e\u0627\u0646"
    ],
    "name:aze_x_preferred":[
        "D\u00fcz C\u0131rdaxan"
    ],
    "name:ceb_x_preferred":[
        "D\u00fcz C\u0131rdaxan"
    ],
    "name:ita_x_preferred":[
        "D\u00fcz C\u0131rdaxan"
    ],
    "name:kat_x_preferred":[
        "\u10d3\u10d8\u10e3\u10d6-\u10ef\u10d8\u10e0\u10d3\u10d0\u10ee\u10d0\u10dc\u10d8"
    ],
    "name:msa_x_preferred":[
        "D\u00fcz C\u0131rdaxan"
    ],
    "name:swe_x_preferred":[
        "D\u00fcz C\u0131rdaxan"
    ],
    "name:und_x_variant":[
        "Dyuzdzhirdakhan",
        "Dyuzdzhyrdakhan"
    ],
    "wof:name":"Duz Cirdaxan",
    "wof:placetype":"locality"
},
  "geometry": {"coordinates":[45.60905,41.01843],"type":"Point"}
}