{
  "type": "Feature",
  "properties": {
    "gn:admin1_code":"17",
    "gn:asciiname":"Padar",
    "gn:country_code":"AZ",
    "gn:dem":34,
    "gn:feature_class":"P",
    "gn:feature_code":"PPL",
    "gn:name":"Padar",
    "gn:population":0,
    "gn:timezone":"Asia/Baku",
    "iso:country":"AZ",
    "name:aze_x_preferred":[
        "Padar"
    ],
    "wof:name":"Padar",
    "wof:placetype":"locality"
},
  "geometry": {"coordinates":[48.89013,41.31634],"type":"Point"}
}