{
  "type": "Feature",
  "properties": {
    "gn:admin1_code":"15",
    "gn:asciiname":"Shotukhlu",
    "gn:country_code":"AZ",
    "gn:dem":326,
    "gn:feature_class":"P",
    "gn:feature_code":"PPL",
    "gn:name":"Shotukhlu",
    "gn:population":0,
    "gn:timezone":"Asia/Baku",
    "iso:country":"AZ",
    "name:aze_x_preferred":[
        "\u015eot\u00fckl\u00fc"
    ],
    "wof:name":"Shotukhlu",
    "wof:placetype":"locality"
},
  "geometry": {"coordinates":[48.24859,39.22976],"type":"Point"}
}