{
  "type": "Feature",
  "properties": {
    "gn:admin1_code":"17",
    "gn:asciiname":"Shakh-Nazarly",
    "gn:country_code":"AZ",
    "gn:dem":72,
    "gn:feature_class":"P",
    "gn:feature_code":"PPL",
    "gn:name":"Shakh-Nazarly",
    "gn:population":0,
    "gn:timezone":"Asia/Baku",
    "iso:country":"AZ",
    "name:azb_x_preferred":[
        "\u0634\u0627\u0647\u200c\u0646\u0638\u0631\u0644\u06cc"
    ],
    "name:aze_x_preferred":[
        "\u015eahn\u0259z\u0259rli"
    ],
    "name:ceb_x_preferred":[
        "Shakh-Nazarly"
    ],
    "name:ell_x_preferred":[
        "\u03a3\u03b1\u03c7\u03bd\u03b5\u03b6\u03b5\u03c1\u03bb\u03af"
    ],
    "name:fas_x_preferred":[
        "\u0634\u0627\u0647\u200c\u0646\u0638\u0631\u0644\u06cc"
    ],
    "name:ita_x_preferred":[
        "\u015eahn\u0259z\u0259rli"
    ],
    "name:msa_x_preferred":[
        "\u015eahn\u0259z\u0259rli"
    ],
    "name:swe_x_preferred":[
        "Shakh-Nazarly"
    ],
    "name:und_x_variant":[
        "B\u00ebyuk Shakhnazarli",
        "Shakh-Nazarly",
        "Beyuk- Shakhnazarli",
        "\u015eahn\u0259z\u0259rli",
        "Shakhnazarli"
    ],
    "name:urd_x_preferred":[
        "\u0633\u06c1\u0646\u06cc\u0632\u06cc\u0631\u0644\u06cc"
    ],
    "wof:name":"Shakh-Nazarly",
    "wof:placetype":"locality"
},
  "geometry": {"coordinates":[48.87835,41.28573],"type":"Point"}
}