{
  "type": "Feature",
  "properties": {
    "gn:admin1_code":"17",
    "gn:asciiname":"Shakh-Nazarly",
    "gn:country_code":"AZ",
    "gn:dem":72,
    "gn:feature_class":"P",
    "gn:feature_code":"PPL",
    "gn:name":"Shakh-Nazarly",
    "gn:population":0,
    "gn:timezone":"Asia/Baku",
    "iso:country":"AZ",
    "name:und_x_variant":[
        "B\u00ebyuk Shakhnazarli",
        "Shakh-Nazarly",
        "Beyuk- Shakhnazarli",
        "\u015eahn\u0259z\u0259rli",
        "Shakhnazarli"
    ],
    "wof:name":"Shakh-Nazarly",
    "wof:placetype":"locality"
},
  "geometry": {"coordinates":[48.87835,41.28573],"type":"Point"}
}