{
  "type": "Feature",
  "properties": {
    "gn:admin1_code":"51",
    "gn:asciiname":"Irmashly",
    "gn:country_code":"AZ",
    "gn:dem":533,
    "gn:feature_class":"P",
    "gn:feature_code":"PPL",
    "gn:name":"Irmashly",
    "gn:population":0,
    "gn:timezone":"Asia/Baku",
    "iso:country":"AZ",
    "name:aze_x_preferred":[
        "Engelsk\u0259nd"
    ],
    "name:rus_x_preferred":[
        "Engel\u2019skend"
    ],
    "name:und_x_variant":[
        "\u0130rma\u015fl\u0131",
        "Eygenfel\u2019d"
    ],
    "wof:name":"Irmashly",
    "wof:placetype":"locality"
},
  "geometry": {"coordinates":[45.89112,40.8431],"type":"Point"}
}