{
  "type": "Feature",
  "properties": {
    "gn:admin1_code":"31",
    "gn:asciiname":"Bibihoni",
    "gn:country_code":"AZ",
    "gn:dem":619,
    "gn:feature_class":"P",
    "gn:feature_code":"PPL",
    "gn:name":"Bibihoni",
    "gn:population":0,
    "gn:timezone":"Asia/Baku",
    "iso:country":"AZ",
    "name:aze_x_preferred":[
        "Bibihoni"
    ],
    "name:aze_x_variant":[
        "Bibiyoni",
        "Bibiyani"
    ],
    "name:und_x_variant":[
        "Bibiany",
        "Bibioni",
        "Bibinoni"
    ],
    "wof:name":"Bibihoni",
    "wof:placetype":"locality"
},
  "geometry": {"coordinates":[48.57071,38.74296],"type":"Point"}
}