{
  "type": "Feature",
  "properties": {
    "gn:admin1_code":"47",
    "gn:asciiname":"Qirxbulaq",
    "gn:country_code":"AZ",
    "gn:dem":487,
    "gn:feature_class":"P",
    "gn:feature_code":"PPL",
    "gn:name":"Q\u0131rxbulaq",
    "gn:population":0,
    "gn:timezone":"Asia/Baku",
    "iso:country":"AZ",
    "name:aze_x_preferred":[
        "Q\u0131rxbulaq"
    ],
    "name:aze_x_variant":[
        "Vayvay"
    ],
    "name:ita_x_preferred":[
        "Q\u0131rxbulaq"
    ],
    "name:msa_x_preferred":[
        "Q\u0131rxbulaq"
    ],
    "wof:name":"Qirxbulaq",
    "wof:placetype":"locality"
},
  "geometry": {"coordinates":[47.25381,41.1434],"type":"Point"}
}