{
  "type": "Feature",
  "properties": {
    "gn:admin1_code":"27",
    "gn:asciiname":"Khalilli",
    "gn:country_code":"AZ",
    "gn:dem":-10,
    "gn:feature_class":"P",
    "gn:feature_code":"PPL",
    "gn:name":"Khalilli",
    "gn:population":0,
    "gn:timezone":"Asia/Baku",
    "iso:country":"AZ",
    "name:und_x_variant":[
        "Khalily",
        "Khalilli"
    ],
    "wof:name":"Khalilli",
    "wof:placetype":"locality"
},
  "geometry": {"coordinates":[47.99556,40.16194],"type":"Point"}
}