{
  "type": "Feature",
  "properties": {
    "gn:admin1_code":"58",
    "gn:asciiname":"Sandlyar",
    "gn:country_code":"AZ",
    "gn:dem":1383,
    "gn:feature_class":"P",
    "gn:feature_code":"PPL",
    "gn:name":"Sandlyar",
    "gn:population":0,
    "gn:timezone":"Asia/Baku",
    "iso:country":"AZ",
    "name:ita_x_preferred":[
        "Sandlyar"
    ],
    "name:kat_x_preferred":[
        "\u10e1\u10d0\u10dc\u10d3\u10da\u10d8\u10d0\u10e0\u10d8"
    ],
    "name:msa_x_preferred":[
        "Sandlyar"
    ],
    "wof:name":"Sandlyar",
    "wof:placetype":"locality"
},
  "geometry": {"coordinates":[45.49278,40.69472],"type":"Point"}
}