{
  "type": "Feature",
  "properties": {
    "gn:admin1_code":"08",
    "gn:asciiname":"Azaru",
    "gn:country_code":"AZ",
    "gn:dem":858,
    "gn:feature_class":"P",
    "gn:feature_code":"PPL",
    "gn:name":"Azaru",
    "gn:population":0,
    "gn:timezone":"Asia/Baku",
    "iso:country":"AZ",
    "name:azb_x_preferred":[
        "\u0622\u0632\u0627\u0631\u0648"
    ],
    "name:aze_x_preferred":[
        "Azaru"
    ],
    "name:fas_x_preferred":[
        "\u0622\u0632\u0627\u0631\u0648\u062f"
    ],
    "name:ita_x_preferred":[
        "Azaru"
    ],
    "name:kat_x_preferred":[
        "\u10d0\u10d6\u10d0\u10e0\u10e3"
    ],
    "name:kur_x_preferred":[
        "Azar\u00fb"
    ],
    "name:msa_x_preferred":[
        "Azaru"
    ],
    "name:tur_x_preferred":[
        "Azaru"
    ],
    "name:und_x_variant":[
        "Azeru"
    ],
    "wof:name":"Azaru",
    "wof:placetype":"locality"
},
  "geometry": {"coordinates":[48.604,38.57579000000001],"type":"Point"}
}