{
  "type": "Feature",
  "properties": {
    "gn:admin1_code":"08",
    "gn:asciiname":"Azaru",
    "gn:country_code":"AZ",
    "gn:dem":858,
    "gn:feature_class":"P",
    "gn:feature_code":"PPL",
    "gn:name":"Azaru",
    "gn:population":0,
    "gn:timezone":"Asia/Baku",
    "iso:country":"AZ",
    "name:und_x_variant":[
        "Azeru"
    ],
    "wof:name":"Azaru",
    "wof:placetype":"locality"
},
  "geometry": {"coordinates":[48.604,38.57579000000001],"type":"Point"}
}