{
  "type": "Feature",
  "properties": {
    "gn:admin1_code":"29",
    "gn:asciiname":"Silim",
    "gn:country_code":"AZ",
    "gn:dem":-14,
    "gn:feature_class":"P",
    "gn:feature_code":"PPL",
    "gn:name":"\u015eilim",
    "gn:population":0,
    "gn:timezone":"Asia/Baku",
    "iso:country":"AZ",
    "name:aze_x_preferred":[
        "\u015eilim"
    ],
    "name:msa_x_preferred":[
        "\u015eilim"
    ],
    "name:und_x_variant":[
        "Shilim"
    ],
    "wof:name":"Silim",
    "wof:placetype":"locality"
},
  "geometry": {"coordinates":[48.85536,38.70714],"type":"Point"}
}