{
  "type": "Feature",
  "properties": {
    "gn:admin1_code":"24",
    "gn:asciiname":"Qaralar",
    "gn:country_code":"AZ",
    "gn:dem":-2,
    "gn:feature_class":"P",
    "gn:feature_code":"PPL",
    "gn:name":"Qaralar",
    "gn:population":0,
    "gn:timezone":"Asia/Baku",
    "iso:country":"AZ",
    "name:und_x_variant":[
        "Verkhniy Karalar",
        "Karalar",
        "Qaralar"
    ],
    "wof:name":"Qaralar",
    "wof:placetype":"locality"
},
  "geometry": {"coordinates":[48.08485,39.82615],"type":"Point"}
}