{
  "type": "Feature",
  "properties": {
    "gn:admin1_code":"19",
    "gn:asciiname":"Maarif",
    "gn:country_code":"AZ",
    "gn:dem":1117,
    "gn:feature_class":"P",
    "gn:feature_code":"PPL",
    "gn:name":"Maarif",
    "gn:population":0,
    "gn:timezone":"Asia/Baku",
    "iso:country":"AZ",
    "wof:name":"Maarif",
    "wof:placetype":"locality"
},
  "geometry": {"coordinates":[46.13333,40.65],"type":"Point"}
}