{
  "type": "Feature",
  "properties": {
    "gn:admin1_code":"46",
    "gn:asciiname":"Bala Hasimxanli",
    "gn:country_code":"AZ",
    "gn:dem":-23,
    "gn:feature_class":"P",
    "gn:feature_code":"PPL",
    "gn:name":"Bala Ha\u015f\u0131mxanl\u0131",
    "gn:population":0,
    "gn:timezone":"Asia/Baku",
    "iso:country":"AZ",
    "name:und_x_variant":[
        "Bala Gashimkhanly",
        "Bala Ha\u015f\u0131mxanl\u0131",
        "Dzhanarly"
    ],
    "wof:name":"Bala Hasimxanli",
    "wof:placetype":"locality"
},
  "geometry": {"coordinates":[48.81945,39.79718],"type":"Point"}
}