{
  "type": "Feature",
  "properties": {
    "gn:admin1_code":"46",
    "gn:asciiname":"Bala Hasimxanli",
    "gn:country_code":"AZ",
    "gn:dem":-23,
    "gn:feature_class":"P",
    "gn:feature_code":"PPL",
    "gn:name":"Bala Ha\u015f\u0131mxanl\u0131",
    "gn:population":0,
    "gn:timezone":"Asia/Baku",
    "iso:country":"AZ",
    "name:azb_x_preferred":[
        "\u0628\u0627\u0644\u0627 \u0647\u0627\u0634\u06cc\u0645 \u062e\u0627\u0646\u0644\u06cc"
    ],
    "name:aze_x_preferred":[
        "Bala H\u0259\u015fimxanl\u0131"
    ],
    "name:ceb_x_preferred":[
        "Bala Ha\u015f\u0131mxanl\u0131"
    ],
    "name:ita_x_preferred":[
        "Bala Ha\u015fimxanl\u0131"
    ],
    "name:msa_x_preferred":[
        "Bala Ha\u015fimxanl\u0131"
    ],
    "name:swe_x_preferred":[
        "Bala Ha\u015f\u0131mxanl\u0131"
    ],
    "name:und_x_variant":[
        "Bala Gashimkhanly",
        "Bala Ha\u015f\u0131mxanl\u0131",
        "Dzhanarly"
    ],
    "wof:name":"Bala Hasimxanli",
    "wof:placetype":"locality"
},
  "geometry": {"coordinates":[48.81945,39.79718],"type":"Point"}
}