{
  "type": "Feature",
  "properties": {
    "gn:admin1_code":"15",
    "gn:asciiname":"Astrakhanovka",
    "gn:country_code":"AZ",
    "gn:dem":24,
    "gn:feature_class":"P",
    "gn:feature_code":"PPL",
    "gn:name":"Astrakhanovka",
    "gn:population":0,
    "gn:timezone":"Asia/Baku",
    "iso:country":"AZ",
    "name:ceb_x_preferred":[
        "Astrakhanovka"
    ],
    "name:swe_x_preferred":[
        "Astrakhanovka"
    ],
    "wof:name":"Astrakhanovka",
    "wof:placetype":"locality"
},
  "geometry": {"coordinates":[48.51667,39.21167],"type":"Point"}
}