{
  "type": "Feature",
  "properties": {
    "gn:admin1_code":"37",
    "gn:asciiname":"Filfili",
    "gn:country_code":"AZ",
    "gn:dem":1144,
    "gn:feature_class":"P",
    "gn:feature_code":"PPL",
    "gn:name":"Filfili",
    "gn:population":0,
    "gn:timezone":"Asia/Baku",
    "iso:country":"AZ",
    "name:eng_x_preferred":[
        "Filfili"
    ],
    "name:rus_x_preferred":[
        "\u0424\u0438\u043b\u044c\u0444\u0438\u043b\u0438"
    ],
    "name:rus_x_variant":[
        "Fil\u2019fili"
    ],
    "name:und_x_variant":[
        "Bash-Fil\u2019filli",
        "Filifli",
        "Filfili"
    ],
    "wof:name":"Filfili",
    "wof:placetype":"locality"
},
  "geometry": {"coordinates":[47.59512,41.11693],"type":"Point"}
}