{
  "type": "Feature",
  "properties": {
    "gn:admin1_code":"32",
    "gn:asciiname":"Mamedrzakyudzha",
    "gn:country_code":"AZ",
    "gn:dem":64,
    "gn:feature_class":"P",
    "gn:feature_code":"PPL",
    "gn:name":"Mamedrzakyudzha",
    "gn:population":0,
    "gn:timezone":"Asia/Baku",
    "iso:country":"AZ",
    "name:aze_x_preferred":[
        "M\u0259mm\u0259drak\u00fcc\u0259"
    ],
    "name:aze_x_variant":[
        "M\u0259mm\u0259drzak\u00fcc\u0259"
    ],
    "name:und_x_variant":[
        "Mamedi-Rzakyudzha",
        "Mamedrzakyudzha"
    ],
    "wof:name":"Mamedrzakyudzha",
    "wof:placetype":"locality"
},
  "geometry": {"coordinates":[48.61139,38.97416],"type":"Point"}
}