{
  "type": "Feature",
  "properties": {
    "gn:admin1_code":"58",
    "gn:asciiname":"Mollalar",
    "gn:country_code":"AZ",
    "gn:dem":1451,
    "gn:feature_class":"P",
    "gn:feature_code":"PPL",
    "gn:name":"Mollalar",
    "gn:population":0,
    "gn:timezone":"Asia/Baku",
    "iso:country":"AZ",
    "wof:name":"Mollalar",
    "wof:placetype":"locality"
},
  "geometry": {"coordinates":[45.55577,40.70478],"type":"Point"}
}