{
  "type": "Feature",
  "properties": {
    "gn:admin1_code":"58",
    "gn:asciiname":"Mollalar",
    "gn:country_code":"AZ",
    "gn:dem":1451,
    "gn:feature_class":"P",
    "gn:feature_code":"PPL",
    "gn:name":"Mollalar",
    "gn:population":0,
    "gn:timezone":"Asia/Baku",
    "iso:country":"AZ",
    "name:azb_x_preferred":[
        "\u0645\u0648\u0644\u0644\u0627\u0644\u0627\u0631"
    ],
    "name:aze_x_preferred":[
        "Mollalar"
    ],
    "name:ell_x_preferred":[
        "\u039c\u03bf\u03bb\u03bb\u03b1\u03bb\u03ac\u03c1"
    ],
    "name:ita_x_preferred":[
        "Mollalar"
    ],
    "name:kat_x_preferred":[
        "\u10db\u10dd\u10da\u10d0\u10da\u10d0\u10e0\u10d8"
    ],
    "name:msa_x_preferred":[
        "Mollalar"
    ],
    "wof:name":"Mollalar",
    "wof:placetype":"locality"
},
  "geometry": {"coordinates":[45.55577,40.70478],"type":"Point"}
}