{
  "type": "Feature",
  "properties": {
    "iso:country":"AZ",
    "name:ara_x_preferred":[
        "\u0632\u064a\u0631\u0627"
    ],
    "name:aze_x_preferred":[
        "Zir\u0259"
    ],
    "name:ceb_x_preferred":[
        "Zyrya"
    ],
    "name:dut_x_preferred":[
        "Zir\u0259"
    ],
    "name:eng_x_preferred":[
        "Zir\u01dd"
    ],
    "name:est_x_preferred":[
        "Zir\u0259"
    ],
    "name:rus_x_preferred":[
        "\u0417\u0438\u0440\u044f"
    ],
    "name:swe_x_preferred":[
        "Zyrya"
    ],
    "name:ukr_x_preferred":[
        "\u0417\u0456\u0440\u0430"
    ],
    "name:unk_x_variant":[
        "Zirya"
    ],
    "qs:gn_country":"AZ",
    "qs:gn_fcode":"PPL",
    "qs:gn_pop":10099,
    "qs:name":"Zyrya",
    "qs:name_adm0":"Azerbaijan",
    "qs:name_adm1":"Baki",
    "qs:photos":0,
    "qs:photos_1k":0,
    "qs:photos_9k":0,
    "qs:photos_9r":0,
    "qs:photos_all":0,
    "qs:photos_sr":0,
    "qs:placetype":"Town",
    "qs:pop_sr":"6",
    "qs:woe_adm0":23424741,
    "wof:name":"Zyrya",
    "wof:placetype":"locality",
    "wof:population":10099
},
  "geometry": {"coordinates":[50.2917,40.3661],"type":"Point"}
}