{
  "type": "Feature",
  "properties": {
    "gn:admin1_code":"04",
    "gn:asciiname":"Kukal",
    "gn:country_code":"AZ",
    "gn:dem":75,
    "gn:feature_class":"P",
    "gn:feature_code":"PPL",
    "gn:name":"K\u00fck\u0259l",
    "gn:population":0,
    "gn:timezone":"Asia/Baku",
    "iso:country":"AZ",
    "name:aze_x_preferred":[
        "K\u00fck\u0259l"
    ],
    "name:ceb_x_preferred":[
        "K\u00fck\u0259l"
    ],
    "name:eng_x_preferred":[
        "K\u00fck\u01ddl"
    ],
    "name:ita_x_preferred":[
        "K\u00fck\u0259l"
    ],
    "name:kat_x_preferred":[
        "\u10e5\u10d8\u10e3\u10e5\u10d4\u10da\u10d8"
    ],
    "name:msa_x_preferred":[
        "K\u00fck\u0259l"
    ],
    "name:rus_x_preferred":[
        "\u041a\u044e\u043a\u0435\u043b\u044c"
    ],
    "name:swe_x_preferred":[
        "K\u00fck\u0259l"
    ],
    "name:und_x_variant":[
        "Kyukel\u2019"
    ],
    "wof:name":"Kukal",
    "wof:placetype":"locality"
},
  "geometry": {"coordinates":[47.56785,40.67093],"type":"Point"}
}