{
  "type": "Feature",
  "properties": {
    "gn:admin1_code":"17",
    "gn:asciiname":"Borbor",
    "gn:country_code":"AZ",
    "gn:dem":24,
    "gn:feature_class":"P",
    "gn:feature_code":"PPL",
    "gn:name":"Borbor",
    "gn:population":0,
    "gn:timezone":"Asia/Baku",
    "iso:country":"AZ",
    "name:azb_x_preferred":[
        "\u0628\u0648\u0631\u0628\u0648\u0631"
    ],
    "name:aze_x_preferred":[
        "Borbor"
    ],
    "name:fas_x_preferred":[
        "\u0628\u0648\u0631\u0628\u0648\u0631"
    ],
    "name:msa_x_preferred":[
        "Borbor"
    ],
    "name:und_x_variant":[
        "Bur-Bur",
        "Borbor"
    ],
    "wof:name":"Borbor",
    "wof:placetype":"locality"
},
  "geometry": {"coordinates":[48.90111,41.31677],"type":"Point"}
}