{
  "type": "Feature",
  "properties": {
    "gn:admin1_code":"31",
    "gn:asciiname":"Murya",
    "gn:country_code":"AZ",
    "gn:dem":771,
    "gn:feature_class":"P",
    "gn:feature_code":"PPL",
    "gn:name":"Murya",
    "gn:population":0,
    "gn:timezone":"Asia/Baku",
    "iso:country":"AZ",
    "name:rus_x_preferred":[
        "Mur\u2019ya"
    ],
    "wof:name":"Murya",
    "wof:placetype":"locality"
},
  "geometry": {"coordinates":[48.40600000000001,38.83298],"type":"Point"}
}