{
  "type": "Feature",
  "properties": {
    "gn:admin1_code":"35",
    "gn:admin2_code":"147365.0",
    "gn:asciiname":"Bazmari",
    "gn:country_code":"AZ",
    "gn:dem":1876,
    "gn:feature_class":"P",
    "gn:feature_code":"PPL",
    "gn:name":"Bazmari",
    "gn:population":0,
    "gn:timezone":"Asia/Baku",
    "iso:country":"AZ",
    "name:aze_x_preferred":[
        "P\u0259zm\u0259ri"
    ],
    "name:und_x_variant":[
        "Pazmara",
        "Bazmari",
        "Pazmari"
    ],
    "wof:name":"Bazmari",
    "wof:placetype":"locality"
},
  "geometry": {"coordinates":[46.01409,39.03068],"type":"Point"}
}