{
  "type": "Feature",
  "properties": {
    "gn:admin1_code":"58",
    "gn:asciiname":"Avdal",
    "gn:country_code":"AZ",
    "gn:dem":867,
    "gn:feature_class":"P",
    "gn:feature_code":"PPL",
    "gn:name":"Avdal",
    "gn:population":0,
    "gn:timezone":"Asia/Baku",
    "iso:country":"AZ",
    "name:aze_x_preferred":[
        "Avdal"
    ],
    "name:rus_x_preferred":[
        "\u0410\u0432\u0434\u0430\u043b"
    ],
    "name:ukr_x_preferred":[
        "\u0410\u0432\u0434\u0430\u043b"
    ],
    "wof:name":"Avdal",
    "wof:placetype":"locality"
},
  "geometry": {"coordinates":[45.68261,40.79846],"type":"Point"}
}