{
  "type": "Feature",
  "properties": {
    "gn:admin1_code":"35",
    "gn:admin2_code":"147997.0",
    "gn:asciiname":"Maxta",
    "gn:country_code":"AZ",
    "gn:dem":809,
    "gn:feature_class":"P",
    "gn:feature_code":"PPL",
    "gn:name":"Maxta",
    "gn:population":0,
    "gn:timezone":"Asia/Baku",
    "iso:country":"AZ",
    "name:azb_x_preferred":[
        "\u0645\u0627\u062e\u062a\u0627"
    ],
    "name:aze_x_preferred":[
        "Maxta"
    ],
    "name:ceb_x_preferred":[
        "Maxta"
    ],
    "name:hye_x_preferred":[
        "\u0544\u0561\u056d\u057f\u0561"
    ],
    "name:ita_x_preferred":[
        "Maxta"
    ],
    "name:kat_x_preferred":[
        "\u10db\u10d0\u10ee\u10d7\u10d0"
    ],
    "name:min_x_preferred":[
        "Maxta"
    ],
    "name:msa_x_preferred":[
        "Maxta"
    ],
    "name:swe_x_preferred":[
        "Maxta"
    ],
    "name:und_x_variant":[
        "Makhta",
        "Maxta"
    ],
    "wof:name":"Maxta",
    "wof:placetype":"locality"
},
  "geometry": {"coordinates":[44.95629,39.59065],"type":"Point"}
}