{
  "type": "Feature",
  "properties": {
    "gn:admin1_code":"35",
    "gn:admin2_code":"147997.0",
    "gn:asciiname":"Maxta",
    "gn:country_code":"AZ",
    "gn:dem":809,
    "gn:feature_class":"P",
    "gn:feature_code":"PPL",
    "gn:name":"Maxta",
    "gn:population":0,
    "gn:timezone":"Asia/Baku",
    "iso:country":"AZ",
    "name:und_x_variant":[
        "Makhta",
        "Maxta"
    ],
    "wof:name":"Maxta",
    "wof:placetype":"locality"
},
  "geometry": {"coordinates":[44.95629,39.59065],"type":"Point"}
}