{
  "type": "Feature",
  "properties": {
    "iso:country":"AZ",
    "name:azb_x_preferred":[
        "\u0645\u0631\u062f\u06a9\u0627\u0646"
    ],
    "name:aze_x_preferred":[
        "M\u0259rd\u0259kan"
    ],
    "name:deu_x_preferred":[
        "M\u0259rd\u0259kan"
    ],
    "name:eng_x_preferred":[
        "M\u01ddrd\u01ddkan"
    ],
    "name:eng_x_variant":[
        "M\u0259rd\u0259kan"
    ],
    "name:fas_x_preferred":[
        "\u0645\u0631\u062f\u06a9\u0646"
    ],
    "name:fra_x_preferred":[
        "M\u0259rd\u0259kan"
    ],
    "name:hye_x_preferred":[
        "\u0544\u0561\u0580\u0564\u0561\u056f\u0575\u0561\u0576"
    ],
    "name:nld_x_preferred":[
        "M\u0259rd\u0259kan"
    ],
    "name:rus_x_preferred":[
        "\u041c\u0430\u0440\u0434\u0430\u043a\u044f\u043d"
    ],
    "name:tur_x_preferred":[
        "Mardakan"
    ],
    "name:ukr_x_preferred":[
        "\u041c\u0430\u0440\u0434\u0430\u043a\u0430\u043d"
    ],
    "name:unk_x_variant":[
        "Mardakjan"
    ],
    "qs:gn_country":"AZ",
    "qs:gn_fcode":"PPL",
    "qs:gn_pop":15267,
    "qs:name":"M\u00e4rd\u00e4kan",
    "qs:name_adm0":"Azerbaijan",
    "qs:name_adm1":"Baki",
    "qs:photos":99,
    "qs:photos_1k":20,
    "qs:photos_9k":1,
    "qs:photos_9r":3,
    "qs:photos_all":99,
    "qs:photos_sr":3,
    "qs:placetype":"Town",
    "qs:pop_sr":"6",
    "qs:woe_adm0":23424741,
    "wof:name":"M\u00e4rd\u00e4kan",
    "wof:placetype":"locality",
    "wof:population":15267
},
  "geometry": {"coordinates":[50.13889,40.49222],"type":"Point"}
}