{
  "type": "Feature",
  "properties": {
    "gn:admin1_code":"42",
    "gn:asciiname":"Hapit",
    "gn:country_code":"AZ",
    "gn:dem":1274,
    "gn:feature_class":"P",
    "gn:feature_code":"PPL",
    "gn:name":"Hap\u0131t",
    "gn:population":0,
    "gn:timezone":"Asia/Baku",
    "iso:country":"AZ",
    "name:aze_x_preferred":[
        "Hap\u0131t"
    ],
    "name:und_x_variant":[
        "Gaput"
    ],
    "wof:name":"Hapit",
    "wof:placetype":"locality"
},
  "geometry": {"coordinates":[48.58058,41.16605],"type":"Point"}
}