{
  "type": "Feature",
  "properties": {
    "gn:admin1_code":"31",
    "gn:asciiname":"Nyuvedi",
    "gn:country_code":"AZ",
    "gn:dem":574,
    "gn:feature_class":"P",
    "gn:feature_code":"PPL",
    "gn:name":"Nyuvedi",
    "gn:population":0,
    "gn:timezone":"Asia/Baku",
    "iso:country":"AZ",
    "name:und_x_variant":[
        "Nyuady",
        "N\u00fcv\u0259di"
    ],
    "wof:name":"Nyuvedi",
    "wof:placetype":"locality"
},
  "geometry": {"coordinates":[48.46694,38.82556],"type":"Point"}
}