{
  "type": "Feature",
  "properties": {
    "gn:admin1_code":"35",
    "gn:admin2_code":"147212.0",
    "gn:asciiname":"Ayrins",
    "gn:country_code":"AZ",
    "gn:dem":1293,
    "gn:feature_class":"P",
    "gn:feature_code":"PPL",
    "gn:name":"Ayr\u0131ns",
    "gn:population":0,
    "gn:timezone":"Asia/Baku",
    "iso:country":"AZ",
    "name:aze_x_preferred":[
        "Ar\u0131nc"
    ],
    "name:aze_x_variant":[
        "Ayr\u0131ns"
    ],
    "name:und_x_variant":[
        "Aryndzhkend",
        "Aryndzh",
        "Arindzh"
    ],
    "wof:name":"Ayrins",
    "wof:placetype":"locality"
},
  "geometry": {"coordinates":[45.58568,39.43378],"type":"Point"}
}