{
  "type": "Feature",
  "properties": {
    "gn:admin1_code":"10",
    "gn:asciiname":"Saribulaq",
    "gn:country_code":"AZ",
    "gn:dem":225,
    "gn:feature_class":"P",
    "gn:feature_code":"PPL",
    "gn:name":"Sar\u0131bulaq",
    "gn:population":0,
    "gn:timezone":"Asia/Baku",
    "iso:country":"AZ",
    "name:aze_x_preferred":[
        "Sar\u0131bulaq"
    ],
    "name:und_x_variant":[
        "Sarykhbulakhbina",
        "Sarybulak",
        "Sarybulakhbina",
        "\u015ear\u0131bulaq"
    ],
    "wof:name":"Saribulaq",
    "wof:placetype":"locality"
},
  "geometry": {"coordinates":[46.30251,41.67901],"type":"Point"}
}