{
  "type": "Feature",
  "properties": {
    "gn:admin1_code":"60",
    "gn:asciiname":"Yaquboba",
    "gn:country_code":"AZ",
    "gn:dem":62,
    "gn:feature_class":"P",
    "gn:feature_code":"PPL",
    "gn:name":"Yaquboba",
    "gn:population":0,
    "gn:timezone":"Asia/Baku",
    "iso:country":"AZ",
    "name:und_x_variant":[
        "Yaguboba",
        "Yaquboba"
    ],
    "wof:name":"Yaquboba",
    "wof:placetype":"locality"
},
  "geometry": {"coordinates":[48.60182,41.74365],"type":"Point"}
}