{
  "type": "Feature",
  "properties": {
    "gn:admin1_code":"60",
    "gn:asciiname":"Yaquboba",
    "gn:country_code":"AZ",
    "gn:dem":62,
    "gn:feature_class":"P",
    "gn:feature_code":"PPL",
    "gn:name":"Yaquboba",
    "gn:population":0,
    "gn:timezone":"Asia/Baku",
    "iso:country":"AZ",
    "name:azb_x_preferred":[
        "\u06cc\u0627\u0642\u0648\u0628 \u0627\u0648\u0628\u0627"
    ],
    "name:aze_x_preferred":[
        "Yaquboba"
    ],
    "name:ita_x_preferred":[
        "Yaquboba"
    ],
    "name:lez_x_preferred":[
        "\u042f\u043a\u044a\u0443\u0431\u0443\u0431\u0430"
    ],
    "name:msa_x_preferred":[
        "Yaquboba"
    ],
    "name:und_x_variant":[
        "Yaguboba"
    ],
    "name:urd_x_preferred":[
        "\u06cc\u0642\u0628\u0648\u0628\u0627"
    ],
    "wof:name":"Yaquboba",
    "wof:placetype":"locality"
},
  "geometry": {"coordinates":[48.60182,41.74365],"type":"Point"}
}