{
  "type": "Feature",
  "properties": {
    "gn:admin1_code":"27",
    "gn:asciiname":"Magerramli",
    "gn:country_code":"AZ",
    "gn:dem":-16,
    "gn:feature_class":"P",
    "gn:feature_code":"PPL",
    "gn:name":"Magerramli",
    "gn:population":0,
    "gn:timezone":"Asia/Baku",
    "iso:country":"AZ",
    "name:und_x_variant":[
        "M\u0259h\u0259rr\u0259mli",
        "Gamzaly"
    ],
    "wof:name":"Magerramli",
    "wof:placetype":"locality"
},
  "geometry": {"coordinates":[48.35346,40.16785],"type":"Point"}
}