{
  "type": "Feature",
  "properties": {
    "gn:admin1_code":"71",
    "gn:asciiname":"Sahhuseynli",
    "gn:country_code":"AZ",
    "gn:dem":-6,
    "gn:feature_class":"P",
    "gn:feature_code":"PPL",
    "gn:name":"\u015eahh\u00fcseynli",
    "gn:population":0,
    "gn:timezone":"Asia/Baku",
    "iso:country":"AZ",
    "name:azb_x_preferred":[
        "\u0634\u0627\u0647\u200c\u062d\u0633\u06cc\u0646\u200c\u0644\u06cc"
    ],
    "name:aze_x_preferred":[
        "\u015eahs\u00fcnni"
    ],
    "name:aze_x_variant":[
        "\u015eahh\u00fcseynli"
    ],
    "name:ceb_x_preferred":[
        "\u015eahh\u00fcseynli"
    ],
    "name:fas_x_preferred":[
        "\u0634\u0627\u0647\u200c\u062d\u0633\u06cc\u0646\u200c\u0644\u06cc"
    ],
    "name:ita_x_preferred":[
        "\u015eahh\u00fcseynli"
    ],
    "name:kat_x_preferred":[
        "\u10e8\u10d0\u10ee\u10f0\u10d8\u10e3\u10e1\u10d4\u10d8\u10dc\u10da\u10d8"
    ],
    "name:msa_x_preferred":[
        "\u015eahh\u00fcseynli"
    ],
    "name:swe_x_preferred":[
        "\u015eahh\u00fcseynli"
    ],
    "name:und_x_variant":[
        "\u015eahh\u00fcseynl\u00fc",
        "Shakhsunni",
        "Shakhsyunnyu",
        "Shakhsyunlyu",
        "Shakhguseynli"
    ],
    "name:urd_x_preferred":[
        "\u0633\u06c1\u06be\u0633\u06cc\u0646\u0644\u06cc"
    ],
    "wof:name":"Sahhuseynli",
    "wof:placetype":"locality"
},
  "geometry": {"coordinates":[47.87582,40.13877],"type":"Point"}
}