{
  "type": "Feature",
  "properties": {
    "gn:admin1_code":"71",
    "gn:asciiname":"Sahhuseynli",
    "gn:country_code":"AZ",
    "gn:dem":-6,
    "gn:feature_class":"P",
    "gn:feature_code":"PPL",
    "gn:name":"\u015eahh\u00fcseynli",
    "gn:population":0,
    "gn:timezone":"Asia/Baku",
    "iso:country":"AZ",
    "name:aze_x_preferred":[
        "\u015eahs\u00fcnni"
    ],
    "name:und_x_variant":[
        "\u015eahh\u00fcseynl\u00fc",
        "Shakhsunni",
        "Shakhsyunnyu",
        "Shakhsyunlyu",
        "\u015eahh\u00fcseynli",
        "Shakhguseynli"
    ],
    "wof:name":"Sahhuseynli",
    "wof:placetype":"locality"
},
  "geometry": {"coordinates":[47.87582,40.13877],"type":"Point"}
}