{
  "type": "Feature",
  "properties": {
    "gn:country":"AZ",
    "gn:fcode":"PPL",
    "gn:population":4410,
    "iso:country":"AZ",
    "name:eng_x_preferred":[
        "Mu\u011fan"
    ],
    "name:rus_x_preferred":[
        "\u041c\u0443\u0433\u0430\u043d\u044c"
    ],
    "qs:name":"Mughan",
    "qs:photos_9r":0,
    "qs:photos_sr":0,
    "qs:pop_sr":"4",
    "wof:name":"Mughan",
    "wof:placetype":"locality",
    "wof:population":4410
},
  "geometry": {"coordinates":[48.81886,40.09902],"type":"Point"}
}