{
  "type": "Feature",
  "properties": {
    "gn:admin1_code":"35",
    "gn:admin2_code":"147365.0",
    "gn:asciiname":"Deste",
    "gn:country_code":"AZ",
    "gn:dem":696,
    "gn:feature_class":"P",
    "gn:feature_code":"PPL",
    "gn:name":"Deste",
    "gn:population":4282,
    "gn:timezone":"Asia/Baku",
    "iso:country":"AZ",
    "name:azb_x_preferred":[
        "\u062f\u0633\u062a\u0647"
    ],
    "name:aze_x_colloquial":[
        "D\u0259st\u0259"
    ],
    "name:aze_x_historical":[
        "D\u0259st\u0259"
    ],
    "name:aze_x_preferred":[
        "D\u0259st\u0259"
    ],
    "name:ceb_x_preferred":[
        "Deste"
    ],
    "name:eng_x_historical":[
        "Dasta"
    ],
    "name:eng_x_preferred":[
        "Dasta"
    ],
    "name:fas_x_preferred":[
        "\u062f\u0633\u062a\u0647"
    ],
    "name:hye_x_preferred":[
        "\u0534\u0561\u057d\u057f\u0561\u056f"
    ],
    "name:ita_x_preferred":[
        "D\u0259st\u0259"
    ],
    "name:kat_x_preferred":[
        "\u10d3\u10d0\u10e1\u10d7\u10d0"
    ],
    "name:msa_x_preferred":[
        "D\u0259st\u0259"
    ],
    "name:swe_x_preferred":[
        "Deste"
    ],
    "name:tur_x_historical":[
        "Deste"
    ],
    "name:tur_x_preferred":[
        "Deste"
    ],
    "wof:name":"Deste",
    "wof:placetype":"locality",
    "wof:population":4282
},
  "geometry": {"coordinates":[45.90963,38.88375],"type":"Point"}
}