{
  "type": "Feature",
  "properties": {
    "gn:admin1_code":"22",
    "gn:asciiname":"Qarayazi",
    "gn:country_code":"AZ",
    "gn:dem":193,
    "gn:feature_class":"P",
    "gn:feature_code":"PPL",
    "gn:name":"Qarayaz\u0131",
    "gn:population":0,
    "gn:timezone":"Asia/Baku",
    "iso:country":"AZ",
    "name:eng_x_preferred":[
        "Qarayaz\u0131"
    ],
    "name:rus_x_preferred":[
        "\u041a\u0430\u0440\u0430\u044f\u0437\u044b"
    ],
    "name:und_x_variant":[
        "Karayazy",
        "Qarayaz\u0131"
    ],
    "wof:name":"Qarayazi",
    "wof:placetype":"locality"
},
  "geometry": {"coordinates":[47.9813,40.62809],"type":"Point"}
}