{
  "type": "Feature",
  "properties": {
    "gn:admin1_code":"04",
    "gn:asciiname":"Tatlar",
    "gn:country_code":"AZ",
    "gn:dem":35,
    "gn:feature_class":"P",
    "gn:feature_code":"PPL",
    "gn:name":"Tatlar",
    "gn:population":0,
    "gn:timezone":"Asia/Baku",
    "iso:country":"AZ",
    "name:aze_x_preferred":[
        "Tatlar"
    ],
    "name:ita_x_preferred":[
        "Tatlar"
    ],
    "name:kat_x_preferred":[
        "\u10d7\u10d0\u10d7\u10da\u10d0\u10e0\u10d8"
    ],
    "name:tur_x_preferred":[
        "Tatlar"
    ],
    "wof:name":"Tatlar",
    "wof:placetype":"locality"
},
  "geometry": {"coordinates":[47.42984000000001,40.65305],"type":"Point"}
}