{
  "type": "Feature",
  "properties": {
    "gn:admin1_code":"14",
    "gn:asciiname":"Balyand",
    "gn:country_code":"AZ",
    "gn:dem":540,
    "gn:feature_class":"P",
    "gn:feature_code":"PPL",
    "gn:name":"Balyand",
    "gn:population":0,
    "gn:timezone":"Asia/Baku",
    "iso:country":"AZ",
    "name:aze_x_preferred":[
        "Balyand"
    ],
    "name:hye_x_preferred":[
        "\u0532\u0561\u056c\u0575\u0561\u0576\u0564"
    ],
    "name:rus_x_preferred":[
        "\u0411\u0430\u043b\u044f\u043d\u0434"
    ],
    "wof:name":"Balyand",
    "wof:placetype":"locality"
},
  "geometry": {"coordinates":[47.10559,39.46911],"type":"Point"}
}