{
  "type": "Feature",
  "properties": {
    "gn:admin1_code":"19",
    "gn:asciiname":"Ataxal",
    "gn:country_code":"AZ",
    "gn:dem":1202,
    "gn:feature_class":"P",
    "gn:feature_code":"PPL",
    "gn:name":"Ataxal",
    "gn:population":0,
    "gn:timezone":"Asia/Baku",
    "iso:country":"AZ",
    "name:und_x_variant":[
        "Atakhal",
        "Ataxal"
    ],
    "wof:name":"Ataxal",
    "wof:placetype":"locality"
},
  "geometry": {"coordinates":[45.62638,40.58571],"type":"Point"}
}