{
  "type": "Feature",
  "properties": {
    "gn:admin1_code":"19",
    "gn:asciiname":"Ataxal",
    "gn:country_code":"AZ",
    "gn:dem":1202,
    "gn:feature_class":"P",
    "gn:feature_code":"PPL",
    "gn:name":"Ataxal",
    "gn:population":0,
    "gn:timezone":"Asia/Baku",
    "iso:country":"AZ",
    "name:aze_x_preferred":[
        "Ataxal"
    ],
    "name:ita_x_preferred":[
        "Ataxal"
    ],
    "name:kat_x_preferred":[
        "\u10d0\u10d7\u10d0\u10ee\u10d0\u10da\u10d8"
    ],
    "name:msa_x_preferred":[
        "Ataxal"
    ],
    "name:und_x_variant":[
        "Atakhal"
    ],
    "wof:name":"Ataxal",
    "wof:placetype":"locality"
},
  "geometry": {"coordinates":[45.62638,40.58571],"type":"Point"}
}