{
  "type": "Feature",
  "properties": {
    "gn:admin1_code":"25",
    "gn:asciiname":"Qalagah",
    "gn:country_code":"AZ",
    "gn:dem":643,
    "gn:feature_class":"P",
    "gn:feature_code":"PPL",
    "gn:name":"Qalagah",
    "gn:population":0,
    "gn:timezone":"Asia/Baku",
    "iso:country":"AZ",
    "name:azb_x_preferred":[
        "\u0642\u0627\u0644\u0627\u06af\u0627\u0647"
    ],
    "name:aze_x_preferred":[
        "Qalagah"
    ],
    "name:ceb_x_preferred":[
        "Qalagah"
    ],
    "name:eng_x_preferred":[
        "Qalagah"
    ],
    "name:fas_x_preferred":[
        "\u0642\u0644\u0639\u0647\u200c\u06af\u0627\u0647"
    ],
    "name:ita_x_preferred":[
        "Qalagah"
    ],
    "name:kat_x_preferred":[
        "\u10e7\u10d0\u10da\u10d0\u10d2\u10d0\u10f0\u10d8"
    ],
    "name:lez_x_preferred":[
        "\u0413\u0430\u043b\u0430\u0433\u0430\u0433\u044c"
    ],
    "name:msa_x_preferred":[
        "Qalagah"
    ],
    "name:rus_x_preferred":[
        "\u041a\u0430\u043b\u0430\u0433\u044f\u0445"
    ],
    "name:rus_x_variant":[
        "\u0413\u0430\u043b\u0430\u0433\u0430\u0445"
    ],
    "name:swe_x_preferred":[
        "Qalagah"
    ],
    "name:und_x_variant":[
        "Kalagyakh",
        "Kalaga",
        "Qalagah"
    ],
    "wof:name":"Qalagah",
    "wof:placetype":"locality"
},
  "geometry": {"coordinates":[47.93636,40.71437],"type":"Point"}
}