{
  "type": "Feature",
  "properties": {
    "gn:admin1_code":"25",
    "gn:asciiname":"Qalagah",
    "gn:country_code":"AZ",
    "gn:dem":643,
    "gn:feature_class":"P",
    "gn:feature_code":"PPL",
    "gn:name":"Qalagah",
    "gn:population":0,
    "gn:timezone":"Asia/Baku",
    "iso:country":"AZ",
    "name:eng_x_preferred":[
        "Qalagah"
    ],
    "name:rus_x_preferred":[
        "\u041a\u0430\u043b\u0430\u0433\u044f\u0445"
    ],
    "name:und_x_variant":[
        "Kalagyakh",
        "Kalaga",
        "Qalagah"
    ],
    "wof:name":"Qalagah",
    "wof:placetype":"locality"
},
  "geometry": {"coordinates":[47.93636,40.71437],"type":"Point"}
}