{
  "type": "Feature",
  "properties": {
    "gn:admin1_code":"29",
    "gn:asciiname":"Shilyavar",
    "gn:country_code":"AZ",
    "gn:dem":-15,
    "gn:feature_class":"P",
    "gn:feature_code":"PPL",
    "gn:name":"Shilyavar",
    "gn:population":0,
    "gn:timezone":"Asia/Baku",
    "iso:country":"AZ",
    "name:azb_x_preferred":[
        "\u0634\u06cc\u0644\u0647\u200c\u0648\u0631"
    ],
    "name:aze_x_preferred":[
        "\u015eil\u0259var"
    ],
    "name:ceb_x_preferred":[
        "Shilyavar"
    ],
    "name:fas_x_preferred":[
        "\u0634\u06cc\u0644\u0647\u200c\u0648\u0631"
    ],
    "name:ita_x_preferred":[
        "\u015eilavar"
    ],
    "name:msa_x_preferred":[
        "\u015eilavar"
    ],
    "name:swe_x_preferred":[
        "Shilyavar"
    ],
    "name:und_x_variant":[
        "Shilavar",
        "Shilyavar",
        "\u015eilavar"
    ],
    "wof:name":"Shilyavar",
    "wof:placetype":"locality"
},
  "geometry": {"coordinates":[48.82958,38.75113],"type":"Point"}
}