{
  "type": "Feature",
  "properties": {
    "gn:admin1_code":"40",
    "gn:asciiname":"Omaragaly",
    "gn:country_code":"AZ",
    "gn:dem":262,
    "gn:feature_class":"P",
    "gn:feature_code":"PPL",
    "gn:name":"Omaragaly",
    "gn:population":0,
    "gn:timezone":"Asia/Baku",
    "iso:country":"AZ",
    "name:und_x_variant":[
        "\u00d6m\u0259ra\u011fal\u0131"
    ],
    "wof:name":"Omaragaly",
    "wof:placetype":"locality"
},
  "geometry": {"coordinates":[45.20383,41.27951],"type":"Point"}
}