{
  "type": "Feature",
  "properties": {
    "gn:admin1_code":"50",
    "gn:asciiname":"Yeni Qizmeydan",
    "gn:country_code":"AZ",
    "gn:dem":1279,
    "gn:feature_class":"P",
    "gn:feature_code":"PPL",
    "gn:name":"Yeni Q\u0131zmeydan",
    "gn:population":0,
    "gn:timezone":"Asia/Baku",
    "iso:country":"AZ",
    "name:azb_x_preferred":[
        "\u06cc\u0626\u0646\u06cc \u0642\u06cc\u0632\u0645\u06cc\u062f\u0627\u0646"
    ],
    "name:aze_x_preferred":[
        "Yeni Q\u0131zmeydan"
    ],
    "name:eng_x_preferred":[
        "Novoastraxanka"
    ],
    "name:kat_x_preferred":[
        "\u10d8\u10d4\u10dc\u10d8-\u10e7\u10d8\u10d6\u10db\u10d4\u10d8\u10d3\u10d0\u10dc\u10d8"
    ],
    "name:msa_x_preferred":[
        "Yeni Q\u0131zmeydan"
    ],
    "name:rus_x_preferred":[
        "\u0410\u0441\u0442\u0440\u0430\u0445\u0430\u043d\u043a\u0430"
    ],
    "name:und_x_variant":[
        "Novo-Astrakhanovka",
        "Novoastrakhanka",
        "Novoastraxanka"
    ],
    "name:urd_x_preferred":[
        "\u06cc\u0646\u06cc \u0642\u06cc\u0632\u0645\u06d2 \u062f\u0627\u0646"
    ],
    "wof:name":"Yeni Qizmeydan",
    "wof:placetype":"locality"
},
  "geometry": {"coordinates":[48.7056,40.78586],"type":"Point"}
}