{
  "type": "Feature",
  "properties": {
    "gn:admin1_code":"50",
    "gn:asciiname":"Yeni Qizmeydan",
    "gn:country_code":"AZ",
    "gn:dem":1279,
    "gn:feature_class":"P",
    "gn:feature_code":"PPL",
    "gn:name":"Yeni Q\u0131zmeydan",
    "gn:population":0,
    "gn:timezone":"Asia/Baku",
    "iso:country":"AZ",
    "name:aze_x_preferred":[
        "Yeni Q\u0131zmeydan"
    ],
    "name:eng_x_preferred":[
        "Novoastraxanka"
    ],
    "name:rus_x_preferred":[
        "\u0410\u0441\u0442\u0440\u0430\u0445\u0430\u043d\u043a\u0430"
    ],
    "name:und_x_variant":[
        "Novo-Astrakhanovka",
        "Novoastrakhanka",
        "Novoastraxanka"
    ],
    "wof:name":"Yeni Qizmeydan",
    "wof:placetype":"locality"
},
  "geometry": {"coordinates":[48.7056,40.78586],"type":"Point"}
}