{
  "type": "Feature",
  "properties": {
    "gn:admin1_code":"47",
    "gn:asciiname":"Sirinbulaq",
    "gn:country_code":"AZ",
    "gn:dem":548,
    "gn:feature_class":"P",
    "gn:feature_code":"PPL",
    "gn:name":"\u015eirinbulaq",
    "gn:population":0,
    "gn:timezone":"Asia/Baku",
    "iso:country":"AZ",
    "name:azb_x_preferred":[
        "\u0634\u06cc\u0631\u06cc\u0646 \u0628\u0648\u0644\u0627\u0642"
    ],
    "name:aze_x_preferred":[
        "\u015eirinbulaq"
    ],
    "name:ceb_x_preferred":[
        "\u015eirinbulaq"
    ],
    "name:ita_x_preferred":[
        "\u015eirinbulaq"
    ],
    "name:msa_x_preferred":[
        "\u015eirinbulaq"
    ],
    "name:swe_x_preferred":[
        "\u015eirinbulaq"
    ],
    "name:und_x_variant":[
        "Alikhanly-Shirin-Bulag",
        "\u015eirinbulaq",
        "Shirinbulak"
    ],
    "wof:name":"Sirinbulaq",
    "wof:placetype":"locality"
},
  "geometry": {"coordinates":[47.23152,40.96459],"type":"Point"}
}