{
  "type": "Feature",
  "properties": {
    "gn:admin1_code":"47",
    "gn:asciiname":"Sirinbulaq",
    "gn:country_code":"AZ",
    "gn:dem":548,
    "gn:feature_class":"P",
    "gn:feature_code":"PPL",
    "gn:name":"\u015eirinbulaq",
    "gn:population":0,
    "gn:timezone":"Asia/Baku",
    "iso:country":"AZ",
    "name:und_x_variant":[
        "Alikhanly-Shirin-Bulag",
        "\u015eirinbulaq",
        "Shirinbulak"
    ],
    "wof:name":"Sirinbulaq",
    "wof:placetype":"locality"
},
  "geometry": {"coordinates":[47.23152,40.96459],"type":"Point"}
}