{
  "type": "Feature",
  "properties": {
    "gn:admin1_code":"62",
    "gn:asciiname":"Damcili",
    "gn:country_code":"AZ",
    "gn:dem":636,
    "gn:feature_class":"P",
    "gn:feature_code":"PPL",
    "gn:name":"Damc\u0131l\u0131",
    "gn:population":0,
    "gn:timezone":"Asia/Baku",
    "iso:country":"AZ",
    "name:azb_x_preferred":[
        "\u062f\u0627\u0645\u062c\u06cc\u0644\u06cc"
    ],
    "name:aze_x_preferred":[
        "Damc\u0131l\u0131"
    ],
    "name:epo_x_preferred":[
        "Damc\u0131l\u0131"
    ],
    "name:kat_x_preferred":[
        "\u10d3\u10d0\u10db\u10ef\u10d8\u10da\u10d8"
    ],
    "name:msa_x_preferred":[
        "Damc\u0131l\u0131"
    ],
    "name:und_x_variant":[
        "Damdzhaly",
        "Damdzhyly",
        "Damzhaly"
    ],
    "wof:name":"Damcili",
    "wof:placetype":"locality"
},
  "geometry": {"coordinates":[46.22845,40.6272],"type":"Point"}
}