{
  "type": "Feature",
  "properties": {
    "gn:admin1_code":"62",
    "gn:asciiname":"Damcili",
    "gn:country_code":"AZ",
    "gn:dem":636,
    "gn:feature_class":"P",
    "gn:feature_code":"PPL",
    "gn:name":"Damc\u0131l\u0131",
    "gn:population":0,
    "gn:timezone":"Asia/Baku",
    "iso:country":"AZ",
    "name:und_x_variant":[
        "Damdzhaly",
        "Damdzhyly",
        "Damzhaly",
        "Damc\u0131l\u0131"
    ],
    "wof:name":"Damcili",
    "wof:placetype":"locality"
},
  "geometry": {"coordinates":[46.22845,40.6272],"type":"Point"}
}