{
  "type": "Feature",
  "properties": {
    "gn:admin1_code":"69",
    "gn:asciiname":"Turaabad",
    "gn:country_code":"AZ",
    "gn:dem":351,
    "gn:feature_class":"P",
    "gn:feature_code":"PPL",
    "gn:name":"Turaabad",
    "gn:population":0,
    "gn:timezone":"Asia/Baku",
    "iso:country":"AZ",
    "name:aze_x_preferred":[
        "Turaabad"
    ],
    "name:rus_x_preferred":[
        "\u0422\u0443\u0440\u0430\u0431\u0430\u0434"
    ],
    "name:und_x_variant":[
        "Turabat",
        "Turabad"
    ],
    "wof:name":"Turaabad",
    "wof:placetype":"locality"
},
  "geometry": {"coordinates":[46.71881,39.04509],"type":"Point"}
}