{
  "type": "Feature",
  "properties": {
    "gn:admin1_code":"69",
    "gn:asciiname":"Turaabad",
    "gn:country_code":"AZ",
    "gn:dem":351,
    "gn:feature_class":"P",
    "gn:feature_code":"PPL",
    "gn:name":"Turaabad",
    "gn:population":0,
    "gn:timezone":"Asia/Baku",
    "iso:country":"AZ",
    "name:azb_x_preferred":[
        "\u062a\u0648\u0631\u0627\u0628\u0627\u062f"
    ],
    "name:aze_x_preferred":[
        "Turaabad"
    ],
    "name:aze_x_variant":[
        "Turabad"
    ],
    "name:fas_x_preferred":[
        "\u062a\u0648\u0631\u0622\u0628\u0627\u062f"
    ],
    "name:kat_x_preferred":[
        "\u10d7\u10e3\u10e0\u10d0\u10d1\u10d0\u10d3\u10d8"
    ],
    "name:msa_x_preferred":[
        "Turabad"
    ],
    "name:rus_x_preferred":[
        "\u0422\u0443\u0440\u0430\u0431\u0430\u0434"
    ],
    "name:und_x_variant":[
        "Turabat"
    ],
    "wof:name":"Turaabad",
    "wof:placetype":"locality"
},
  "geometry": {"coordinates":[46.71881,39.04509],"type":"Point"}
}