{
  "type": "Feature",
  "properties": {
    "gn:admin1_code":"70",
    "gn:asciiname":"Agdam Qalal",
    "gn:country_code":"AZ",
    "gn:dem":1239,
    "gn:feature_class":"P",
    "gn:feature_code":"PPL",
    "gn:name":"A\u011fdam Qalal",
    "gn:population":0,
    "gn:timezone":"Asia/Baku",
    "iso:country":"AZ",
    "name:eng_x_preferred":[
        "A\u011fdam Qalal"
    ],
    "name:rus_x_preferred":[
        "\u0410\u0433\u0434\u0430\u043c\u043a\u0430\u043b\u0430\u043b"
    ],
    "name:und_x_variant":[
        "Agdamkelyal",
        "Agdamkelal",
        "A\u011fdam Qalal",
        "Agdamkalal"
    ],
    "wof:name":"Agdam Qalal",
    "wof:placetype":"locality"
},
  "geometry": {"coordinates":[46.89029,41.64389],"type":"Point"}
}