{
  "type": "Feature",
  "properties": {
    "gn:admin1_code":"06",
    "gn:asciiname":"Kyulyulyu",
    "gn:country_code":"AZ",
    "gn:dem":206,
    "gn:feature_class":"P",
    "gn:feature_code":"PPL",
    "gn:name":"Kyulyulyu",
    "gn:population":0,
    "gn:timezone":"Asia/Baku",
    "iso:country":"AZ",
    "name:aze_x_preferred":[
        "K\u00fcl\u00fcll\u00fc"
    ],
    "name:und_x_variant":[
        "Kululu",
        "Kyulyulyu"
    ],
    "wof:name":"Kyulyulyu",
    "wof:placetype":"locality"
},
  "geometry": {"coordinates":[48.2022,40.60648],"type":"Point"}
}