{
  "type": "Feature",
  "properties": {
    "gn:admin1_code":"11",
    "gn:asciiname":"Sarkyarlar",
    "gn:country_code":"AZ",
    "gn:dem":27,
    "gn:feature_class":"P",
    "gn:feature_code":"PPL",
    "gn:name":"Sarkyarlar",
    "gn:population":0,
    "gn:timezone":"Asia/Baku",
    "iso:country":"AZ",
    "name:aze_x_preferred":[
        "S\u0259rkarlar"
    ],
    "wof:name":"Sarkyarlar",
    "wof:placetype":"locality"
},
  "geometry": {"coordinates":[47.2619,40.36745],"type":"Point"}
}