{
  "type": "Feature",
  "properties": {
    "gn:admin1_code":"58",
    "gn:asciiname":"Agbulaq",
    "gn:country_code":"AZ",
    "gn:dem":898,
    "gn:feature_class":"P",
    "gn:feature_code":"PPL",
    "gn:name":"A\u011fbulaq",
    "gn:population":0,
    "gn:timezone":"Asia/Baku",
    "iso:country":"AZ",
    "name:azb_x_preferred":[
        "\u0622\u063a \u0628\u0648\u0644\u0627\u0642"
    ],
    "name:aze_x_preferred":[
        "A\u011fbulaq"
    ],
    "name:ceb_x_preferred":[
        "A\u011fbulaq"
    ],
    "name:ita_x_preferred":[
        "A\u011fbulaq"
    ],
    "name:kat_x_preferred":[
        "\u10d0\u10e6\u10d1\u10e3\u10da\u10d0\u10d2\u10d8"
    ],
    "name:msa_x_preferred":[
        "A\u011fbulaq"
    ],
    "name:und_x_variant":[
        "Agbulak",
        "A\u011fbulaq"
    ],
    "wof:name":"Agbulaq",
    "wof:placetype":"locality"
},
  "geometry": {"coordinates":[45.61382,40.83824],"type":"Point"}
}