{
  "type": "Feature",
  "properties": {
    "gn:admin1_code":"26",
    "gn:asciiname":"Tekekayasy",
    "gn:country_code":"AZ",
    "gn:dem":1612,
    "gn:feature_class":"P",
    "gn:feature_code":"PPL",
    "gn:name":"Tekekayasy",
    "gn:population":0,
    "gn:timezone":"Asia/Baku",
    "iso:country":"AZ",
    "name:azb_x_preferred":[
        "\u062a\u06a9\u0647 \u0686\u0627\u06cc\u0627"
    ],
    "name:aze_x_preferred":[
        "T\u0259k\u0259qaya"
    ],
    "name:aze_x_variant":[
        "T\u0259k\u0259\u00e7aya"
    ],
    "name:ell_x_preferred":[
        "\u03a4\u03b5\u03ba\u03b5\u03c4\u03c3\u03ac\u03b3\u03b9\u03b1"
    ],
    "name:fas_x_preferred":[
        "\u062a\u06a9\u0686\u0627\u06cc\u0627"
    ],
    "name:hye_x_preferred":[
        "T\u2019ek\u2019eak"
    ],
    "name:hye_x_variant":[
        "\u0539\u0565\u0584\u0565\u0561\u056f"
    ],
    "name:msa_x_preferred":[
        "T\u0259k\u0259\u00e7aya"
    ],
    "name:rus_x_preferred":[
        "\u0422\u0435\u043a\u044f\u043a\u0430\u044f"
    ],
    "name:und_x_variant":[
        "Tekyagayasi",
        "Tekyakaya"
    ],
    "wof:name":"Tekekayasy",
    "wof:placetype":"locality"
},
  "geometry": {"coordinates":[46.13117,40.26441],"type":"Point"}
}