{
  "type": "Feature",
  "properties": {
    "gn:admin1_code":"08",
    "gn:asciiname":"Tangyarud",
    "gn:country_code":"AZ",
    "gn:dem":21,
    "gn:feature_class":"P",
    "gn:feature_code":"PPL",
    "gn:name":"Tangyarud",
    "gn:population":0,
    "gn:timezone":"Asia/Baku",
    "iso:country":"AZ",
    "name:aze_x_preferred":[
        "T\u0259ng\u0259r\u00fcd"
    ],
    "name:und_x_variant":[
        "Tangerud",
        "T\u0259ng\u0259rud"
    ],
    "wof:name":"Tangyarud",
    "wof:placetype":"locality"
},
  "geometry": {"coordinates":[48.81672,38.57798],"type":"Point"}
}