{
  "type": "Feature",
  "properties": {
    "gn:admin1_code":"08",
    "gn:asciiname":"Tangyarud",
    "gn:country_code":"AZ",
    "gn:dem":21,
    "gn:feature_class":"P",
    "gn:feature_code":"PPL",
    "gn:name":"Tangyarud",
    "gn:population":0,
    "gn:timezone":"Asia/Baku",
    "iso:country":"AZ",
    "name:azb_x_preferred":[
        "\u062a\u0646\u06af\u0647\u200c\u0631\u0648\u062f"
    ],
    "name:aze_x_preferred":[
        "T\u0259ng\u0259r\u00fcd"
    ],
    "name:ceb_x_preferred":[
        "Tangyarud"
    ],
    "name:fas_x_preferred":[
        "\u062a\u0646\u06af\u0647\u200c\u0631\u0648\u062f"
    ],
    "name:ita_x_preferred":[
        "T\u0259ng\u0259rud"
    ],
    "name:kat_x_preferred":[
        "\u10d7\u10d0\u10dc\u10d2\u10d4\u10e0\u10e3\u10d3\u10d8"
    ],
    "name:msa_x_preferred":[
        "T\u0259ng\u0259rud"
    ],
    "name:rus_x_preferred":[
        "\u0422\u0430\u043d\u0433\u0435\u0440\u044e\u0434"
    ],
    "name:swe_x_preferred":[
        "Tangyarud"
    ],
    "name:und_x_variant":[
        "Tangerud"
    ],
    "wof:name":"Tangyarud",
    "wof:placetype":"locality"
},
  "geometry": {"coordinates":[48.81672,38.57798],"type":"Point"}
}