{
  "type": "Feature",
  "properties": {
    "gn:admin1_code":"57",
    "gn:asciiname":"Lyulyasaz",
    "gn:country_code":"AZ",
    "gn:dem":773,
    "gn:feature_class":"P",
    "gn:feature_code":"PPL",
    "gn:name":"Lyulyasaz",
    "gn:population":0,
    "gn:timezone":"Asia/Baku",
    "iso:country":"AZ",
    "name:aze_x_preferred":[
        "L\u00fcl\u0259saz"
    ],
    "name:aze_x_variant":[
        "Akop-Kamari"
    ],
    "name:fas_x_preferred":[
        "\u0647\u0627\u06a9\u0648\u0628 \u06a9\u0627\u0645\u0627\u0631\u06cc"
    ],
    "name:hye_x_preferred":[
        "\u0540\u0561\u056f\u0578\u0562 \u053f\u0561\u0574\u0561\u0580\u056b"
    ],
    "name:hye_x_variant":[
        "Hakob Kamari",
        "Varnkat\u2019agh",
        "\u054e\u0561\u0580\u0576\u056f\u0561\u0569\u0561\u0572"
    ],
    "name:ita_x_preferred":[
        "L\u00fcl\u0259saz"
    ],
    "name:msa_x_preferred":[
        "L\u00fcl\u0259saz"
    ],
    "name:rus_x_preferred":[
        "\u0410\u043a\u043e\u043f-\u041a\u0430\u043c\u0430\u0440\u0438"
    ],
    "name:und_x_variant":[
        "Lyulyasaz",
        "Lulasaz",
        "Lioulasaz"
    ],
    "wof:name":"Lyulyasaz",
    "wof:placetype":"locality"
},
  "geometry": {"coordinates":[46.73064,40.27428],"type":"Point"}
}