{
  "type": "Feature",
  "properties": {
    "gn:admin1_code":"45",
    "gn:asciiname":"Abbasbeyli",
    "gn:country_code":"AZ",
    "gn:dem":-10,
    "gn:feature_class":"P",
    "gn:feature_code":"PPL",
    "gn:name":"Abbasbeyli",
    "gn:population":0,
    "gn:timezone":"Asia/Baku",
    "iso:country":"AZ",
    "name:azb_x_preferred":[
        "\u0639\u0628\u0627\u0633\u200c\u0628\u06cc\u0644\u06cc"
    ],
    "name:aze_x_preferred":[
        "N\u0259rimanov"
    ],
    "name:aze_x_variant":[
        "N\u0259r\u0131manov"
    ],
    "name:ell_x_preferred":[
        "\u0391\u03bc\u03c0\u03b1\u03c3\u03bc\u03c0\u03b5\u03ca\u03bb\u03af"
    ],
    "name:fas_x_preferred":[
        "\u0639\u0628\u0627\u0633\u200c\u0628\u06cc\u0644\u06cc"
    ],
    "name:kat_x_preferred":[
        "\u10d0\u10d1\u10d0\u10e1\u10d1\u10d4\u10d8\u10da\u10d8"
    ],
    "name:msa_x_preferred":[
        "Abbasbeyli"
    ],
    "name:und_x_variant":[
        "Abasbeyli",
        "Abbasbeyli",
        "Narimanov"
    ],
    "wof:name":"Abbasbeyli",
    "wof:placetype":"locality"
},
  "geometry": {"coordinates":[48.35908,39.962],"type":"Point"}
}