{
  "type": "Feature",
  "properties": {
    "gn:admin1_code":"45",
    "gn:asciiname":"Abbasbeyli",
    "gn:country_code":"AZ",
    "gn:dem":-10,
    "gn:feature_class":"P",
    "gn:feature_code":"PPL",
    "gn:name":"Abbasbeyli",
    "gn:population":0,
    "gn:timezone":"Asia/Baku",
    "iso:country":"AZ",
    "name:aze_x_preferred":[
        "N\u0259rimanov"
    ],
    "name:aze_x_variant":[
        "N\u0259r\u0131manov"
    ],
    "name:und_x_variant":[
        "Abasbeyli",
        "Abbasbeyli",
        "Narimanov"
    ],
    "wof:name":"Abbasbeyli",
    "wof:placetype":"locality"
},
  "geometry": {"coordinates":[48.35908,39.962],"type":"Point"}
}