{
  "type": "Feature",
  "properties": {
    "gn:admin1_code":"10",
    "gn:asciiname":"Qamistala",
    "gn:country_code":"AZ",
    "gn:dem":225,
    "gn:feature_class":"P",
    "gn:feature_code":"PPL",
    "gn:name":"Qam\u0131\u015ftala",
    "gn:population":0,
    "gn:timezone":"Asia/Baku",
    "iso:country":"AZ",
    "name:ava_x_preferred":[
        "\u041d\u0443\u0446I\u0438\u0431"
    ],
    "name:aze_x_preferred":[
        "Qam\u0131\u015ftala"
    ],
    "name:ita_x_preferred":[
        "Qam\u0131\u015ftala"
    ],
    "name:kat_x_preferred":[
        "\u10e7\u10d0\u10db\u10d8\u10e8\u10d7\u10d0\u10da\u10d0"
    ],
    "name:msa_x_preferred":[
        "Qam\u0131\u015ftala"
    ],
    "name:und_x_variant":[
        "Kamyshtala",
        "Qam\u0131\u015ftala"
    ],
    "wof:name":"Qamistala",
    "wof:placetype":"locality"
},
  "geometry": {"coordinates":[46.43814,41.62944],"type":"Point"}
}