{
  "type": "Feature",
  "properties": {
    "gn:admin1_code":"31",
    "gn:asciiname":"Hovil",
    "gn:country_code":"AZ",
    "gn:dem":675,
    "gn:feature_class":"P",
    "gn:feature_code":"PPL",
    "gn:name":"Hovil",
    "gn:population":0,
    "gn:timezone":"Asia/Baku",
    "iso:country":"AZ",
    "name:aze_x_preferred":[
        "Hovil"
    ],
    "name:ceb_x_preferred":[
        "Hovil"
    ],
    "name:ita_x_preferred":[
        "Hovil"
    ],
    "name:msa_x_preferred":[
        "Hovil"
    ],
    "name:und_x_variant":[
        "Khovil\u2019",
        "Govyl\u2019",
        "Hovil"
    ],
    "wof:name":"Hovil",
    "wof:placetype":"locality"
},
  "geometry": {"coordinates":[48.61462,38.66353],"type":"Point"}
}