{
  "type": "Feature",
  "properties": {
    "gn:admin1_code":"62",
    "gn:asciiname":"Xanlar",
    "gn:country_code":"AZ",
    "gn:dem":767,
    "gn:feature_class":"P",
    "gn:feature_code":"PPL",
    "gn:name":"Xanlar",
    "gn:population":0,
    "gn:timezone":"Asia/Baku",
    "iso:country":"AZ",
    "name:aze_x_preferred":[
        "Xanlar"
    ],
    "name:und_x_variant":[
        "Khanlar"
    ],
    "wof:name":"Xanlar",
    "wof:placetype":"locality"
},
  "geometry": {"coordinates":[46.33123,40.56101],"type":"Point"}
}