{
  "type": "Feature",
  "properties": {
    "gn:admin1_code":"62",
    "gn:asciiname":"Xanlar",
    "gn:country_code":"AZ",
    "gn:dem":767,
    "gn:feature_class":"P",
    "gn:feature_code":"PPL",
    "gn:name":"Xanlar",
    "gn:population":0,
    "gn:timezone":"Asia/Baku",
    "iso:country":"AZ",
    "name:aze_x_preferred":[
        "Xanlar"
    ],
    "name:ben_x_preferred":[
        "\u099c\u09cd\u09af\u09be\u09a8\u09b2\u09be\u09b0"
    ],
    "name:ell_x_preferred":[
        "\u039e\u03b1\u03bd\u03bb\u03ac\u03c1"
    ],
    "name:heb_x_preferred":[
        "\u05e9\u05d0\u05e0\u05dc\u05d0\u05e8"
    ],
    "name:hin_x_preferred":[
        "\u091c\u093c\u0948\u0928\u094d\u0932\u0930"
    ],
    "name:hun_x_preferred":[
        "Xanlar"
    ],
    "name:und_x_variant":[
        "Khanlar"
    ],
    "name:urd_x_preferred":[
        "\u0632\u06cc\u0646\u0644\u0627\u0631"
    ],
    "wof:name":"Xanlar",
    "wof:placetype":"locality"
},
  "geometry": {"coordinates":[46.33123,40.56101],"type":"Point"}
}