{
  "type": "Feature",
  "properties": {
    "gn:admin1_code":"62",
    "gn:asciiname":"Mixaylovka",
    "gn:country_code":"AZ",
    "gn:dem":1166,
    "gn:feature_class":"P",
    "gn:feature_code":"PPL",
    "gn:name":"Mixaylovka",
    "gn:population":0,
    "gn:timezone":"Asia/Baku",
    "iso:country":"AZ",
    "name:aze_x_preferred":[
        "Mixaylovka"
    ],
    "name:aze_x_variant":[
        "B\u0259n\u00f6v\u015f\u0259li"
    ],
    "name:ceb_x_preferred":[
        "Mixaylovka"
    ],
    "name:hye_x_preferred":[
        "Getashen"
    ],
    "name:hye_x_variant":[
        "\u0533\u0565\u057f\u0561\u0577\u0565\u0576"
    ],
    "name:ita_x_preferred":[
        "Mixaylovka"
    ],
    "name:kat_x_preferred":[
        "\u10db\u10d8\u10ee\u10d0\u10d8\u10da\u10dd\u10d5\u10d9\u10d0"
    ],
    "name:msa_x_preferred":[
        "Mixaylovka"
    ],
    "name:swe_x_preferred":[
        "Mixaylovka"
    ],
    "name:und_x_variant":[
        "Mikhailovka"
    ],
    "wof:name":"Mixaylovka",
    "wof:placetype":"locality"
},
  "geometry": {"coordinates":[46.35866,40.49712],"type":"Point"}
}