{
  "type": "Feature",
  "properties": {
    "gn:admin1_code":"26",
    "gn:asciiname":"Seyidlyar",
    "gn:country_code":"AZ",
    "gn:dem":1570,
    "gn:feature_class":"P",
    "gn:feature_code":"PPL",
    "gn:name":"Seyidlyar",
    "gn:population":0,
    "gn:timezone":"Asia/Baku",
    "iso:country":"AZ",
    "name:eng_x_preferred":[
        "Seyidl\u01ddr"
    ],
    "name:hye_x_preferred":[
        "Nor Karach\u2019inar"
    ],
    "name:hye_x_variant":[
        "\u0546\u0578\u0580 \u053f\u0561\u0580\u0561\u0579\u056b\u0576\u0561\u0580"
    ],
    "name:rus_x_preferred":[
        "\u0421\u0435\u0439\u0434\u043b\u044f\u0440"
    ],
    "name:und_x_variant":[
        "Seidlyar",
        "Seydlyar",
        "Seyidl\u0259r"
    ],
    "wof:name":"Seyidlyar",
    "wof:placetype":"locality"
},
  "geometry": {"coordinates":[46.08843,40.22782],"type":"Point"}
}