{
  "type": "Feature",
  "properties": {
    "gn:admin1_code":"46",
    "gn:asciiname":"Yenibeyli",
    "gn:country_code":"AZ",
    "gn:dem":-14,
    "gn:feature_class":"P",
    "gn:feature_code":"PPL",
    "gn:name":"Yenibeyli",
    "gn:population":0,
    "gn:timezone":"Asia/Baku",
    "iso:country":"AZ",
    "name:azb_x_preferred":[
        "\u06cc\u0648\u0644\u0686\u0648 \u0628\u06cc\u200c\u0644\u06cc"
    ],
    "name:aze_x_preferred":[
        "Yol\u00e7ub\u0259yli"
    ],
    "name:ceb_x_preferred":[
        "Yenibeyli"
    ],
    "name:eng_x_preferred":[
        "Yol\u00e7ub\u01ddyli"
    ],
    "name:ita_x_preferred":[
        "Yol\u00e7ub\u0259yli"
    ],
    "name:msa_x_preferred":[
        "Yol\u00e7ub\u0259yli"
    ],
    "name:rus_x_preferred":[
        "\u0415\u043b\u0447\u0443\u0431\u0435\u0439\u043b\u0438"
    ],
    "name:swe_x_preferred":[
        "Yenibeyli"
    ],
    "name:und_x_variant":[
        "Yelshbekly",
        "Y\u00eblchubeyli"
    ],
    "wof:name":"Yenibeyli",
    "wof:placetype":"locality"
},
  "geometry": {"coordinates":[48.39006,40.05802],"type":"Point"}
}