{
  "type": "Feature",
  "properties": {
    "gn:admin1_code":"03",
    "gn:asciiname":"Qaraqasli",
    "gn:country_code":"AZ",
    "gn:dem":257,
    "gn:feature_class":"P",
    "gn:feature_code":"PPL",
    "gn:name":"Qaraqa\u015fl\u0131",
    "gn:population":0,
    "gn:timezone":"Asia/Baku",
    "iso:country":"AZ",
    "name:aze_x_preferred":[
        "Qaraqa\u015fl\u0131"
    ],
    "name:rus_x_preferred":[
        "\u041a\u0430\u0440\u0430\u043a\u0430\u0448\u043b\u044b"
    ],
    "name:und_x_variant":[
        "Karakashly"
    ],
    "wof:name":"Qaraqasli",
    "wof:placetype":"locality"
},
  "geometry": {"coordinates":[46.99496,40.07535],"type":"Point"}
}