{
  "type": "Feature",
  "properties": {
    "gn:admin1_code":"28",
    "gn:asciiname":"Hacixanli",
    "gn:country_code":"AZ",
    "gn:dem":1619,
    "gn:feature_class":"P",
    "gn:feature_code":"PPL",
    "gn:name":"Hac\u0131xanl\u0131",
    "gn:population":0,
    "gn:timezone":"Asia/Baku",
    "iso:country":"AZ",
    "name:aze_x_preferred":[
        "Zorke\u015fi\u015f"
    ],
    "name:aze_x_variant":[
        "Hac\u0131xanl\u0131"
    ],
    "name:fas_x_preferred":[
        "\u0632\u0648\u0631\u06a9\u0634\u06cc\u0634"
    ],
    "name:hye_x_preferred":[
        "Zork\u2019eshish"
    ],
    "name:hye_x_variant":[
        "\u0536\u0578\u0580\u0584\u0565\u0577\u056b\u0577",
        "Zorats\u2019ik\u2019",
        "\u0536\u0578\u0580\u0561\u0581\u056b\u0584"
    ],
    "name:kat_x_preferred":[
        "\u10d6\u10dd\u10e0\u10e5\u10d4\u10e8\u10d8\u10e8\u10d8"
    ],
    "name:msa_x_preferred":[
        "Zorkeshish"
    ],
    "name:rus_x_preferred":[
        "\u0417\u043e\u0440\u043a\u0435\u0448\u0438\u0448"
    ],
    "name:und_x_variant":[
        "Zorkishiga",
        "Zorkeshysh",
        "Zorkeshish",
        "\u0417\u043e\u0440\u043a\u0435\u0448\u0438\u0448"
    ],
    "wof:name":"Hacixanli",
    "wof:placetype":"locality"
},
  "geometry": {"coordinates":[46.26715,39.85952],"type":"Point"}
}