{
  "type": "Feature",
  "properties": {
    "gn:admin1_code":"28",
    "gn:asciiname":"Arab",
    "gn:country_code":"AZ",
    "gn:dem":1095,
    "gn:feature_class":"P",
    "gn:feature_code":"PPL",
    "gn:name":"Arab",
    "gn:population":0,
    "gn:timezone":"Asia/Baku",
    "iso:country":"AZ",
    "name:aze_x_preferred":[
        "\u018fr\u0259b"
    ],
    "name:rus_x_preferred":[
        "\u0410\u0440\u0430\u0431"
    ],
    "wof:name":"Arab",
    "wof:placetype":"locality"
},
  "geometry": {"coordinates":[46.6013,39.59255],"type":"Point"}
}