{
  "type": "Feature",
  "properties": {
    "gn:admin1_code":"17",
    "gn:asciiname":"Tazakend",
    "gn:country_code":"AZ",
    "gn:dem":31,
    "gn:feature_class":"P",
    "gn:feature_code":"PPL",
    "gn:name":"Tazakend",
    "gn:population":0,
    "gn:timezone":"Asia/Baku",
    "iso:country":"AZ",
    "name:und_x_variant":[
        "T\u0259z\u0259k\u0259nd"
    ],
    "wof:name":"Tazakend",
    "wof:placetype":"locality"
},
  "geometry": {"coordinates":[48.8879,41.3475],"type":"Point"}
}