{
  "type": "Feature",
  "properties": {
    "gn:admin1_code":"39",
    "gn:asciiname":"Deymadagly",
    "gn:country_code":"AZ",
    "gn:dem":211,
    "gn:feature_class":"P",
    "gn:feature_code":"PPL",
    "gn:name":"Deymadagly",
    "gn:population":0,
    "gn:timezone":"Asia/Baku",
    "iso:country":"AZ",
    "name:und_x_variant":[
        "Daymadagly",
        "Deymadagly",
        "D\u0259ym\u0259da\u011fl\u0131"
    ],
    "wof:name":"Deymadagly",
    "wof:placetype":"locality"
},
  "geometry": {"coordinates":[46.77499,41.33127],"type":"Point"}
}