{
  "type": "Feature",
  "properties": {
    "gn:admin1_code":"18",
    "gn:asciiname":"Horadiz",
    "gn:country_code":"AZ",
    "gn:dem":255,
    "gn:feature_class":"P",
    "gn:feature_code":"PPL",
    "gn:name":"Horadiz",
    "gn:population":0,
    "gn:timezone":"Asia/Baku",
    "iso:country":"AZ",
    "name:azb_x_preferred":[
        "\u0647\u0648\u0631\u0627\u062f\u06cc\u0632"
    ],
    "name:aze_x_preferred":[
        "Horadiz"
    ],
    "name:bel_x_preferred":[
        "\u0413\u0430\u0440\u0430\u0434\u044b\u0437"
    ],
    "name:ceb_x_preferred":[
        "Horadiz"
    ],
    "name:che_x_preferred":[
        "\u0413\u043e\u0440\u0430\u0434\u0438\u0437"
    ],
    "name:fas_x_preferred":[
        "\u0647\u0648\u0631\u0627\u062f\u0632"
    ],
    "name:fin_x_preferred":[
        "Horadiz"
    ],
    "name:hsb_x_preferred":[
        "Horadiz"
    ],
    "name:hye_x_preferred":[
        "\u0540\u0578\u0580\u0561\u0564\u056b\u0566"
    ],
    "name:hye_x_variant":[
        "\u053d\u0578\u057c\u0561\u057f\u0578\u0582\u0576\u056b\u0584"
    ],
    "name:ita_x_preferred":[
        "Horadiz"
    ],
    "name:kat_x_preferred":[
        "\u10f0\u10dd\u10e0\u10d0\u10d3\u10d8\u10d6\u10d8"
    ],
    "name:msa_x_preferred":[
        "Horadiz"
    ],
    "name:pol_x_preferred":[
        "Horadiz"
    ],
    "name:rus_x_preferred":[
        "\u0413\u043e\u0440\u0430\u0434\u0438\u0437"
    ],
    "name:swe_x_preferred":[
        "Horadiz"
    ],
    "name:und_x_variant":[
        "Goradiz",
        "\u0413\u043e\u0440\u0430\u0434\u0438\u0437"
    ],
    "wof:name":"Horadiz",
    "wof:placetype":"locality"
},
  "geometry": {"coordinates":[47.23321,39.45162],"type":"Point"}
}