{
  "type": "Feature",
  "properties": {
    "gn:admin1_code":"18",
    "gn:asciiname":"Horadiz",
    "gn:country_code":"AZ",
    "gn:dem":255,
    "gn:feature_class":"P",
    "gn:feature_code":"PPL",
    "gn:name":"Horadiz",
    "gn:population":0,
    "gn:timezone":"Asia/Baku",
    "iso:country":"AZ",
    "name:aze_x_preferred":[
        "Horadiz"
    ],
    "name:hye_x_preferred":[
        "\u0540\u0578\u0580\u0561\u0564\u056b\u0566"
    ],
    "name:rus_x_preferred":[
        "\u0413\u043e\u0440\u0430\u0434\u0438\u0437"
    ],
    "name:und_x_variant":[
        "Goradiz",
        "\u0413\u043e\u0440\u0430\u0434\u0438\u0437"
    ],
    "wof:name":"Horadiz",
    "wof:placetype":"locality"
},
  "geometry": {"coordinates":[47.23321,39.45162],"type":"Point"}
}