{
  "type": "Feature",
  "properties": {
    "gn:admin1_code":"35",
    "gn:admin2_code":"147365.0",
    "gn:asciiname":"Ashagy Andamich",
    "gn:country_code":"AZ",
    "gn:dem":1042,
    "gn:feature_class":"P",
    "gn:feature_code":"PPL",
    "gn:name":"Ashagy Andamich",
    "gn:population":0,
    "gn:timezone":"Asia/Baku",
    "iso:country":"AZ",
    "name:aze_x_preferred":[
        "A\u015fa\u011f\u0131 \u018fnd\u0259mic"
    ],
    "name:aze_x_variant":[
        "A\u015fa\u011f\u0131 \u018fnd\u0259mi\u00e7"
    ],
    "name:und_x_variant":[
        "Ashaga Andamish",
        "Ashagy Andamich"
    ],
    "wof:name":"Ashagy Andamich",
    "wof:placetype":"locality"
},
  "geometry": {"coordinates":[46.02016,38.92744],"type":"Point"}
}