{
  "type": "Feature",
  "properties": {
    "gn:admin1_code":"17",
    "gn:asciiname":"Qorqan",
    "gn:country_code":"AZ",
    "gn:dem":517,
    "gn:feature_class":"P",
    "gn:feature_code":"PPL",
    "gn:name":"Qorqan",
    "gn:population":0,
    "gn:timezone":"Asia/Baku",
    "iso:country":"AZ",
    "name:und_x_variant":[
        "Korgan",
        "Qorqan"
    ],
    "wof:name":"Qorqan",
    "wof:placetype":"locality"
},
  "geometry": {"coordinates":[48.80777,41.17013],"type":"Point"}
}