{
  "type": "Feature",
  "properties": {
    "gn:admin1_code":"17",
    "gn:asciiname":"Qorqan",
    "gn:country_code":"AZ",
    "gn:dem":517,
    "gn:feature_class":"P",
    "gn:feature_code":"PPL",
    "gn:name":"Qorqan",
    "gn:population":0,
    "gn:timezone":"Asia/Baku",
    "iso:country":"AZ",
    "name:azb_x_preferred":[
        "\u0642\u0648\u0631\u063a\u0627\u0646"
    ],
    "name:aze_x_preferred":[
        "Qor\u011fan"
    ],
    "name:fas_x_preferred":[
        "\u06af\u0631\u06af\u0627\u0646"
    ],
    "name:ita_x_preferred":[
        "Qorqan"
    ],
    "name:msa_x_preferred":[
        "Qorqan"
    ],
    "name:und_x_variant":[
        "Korgan",
        "Qorqan"
    ],
    "wof:name":"Qorqan",
    "wof:placetype":"locality"
},
  "geometry": {"coordinates":[48.80777,41.17013],"type":"Point"}
}