{
  "type": "Feature",
  "properties": {
    "gn:admin1_code":"06",
    "gn:asciiname":"Khalilli",
    "gn:country_code":"AZ",
    "gn:dem":32,
    "gn:feature_class":"P",
    "gn:feature_code":"PPL",
    "gn:name":"Khalilli",
    "gn:population":0,
    "gn:timezone":"Asia/Baku",
    "iso:country":"AZ",
    "name:und_x_variant":[
        "Khayli",
        "Khalli",
        "Khalilli",
        "X\u0259lilli"
    ],
    "wof:name":"Khalilli",
    "wof:placetype":"locality"
},
  "geometry": {"coordinates":[48.17027,40.49402],"type":"Point"}
}