{
  "type": "Feature",
  "properties": {
    "gn:admin1_code":"65",
    "gn:asciiname":"Amaras",
    "gn:country_code":"AZ",
    "gn:dem":539,
    "gn:feature_class":"P",
    "gn:feature_code":"PPL",
    "gn:name":"Amaras",
    "gn:population":0,
    "gn:timezone":"Asia/Baku",
    "iso:country":"AZ",
    "name:hye_x_preferred":[
        "\u0531\u0574\u0561\u0580\u0561\u057d"
    ],
    "wof:name":"Amaras",
    "wof:placetype":"locality"
},
  "geometry": {"coordinates":[47.07216,39.68376],"type":"Point"}
}