{
  "type": "Feature",
  "properties": {
    "gn:admin1_code":"11",
    "gn:asciiname":"Soganverdilar",
    "gn:country_code":"AZ",
    "gn:dem":96,
    "gn:feature_class":"P",
    "gn:feature_code":"PPL",
    "gn:name":"Soganverdilar",
    "gn:population":0,
    "gn:timezone":"Asia/Baku",
    "iso:country":"AZ",
    "name:aze_x_preferred":[
        "So\u011fanverdil\u0259r"
    ],
    "name:und_x_variant":[
        "Subkhanverdilar",
        "Soganverdilar"
    ],
    "wof:name":"Soganverdilar",
    "wof:placetype":"locality"
},
  "geometry": {"coordinates":[47.12226,40.23266],"type":"Point"}
}