{
  "type": "Feature",
  "properties": {
    "gn:admin1_code":"11",
    "gn:asciiname":"Soganverdilar",
    "gn:country_code":"AZ",
    "gn:dem":96,
    "gn:feature_class":"P",
    "gn:feature_code":"PPL",
    "gn:name":"Soganverdilar",
    "gn:population":0,
    "gn:timezone":"Asia/Baku",
    "iso:country":"AZ",
    "name:aze_x_preferred":[
        "So\u011fanverdil\u0259r"
    ],
    "name:ceb_x_preferred":[
        "Soganverdilar"
    ],
    "name:ita_x_preferred":[
        "So\u011fanverdil\u0259r"
    ],
    "name:kat_x_preferred":[
        "\u10e1\u10dd\u10e6\u10d0\u10dc\u10d5\u10d4\u10e0\u10d3\u10d8\u10da\u10d0\u10e0\u10d8"
    ],
    "name:msa_x_preferred":[
        "So\u011fanverdil\u0259r"
    ],
    "name:swe_x_preferred":[
        "Soganverdilar"
    ],
    "name:und_x_variant":[
        "Subkhanverdilar",
        "Soganverdilar"
    ],
    "wof:name":"Soganverdilar",
    "wof:placetype":"locality"
},
  "geometry": {"coordinates":[47.12226,40.23266],"type":"Point"}
}