{
  "type": "Feature",
  "properties": {
    "gn:admin1_code":"04",
    "gn:asciiname":"Emirarkh",
    "gn:country_code":"AZ",
    "gn:dem":17,
    "gn:feature_class":"P",
    "gn:feature_code":"PPL",
    "gn:name":"Emirarkh",
    "gn:population":0,
    "gn:timezone":"Asia/Baku",
    "iso:country":"AZ",
    "name:und_x_variant":[
        "Amirarkh",
        "\u018fmirarx"
    ],
    "wof:name":"Emirarkh",
    "wof:placetype":"locality"
},
  "geometry": {"coordinates":[47.37909000000001,40.55725],"type":"Point"}
}