{
  "type": "Feature",
  "properties": {
    "gn:admin1_code":"04",
    "gn:asciiname":"Emirarkh",
    "gn:country_code":"AZ",
    "gn:dem":17,
    "gn:feature_class":"P",
    "gn:feature_code":"PPL",
    "gn:name":"Emirarkh",
    "gn:population":0,
    "gn:timezone":"Asia/Baku",
    "iso:country":"AZ",
    "name:azb_x_preferred":[
        "\u0627\u0645\u06cc\u0631\u0627\u0631\u062e"
    ],
    "name:aze_x_preferred":[
        "\u018fmirarx"
    ],
    "name:ceb_x_preferred":[
        "Emirarkh"
    ],
    "name:ita_x_preferred":[
        "\u018fmirarx"
    ],
    "name:kat_x_preferred":[
        "\u10d0\u10db\u10d8\u10e0\u10d0\u10e0\u10ee\u10d8"
    ],
    "name:msa_x_preferred":[
        "\u018fmirarx"
    ],
    "name:rus_x_preferred":[
        "\u0410\u043c\u0438\u0440\u0430\u0440\u0445"
    ],
    "name:swe_x_preferred":[
        "Emirarkh"
    ],
    "name:und_x_variant":[
        "Amirarkh"
    ],
    "wof:name":"Emirarkh",
    "wof:placetype":"locality"
},
  "geometry": {"coordinates":[47.37909000000001,40.55725],"type":"Point"}
}