{
  "type": "Feature",
  "properties": {
    "gn:admin1_code":"02",
    "gn:asciiname":"Nadzhafulibeyli",
    "gn:country_code":"AZ",
    "gn:dem":22,
    "gn:feature_class":"P",
    "gn:feature_code":"PPL",
    "gn:name":"Nadzhafulibeyli",
    "gn:population":0,
    "gn:timezone":"Asia/Baku",
    "iso:country":"AZ",
    "name:aze_x_preferred":[
        "N\u0259c\u0259fqulub\u0259yli"
    ],
    "name:und_x_variant":[
        "Nadzhafkulubeyli",
        "Nadzhafkulibeyli",
        "N\u0259c\u0259fqulub\u0259li"
    ],
    "wof:name":"Nadzhafulibeyli",
    "wof:placetype":"locality"
},
  "geometry": {"coordinates":[47.54898,40.1597],"type":"Point"}
}