{
  "type": "Feature",
  "properties": {
    "gn:admin1_code":"47",
    "gn:asciiname":"Cunud",
    "gn:country_code":"AZ",
    "gn:dem":670,
    "gn:feature_class":"P",
    "gn:feature_code":"PPL",
    "gn:name":"Cunud",
    "gn:population":0,
    "gn:timezone":"Asia/Baku",
    "iso:country":"AZ",
    "name:aze_x_preferred":[
        "Cunud"
    ],
    "name:und_x_variant":[
        "Dzhunut",
        "Cunut"
    ],
    "wof:name":"Cunud",
    "wof:placetype":"locality"
},
  "geometry": {"coordinates":[47.04744,41.35085],"type":"Point"}
}