{
  "type": "Feature",
  "properties": {
    "gn:admin1_code":"65",
    "gn:asciiname":"Shekher",
    "gn:country_code":"AZ",
    "gn:dem":764,
    "gn:feature_class":"P",
    "gn:feature_code":"PPL",
    "gn:name":"Shekher",
    "gn:population":0,
    "gn:timezone":"Asia/Baku",
    "iso:country":"AZ",
    "name:aze_x_preferred":[
        "\u015e\u0259k\u0259r"
    ],
    "name:hye_x_preferred":[
        "\u0547\u0565\u056d\u0565\u0580"
    ],
    "name:rus_x_preferred":[
        "\u0428\u0435\u0445\u0435\u0440"
    ],
    "wof:name":"Shekher",
    "wof:placetype":"locality"
},
  "geometry": {"coordinates":[46.98117,39.65113],"type":"Point"}
}