{
  "type": "Feature",
  "properties": {
    "gn:admin1_code":"31",
    "gn:asciiname":"Khalfakyudzha",
    "gn:country_code":"AZ",
    "gn:dem":1225,
    "gn:feature_class":"P",
    "gn:feature_code":"PPL",
    "gn:name":"Khalfakyudzha",
    "gn:population":0,
    "gn:timezone":"Asia/Baku",
    "iso:country":"AZ",
    "name:aze_x_preferred":[
        "X\u0259l\u0131f\u0259k\u00fcc\u0259"
    ],
    "name:und_x_variant":[
        "X\u0259lf\u0259k\u00fcc\u0259"
    ],
    "wof:name":"Khalfakyudzha",
    "wof:placetype":"locality"
},
  "geometry": {"coordinates":[48.4349,38.74624],"type":"Point"}
}