{
  "type": "Feature",
  "properties": {
    "gn:admin1_code":"46",
    "gn:asciiname":"Chygyrgan",
    "gn:country_code":"AZ",
    "gn:dem":-23,
    "gn:feature_class":"P",
    "gn:feature_code":"PPL",
    "gn:name":"Chygyrgan",
    "gn:population":0,
    "gn:timezone":"Asia/Baku",
    "iso:country":"AZ",
    "name:azb_x_preferred":[
        "\u0686\u06cc\u063a\u06cc\u0631\u063a\u0627\u0646"
    ],
    "name:aze_x_preferred":[
        "\u00c7\u0131\u011f\u0131r\u011fan"
    ],
    "name:ceb_x_preferred":[
        "Chygyrgan"
    ],
    "name:ita_x_preferred":[
        "\u00c7\u0131\u011f\u0131r\u011fan"
    ],
    "name:msa_x_preferred":[
        "\u00c7\u0131\u011f\u0131r\u011fan"
    ],
    "name:swe_x_preferred":[
        "Chygyrgan"
    ],
    "name:und_x_variant":[
        "Chagyrgan",
        "Chygyrgan"
    ],
    "wof:name":"Chygyrgan",
    "wof:placetype":"locality"
},
  "geometry": {"coordinates":[48.92974,39.77001],"type":"Point"}
}