{
  "type": "Feature",
  "properties": {
    "gn:admin1_code":"35",
    "gn:admin2_code":"8014931.0",
    "gn:asciiname":"Yurdcu",
    "gn:country_code":"AZ",
    "gn:dem":1008,
    "gn:feature_class":"P",
    "gn:feature_code":"PPL",
    "gn:name":"Yurd\u00e7u",
    "gn:population":0,
    "gn:timezone":"Asia/Baku",
    "iso:country":"AZ",
    "name:azb_x_preferred":[
        "\u06cc\u0648\u0631\u062f\u0686\u0648"
    ],
    "name:aze_x_preferred":[
        "Yurd\u00e7u"
    ],
    "name:hye_x_preferred":[
        "\u0545\u0578\u0582\u0580\u0564\u0579\u056b"
    ],
    "name:ita_x_preferred":[
        "Yurd\u00e7u"
    ],
    "name:kat_x_preferred":[
        "\u10d8\u10e3\u10e0\u10d3\u10e9\u10e3"
    ],
    "name:msa_x_preferred":[
        "Yurd\u00e7u"
    ],
    "name:pol_x_preferred":[
        "Yurd\u00e7u"
    ],
    "name:und_x_variant":[
        "Yurtchi",
        "Yurdchu"
    ],
    "name:urd_x_preferred":[
        "\u06cc\u0648\u0631\u062f\u06a9\u0648"
    ],
    "wof:name":"Yurdcu",
    "wof:placetype":"locality"
},
  "geometry": {"coordinates":[45.15001,39.4089],"type":"Point"}
}