{
  "type": "Feature",
  "properties": {
    "gn:admin1_code":"71",
    "gn:asciiname":"Karavelli",
    "gn:country_code":"AZ",
    "gn:dem":-8,
    "gn:feature_class":"P",
    "gn:feature_code":"PPL",
    "gn:name":"Karavelli",
    "gn:population":0,
    "gn:timezone":"Asia/Baku",
    "iso:country":"AZ",
    "name:eng_x_preferred":[
        "Qarav\u01ddlli"
    ],
    "name:rus_x_preferred":[
        "\u041a\u0430\u0440\u0430\u0432\u0435\u043b\u043b\u0438"
    ],
    "name:und_x_variant":[
        "Karavelyan",
        "Karavelli",
        "Qarav\u0259lli"
    ],
    "wof:name":"Karavelli",
    "wof:placetype":"locality"
},
  "geometry": {"coordinates":[47.78027,40.16914000000001],"type":"Point"}
}