{
  "type": "Feature",
  "properties": {
    "gn:admin1_code":"64",
    "gn:asciiname":"Dagraz",
    "gn:country_code":"AZ",
    "gn:dem":1010,
    "gn:feature_class":"P",
    "gn:feature_code":"PPL",
    "gn:name":"Dagraz",
    "gn:population":0,
    "gn:timezone":"Asia/Baku",
    "iso:country":"AZ",
    "name:aze_x_preferred":[
        "D\u0259hr\u0259z"
    ],
    "name:hye_x_preferred":[
        "\u0534\u0561\u0570\u0580\u0561\u0566"
    ],
    "name:hye_x_variant":[
        "Dahraz",
        "Dahrav"
    ],
    "name:rus_x_preferred":[
        "\u0414\u0430\u0433\u0440\u0430\u0437"
    ],
    "name:und_x_variant":[
        "Dahrav",
        "Dagraz",
        "Dahraz",
        "\u0414\u0430\u0433\u0440\u0430\u0437"
    ],
    "wof:name":"Dagraz",
    "wof:placetype":"locality"
},
  "geometry": {"coordinates":[46.87402,39.87174],"type":"Point"}
}