{
  "type": "Feature",
  "properties": {
    "gn:admin1_code":"31",
    "gn:asciiname":"Asagi Bradi",
    "gn:country_code":"AZ",
    "gn:dem":1011,
    "gn:feature_class":"P",
    "gn:feature_code":"PPL",
    "gn:name":"A\u015fa\u011f\u0131 Bradi",
    "gn:population":0,
    "gn:timezone":"Asia/Baku",
    "iso:country":"AZ",
    "name:ita_x_preferred":[
        "A\u015fa\u011f\u0131 Bradi"
    ],
    "name:msa_x_preferred":[
        "A\u015fa\u011f\u0131 Bradi"
    ],
    "name:und_x_variant":[
        "Ashagy-Burady",
        "Borady"
    ],
    "wof:name":"Asagi Bradi",
    "wof:placetype":"locality"
},
  "geometry": {"coordinates":[48.58974,38.64826],"type":"Point"}
}