{
  "type": "Feature",
  "properties": {
    "gn:admin1_code":"58",
    "gn:asciiname":"Qosa",
    "gn:country_code":"AZ",
    "gn:dem":1409,
    "gn:feature_class":"P",
    "gn:feature_code":"PPL",
    "gn:name":"Qo\u015fa",
    "gn:population":0,
    "gn:timezone":"Asia/Baku",
    "iso:country":"AZ",
    "name:aze_x_preferred":[
        "Qo\u015fa"
    ],
    "name:ita_x_preferred":[
        "Qo\u015fa"
    ],
    "name:msa_x_preferred":[
        "Qo\u015fa"
    ],
    "name:und_x_variant":[
        "Kosha"
    ],
    "wof:name":"Qosa",
    "wof:placetype":"locality"
},
  "geometry": {"coordinates":[45.56448,40.77721],"type":"Point"}
}