{
  "type": "Feature",
  "properties": {
    "gn:admin1_code":"31",
    "gn:asciiname":"Huseynabad",
    "gn:country_code":"AZ",
    "gn:dem":1590,
    "gn:feature_class":"P",
    "gn:feature_code":"PPL",
    "gn:name":"H\u00fcseynabad",
    "gn:population":0,
    "gn:timezone":"Asia/Baku",
    "iso:country":"AZ",
    "name:aze_x_preferred":[
        "H\u00fcseynabad"
    ],
    "name:ell_x_preferred":[
        "\u03a7\u03b9\u03bf\u03c5\u03c3\u03b5\u03ca\u03bd\u03b1\u03bc\u03c0\u03ac\u03bd\u03c4"
    ],
    "name:ita_x_preferred":[
        "H\u00fcseynabad"
    ],
    "name:msa_x_preferred":[
        "H\u00fcseynabad"
    ],
    "name:und_x_variant":[
        "Guseynabad"
    ],
    "wof:name":"Huseynabad",
    "wof:placetype":"locality"
},
  "geometry": {"coordinates":[48.33306,38.63239],"type":"Point"}
}