{
  "type": "Feature",
  "properties": {
    "gn:admin1_code":"31",
    "gn:asciiname":"Huseynabad",
    "gn:country_code":"AZ",
    "gn:dem":1590,
    "gn:feature_class":"P",
    "gn:feature_code":"PPL",
    "gn:name":"H\u00fcseynabad",
    "gn:population":0,
    "gn:timezone":"Asia/Baku",
    "iso:country":"AZ",
    "name:aze_x_preferred":[
        "H\u00fcseynabad"
    ],
    "name:und_x_variant":[
        "Guseynabad"
    ],
    "wof:name":"Huseynabad",
    "wof:placetype":"locality"
},
  "geometry": {"coordinates":[48.33306,38.63239],"type":"Point"}
}