{
  "type": "Feature",
  "properties": {
    "gn:admin1_code":"36",
    "gn:asciiname":"Shorkend",
    "gn:country_code":"AZ",
    "gn:dem":-23,
    "gn:feature_class":"P",
    "gn:feature_code":"PPL",
    "gn:name":"Shorkend",
    "gn:population":0,
    "gn:timezone":"Asia/Baku",
    "iso:country":"AZ",
    "name:und_x_variant":[
        "\u015eork\u0259nd"
    ],
    "wof:name":"Shorkend",
    "wof:placetype":"locality"
},
  "geometry": {"coordinates":[49.00084,39.60681],"type":"Point"}
}