{
  "type": "Feature",
  "properties": {
    "gn:admin1_code":"18",
    "gn:asciiname":"Chemen",
    "gn:country_code":"AZ",
    "gn:dem":583,
    "gn:feature_class":"P",
    "gn:feature_code":"PPL",
    "gn:name":"Chemen",
    "gn:population":0,
    "gn:timezone":"Asia/Baku",
    "iso:country":"AZ",
    "name:aze_x_preferred":[
        "\u00c7im\u0259n"
    ],
    "name:rus_x_preferred":[
        "\u0427\u0438\u043c\u0430\u043d"
    ],
    "name:und_x_variant":[
        "Chiman"
    ],
    "wof:name":"Chemen",
    "wof:placetype":"locality"
},
  "geometry": {"coordinates":[47.09655,39.56706],"type":"Point"}
}