{
  "type": "Feature",
  "properties": {
    "gn:admin1_code":"18",
    "gn:asciiname":"Chemen",
    "gn:country_code":"AZ",
    "gn:dem":583,
    "gn:feature_class":"P",
    "gn:feature_code":"PPL",
    "gn:name":"Chemen",
    "gn:population":0,
    "gn:timezone":"Asia/Baku",
    "iso:country":"AZ",
    "name:aze_x_preferred":[
        "\u00c7im\u0259n"
    ],
    "name:ell_x_preferred":[
        "\u03a4\u03c3\u03b9\u03bc\u03ad\u03bd"
    ],
    "name:fas_x_preferred":[
        "\u0686\u0645\u0646"
    ],
    "name:ita_x_preferred":[
        "\u00c7im\u0259n"
    ],
    "name:kat_x_preferred":[
        "\u10e9\u10d8\u10db\u10d0\u10dc\u10d8"
    ],
    "name:msa_x_preferred":[
        "\u00c7im\u0259n"
    ],
    "name:rus_x_preferred":[
        "\u0427\u0438\u043c\u0430\u043d"
    ],
    "name:und_x_variant":[
        "Chiman"
    ],
    "wof:name":"Chemen",
    "wof:placetype":"locality"
},
  "geometry": {"coordinates":[47.09655,39.56706],"type":"Point"}
}