{
  "type": "Feature",
  "properties": {
    "gn:admin1_code":"45",
    "gn:asciiname":"Saatli",
    "gn:country_code":"AZ",
    "gn:dem":-7,
    "gn:feature_class":"P",
    "gn:feature_code":"PPLA",
    "gn:name":"Saatl\u0131",
    "gn:population":87000,
    "gn:timezone":"Asia/Baku",
    "iso:country":"AZ",
    "name:ara_x_preferred":[
        "\u0645\u0642\u0627\u0637\u0639\u0629 \u0633\u0627\u062a\u0644\u064a"
    ],
    "name:azb_x_preferred":[
        "\u0633\u0627\u0639\u0627\u062a\u0644\u06cc \u0631\u0627\u06cc\u0648\u0646\u0648"
    ],
    "name:aze_x_preferred":[
        "Saatl\u0131 rayonu"
    ],
    "name:bre_x_preferred":[
        "Saatl\u0131"
    ],
    "name:ceb_x_preferred":[
        "Saatly Rayon"
    ],
    "name:che_x_preferred":[
        "\u0421\u0430\u0430\u0442\u043b\u0438\u043d \u043a\u04c0\u043e\u0448\u0442"
    ],
    "name:deu_x_preferred":[
        "Saatl\u0131"
    ],
    "name:fas_x_preferred":[
        "\u0634\u0647\u0631\u0633\u062a\u0627\u0646 \u0633\u0627\u0639\u062a\u0644\u06cc"
    ],
    "name:fin_x_preferred":[
        "Saatl\u0131n piirikunta"
    ],
    "name:fra_x_preferred":[
        "Saatl\u0131"
    ],
    "name:hrv_x_preferred":[
        "Satlinski rajon"
    ],
    "name:ind_x_preferred":[
        "Saatly"
    ],
    "name:kor_x_preferred":[
        "\uc0ac\ud2c0\ub974 \uad6c"
    ],
    "name:mkd_x_preferred":[
        "\u0421\u0430\u0430\u0442\u043b\u0438"
    ],
    "name:msa_x_preferred":[
        "Daerah Saatly"
    ],
    "name:nld_x_preferred":[
        "Saatl\u0131"
    ],
    "name:nor_x_preferred":[
        "Saatl\u0131"
    ],
    "name:pnb_x_preferred":[
        "\u0634\u0627\u062a\u0644\u06cc"
    ],
    "name:pol_x_preferred":[
        "Rejon Saatl\u0131"
    ],
    "name:por_x_preferred":[
        "Saatly"
    ],
    "name:rus_x_preferred":[
        "\u0421\u0430\u0430\u0442\u043b\u044b"
    ],
    "name:rus_x_variant":[
        "\u0421\u0430\u0430\u0442\u043b\u0438\u043d\u0441\u043a\u0438\u0439 \u0440\u0430\u0439\u043e\u043d"
    ],
    "name:sqi_x_preferred":[
        "Saatly"
    ],
    "name:srp_x_preferred":[
        "\u0421\u0430\u0442\u043b\u0438\u043d\u0441\u043a\u0438 \u0440\u0435\u0458\u043e\u043d"
    ],
    "name:sun_x_preferred":[
        "Rayon Saatly"
    ],
    "name:swe_x_preferred":[
        "Saatl\u0131 Rayonu"
    ],
    "name:tur_x_preferred":[
        "Saatl\u0131 Rayonu"
    ],
    "name:und_x_variant":[
        "Saotly"
    ],
    "name:vie_x_preferred":[
        "Saatly"
    ],
    "name:war_x_preferred":[
        "Saatly Rayon"
    ],
    "name:zho_x_preferred":[
        "\u85a9\u7279\u96f7\u5340"
    ],
    "wof:name":"Saatli",
    "wof:placetype":"locality",
    "wof:population":87000
},
  "geometry": {"coordinates":[48.36892,39.93214],"type":"Point"}
}