{
  "type": "Feature",
  "properties": {
    "gn:admin1_code":"45",
    "gn:asciiname":"Saatli",
    "gn:country_code":"AZ",
    "gn:dem":-7,
    "gn:feature_class":"P",
    "gn:feature_code":"PPLA",
    "gn:name":"Saatl\u0131",
    "gn:population":87000,
    "gn:timezone":"Asia/Baku",
    "iso:country":"AZ",
    "name:rus_x_preferred":[
        "\u0421\u0430\u0430\u0442\u043b\u044b"
    ],
    "name:und_x_variant":[
        "Saatly",
        "Saotly",
        "Saatl\u0131"
    ],
    "wof:name":"Saatli",
    "wof:placetype":"locality",
    "wof:population":87000
},
  "geometry": {"coordinates":[48.36892,39.93214],"type":"Point"}
}