{
  "type": "Feature",
  "properties": {
    "gn:admin1_code":"09",
    "gn:asciiname":"Akhmedly",
    "gn:country_code":"AZ",
    "gn:dem":39,
    "gn:feature_class":"P",
    "gn:feature_code":"PPL",
    "gn:name":"Akhmedly",
    "gn:population":0,
    "gn:timezone":"Asia/Baku",
    "iso:country":"AZ",
    "name:ara_x_preferred":[
        "\u0623\u062d\u0645\u062f\u0644\u064a"
    ],
    "name:azb_x_preferred":[
        "\u0627\u062d\u0645\u062f\u0644\u06cc"
    ],
    "name:aze_x_preferred":[
        "\u018fhm\u0259dli"
    ],
    "name:ceb_x_preferred":[
        "Akhmedly"
    ],
    "name:eng_x_preferred":[
        "\u018fhm\u01dddli"
    ],
    "name:fas_x_preferred":[
        "\u0627\u062d\u0645\u062f\u0644\u06cc"
    ],
    "name:rus_x_preferred":[
        "\u0410\u0445\u043c\u0435\u0434\u043b\u0438"
    ],
    "name:swe_x_preferred":[
        "\u018fhm\u0259dli"
    ],
    "name:und_x_variant":[
        "Akhmedli",
        "Akhmedly"
    ],
    "wof:name":"Akhmedly",
    "wof:placetype":"locality"
},
  "geometry": {"coordinates":[49.94737,40.38584],"type":"Point"}
}