{
  "type": "Feature",
  "properties": {
    "gn:admin1_code":"31",
    "gn:asciiname":"Keskon",
    "gn:country_code":"AZ",
    "gn:dem":833,
    "gn:feature_class":"P",
    "gn:feature_code":"PPL",
    "gn:name":"Keskon",
    "gn:population":0,
    "gn:timezone":"Asia/Baku",
    "iso:country":"AZ",
    "name:aze_x_preferred":[
        "Keskon"
    ],
    "name:aze_x_variant":[
        "Geskon"
    ],
    "wof:name":"Keskon",
    "wof:placetype":"locality"
},
  "geometry": {"coordinates":[48.35247,38.83172],"type":"Point"}
}