{
  "type": "Feature",
  "properties": {
    "gn:admin1_code":"22",
    "gn:asciiname":"Geraybeyli",
    "gn:country_code":"AZ",
    "gn:dem":18,
    "gn:feature_class":"P",
    "gn:feature_code":"PPL",
    "gn:name":"Geraybeyli",
    "gn:population":0,
    "gn:timezone":"Asia/Baku",
    "iso:country":"AZ",
    "name:aze_x_preferred":[
        "G\u0259rayb\u0259yli"
    ],
    "wof:name":"Geraybeyli",
    "wof:placetype":"locality"
},
  "geometry": {"coordinates":[47.65583,40.53083],"type":"Point"}
}