{
  "type": "Feature",
  "properties": {
    "gn:admin1_code":"08",
    "gn:asciiname":"Veneshikesh",
    "gn:country_code":"AZ",
    "gn:dem":164,
    "gn:feature_class":"P",
    "gn:feature_code":"PPL",
    "gn:name":"Veneshikesh",
    "gn:population":0,
    "gn:timezone":"Asia/Baku",
    "iso:country":"AZ",
    "name:aze_x_preferred":[
        "V\u0259n\u0259\u015fik\u0259\u015f"
    ],
    "wof:name":"Veneshikesh",
    "wof:placetype":"locality"
},
  "geometry": {"coordinates":[48.72618,38.53535],"type":"Point"}
}