{
  "type": "Feature",
  "properties": {
    "gn:admin1_code":"35",
    "gn:admin2_code":"7669114.0",
    "gn:asciiname":"Leninabad",
    "gn:country_code":"AZ",
    "gn:dem":918,
    "gn:feature_class":"P",
    "gn:feature_code":"PPL",
    "gn:name":"Leninabad",
    "gn:population":0,
    "gn:timezone":"Asia/Baku",
    "iso:country":"AZ",
    "name:aze_x_preferred":[
        "K\u0259rimb\u0259yli"
    ],
    "name:aze_x_variant":[
        "A\u015fa\u011f\u0131 Leninabad"
    ],
    "name:ceb_x_preferred":[
        "Leninabad"
    ],
    "name:hye_x_preferred":[
        "\u053c\u0565\u0576\u056b\u0576\u0561\u0562\u0561\u0564"
    ],
    "name:swe_x_preferred":[
        "Leninabad"
    ],
    "name:und_x_variant":[
        "Ashagy Leninabad"
    ],
    "wof:name":"Leninabad",
    "wof:placetype":"locality"
},
  "geometry": {"coordinates":[45.45336,39.25209],"type":"Point"}
}