{
  "type": "Feature",
  "properties": {
    "gn:admin1_code":"42",
    "gn:asciiname":"Kyurkyun",
    "gn:country_code":"AZ",
    "gn:dem":1016,
    "gn:feature_class":"P",
    "gn:feature_code":"PPL",
    "gn:name":"Kyurkyun",
    "gn:population":0,
    "gn:timezone":"Asia/Baku",
    "iso:country":"AZ",
    "name:azb_x_preferred":[
        "\u06a9\u0648\u0631\u06a9\u0648\u0646"
    ],
    "name:aze_x_preferred":[
        "K\u00fcrk\u00fcn"
    ],
    "name:ceb_x_preferred":[
        "Kyurkyun"
    ],
    "name:ita_x_preferred":[
        "K\u00fcrk\u00fcn"
    ],
    "name:msa_x_preferred":[
        "K\u00fcrk\u00fcn"
    ],
    "name:swe_x_preferred":[
        "Kyurkyun"
    ],
    "name:und_x_variant":[
        "K\u00fcrk\u00fcn"
    ],
    "wof:name":"Kyurkyun",
    "wof:placetype":"locality"
},
  "geometry": {"coordinates":[48.35906,41.37336],"type":"Point"}
}