{
  "type": "Feature",
  "properties": {
    "gn:admin1_code":"50",
    "gn:asciiname":"Saradil",
    "gn:country_code":"AZ",
    "gn:dem":740,
    "gn:feature_class":"P",
    "gn:feature_code":"PPL",
    "gn:name":"\u015e\u0259r\u0259dil",
    "gn:population":0,
    "gn:timezone":"Asia/Baku",
    "iso:country":"AZ",
    "name:und_x_variant":[
        "Sharadil\u2019",
        "Sheradil\u2019",
        "\u015e\u0259r\u0259dil"
    ],
    "wof:name":"Saradil",
    "wof:placetype":"locality"
},
  "geometry": {"coordinates":[48.47432,40.62001],"type":"Point"}
}