{
  "type": "Feature",
  "properties": {
    "gn:admin1_code":"50",
    "gn:asciiname":"Saradil",
    "gn:country_code":"AZ",
    "gn:dem":740,
    "gn:feature_class":"P",
    "gn:feature_code":"PPL",
    "gn:name":"\u015e\u0259r\u0259dil",
    "gn:population":0,
    "gn:timezone":"Asia/Baku",
    "iso:country":"AZ",
    "name:aze_x_preferred":[
        "\u015e\u0259r\u0259dil"
    ],
    "name:ceb_x_preferred":[
        "\u015e\u0259r\u0259dil"
    ],
    "name:ita_x_preferred":[
        "\u015e\u0259r\u0259dil"
    ],
    "name:kat_x_preferred":[
        "\u10e8\u10d0\u10e0\u10d0\u10d3\u10d8\u10da\u10d8"
    ],
    "name:min_x_preferred":[
        "\u015e\u0259r\u0259dil"
    ],
    "name:msa_x_preferred":[
        "\u015e\u0259r\u0259dil"
    ],
    "name:swe_x_preferred":[
        "\u015e\u0259r\u0259dil"
    ],
    "name:und_x_variant":[
        "Sharadil\u2019",
        "Sheradil\u2019"
    ],
    "wof:name":"Saradil",
    "wof:placetype":"locality"
},
  "geometry": {"coordinates":[48.47432,40.62001],"type":"Point"}
}