{
  "type": "Feature",
  "properties": {
    "iso:country":"AZ",
    "name:azb_x_preferred":[
        "\u0628\u0627\u0646\u06a9\u0647"
    ],
    "name:aze_x_preferred":[
        "Bank\u0259"
    ],
    "name:bar_x_preferred":[
        "Banke"
    ],
    "name:ceb_x_preferred":[
        "Severo-Vostotchnyi Bank"
    ],
    "name:eng_x_preferred":[
        "Bank\u0259"
    ],
    "name:fas_x_preferred":[
        "\u0628\u0627\u0646\u06a9\u0647"
    ],
    "name:msa_x_preferred":[
        "Bank\u0259"
    ],
    "name:nld_x_preferred":[
        "Bank\u0259"
    ],
    "name:rus_x_preferred":[
        "\u0411\u0430\u043d\u043a"
    ],
    "name:swe_x_preferred":[
        "Severo-Vostotchnyi Bank"
    ],
    "name:unk_x_variant":[
        "Imeni Kirova"
    ],
    "qs:gn_country":"AZ",
    "qs:gn_fcode":"PPL",
    "qs:gn_pop":7075,
    "qs:name":"Bank",
    "qs:name_adm0":"Azerbaijan",
    "qs:name_adm1":"Neftcala",
    "qs:photos":0,
    "qs:photos_1k":0,
    "qs:photos_9k":0,
    "qs:photos_9r":0,
    "qs:photos_all":0,
    "qs:photos_sr":0,
    "qs:placetype":"Town",
    "qs:pop_sr":"5",
    "qs:woe_adm0":23424741,
    "wd:wordcount":81,
    "wof:name":"Bank",
    "wof:placetype":"locality",
    "wof:population":7075
},
  "geometry": {"coordinates":[49.24792,39.41117],"type":"Point"}
}