{
  "type": "Feature",
  "properties": {
    "gn:admin1_code":"31",
    "gn:asciiname":"Osnakhakyudzha",
    "gn:country_code":"AZ",
    "gn:dem":1247,
    "gn:feature_class":"P",
    "gn:feature_code":"PPL",
    "gn:name":"Osnakhakyudzha",
    "gn:population":0,
    "gn:timezone":"Asia/Baku",
    "iso:country":"AZ",
    "name:aze_x_preferred":[
        "Osna\u011fak\u00fcc\u0259"
    ],
    "wof:name":"Osnakhakyudzha",
    "wof:placetype":"locality"
},
  "geometry": {"coordinates":[48.42532,38.74517],"type":"Point"}
}