{
  "type": "Feature",
  "properties": {
    "gn:admin1_code":"57",
    "gn:asciiname":"Miqrelalay",
    "gn:country_code":"AZ",
    "gn:dem":760,
    "gn:feature_class":"P",
    "gn:feature_code":"PPL",
    "gn:name":"Miqrelalay",
    "gn:population":0,
    "gn:timezone":"Asia/Baku",
    "iso:country":"AZ",
    "name:aze_x_preferred":[
        "Miqrelalay"
    ],
    "name:hye_x_preferred":[
        "K\u2019mk\u2019adzor"
    ],
    "name:hye_x_variant":[
        "\u0554\u0574\u0584\u0561\u0571\u0578\u0580"
    ],
    "name:rus_x_preferred":[
        "Mingrel\u2019sk"
    ],
    "name:rus_x_variant":[
        "\u041c\u0438\u043d\u0433\u0440\u0435\u043b\u044c\u0441\u043a"
    ],
    "name:und_x_variant":[
        "Mingrelsk",
        "Minqrelsk"
    ],
    "wof:name":"Miqrelalay",
    "wof:placetype":"locality"
},
  "geometry": {"coordinates":[46.73447,40.2464],"type":"Point"}
}