{
  "type": "Feature",
  "properties": {
    "gn:admin1_code":"57",
    "gn:asciiname":"Miqrelalay",
    "gn:country_code":"AZ",
    "gn:dem":760,
    "gn:feature_class":"P",
    "gn:feature_code":"PPL",
    "gn:name":"Miqrelalay",
    "gn:population":0,
    "gn:timezone":"Asia/Baku",
    "iso:country":"AZ",
    "name:azb_x_preferred":[
        "\u0645\u0642\u0631\u0644\u0627\u0644\u0627\u06cc"
    ],
    "name:aze_x_preferred":[
        "Miqrelalay"
    ],
    "name:aze_x_variant":[
        "Meqrelalay"
    ],
    "name:bel_x_preferred":[
        "\u0412\u0430\u0440\u043d\u043a\u0430\u0442\u0430\u0433"
    ],
    "name:fas_x_preferred":[
        "\u0648\u0627\u0631\u0646\u06a9\u0627\u062a\u0627\u063a"
    ],
    "name:fra_x_preferred":[
        "Varnkatagh"
    ],
    "name:hye_x_preferred":[
        "K\u2019mk\u2019adzor"
    ],
    "name:hye_x_variant":[
        "\u0554\u0574\u0584\u0561\u0571\u0578\u0580",
        "\u054e\u0561\u0580\u0576\u056f\u0561\u0569\u0561\u0572"
    ],
    "name:ita_x_preferred":[
        "Varnkatagh"
    ],
    "name:msa_x_preferred":[
        "Miqrelalay"
    ],
    "name:rus_x_preferred":[
        "Mingrel\u2019sk"
    ],
    "name:rus_x_variant":[
        "\u041c\u0438\u043d\u0433\u0440\u0435\u043b\u044c\u0441\u043a"
    ],
    "name:ukr_x_preferred":[
        "\u0412\u0430\u0440\u043d\u043a\u0430\u0442\u0430\u0433"
    ],
    "name:und_x_variant":[
        "Mingrelsk",
        "Minqrelsk"
    ],
    "wof:name":"Miqrelalay",
    "wof:placetype":"locality"
},
  "geometry": {"coordinates":[46.73447,40.2464],"type":"Point"}
}