{
  "type": "Feature",
  "properties": {
    "gn:country":"AZ",
    "gn:fcode":"PPL",
    "gn:population":72989,
    "iso:country":"AZ",
    "name:ast_x_preferred":[
        "Qara\u00e7uxur"
    ],
    "name:azb_x_preferred":[
        "\u0642\u0627\u0631\u0627\u0686\u0648\u062e\u0648\u0631"
    ],
    "name:aze_x_preferred":[
        "Qara\u00e7uxur"
    ],
    "name:ceb_x_preferred":[
        "Qara\u00e7uxur"
    ],
    "name:ces_x_preferred":[
        "Garad\u017euchur"
    ],
    "name:che_x_preferred":[
        "\u0413\u0430\u0440\u0430\u0447\u0443\u0445\u0443\u0440"
    ],
    "name:ell_x_preferred":[
        "\u039a\u03b1\u03c1\u03b1\u03c4\u03c3\u03bf\u03c5\u03c3\u03bf\u03cd\u03c1"
    ],
    "name:eng_x_preferred":[
        "Qara\u00e7uxur"
    ],
    "name:fas_x_preferred":[
        "\u0642\u0627\u0631\u0627\u0686\u0648\u062e\u0648\u0631"
    ],
    "name:fra_x_preferred":[
        "Qara\u00e7uxur"
    ],
    "name:jpn_x_preferred":[
        "\u30ab\u30e9\u30c1\u30e5\u30af\u30eb"
    ],
    "name:mlg_x_preferred":[
        "Qara\u00e7uxur"
    ],
    "name:nld_x_preferred":[
        "Qara\u00e7uxur"
    ],
    "name:pol_x_preferred":[
        "Qara\u00e7uxur"
    ],
    "name:por_x_preferred":[
        "Qara\u00e7uxur"
    ],
    "name:ron_x_preferred":[
        "Qaracuxur"
    ],
    "name:rus_x_preferred":[
        "\u0413\u0430\u0440\u0430\u0447\u0443\u0445\u0443\u0440"
    ],
    "name:rus_x_variant":[
        "\u041a\u0430\u0440\u0430\u0447\u0443\u0445\u0443\u0440"
    ],
    "name:swe_x_preferred":[
        "Qara\u00e7uxur"
    ],
    "name:tur_x_preferred":[
        "Baskal"
    ],
    "name:und_x_variant":[
        "Kaganovicha"
    ],
    "qs:name":"Qara\u00e7uxur",
    "qs:photos_9r":0,
    "qs:photos_sr":0,
    "qs:pop_sr":"8",
    "wd:wordcount":65,
    "wof:name":"Qara\u00e7uxur",
    "wof:placetype":"locality",
    "wof:population":72989
},
  "geometry": {"coordinates":[49.97361,40.39667],"type":"Point"}
}