{
  "type": "Feature",
  "properties": {
    "gn:admin1_code":"27",
    "gn:asciiname":"Muradxan",
    "gn:country_code":"AZ",
    "gn:dem":-10,
    "gn:feature_class":"P",
    "gn:feature_code":"PPL",
    "gn:name":"Muradxan",
    "gn:population":0,
    "gn:timezone":"Asia/Baku",
    "iso:country":"AZ",
    "name:azb_x_preferred":[
        "\u0645\u0648\u0631\u0627\u062f\u062e\u0627\u0646"
    ],
    "name:aze_x_preferred":[
        "Muradxan"
    ],
    "name:eng_x_preferred":[
        "Muradxan"
    ],
    "name:ita_x_preferred":[
        "Muradxan"
    ],
    "name:msa_x_preferred":[
        "Muradxan"
    ],
    "name:rus_x_preferred":[
        "\u041c\u0443\u0440\u0430\u0434\u0445\u0430\u043d"
    ],
    "name:und_x_variant":[
        "Muradzhanly",
        "Muradkhan"
    ],
    "wof:name":"Muradxan",
    "wof:placetype":"locality"
},
  "geometry": {"coordinates":[48.14613,40.19032],"type":"Point"}
}