{
  "type": "Feature",
  "properties": {
    "gn:admin1_code":"31",
    "gn:asciiname":"Noda",
    "gn:country_code":"AZ",
    "gn:dem":730,
    "gn:feature_class":"P",
    "gn:feature_code":"PPL",
    "gn:name":"Noda",
    "gn:population":0,
    "gn:timezone":"Asia/Baku",
    "iso:country":"AZ",
    "name:ceb_x_preferred":[
        "Noda"
    ],
    "name:ita_x_preferred":[
        "Noda"
    ],
    "name:msa_x_preferred":[
        "Noda"
    ],
    "wof:name":"Noda",
    "wof:placetype":"locality"
},
  "geometry": {"coordinates":[48.4591,38.81163],"type":"Point"}
}