{
  "type": "Feature",
  "properties": {
    "gn:admin1_code":"31",
    "gn:asciiname":"Kegna-Orand",
    "gn:country_code":"AZ",
    "gn:dem":1645,
    "gn:feature_class":"P",
    "gn:feature_code":"PPL",
    "gn:name":"Kegna-Orand",
    "gn:population":0,
    "gn:timezone":"Asia/Baku",
    "iso:country":"AZ",
    "name:aze_x_preferred":[
        "K\u00f6hn\u0259 Orand"
    ],
    "wof:name":"Kegna-Orand",
    "wof:placetype":"locality"
},
  "geometry": {"coordinates":[48.34349,38.76153],"type":"Point"}
}