{
  "type": "Feature",
  "properties": {
    "gn:admin1_code":"16",
    "gn:asciiname":"Molla-Gasanly",
    "gn:country_code":"AZ",
    "gn:dem":1638,
    "gn:feature_class":"P",
    "gn:feature_code":"PPL",
    "gn:name":"Molla-Gasanly",
    "gn:population":0,
    "gn:timezone":"Asia/Baku",
    "iso:country":"AZ",
    "name:und_x_variant":[
        "Mollagasanli",
        "Molla-Gasanly",
        "Mollah\u0259s\u0259nli"
    ],
    "wof:name":"Molla-Gasanly",
    "wof:placetype":"locality"
},
  "geometry": {"coordinates":[46.10357,40.48629],"type":"Point"}
}