{
  "type": "Feature",
  "properties": {
    "gn:admin1_code":"42",
    "gn:asciiname":"Valvala",
    "gn:country_code":"AZ",
    "gn:dem":199,
    "gn:feature_class":"P",
    "gn:feature_code":"PPL",
    "gn:name":"V\u0259lv\u0259l\u0259",
    "gn:population":0,
    "gn:timezone":"Asia/Baku",
    "iso:country":"AZ",
    "name:aze_x_preferred":[
        "V\u0259lv\u0259l\u0259"
    ],
    "name:ceb_x_preferred":[
        "V\u0259lv\u0259l\u0259"
    ],
    "name:ita_x_preferred":[
        "V\u0259lv\u0259l\u0259"
    ],
    "name:msa_x_preferred":[
        "V\u0259lv\u0259l\u0259"
    ],
    "name:swe_x_preferred":[
        "V\u0259lv\u0259l\u0259"
    ],
    "name:und_x_variant":[
        "Vel\u2019veli"
    ],
    "wof:name":"Valvala",
    "wof:placetype":"locality"
},
  "geometry": {"coordinates":[48.77892,41.33687000000001],"type":"Point"}
}