{
  "type": "Feature",
  "properties": {
    "gn:admin1_code":"32",
    "gn:asciiname":"Alisanli",
    "gn:country_code":"AZ",
    "gn:dem":-15,
    "gn:feature_class":"P",
    "gn:feature_code":"PPL",
    "gn:name":"Al\u0131\u015fanl\u0131",
    "gn:population":0,
    "gn:timezone":"Asia/Baku",
    "iso:country":"AZ",
    "name:azb_x_preferred":[
        "\u0622\u0644\u06cc\u0634\u0627\u0646\u0644\u06cc"
    ],
    "name:aze_x_preferred":[
        "Al\u0131\u015fanl\u0131"
    ],
    "name:ceb_x_preferred":[
        "Al\u0131\u015fanl\u0131"
    ],
    "name:fas_x_preferred":[
        "\u0627\u0644\u06cc\u0633\u0627\u0646\u0644\u06cc"
    ],
    "name:ita_x_preferred":[
        "Al\u0131\u015fanl\u0131"
    ],
    "name:msa_x_preferred":[
        "Al\u0131\u015fanl\u0131"
    ],
    "name:swe_x_preferred":[
        "Al\u0131\u015fanl\u0131"
    ],
    "name:und_x_variant":[
        "Alishanly",
        "Alyshanly"
    ],
    "wof:name":"Alisanli",
    "wof:placetype":"locality"
},
  "geometry": {"coordinates":[48.72223,39.06158],"type":"Point"}
}