{
  "type": "Feature",
  "properties": {
    "gn:admin1_code":"05",
    "gn:asciiname":"Alekseyevka",
    "gn:country_code":"AZ",
    "gn:dem":407,
    "gn:feature_class":"P",
    "gn:feature_code":"PPL",
    "gn:name":"Alekseyevka",
    "gn:population":0,
    "gn:timezone":"Asia/Baku",
    "iso:country":"AZ",
    "name:fas_x_preferred":[
        "\u0627\u0644\u06a9\u0633\u06cc\u0648\u06a9\u0627"
    ],
    "name:ita_x_preferred":[
        "Alekseyevka"
    ],
    "name:kat_x_preferred":[
        "\u10d0\u10da\u10d4\u10e5\u10e1\u10d4\u10d4\u10d5\u10d9\u10d0"
    ],
    "name:msa_x_preferred":[
        "Alekseyevka"
    ],
    "name:und_x_variant":[
        "Alexeevka Selo",
        "Alekseyevka"
    ],
    "wof:name":"Alekseyevka",
    "wof:placetype":"locality"
},
  "geometry": {"coordinates":[45.51667,41.06667],"type":"Point"}
}