{
  "type": "Feature",
  "properties": {
    "gn:admin1_code":"36",
    "gn:asciiname":"Asagi Qaramanli",
    "gn:country_code":"AZ",
    "gn:dem":-23,
    "gn:feature_class":"P",
    "gn:feature_code":"PPL",
    "gn:name":"A\u015fa\u011f\u0131 Qaramanl\u0131",
    "gn:population":0,
    "gn:timezone":"Asia/Baku",
    "iso:country":"AZ",
    "name:aze_x_preferred":[
        "A\u015fa\u011f\u0131 Qaraimanl\u0131"
    ],
    "name:und_x_variant":[
        "Nizhniye Karaimanly",
        "Ashagy Karaymanly",
        "Karaimanly",
        "A\u015fa\u011f\u0131 Qaramanl\u0131"
    ],
    "wof:name":"Asagi Qaramanli",
    "wof:placetype":"locality"
},
  "geometry": {"coordinates":[49.04091,39.42985],"type":"Point"}
}