{
  "type": "Feature",
  "properties": {
    "gn:admin1_code":"36",
    "gn:asciiname":"Asagi Qaramanli",
    "gn:country_code":"AZ",
    "gn:dem":-23,
    "gn:feature_class":"P",
    "gn:feature_code":"PPL",
    "gn:name":"A\u015fa\u011f\u0131 Qaramanl\u0131",
    "gn:population":0,
    "gn:timezone":"Asia/Baku",
    "iso:country":"AZ",
    "name:azb_x_preferred":[
        "\u0622\u0634\u0627\u063a\u06cc \u0642\u0627\u0631\u0627\u0645\u0627\u0646\u0644\u06cc"
    ],
    "name:aze_x_preferred":[
        "A\u015fa\u011f\u0131 Qaraimanl\u0131"
    ],
    "name:aze_x_variant":[
        "A\u015fa\u011f\u0131 Qaramanl\u0131"
    ],
    "name:ceb_x_preferred":[
        "A\u015fa\u011f\u0131 Qaramanl\u0131"
    ],
    "name:ita_x_preferred":[
        "A\u015fa\u011f\u0131 Qaramanl\u0131"
    ],
    "name:msa_x_preferred":[
        "A\u015fa\u011f\u0131 Qaramanl\u0131"
    ],
    "name:swe_x_preferred":[
        "A\u015fa\u011f\u0131 Qaramanl\u0131"
    ],
    "name:und_x_variant":[
        "Nizhniye Karaimanly",
        "Ashagy Karaymanly",
        "Karaimanly"
    ],
    "wof:name":"Asagi Qaramanli",
    "wof:placetype":"locality"
},
  "geometry": {"coordinates":[49.04091,39.42985],"type":"Point"}
}