{
  "type": "Feature",
  "properties": {
    "gn:admin1_code":"10",
    "gn:asciiname":"Ayritala",
    "gn:country_code":"AZ",
    "gn:dem":248,
    "gn:feature_class":"P",
    "gn:feature_code":"PPL",
    "gn:name":"Ayritala",
    "gn:population":0,
    "gn:timezone":"Asia/Baku",
    "iso:country":"AZ",
    "name:ava_x_preferred":[
        "\u0413\u044c\u0435\u0442I\u0430\u0440\u0430\u0431\u0442\u0430\u043b\u0430"
    ],
    "name:azb_x_preferred":[
        "\u0627\u06cc\u0631\u06cc \u0637\u0627\u0644\u0627"
    ],
    "name:aze_x_preferred":[
        "\u018fyritala"
    ],
    "name:ell_x_preferred":[
        "\u0395\u03ca\u03c1\u03af\u03c4\u03b1\u03bb\u03b1"
    ],
    "name:ita_x_preferred":[
        "\u018fyritala"
    ],
    "name:kat_x_preferred":[
        "\u10d0\u10d8\u10e0\u10d8\u10d7\u10d0\u10da\u10d0"
    ],
    "name:msa_x_preferred":[
        "\u018fyritala"
    ],
    "name:und_x_variant":[
        "Ayritala"
    ],
    "wof:name":"Ayritala",
    "wof:placetype":"locality"
},
  "geometry": {"coordinates":[46.41492,41.65496],"type":"Point"}
}