{
  "type": "Feature",
  "properties": {
    "gn:admin1_code":"10",
    "gn:asciiname":"Ayritala",
    "gn:country_code":"AZ",
    "gn:dem":248,
    "gn:feature_class":"P",
    "gn:feature_code":"PPL",
    "gn:name":"Ayritala",
    "gn:population":0,
    "gn:timezone":"Asia/Baku",
    "iso:country":"AZ",
    "name:und_x_variant":[
        "\u018fyritala",
        "Ayritala"
    ],
    "wof:name":"Ayritala",
    "wof:placetype":"locality"
},
  "geometry": {"coordinates":[46.41492,41.65496],"type":"Point"}
}