{
  "type": "Feature",
  "properties": {
    "gn:admin1_code":"42",
    "gn:asciiname":"Konakh-Kent",
    "gn:country_code":"AZ",
    "gn:dem":1076,
    "gn:feature_class":"P",
    "gn:feature_code":"PPL",
    "gn:name":"Konakh-Kent",
    "gn:population":0,
    "gn:timezone":"Asia/Baku",
    "iso:country":"AZ",
    "name:eng_x_preferred":[
        "Qonaqk\u01ddnd"
    ],
    "name:rus_x_preferred":[
        "\u041a\u043e\u043d\u0430\u0433\u043a\u0435\u043d\u0434"
    ],
    "name:und_x_variant":[
        "Konakhkend",
        "Konagkend",
        "Konakh-Kent",
        "Qonaqk\u0259nd"
    ],
    "wof:name":"Konakh-Kent",
    "wof:placetype":"locality"
},
  "geometry": {"coordinates":[48.60839,41.07315],"type":"Point"}
}