{
  "type": "Feature",
  "properties": {
    "gn:admin1_code":"66",
    "gn:asciiname":"Horonu",
    "gn:country_code":"AZ",
    "gn:dem":841,
    "gn:feature_class":"P",
    "gn:feature_code":"PPL",
    "gn:name":"Horonu",
    "gn:population":0,
    "gn:timezone":"Asia/Baku",
    "iso:country":"AZ",
    "name:aze_x_preferred":[
        "Horonu"
    ],
    "name:ceb_x_preferred":[
        "Horonu"
    ],
    "name:ita_x_preferred":[
        "Horonu"
    ],
    "name:kat_x_preferred":[
        "\u10f0\u10dd\u10e0\u10dd\u10dc\u10e3"
    ],
    "name:msa_x_preferred":[
        "Horonu"
    ],
    "name:swe_x_preferred":[
        "Horonu"
    ],
    "name:tur_x_preferred":[
        "Horonu"
    ],
    "name:und_x_variant":[
        "Orony",
        "Goronu"
    ],
    "wof:name":"Horonu",
    "wof:placetype":"locality"
},
  "geometry": {"coordinates":[48.3914,38.94139000000001],"type":"Point"}
}