{
  "type": "Feature",
  "properties": {
    "gn:admin1_code":"66",
    "gn:asciiname":"Horonu",
    "gn:country_code":"AZ",
    "gn:dem":841,
    "gn:feature_class":"P",
    "gn:feature_code":"PPL",
    "gn:name":"Horonu",
    "gn:population":0,
    "gn:timezone":"Asia/Baku",
    "iso:country":"AZ",
    "name:und_x_variant":[
        "Orony",
        "Horonu",
        "Goronu"
    ],
    "wof:name":"Horonu",
    "wof:placetype":"locality"
},
  "geometry": {"coordinates":[48.3914,38.94139000000001],"type":"Point"}
}