{
  "type": "Feature",
  "properties": {
    "gn:admin1_code":"14",
    "gn:asciiname":"Huseynalilar",
    "gn:country_code":"AZ",
    "gn:dem":329,
    "gn:feature_class":"P",
    "gn:feature_code":"PPL",
    "gn:name":"H\u00fcseynal\u0131lar",
    "gn:population":0,
    "gn:timezone":"Asia/Baku",
    "iso:country":"AZ",
    "name:aze_x_preferred":[
        "H\u00fcseynal\u0131lar"
    ],
    "name:und_x_variant":[
        "Guseynalylar"
    ],
    "wof:name":"Huseynalilar",
    "wof:placetype":"locality"
},
  "geometry": {"coordinates":[47.05306,39.325],"type":"Point"}
}