{
  "type": "Feature",
  "properties": {
    "gn:admin1_code":"31",
    "gn:asciiname":"Sifyakeran",
    "gn:country_code":"AZ",
    "gn:dem":426,
    "gn:feature_class":"P",
    "gn:feature_code":"PPL",
    "gn:name":"Sifyakeran",
    "gn:population":0,
    "gn:timezone":"Asia/Baku",
    "iso:country":"AZ",
    "name:aze_x_preferred":[
        "Sif\u0259k\u0259ran"
    ],
    "name:aze_x_variant":[
        "Siv\u0259k\u0259ran"
    ],
    "wof:name":"Sifyakeran",
    "wof:placetype":"locality"
},
  "geometry": {"coordinates":[48.61178,38.75332],"type":"Point"}
}