{
  "type": "Feature",
  "properties": {
    "gn:admin1_code":"29",
    "gn:asciiname":"Goysaban",
    "gn:country_code":"AZ",
    "gn:dem":-23,
    "gn:feature_class":"P",
    "gn:feature_code":"PPL",
    "gn:name":"G\u00f6y\u015faban",
    "gn:population":0,
    "gn:timezone":"Asia/Baku",
    "iso:country":"AZ",
    "name:azb_x_preferred":[
        "\u06af\u0624\u06cc \u0634\u0627\u0628\u0627\u0646"
    ],
    "name:aze_x_preferred":[
        "Olxovka"
    ],
    "name:aze_x_variant":[
        "G\u00f6y\u015faban"
    ],
    "name:ceb_x_preferred":[
        "G\u00f6y\u015faban"
    ],
    "name:ita_x_preferred":[
        "G\u00f6y\u015faban"
    ],
    "name:msa_x_preferred":[
        "G\u00f6y\u015faban"
    ],
    "name:swe_x_preferred":[
        "G\u00f6y\u015faban"
    ],
    "name:und_x_variant":[
        "Ol\u2019khovka",
        "Marushli"
    ],
    "wof:name":"Goysaban",
    "wof:placetype":"locality"
},
  "geometry": {"coordinates":[48.82831,38.80584],"type":"Point"}
}