{
  "type": "Feature",
  "properties": {
    "gn:admin1_code":"19",
    "gn:asciiname":"Ragimli",
    "gn:country_code":"AZ",
    "gn:dem":1456,
    "gn:feature_class":"P",
    "gn:feature_code":"PPL",
    "gn:name":"Ragimli",
    "gn:population":0,
    "gn:timezone":"Asia/Baku",
    "iso:country":"AZ",
    "name:aze_x_preferred":[
        "R\u0259himli"
    ],
    "wof:name":"Ragimli",
    "wof:placetype":"locality"
},
  "geometry": {"coordinates":[45.44758,40.65938],"type":"Point"}
}