{
  "type": "Feature",
  "properties": {
    "gn:admin1_code":"64",
    "gn:asciiname":"Naxcivanli",
    "gn:country_code":"AZ",
    "gn:dem":775,
    "gn:feature_class":"P",
    "gn:feature_code":"PPL",
    "gn:name":"Nax\u00e7\u0131vanl\u0131",
    "gn:population":0,
    "gn:timezone":"Asia/Baku",
    "iso:country":"AZ",
    "name:aze_x_preferred":[
        "Nax\u00e7\u0131vanl\u0131"
    ],
    "name:aze_x_variant":[
        "Nax\u00e7\u0131vanik"
    ],
    "name:hye_x_preferred":[
        "\u0546\u0561\u056d\u056b\u057b\u0587\u0561\u0576\u056b\u056f"
    ],
    "name:hye_x_variant":[
        "Nakhijevanik"
    ],
    "name:rus_x_preferred":[
        "\u041d\u0430\u0445\u0438\u0447\u0435\u0432\u0430\u043d\u0438\u043a"
    ],
    "name:und_x_variant":[
        "Nakhidgevanik",
        "Nakhichevanik",
        "Nakhijevanik",
        "\u041d\u0430\u0445\u0438\u0447\u0435\u0432\u0430\u043d\u0438\u043a"
    ],
    "wof:name":"Naxcivanli",
    "wof:placetype":"locality"
},
  "geometry": {"coordinates":[46.87337,39.90897],"type":"Point"}
}