{
  "type": "Feature",
  "properties": {
    "gn:admin1_code":"64",
    "gn:asciiname":"Naxcivanli",
    "gn:country_code":"AZ",
    "gn:dem":775,
    "gn:feature_class":"P",
    "gn:feature_code":"PPL",
    "gn:name":"Nax\u00e7\u0131vanl\u0131",
    "gn:population":0,
    "gn:timezone":"Asia/Baku",
    "iso:country":"AZ",
    "name:azb_x_preferred":[
        "\u0646\u062e\u0686\u06cc\u0648\u0627\u0646\u0644\u06cc"
    ],
    "name:aze_x_preferred":[
        "Nax\u00e7\u0131vanl\u0131"
    ],
    "name:aze_x_variant":[
        "Nax\u00e7\u0131vanik"
    ],
    "name:bel_x_preferred":[
        "\u041d\u0430\u0445\u0456\u0434\u0436\u044d\u0432\u0430\u043d\u0456\u043a"
    ],
    "name:ceb_x_preferred":[
        "Nax\u00e7\u0131vanl\u0131"
    ],
    "name:fas_x_preferred":[
        "\u0646\u0627\u062e\u06cc\u062c\u0648\u0627\u0646\u06cc\u06a9"
    ],
    "name:fra_x_preferred":[
        "Nakhidzhevanik"
    ],
    "name:hye_x_preferred":[
        "\u0546\u0561\u056d\u056b\u057b\u0587\u0561\u0576\u056b\u056f"
    ],
    "name:hye_x_variant":[
        "Nakhijevanik"
    ],
    "name:ita_x_preferred":[
        "Nakhidjevanik"
    ],
    "name:msa_x_preferred":[
        "Nakhichevanik"
    ],
    "name:rus_x_preferred":[
        "\u041d\u0430\u0445\u0438\u0447\u0435\u0432\u0430\u043d\u0438\u043a"
    ],
    "name:swe_x_preferred":[
        "Nax\u00e7\u0131vanl\u0131"
    ],
    "name:ukr_x_preferred":[
        "\u041d\u0430\u0445\u0456\u0434\u0436\u0435\u0432\u0430\u043d\u0456\u043a"
    ],
    "name:und_x_variant":[
        "Nakhidgevanik"
    ],
    "wof:name":"Naxcivanli",
    "wof:placetype":"locality"
},
  "geometry": {"coordinates":[46.87337,39.90897],"type":"Point"}
}