{
  "type": "Feature",
  "properties": {
    "gn:admin1_code":"71",
    "gn:asciiname":"Nazarally",
    "gn:country_code":"AZ",
    "gn:dem":-5,
    "gn:feature_class":"P",
    "gn:feature_code":"PPL",
    "gn:name":"Nazarally",
    "gn:population":0,
    "gn:timezone":"Asia/Baku",
    "iso:country":"AZ",
    "name:aze_x_preferred":[
        "N\u0259z\u0259rall\u0131"
    ],
    "name:aze_x_variant":[
        "N\u0259z\u0259ral\u0131l\u0131"
    ],
    "name:ceb_x_preferred":[
        "Nazarally"
    ],
    "name:kat_x_preferred":[
        "\u10dc\u10d0\u10d6\u10d0\u10e0\u10d0\u10da\u10d8\u10da\u10d8"
    ],
    "name:msa_x_preferred":[
        "N\u0259z\u0259ral\u0131l\u0131"
    ],
    "name:swe_x_preferred":[
        "Nazarally"
    ],
    "name:und_x_variant":[
        "N\u0259z\u0259ral\u0131l\u0131"
    ],
    "wof:name":"Nazarally",
    "wof:placetype":"locality"
},
  "geometry": {"coordinates":[47.78039,40.15076],"type":"Point"}
}