{
  "type": "Feature",
  "properties": {
    "gn:admin1_code":"43",
    "gn:asciiname":"Efendilyar",
    "gn:country_code":"AZ",
    "gn:dem":485,
    "gn:feature_class":"P",
    "gn:feature_code":"PPL",
    "gn:name":"Efendilyar",
    "gn:population":0,
    "gn:timezone":"Asia/Baku",
    "iso:country":"AZ",
    "name:aze_x_preferred":[
        "\u018ff\u0259ndil\u0259r"
    ],
    "name:bel_x_preferred":[
        "\u0410\u0439\u0433\u0435\u043a"
    ],
    "name:fas_x_preferred":[
        "\u0622\u06cc\u06af\u06a9"
    ],
    "name:hye_x_preferred":[
        "Aygek"
    ],
    "name:hye_x_variant":[
        "\u0531\u0575\u0563\u0565\u056f"
    ],
    "name:kat_x_preferred":[
        "\u10d0\u10e4\u10d0\u10dc\u10d3\u10d8\u10da\u10d0\u10e0\u10d8"
    ],
    "name:msa_x_preferred":[
        "\u018ff\u0259ndil\u0259r"
    ],
    "name:rus_x_preferred":[
        "\u042d\u0444\u0435\u043d\u0434\u0438\u043b\u044f\u0440"
    ],
    "name:ukr_x_preferred":[
        "\u0410\u0439\u0491\u0435\u043a"
    ],
    "wof:name":"Efendilyar",
    "wof:placetype":"locality"
},
  "geometry": {"coordinates":[46.70012,39.32805],"type":"Point"}
}