{
  "type": "Feature",
  "properties": {
    "gn:admin1_code":"11",
    "gn:asciiname":"Muganli",
    "gn:country_code":"AZ",
    "gn:dem":108,
    "gn:feature_class":"P",
    "gn:feature_code":"PPL",
    "gn:name":"Mu\u011fanl\u0131",
    "gn:population":0,
    "gn:timezone":"Asia/Baku",
    "iso:country":"AZ",
    "name:aze_x_preferred":[
        "Mu\u011fanl\u0131"
    ],
    "name:und_x_variant":[
        "Muganly"
    ],
    "wof:name":"Muganli",
    "wof:placetype":"locality"
},
  "geometry": {"coordinates":[47.08189,40.35322],"type":"Point"}
}