{
  "type": "Feature",
  "properties": {
    "gn:admin1_code":"41",
    "gn:asciiname":"Beklya",
    "gn:country_code":"AZ",
    "gn:dem":979,
    "gn:feature_class":"P",
    "gn:feature_code":"PPL",
    "gn:name":"Beklya",
    "gn:population":0,
    "gn:timezone":"Asia/Baku",
    "iso:country":"AZ",
    "name:und_x_variant":[
        "Bekle",
        "B\u0259kl\u0259"
    ],
    "wof:name":"Beklya",
    "wof:placetype":"locality"
},
  "geometry": {"coordinates":[48.90101,40.61021],"type":"Point"}
}