{
  "type": "Feature",
  "properties": {
    "gn:admin1_code":"41",
    "gn:asciiname":"Beklya",
    "gn:country_code":"AZ",
    "gn:dem":979,
    "gn:feature_class":"P",
    "gn:feature_code":"PPL",
    "gn:name":"Beklya",
    "gn:population":0,
    "gn:timezone":"Asia/Baku",
    "iso:country":"AZ",
    "name:aze_x_preferred":[
        "B\u0259kl\u0259"
    ],
    "name:ceb_x_preferred":[
        "Beklya"
    ],
    "name:ita_x_preferred":[
        "B\u0259kl\u0259"
    ],
    "name:kat_x_preferred":[
        "\u10d1\u10d0\u10e5\u10da\u10d0"
    ],
    "name:msa_x_preferred":[
        "B\u0259kl\u0259"
    ],
    "name:swe_x_preferred":[
        "Beklya"
    ],
    "name:und_x_variant":[
        "Bekle"
    ],
    "wof:name":"Beklya",
    "wof:placetype":"locality"
},
  "geometry": {"coordinates":[48.90101,40.61021],"type":"Point"}
}