{
  "type": "Feature",
  "properties": {
    "gn:admin1_code":"03",
    "gn:asciiname":"Sotlanli",
    "gn:country_code":"AZ",
    "gn:dem":202,
    "gn:feature_class":"P",
    "gn:feature_code":"PPL",
    "gn:name":"\u015eotlanl\u0131",
    "gn:population":0,
    "gn:timezone":"Asia/Baku",
    "iso:country":"AZ",
    "name:aze_x_preferred":[
        "Sotlanl\u0131"
    ],
    "name:aze_x_variant":[
        "\u015eotlanl\u0131"
    ],
    "name:hye_x_preferred":[
        "Shot\u2019lanly"
    ],
    "name:hye_x_variant":[
        "\u0547\u0578\u0569\u056c\u0561\u0576\u056c\u0568",
        "Shot\u2019lan",
        "\u0547\u0578\u0569\u056c\u0561\u0576"
    ],
    "name:rus_x_preferred":[
        "\u0428\u043e\u0442\u043b\u0430\u043d\u043b\u044b"
    ],
    "name:und_x_variant":[
        "Shotlanly"
    ],
    "wof:name":"Sotlanli",
    "wof:placetype":"locality"
},
  "geometry": {"coordinates":[46.96119,40.23479],"type":"Point"}
}