{
  "type": "Feature",
  "properties": {
    "gn:admin1_code":"29",
    "gn:asciiname":"Kyargelan",
    "gn:country_code":"AZ",
    "gn:dem":-8,
    "gn:feature_class":"P",
    "gn:feature_code":"PPL",
    "gn:name":"Kyargelan",
    "gn:population":0,
    "gn:timezone":"Asia/Baku",
    "iso:country":"AZ",
    "name:azb_x_preferred":[
        "\u06a9\u0631\u06af\u0644\u0627\u0646"
    ],
    "name:aze_x_preferred":[
        "K\u0259rg\u0259lan"
    ],
    "name:ceb_x_preferred":[
        "Kyargelan"
    ],
    "name:fas_x_preferred":[
        "\u06a9\u0631\u06af\u0644\u0627\u0646"
    ],
    "name:ita_x_preferred":[
        "K\u0259rg\u0259lan"
    ],
    "name:msa_x_preferred":[
        "K\u0259rg\u0259lan"
    ],
    "name:swe_x_preferred":[
        "Kyargelan"
    ],
    "name:und_x_variant":[
        "Gergelan",
        "Kergelan",
        "Gerkilan",
        "Kyargelan",
        "Kyargalan",
        "K\u0259rg\u0259lan"
    ],
    "wof:name":"Kyargelan",
    "wof:placetype":"locality"
},
  "geometry": {"coordinates":[48.8079,38.73812],"type":"Point"}
}