{
  "type": "Feature",
  "properties": {
    "gn:admin1_code":"14",
    "gn:asciiname":"Agtepe",
    "gn:country_code":"AZ",
    "gn:dem":451,
    "gn:feature_class":"P",
    "gn:feature_code":"PPL",
    "gn:name":"Agtepe",
    "gn:population":0,
    "gn:timezone":"Asia/Baku",
    "iso:country":"AZ",
    "name:aze_x_preferred":[
        "A\u011ft\u0259p\u0259"
    ],
    "name:hye_x_preferred":[
        "Aghtep\u2019e"
    ],
    "name:hye_x_variant":[
        "\u0531\u0572\u057f\u0565\u0583\u0565"
    ],
    "name:kat_x_preferred":[
        "\u10d0\u10e6\u10d7\u10d0\u10e4\u10d0"
    ],
    "name:min_x_preferred":[
        "A\u011ft\u0259p\u0259"
    ],
    "name:msa_x_preferred":[
        "A\u011ft\u0259p\u0259"
    ],
    "name:rus_x_preferred":[
        "\u0410\u0433\u0442\u0435\u043f\u0435"
    ],
    "name:und_x_variant":[
        "\u0410\u0433\u0442\u0435\u043f\u0435"
    ],
    "wof:name":"Agtepe",
    "wof:placetype":"locality"
},
  "geometry": {"coordinates":[47.02754,39.35732],"type":"Point"}
}