{
  "type": "Feature",
  "properties": {
    "gn:admin1_code":"25",
    "gn:asciiname":"Myushkyamir",
    "gn:country_code":"AZ",
    "gn:dem":1195,
    "gn:feature_class":"P",
    "gn:feature_code":"PPL",
    "gn:name":"Myushkyamir",
    "gn:population":0,
    "gn:timezone":"Asia/Baku",
    "iso:country":"AZ",
    "name:und_x_variant":[
        "Mushkemir",
        "Myushkyamir",
        "M\u00fc\u015fk\u0259mir"
    ],
    "wof:name":"Myushkyamir",
    "wof:placetype":"locality"
},
  "geometry": {"coordinates":[48.33282,40.8199],"type":"Point"}
}