{
  "type": "Feature",
  "properties": {
    "gn:admin1_code":"29",
    "gn:asciiname":"Tatova",
    "gn:country_code":"AZ",
    "gn:dem":-23,
    "gn:feature_class":"P",
    "gn:feature_code":"PPL",
    "gn:name":"Tatova",
    "gn:population":0,
    "gn:timezone":"Asia/Baku",
    "iso:country":"AZ",
    "name:aze_x_preferred":[
        "Tatova"
    ],
    "wof:name":"Tatova",
    "wof:placetype":"locality"
},
  "geometry": {"coordinates":[48.77914000000001,38.82852000000001],"type":"Point"}
}