{
  "type": "Feature",
  "properties": {
    "gn:admin1_code":"08",
    "gn:asciiname":"Selyakeran",
    "gn:country_code":"AZ",
    "gn:dem":-23,
    "gn:feature_class":"P",
    "gn:feature_code":"PPL",
    "gn:name":"Selyakeran",
    "gn:population":0,
    "gn:timezone":"Asia/Baku",
    "iso:country":"AZ",
    "name:azb_x_preferred":[
        "\u0633\u06cc\u0644\u0647\u200c\u06a9\u0631\u0627\u0646"
    ],
    "name:aze_x_preferred":[
        "Sel\u0259k\u0259ran"
    ],
    "name:ceb_x_preferred":[
        "Selyakeran"
    ],
    "name:ell_x_preferred":[
        "\u03a3\u03b5\u03bb\u03b5\u03ba\u03b5\u03c1\u03ac\u03bd"
    ],
    "name:fas_x_preferred":[
        "\u0633\u06cc\u0644\u0647\u200c\u06a9\u0631\u0627\u0646"
    ],
    "name:ita_x_preferred":[
        "Sel\u0259k\u0259ran"
    ],
    "name:kat_x_preferred":[
        "\u10e1\u10d4\u10da\u10d4\u10e5\u10d4\u10e0\u10d0\u10dc\u10d8"
    ],
    "name:msa_x_preferred":[
        "Sel\u0259k\u0259ran"
    ],
    "name:swe_x_preferred":[
        "Selyakeran"
    ],
    "name:und_x_variant":[
        "Selakeran",
        "Selyakeran",
        "Sel\u0259k\u0259ran"
    ],
    "wof:name":"Selyakeran",
    "wof:placetype":"locality"
},
  "geometry": {"coordinates":[48.85603,38.4691],"type":"Point"}
}