{
  "type": "Feature",
  "properties": {
    "gn:admin1_code":"02",
    "gn:asciiname":"Dorduncu Barak",
    "gn:country_code":"AZ",
    "gn:dem":59,
    "gn:feature_class":"P",
    "gn:feature_code":"PPL",
    "gn:name":"D\u00f6rd\u00fcnc\u00fc Barak",
    "gn:population":0,
    "gn:timezone":"Asia/Baku",
    "iso:country":"AZ",
    "name:aze_x_preferred":[
        "D\u00f6rd\u00fcnc\u00fc Barak"
    ],
    "wof:name":"Dorduncu Barak",
    "wof:placetype":"locality"
},
  "geometry": {"coordinates":[47.45639,39.86222],"type":"Point"}
}