{
  "type": "Feature",
  "properties": {
    "gn:admin1_code":"02",
    "gn:asciiname":"Dorduncu Barak",
    "gn:country_code":"AZ",
    "gn:dem":59,
    "gn:feature_class":"P",
    "gn:feature_code":"PPL",
    "gn:name":"D\u00f6rd\u00fcnc\u00fc Barak",
    "gn:population":0,
    "gn:timezone":"Asia/Baku",
    "iso:country":"AZ",
    "name:aze_x_preferred":[
        "D\u00f6rd\u00fcnc\u00fc Barak"
    ],
    "name:ita_x_preferred":[
        "D\u00f6rd\u00fcnc\u00fc Barak"
    ],
    "name:kat_x_preferred":[
        "\u10d3\u10d8\u10dd\u10e0\u10d3\u10d8\u10e3\u10dc\u10ef\u10d8\u10e3-\u10d1\u10d0\u10e0\u10d0\u10e5\u10d8"
    ],
    "name:msa_x_preferred":[
        "D\u00f6rd\u00fcnc\u00fc Barak"
    ],
    "wof:name":"Dorduncu Barak",
    "wof:placetype":"locality"
},
  "geometry": {"coordinates":[47.45639,39.86222],"type":"Point"}
}