{
  "type": "Feature",
  "properties": {
    "gn:admin1_code":"03",
    "gn:asciiname":"Bozavend",
    "gn:country_code":"AZ",
    "gn:dem":417,
    "gn:feature_class":"P",
    "gn:feature_code":"PPL",
    "gn:name":"Bozavend",
    "gn:population":0,
    "gn:timezone":"Asia/Baku",
    "iso:country":"AZ",
    "name:azb_x_preferred":[
        "\u0628\u0648\u0632\u0627\u0648\u0646\u062f"
    ],
    "name:aze_x_preferred":[
        "Bozav\u0259nd"
    ],
    "name:eng_x_preferred":[
        "Bozavend"
    ],
    "name:fas_x_preferred":[
        "\u0628\u0632\u0627\u0648\u0646\u062f"
    ],
    "name:kat_x_preferred":[
        "\u10d1\u10dd\u10d6\u10d0\u10d5\u10d4\u10dc\u10d3\u10d8"
    ],
    "name:min_x_preferred":[
        "Bozavend"
    ],
    "name:msa_x_preferred":[
        "Bozavend"
    ],
    "name:rus_x_preferred":[
        "\u041f\u043e\u043f\u0440\u0430\u0432\u0435\u043d\u0434"
    ],
    "name:tur_x_preferred":[
        "Bozavend"
    ],
    "wof:name":"Bozavend",
    "wof:placetype":"locality"
},
  "geometry": {"coordinates":[46.86611,40.15722],"type":"Point"}
}