{
  "type": "Feature",
  "properties": {
    "gn:admin1_code":"03",
    "gn:asciiname":"Bozavend",
    "gn:country_code":"AZ",
    "gn:dem":417,
    "gn:feature_class":"P",
    "gn:feature_code":"PPL",
    "gn:name":"Bozavend",
    "gn:population":0,
    "gn:timezone":"Asia/Baku",
    "iso:country":"AZ",
    "name:eng_x_preferred":[
        "Bozavend"
    ],
    "name:rus_x_preferred":[
        "\u041f\u043e\u043f\u0440\u0430\u0432\u0435\u043d\u0434"
    ],
    "wof:name":"Bozavend",
    "wof:placetype":"locality"
},
  "geometry": {"coordinates":[46.86611,40.15722],"type":"Point"}
}