{
  "type": "Feature",
  "properties": {
    "gn:admin1_code":"31",
    "gn:asciiname":"Andurma",
    "gn:country_code":"AZ",
    "gn:dem":1563,
    "gn:feature_class":"P",
    "gn:feature_code":"PPL",
    "gn:name":"Andurma",
    "gn:population":0,
    "gn:timezone":"Asia/Baku",
    "iso:country":"AZ",
    "name:aze_x_preferred":[
        "Andurma"
    ],
    "name:ceb_x_preferred":[
        "Andurma"
    ],
    "name:ell_x_preferred":[
        "\u0391\u03bd\u03c4\u03bf\u03cd\u03c1\u03bc\u03b1"
    ],
    "name:ita_x_preferred":[
        "Andurma"
    ],
    "name:msa_x_preferred":[
        "Andurma"
    ],
    "name:swe_x_preferred":[
        "Andurma"
    ],
    "wof:name":"Andurma",
    "wof:placetype":"locality"
},
  "geometry": {"coordinates":[48.47029000000001,38.71215],"type":"Point"}
}