{
  "type": "Feature",
  "properties": {
    "gn:admin1_code":"65",
    "gn:asciiname":"Guneyxirman",
    "gn:country_code":"AZ",
    "gn:dem":625,
    "gn:feature_class":"P",
    "gn:feature_code":"PPL",
    "gn:name":"G\u00fcneyx\u0131rman",
    "gn:population":0,
    "gn:timezone":"Asia/Baku",
    "iso:country":"AZ",
    "name:aze_x_preferred":[
        "G\u00fcneyx\u0131rman"
    ],
    "name:hye_x_preferred":[
        "Chartar"
    ],
    "name:hye_x_variant":[
        "\u0543\u0561\u0580\u057f\u0561\u0580"
    ],
    "name:rus_x_preferred":[
        "\u0413\u044e\u043d\u0435\u0439\u043a\u0430\u043b\u0435\u0440"
    ],
    "name:und_x_variant":[
        "Gyuneykaler",
        "G\u00fcneyqaler",
        "Gioune-Kaler",
        "Gyune-Laler",
        "Gyunekaler",
        "\u0413\u044e\u043d\u0435\u0439\u043a\u0430\u043b\u0435\u0440",
        "Gyune Kaler"
    ],
    "wof:name":"Guneyxirman",
    "wof:placetype":"locality"
},
  "geometry": {"coordinates":[47.03463,39.74604],"type":"Point"}
}