{
  "type": "Feature",
  "properties": {
    "gn:admin1_code":"43",
    "gn:asciiname":"Hal",
    "gn:country_code":"AZ",
    "gn:dem":412,
    "gn:feature_class":"P",
    "gn:feature_code":"PPL",
    "gn:name":"Hal",
    "gn:population":0,
    "gn:timezone":"Asia/Baku",
    "iso:country":"AZ",
    "name:aze_x_preferred":[
        "Hal"
    ],
    "name:bel_x_preferred":[
        "\u0413\u0430\u043b\u0435"
    ],
    "name:hye_x_preferred":[
        "Hale"
    ],
    "name:hye_x_variant":[
        "\u0540\u0561\u056c\u0565"
    ],
    "name:kat_x_preferred":[
        "\u10f0\u10d0\u10da\u10d4"
    ],
    "name:msa_x_preferred":[
        "Hal"
    ],
    "name:rus_x_preferred":[
        "\u0413\u0430\u043b"
    ],
    "name:ukr_x_preferred":[
        "\u0413\u0430\u043b\u0435"
    ],
    "name:und_x_variant":[
        "Gal"
    ],
    "wof:name":"Hal",
    "wof:placetype":"locality"
},
  "geometry": {"coordinates":[46.67847,39.27589],"type":"Point"}
}