{
  "type": "Feature",
  "properties": {
    "gn:admin1_code":"26",
    "gn:asciiname":"Saridas",
    "gn:country_code":"AZ",
    "gn:dem":1735,
    "gn:feature_class":"P",
    "gn:feature_code":"PPL",
    "gn:name":"Sar\u0131da\u015f",
    "gn:population":0,
    "gn:timezone":"Asia/Baku",
    "iso:country":"AZ",
    "name:aze_x_preferred":[
        "Sar\u0131da\u015f"
    ],
    "name:hye_x_preferred":[
        "Shikak\u2019ar"
    ],
    "name:hye_x_variant":[
        "\u0547\u056b\u056f\u0561\u0584\u0561\u0580"
    ],
    "name:msa_x_preferred":[
        "Sar\u0131da\u015f"
    ],
    "name:rus_x_preferred":[
        "\u0421\u0430\u0440\u044b\u0434\u0430\u0448"
    ],
    "name:und_x_variant":[
        "Sarydash",
        "Kyavshan"
    ],
    "wof:name":"Saridas",
    "wof:placetype":"locality"
},
  "geometry": {"coordinates":[46.13512,40.19463],"type":"Point"}
}