{
  "type": "Feature",
  "properties": {
    "gn:admin1_code":"70",
    "gn:asciiname":"Donbabina",
    "gn:country_code":"AZ",
    "gn:dem":241,
    "gn:feature_class":"P",
    "gn:feature_code":"PPL",
    "gn:name":"Donbabina",
    "gn:population":0,
    "gn:timezone":"Asia/Baku",
    "iso:country":"AZ",
    "name:und_x_variant":[
        "Dombabin\u0259"
    ],
    "wof:name":"Donbabina",
    "wof:placetype":"locality"
},
  "geometry": {"coordinates":[46.50899,41.55501],"type":"Point"}
}