{
  "type": "Feature",
  "properties": {
    "gn:admin1_code":"55",
    "gn:asciiname":"Lacinlar",
    "gn:country_code":"AZ",
    "gn:dem":1032,
    "gn:feature_class":"P",
    "gn:feature_code":"PPL",
    "gn:name":"La\u00e7\u0131nlar",
    "gn:population":0,
    "gn:timezone":"Asia/Baku",
    "iso:country":"AZ",
    "name:azb_x_preferred":[
        "\u0644\u0627\u0686\u06cc\u0646\u0644\u0627\u0631"
    ],
    "name:aze_x_preferred":[
        "La\u00e7\u0131nlar"
    ],
    "name:hye_x_preferred":[
        "Lach\u2019inlar"
    ],
    "name:hye_x_variant":[
        "\u053c\u0561\u0579\u056b\u0576\u056c\u0561\u0580"
    ],
    "name:msa_x_preferred":[
        "La\u00e7\u0131nlar"
    ],
    "name:rus_x_preferred":[
        "\u041b\u0430\u0447\u0438\u043d\u043b\u0430\u0440"
    ],
    "name:und_x_variant":[
        "Lachinlar"
    ],
    "name:urd_x_preferred":[
        "\u0644\u0627\u0686\u06cc\u0646\u0644\u0627\u0631"
    ],
    "wof:name":"Lacinlar",
    "wof:placetype":"locality"
},
  "geometry": {"coordinates":[46.71299000000001,39.76606],"type":"Point"}
}