{
  "type": "Feature",
  "properties": {
    "gn:admin1_code":"45",
    "gn:asciiname":"Mamedabad",
    "gn:country_code":"AZ",
    "gn:dem":-15,
    "gn:feature_class":"P",
    "gn:feature_code":"PPL",
    "gn:name":"Mamedabad",
    "gn:population":0,
    "gn:timezone":"Asia/Baku",
    "iso:country":"AZ",
    "name:und_x_variant":[
        "M\u0259mm\u0259dabad"
    ],
    "wof:name":"Mamedabad",
    "wof:placetype":"locality"
},
  "geometry": {"coordinates":[48.47738,39.8665],"type":"Point"}
}