{
  "type": "Feature",
  "properties": {
    "gn:admin1_code":"22",
    "gn:asciiname":"Ulashly-Shykhly",
    "gn:country_code":"AZ",
    "gn:dem":57,
    "gn:feature_class":"P",
    "gn:feature_code":"PPL",
    "gn:name":"Ulashly-Shykhly",
    "gn:population":0,
    "gn:timezone":"Asia/Baku",
    "iso:country":"AZ",
    "name:aze_x_preferred":[
        "Ula\u015fl\u0131 \u015e\u0131xl\u0131"
    ],
    "name:ita_x_preferred":[
        "Ula\u015fl\u0131 \u015e\u0131xl\u0131"
    ],
    "name:kat_x_preferred":[
        "\u10e3\u10da\u10d0\u10e8\u10da\u10d8-\u10e8\u10d8\u10ee\u10da\u10d8"
    ],
    "name:msa_x_preferred":[
        "Ula\u015fl\u0131 \u015e\u0131xl\u0131"
    ],
    "wof:name":"Ulashly-Shykhly",
    "wof:placetype":"locality"
},
  "geometry": {"coordinates":[47.73879,40.60305],"type":"Point"}
}