{
  "type": "Feature",
  "properties": {
    "gn:admin1_code":"29",
    "gn:asciiname":"Mikolan",
    "gn:country_code":"AZ",
    "gn:dem":19,
    "gn:feature_class":"P",
    "gn:feature_code":"PPL",
    "gn:name":"Mikolan",
    "gn:population":0,
    "gn:timezone":"Asia/Baku",
    "iso:country":"AZ",
    "name:aze_x_preferred":[
        "Mikolan"
    ],
    "name:ell_x_preferred":[
        "\u039c\u03b9\u03ba\u03bf\u03bb\u03ac\u03bd"
    ],
    "name:msa_x_preferred":[
        "Mikolan"
    ],
    "wof:name":"Mikolan",
    "wof:placetype":"locality"
},
  "geometry": {"coordinates":[48.78483,38.70303],"type":"Point"}
}