{
  "type": "Feature",
  "properties": {
    "gn:admin1_code":"60",
    "gn:asciiname":"Sabiroba",
    "gn:country_code":"AZ",
    "gn:dem":-14,
    "gn:feature_class":"P",
    "gn:feature_code":"PPL",
    "gn:name":"Sabiroba",
    "gn:population":0,
    "gn:timezone":"Asia/Baku",
    "iso:country":"AZ",
    "name:azb_x_preferred":[
        "\u0635\u0627\u0628\u06cc\u0631 \u0627\u0648\u0628\u0627"
    ],
    "name:aze_x_preferred":[
        "Sabiroba"
    ],
    "name:ita_x_preferred":[
        "Sabiroba"
    ],
    "name:kat_x_preferred":[
        "\u10e1\u10d0\u10d1\u10d8\u10e0\u10dd\u10d1\u10d0"
    ],
    "name:lez_x_preferred":[
        "\u0421\u0430\u0431\u0438\u0440\u0443\u0431\u0430"
    ],
    "name:msa_x_preferred":[
        "Sabiroba"
    ],
    "name:urd_x_preferred":[
        "\u0633\u0628\u0631\u0648\u0628\u0627"
    ],
    "wof:name":"Sabiroba",
    "wof:placetype":"locality"
},
  "geometry": {"coordinates":[48.79,41.6252],"type":"Point"}
}