{
  "type": "Feature",
  "properties": {
    "gn:admin1_code":"25",
    "gn:asciiname":"Buynuz",
    "gn:country_code":"AZ",
    "gn:dem":763,
    "gn:feature_class":"P",
    "gn:feature_code":"PPL",
    "gn:name":"Buynuz",
    "gn:population":0,
    "gn:timezone":"Asia/Baku",
    "iso:country":"AZ",
    "wof:name":"Buynuz",
    "wof:placetype":"locality"
},
  "geometry": {"coordinates":[48.06194,40.919],"type":"Point"}
}