{
  "type": "Feature",
  "properties": {
    "gn:admin1_code":"25",
    "gn:asciiname":"Buynuz",
    "gn:country_code":"AZ",
    "gn:dem":763,
    "gn:feature_class":"P",
    "gn:feature_code":"PPL",
    "gn:name":"Buynuz",
    "gn:population":0,
    "gn:timezone":"Asia/Baku",
    "iso:country":"AZ",
    "name:azb_x_preferred":[
        "\u0628\u0648\u06cc\u0646\u0648\u0632"
    ],
    "name:aze_x_preferred":[
        "Buynuz"
    ],
    "name:ceb_x_preferred":[
        "Buynuz"
    ],
    "name:ita_x_preferred":[
        "Buynuz"
    ],
    "name:kat_x_preferred":[
        "\u10d1\u10e3\u10d8\u10dc\u10e3\u10d6\u10d8"
    ],
    "name:msa_x_preferred":[
        "Buynuz"
    ],
    "name:swe_x_preferred":[
        "Buynuz"
    ],
    "wof:name":"Buynuz",
    "wof:placetype":"locality"
},
  "geometry": {"coordinates":[48.06194,40.919],"type":"Point"}
}