{
  "type": "Feature",
  "properties": {
    "gn:admin1_code":"49",
    "gn:asciiname":"Sarvan",
    "gn:country_code":"AZ",
    "gn:dem":-23,
    "gn:feature_class":"P",
    "gn:feature_code":"PPL",
    "gn:name":"Sarvan",
    "gn:population":0,
    "gn:timezone":"Asia/Baku",
    "iso:country":"AZ",
    "name:azb_x_preferred":[
        "\u0633\u0627\u0631\u0648\u0627\u0646"
    ],
    "name:aze_x_preferred":[
        "Sarvan"
    ],
    "name:ceb_x_preferred":[
        "Sarvan"
    ],
    "name:fas_x_preferred":[
        "\u0633\u0627\u0631\u0628\u0627\u0646"
    ],
    "name:ita_x_preferred":[
        "Sarvan"
    ],
    "name:msa_x_preferred":[
        "Sarvan"
    ],
    "wof:name":"Sarvan",
    "wof:placetype":"locality"
},
  "geometry": {"coordinates":[48.89629,39.48253],"type":"Point"}
}