{
  "type": "Feature",
  "properties": {
    "gn:admin1_code":"50",
    "gn:asciiname":"Avaxil",
    "gn:country_code":"AZ",
    "gn:dem":1368,
    "gn:feature_class":"P",
    "gn:feature_code":"PPL",
    "gn:name":"Avax\u0131l",
    "gn:population":0,
    "gn:timezone":"Asia/Baku",
    "iso:country":"AZ",
    "name:aze_x_preferred":[
        "Avax\u0131l"
    ],
    "name:ceb_x_preferred":[
        "Avax\u0131l"
    ],
    "name:ita_x_preferred":[
        "Avax\u0131l"
    ],
    "name:kat_x_preferred":[
        "\u10d0\u10d5\u10d0\u10ee\u10d8\u10da\u10d8"
    ],
    "name:min_x_preferred":[
        "Avax\u0131l"
    ],
    "name:msa_x_preferred":[
        "Avax\u0131l"
    ],
    "name:swe_x_preferred":[
        "Avax\u0131l"
    ],
    "name:und_x_variant":[
        "Avakhyl",
        "Avax\u0131l"
    ],
    "wof:name":"Avaxil",
    "wof:placetype":"locality"
},
  "geometry": {"coordinates":[48.56182,40.79751],"type":"Point"}
}