{
  "type": "Feature",
  "properties": {
    "gn:admin1_code":"04",
    "gn:asciiname":"Yukhary Lyaki",
    "gn:country_code":"AZ",
    "gn:dem":17,
    "gn:feature_class":"P",
    "gn:feature_code":"PPL",
    "gn:name":"Yukhary Lyaki",
    "gn:population":0,
    "gn:timezone":"Asia/Baku",
    "iso:country":"AZ",
    "name:aze_x_preferred":[
        "Yuxar\u0131 L\u0259ki"
    ],
    "name:eng_x_preferred":[
        "Yuxar\u0131 L\u01ddki"
    ],
    "name:ita_x_preferred":[
        "Yuxar\u0131 L\u0259ki"
    ],
    "name:kat_x_preferred":[
        "\u10d8\u10e3\u10ee\u10d0\u10e0\u10d8-\u10da\u10d0\u10e5\u10d8"
    ],
    "name:msa_x_preferred":[
        "Yuxar\u0131 L\u0259ki"
    ],
    "name:rus_x_preferred":[
        "\u042e\u0445\u0430\u0440\u044b-\u041b\u044f\u043a\u0438"
    ],
    "name:rus_x_variant":[
        "\u042e\u0445\u0430\u0440\u044b \u041b\u044f\u043a\u0438"
    ],
    "name:urd_x_preferred":[
        "\u06cc\u06a9\u0634\u0627\u0631\u06cc \u0644\u06a9\u06cc\u0645"
    ],
    "wof:name":"Yukhary Lyaki",
    "wof:placetype":"locality"
},
  "geometry": {"coordinates":[47.42806,40.5324],"type":"Point"}
}