{
  "type": "Feature",
  "properties": {
    "gn:admin1_code":"36",
    "gn:asciiname":"Pirappa",
    "gn:country_code":"AZ",
    "gn:dem":-25,
    "gn:feature_class":"P",
    "gn:feature_code":"PPL",
    "gn:name":"Pirappa",
    "gn:population":0,
    "gn:timezone":"Asia/Baku",
    "iso:country":"AZ",
    "name:und_x_variant":[
        "Pir\u0259bb\u0259",
        "Pirabba"
    ],
    "wof:name":"Pirappa",
    "wof:placetype":"locality"
},
  "geometry": {"coordinates":[49.00828,39.4997],"type":"Point"}
}