{
  "type": "Feature",
  "properties": {
    "gn:admin1_code":"15",
    "gn:asciiname":"Qaraagac",
    "gn:country_code":"AZ",
    "gn:dem":102,
    "gn:feature_class":"P",
    "gn:feature_code":"PPL",
    "gn:name":"Qaraa\u011fac",
    "gn:population":0,
    "gn:timezone":"Asia/Baku",
    "iso:country":"AZ",
    "name:aze_x_preferred":[
        "Qaraa\u011fac"
    ],
    "name:und_x_variant":[
        "Karaagach"
    ],
    "wof:name":"Qaraagac",
    "wof:placetype":"locality"
},
  "geometry": {"coordinates":[48.45327,39.14686],"type":"Point"}
}