{
  "type": "Feature",
  "properties": {
    "gn:admin1_code":"19",
    "gn:asciiname":"Arabaci",
    "gn:country_code":"AZ",
    "gn:dem":1414,
    "gn:feature_class":"P",
    "gn:feature_code":"PPL",
    "gn:name":"Araba\u00e7\u0131",
    "gn:population":0,
    "gn:timezone":"Asia/Baku",
    "iso:country":"AZ",
    "name:und_x_variant":[
        "Arabachy",
        "Araba\u00e7\u0131"
    ],
    "wof:name":"Arabaci",
    "wof:placetype":"locality"
},
  "geometry": {"coordinates":[45.56929,40.54495],"type":"Point"}
}