{
  "type": "Feature",
  "properties": {
    "gn:admin1_code":"35",
    "gn:admin2_code":"409387.0",
    "gn:asciiname":"Qaragac",
    "gn:country_code":"AZ",
    "gn:dem":831,
    "gn:feature_class":"P",
    "gn:feature_code":"PPL",
    "gn:name":"Qara\u011fac",
    "gn:population":0,
    "gn:timezone":"Asia/Baku",
    "iso:country":"AZ",
    "name:aze_x_preferred":[
        "Qara\u011fac"
    ],
    "wof:name":"Qaragac",
    "wof:placetype":"locality"
},
  "geometry": {"coordinates":[44.8645,39.69113],"type":"Point"}
}