{
  "type": "Feature",
  "properties": {
    "gn:admin1_code":"51",
    "gn:asciiname":"Sheidlyar",
    "gn:country_code":"AZ",
    "gn:dem":1181,
    "gn:feature_class":"P",
    "gn:feature_code":"PPL",
    "gn:name":"Sheidlyar",
    "gn:population":0,
    "gn:timezone":"Asia/Baku",
    "iso:country":"AZ",
    "name:aze_x_preferred":[
        "\u015eeidl\u0259r"
    ],
    "wof:name":"Sheidlyar",
    "wof:placetype":"locality"
},
  "geometry": {"coordinates":[45.93161,40.77913],"type":"Point"}
}