{
  "type": "Feature",
  "properties": {
    "gn:admin1_code":"64",
    "gn:asciiname":"Qarabulaq",
    "gn:country_code":"AZ",
    "gn:dem":923,
    "gn:feature_class":"P",
    "gn:feature_code":"PPL",
    "gn:name":"Qarabulaq",
    "gn:population":0,
    "gn:timezone":"Asia/Baku",
    "iso:country":"AZ",
    "name:aze_x_preferred":[
        "Qarabulaq"
    ],
    "name:hye_x_preferred":[
        "Aknaghbyur"
    ],
    "name:hye_x_variant":[
        "\u0542\u0561\u0580\u0561\u0562\u0578\u0582\u056c\u0561\u0572",
        "\u0531\u056f\u0576\u0561\u0572\u0562\u0575\u0578\u0582\u0580",
        "Gharabulagh"
    ],
    "name:rus_x_preferred":[
        "\u041a\u0430\u0440\u0430\u0431\u0443\u043b\u0430\u043a"
    ],
    "name:und_x_variant":[
        "Gharaboulagh",
        "Karabulakh",
        "Karabulak",
        "\u041a\u0430\u0440\u0430\u0431\u0443\u043b\u0430\u043a"
    ],
    "wof:name":"Qarabulaq",
    "wof:placetype":"locality"
},
  "geometry": {"coordinates":[46.86589,39.70736],"type":"Point"}
}