{
  "type": "Feature",
  "properties": {
    "gn:admin1_code":"27",
    "gn:asciiname":"Sovla",
    "gn:country_code":"AZ",
    "gn:dem":-9,
    "gn:feature_class":"P",
    "gn:feature_code":"PPL",
    "gn:name":"Sovla",
    "gn:population":0,
    "gn:timezone":"Asia/Baku",
    "iso:country":"AZ",
    "name:azb_x_preferred":[
        "\u0633\u0648\u0648\u0644\u0627"
    ],
    "name:aze_x_preferred":[
        "Sovla"
    ],
    "name:ita_x_preferred":[
        "Sovla"
    ],
    "name:msa_x_preferred":[
        "Sovla"
    ],
    "name:und_x_variant":[
        "Beyuk-Sola",
        "Soulu",
        "Beyuk Sovla",
        "Sovla"
    ],
    "wof:name":"Sovla",
    "wof:placetype":"locality"
},
  "geometry": {"coordinates":[47.95701,40.09919],"type":"Point"}
}