{
  "type": "Feature",
  "properties": {
    "gn:admin1_code":"35",
    "gn:admin2_code":"7669114.0",
    "gn:asciiname":"Sirab",
    "gn:country_code":"AZ",
    "gn:dem":1075,
    "gn:feature_class":"P",
    "gn:feature_code":"PPL",
    "gn:name":"Sirab",
    "gn:population":0,
    "gn:timezone":"Asia/Baku",
    "iso:country":"AZ",
    "name:azb_x_preferred":[
        "\u0633\u06cc\u0631\u0627\u0628"
    ],
    "name:aze_x_preferred":[
        "Sirab"
    ],
    "name:ceb_x_preferred":[
        "Sirab"
    ],
    "name:fas_x_preferred":[
        "\u0633\u06cc\u0631\u0627\u0628"
    ],
    "name:hye_x_preferred":[
        "\u054d\u056b\u0580\u0561\u0562"
    ],
    "name:ita_x_preferred":[
        "Sirab"
    ],
    "name:kat_x_preferred":[
        "\u10e1\u10d8\u10e0\u10d0\u10d1\u10d8"
    ],
    "name:msa_x_preferred":[
        "Sirab"
    ],
    "name:swe_x_preferred":[
        "Sirab"
    ],
    "name:und_x_variant":[
        "Siab",
        "Surab"
    ],
    "wof:name":"Sirab",
    "wof:placetype":"locality"
},
  "geometry": {"coordinates":[45.51332,39.29128],"type":"Point"}
}