{
  "type": "Feature",
  "properties": {
    "gn:admin1_code":"42",
    "gn:asciiname":"Qayadali",
    "gn:country_code":"AZ",
    "gn:dem":1567,
    "gn:feature_class":"P",
    "gn:feature_code":"PPL",
    "gn:name":"Qayadal\u0131",
    "gn:population":0,
    "gn:timezone":"Asia/Baku",
    "iso:country":"AZ",
    "name:azb_x_preferred":[
        "\u062f\u0627\u0634\u062f\u0627\u0644\u06cc"
    ],
    "name:aze_x_preferred":[
        "Qayadal\u0131"
    ],
    "name:ita_x_preferred":[
        "Qayadal\u0131"
    ],
    "name:msa_x_preferred":[
        "Qayadal\u0131"
    ],
    "name:und_x_variant":[
        "Kayadaly"
    ],
    "wof:name":"Qayadali",
    "wof:placetype":"locality"
},
  "geometry": {"coordinates":[48.45479,41.12476],"type":"Point"}
}