{
  "type": "Feature",
  "properties": {
    "gn:admin1_code":"16",
    "gn:asciiname":"Suqovusan",
    "gn:country_code":"AZ",
    "gn:dem":1320,
    "gn:feature_class":"P",
    "gn:feature_code":"PPL",
    "gn:name":"Suqovu\u015fan",
    "gn:population":0,
    "gn:timezone":"Asia/Baku",
    "iso:country":"AZ",
    "name:aze_x_preferred":[
        "Suqovu\u015fan"
    ],
    "name:und_x_variant":[
        "Gedamish",
        "Ged\u0259mi\u015f",
        "Kedalish"
    ],
    "wof:name":"Suqovusan",
    "wof:placetype":"locality"
},
  "geometry": {"coordinates":[46.16444,40.41157000000001],"type":"Point"}
}