{
  "type": "Feature",
  "properties": {
    "gn:admin1_code":"08",
    "gn:asciiname":"Sarak",
    "gn:country_code":"AZ",
    "gn:dem":2,
    "gn:feature_class":"P",
    "gn:feature_code":"PPL",
    "gn:name":"Sarak",
    "gn:population":0,
    "gn:timezone":"Asia/Baku",
    "iso:country":"AZ",
    "name:azb_x_preferred":[
        "\u0633\u0631\u06a9"
    ],
    "name:aze_x_preferred":[
        "S\u0259r\u0259k"
    ],
    "name:ceb_x_preferred":[
        "Sarak"
    ],
    "name:fas_x_preferred":[
        "\u0633\u0631\u06a9"
    ],
    "name:ita_x_preferred":[
        "S\u0259r\u0259k"
    ],
    "name:kat_x_preferred":[
        "\u10e1\u10d0\u10e0\u10d0\u10e5\u10d8"
    ],
    "name:msa_x_preferred":[
        "S\u0259r\u0259k"
    ],
    "name:swe_x_preferred":[
        "Sarak"
    ],
    "name:und_x_variant":[
        "S\u0259r\u0259k",
        "Sarak"
    ],
    "wof:name":"Sarak",
    "wof:placetype":"locality"
},
  "geometry": {"coordinates":[48.78791,38.49836],"type":"Point"}
}