{
  "type": "Feature",
  "properties": {
    "gn:admin1_code":"03",
    "gn:asciiname":"Muganli",
    "gn:country_code":"AZ",
    "gn:dem":393,
    "gn:feature_class":"P",
    "gn:feature_code":"PPL",
    "gn:name":"Mu\u011fanl\u0131",
    "gn:population":0,
    "gn:timezone":"Asia/Baku",
    "iso:country":"AZ",
    "name:aze_x_preferred":[
        "Mu\u011fanl\u0131"
    ],
    "name:hye_x_preferred":[
        "Mughanly"
    ],
    "name:hye_x_variant":[
        "\u0544\u0578\u0582\u0572\u0561\u0576\u056c\u0568"
    ],
    "name:rus_x_preferred":[
        "\u041c\u0443\u0433\u0430\u043d\u043b\u044b"
    ],
    "name:und_x_variant":[
        "Muganly",
        "\u041c\u0443\u0433\u0430\u043d\u043b\u044b"
    ],
    "wof:name":"Muganli",
    "wof:placetype":"locality"
},
  "geometry": {"coordinates":[46.93794000000001,39.94592],"type":"Point"}
}