{
  "type": "Feature",
  "properties": {
    "gn:admin1_code":"03",
    "gn:asciiname":"Alimardanly",
    "gn:country_code":"AZ",
    "gn:dem":410,
    "gn:feature_class":"P",
    "gn:feature_code":"PPL",
    "gn:name":"Alimardanly",
    "gn:population":0,
    "gn:timezone":"Asia/Baku",
    "iso:country":"AZ",
    "name:aze_x_preferred":[
        "\u018flim\u0259rdanl\u0131"
    ],
    "name:rus_x_preferred":[
        "\u0410\u043b\u0438\u043c\u0430\u0440\u0434\u0430\u043d\u043b\u044b"
    ],
    "wof:name":"Alimardanly",
    "wof:placetype":"locality"
},
  "geometry": {"coordinates":[46.89541,39.97503],"type":"Point"}
}