{
  "type": "Feature",
  "properties": {
    "gn:admin1_code":"08",
    "gn:asciiname":"Sygakeran",
    "gn:country_code":"AZ",
    "gn:dem":311,
    "gn:feature_class":"P",
    "gn:feature_code":"PPL",
    "gn:name":"Sygakeran",
    "gn:population":0,
    "gn:timezone":"Asia/Baku",
    "iso:country":"AZ",
    "name:aze_x_preferred":[
        "S\u0131h\u0259k\u0259ran"
    ],
    "wof:name":"Sygakeran",
    "wof:placetype":"locality"
},
  "geometry": {"coordinates":[48.76489,38.61153],"type":"Point"}
}