{
  "type": "Feature",
  "properties": {
    "gn:admin1_code":"19",
    "gn:asciiname":"Eyrivank",
    "gn:country_code":"AZ",
    "gn:dem":1352,
    "gn:feature_class":"P",
    "gn:feature_code":"PPL",
    "gn:name":"Eyrivank",
    "gn:population":0,
    "gn:timezone":"Asia/Baku",
    "iso:country":"AZ",
    "name:und_x_variant":[
        "\u018fyriv\u0259ng"
    ],
    "wof:name":"Eyrivank",
    "wof:placetype":"locality"
},
  "geometry": {"coordinates":[45.59493,40.5316],"type":"Point"}
}