{
  "type": "Feature",
  "properties": {
    "gn:admin1_code":"19",
    "gn:asciiname":"Eyrivank",
    "gn:country_code":"AZ",
    "gn:dem":1352,
    "gn:feature_class":"P",
    "gn:feature_code":"PPL",
    "gn:name":"Eyrivank",
    "gn:population":0,
    "gn:timezone":"Asia/Baku",
    "iso:country":"AZ",
    "name:azb_x_preferred":[
        "\u0627\u06cc\u0631\u06cc \u0648\u0646\u06af"
    ],
    "name:aze_x_preferred":[
        "\u018fyriv\u0259ng"
    ],
    "name:ita_x_preferred":[
        "\u018fyriv\u0259ng"
    ],
    "name:kat_x_preferred":[
        "\u10d0\u10d8\u10e0\u10d8\u10d5\u10d0\u10dc\u10d2\u10d8"
    ],
    "name:msa_x_preferred":[
        "\u018fyriv\u0259ng"
    ],
    "wof:name":"Eyrivank",
    "wof:placetype":"locality"
},
  "geometry": {"coordinates":[45.59493,40.5316],"type":"Point"}
}