{
  "type": "Feature",
  "properties": {
    "gn:admin1_code":"44",
    "gn:asciiname":"Caqarqislaq",
    "gn:country_code":"AZ",
    "gn:dem":266,
    "gn:feature_class":"P",
    "gn:feature_code":"PPL",
    "gn:name":"Caqarq\u0131\u015flaq",
    "gn:population":0,
    "gn:timezone":"Asia/Baku",
    "iso:country":"AZ",
    "name:aze_x_preferred":[
        "Caqarq\u0131\u015flaq"
    ],
    "name:und_x_variant":[
        "Dzhagarkyshlak"
    ],
    "wof:name":"Caqarqislaq",
    "wof:placetype":"locality"
},
  "geometry": {"coordinates":[48.55494,41.54589],"type":"Point"}
}