{
  "type": "Feature",
  "properties": {
    "gn:admin1_code":"44",
    "gn:asciiname":"Caqarqislaq",
    "gn:country_code":"AZ",
    "gn:dem":266,
    "gn:feature_class":"P",
    "gn:feature_code":"PPL",
    "gn:name":"Caqarq\u0131\u015flaq",
    "gn:population":0,
    "gn:timezone":"Asia/Baku",
    "iso:country":"AZ",
    "name:aze_x_preferred":[
        "Caqarq\u0131\u015flaq"
    ],
    "name:ell_x_preferred":[
        "\u03a3\u03b1\u03ba\u03b1\u03c1\u03ba\u03b9\u03c3\u03bb\u03ac\u03ba"
    ],
    "name:ita_x_preferred":[
        "Caqarq\u0131\u015flaq"
    ],
    "name:kat_x_preferred":[
        "\u10ef\u10d0\u10d2\u10d0\u10e0\u10e5\u10d8\u10e8\u10da\u10d0\u10d2\u10d8"
    ],
    "name:lez_x_preferred":[
        "\u0427I\u0430\u043aI\u0430\u0440 \u0445\u044a\u0438\u0448\u043b\u0430\u0445"
    ],
    "name:msa_x_preferred":[
        "Caqarq\u0131\u015flaq"
    ],
    "name:und_x_variant":[
        "Dzhagarkyshlak"
    ],
    "wof:name":"Caqarqislaq",
    "wof:placetype":"locality"
},
  "geometry": {"coordinates":[48.55494,41.54589],"type":"Point"}
}