{
  "type": "Feature",
  "properties": {
    "gn:admin1_code":"43",
    "gn:asciiname":"Xocik",
    "gn:country_code":"AZ",
    "gn:dem":504,
    "gn:feature_class":"P",
    "gn:feature_code":"PPL",
    "gn:name":"Xocik",
    "gn:population":0,
    "gn:timezone":"Asia/Baku",
    "iso:country":"AZ",
    "name:aze_x_preferred":[
        "Xocik"
    ],
    "name:hye_x_preferred":[
        "Khojik"
    ],
    "name:hye_x_variant":[
        "\u053d\u0578\u057b\u056b\u056f"
    ],
    "name:rus_x_preferred":[
        "\u0425\u043e\u0434\u0436\u0438\u043a"
    ],
    "name:und_x_variant":[
        "Khodzhik",
        "\u0425\u043e\u0434\u0436\u0438\u043a"
    ],
    "wof:name":"Xocik",
    "wof:placetype":"locality"
},
  "geometry": {"coordinates":[46.68249,39.35129000000001],"type":"Point"}
}