{
  "type": "Feature",
  "properties": {
    "gn:admin1_code":"46",
    "gn:asciiname":"Gyudadzhyugyur",
    "gn:country_code":"AZ",
    "gn:dem":-19,
    "gn:feature_class":"P",
    "gn:feature_code":"PPL",
    "gn:name":"Gyudadzhyugyur",
    "gn:population":0,
    "gn:timezone":"Asia/Baku",
    "iso:country":"AZ",
    "name:azb_x_preferred":[
        "\u06af\u0648\u062f\u062c\u0648\u0647\u0648\u0631"
    ],
    "name:aze_x_preferred":[
        "G\u00fcd\u0259c\u00fch\u00fcr"
    ],
    "name:ceb_x_preferred":[
        "Gyudadzhyugyur"
    ],
    "name:ita_x_preferred":[
        "G\u00fcd\u0259c\u00fch\u00fcr"
    ],
    "name:msa_x_preferred":[
        "G\u00fcd\u0259c\u00fch\u00fcr"
    ],
    "name:swe_x_preferred":[
        "Gyudadzhyugyur"
    ],
    "name:und_x_variant":[
        "Gyudadzhyugy",
        "Gyudadzhugur",
        "Gyudadzhur",
        "G\u00fcd\u0259c\u00fch\u00fcr"
    ],
    "wof:name":"Gyudadzhyugyur",
    "wof:placetype":"locality"
},
  "geometry": {"coordinates":[48.7269,39.99739],"type":"Point"}
}