{
  "type": "Feature",
  "properties": {
    "gn:admin1_code":"11",
    "gn:asciiname":"Shorally",
    "gn:country_code":"AZ",
    "gn:dem":65,
    "gn:feature_class":"P",
    "gn:feature_code":"PPL",
    "gn:name":"Shorally",
    "gn:population":0,
    "gn:timezone":"Asia/Baku",
    "iso:country":"AZ",
    "name:aze_x_preferred":[
        "\u015eor\u0259lli"
    ],
    "wof:name":"Shorally",
    "wof:placetype":"locality"
},
  "geometry": {"coordinates":[47.13132,40.41376],"type":"Point"}
}