{
  "type": "Feature",
  "properties": {
    "gn:admin1_code":"11",
    "gn:asciiname":"Shorally",
    "gn:country_code":"AZ",
    "gn:dem":65,
    "gn:feature_class":"P",
    "gn:feature_code":"PPL",
    "gn:name":"Shorally",
    "gn:population":0,
    "gn:timezone":"Asia/Baku",
    "iso:country":"AZ",
    "name:azb_x_preferred":[
        "\u0634\u0648\u0631\u0644\u0644\u06cc"
    ],
    "name:aze_x_preferred":[
        "\u015eor\u0259lli"
    ],
    "name:ceb_x_preferred":[
        "Shorally"
    ],
    "name:ita_x_preferred":[
        "\u015eor\u0259lli"
    ],
    "name:kat_x_preferred":[
        "\u10e8\u10dd\u10e0\u10d0\u10da\u10d8"
    ],
    "name:msa_x_preferred":[
        "\u015eor\u0259lli"
    ],
    "name:swe_x_preferred":[
        "Shorally"
    ],
    "wof:name":"Shorally",
    "wof:placetype":"locality"
},
  "geometry": {"coordinates":[47.13132,40.41376],"type":"Point"}
}