{
  "type": "Feature",
  "properties": {
    "gn:admin1_code":"26",
    "gn:asciiname":"Tsaghkunk'",
    "gn:country_code":"AZ",
    "gn:dem":1821,
    "gn:feature_class":"P",
    "gn:feature_code":"PPL",
    "gn:name":"Tsaghkunk\u2019",
    "gn:population":0,
    "gn:timezone":"Asia/Baku",
    "iso:country":"AZ",
    "name:hye_x_preferred":[
        "Tsaghkunk\u2019"
    ],
    "name:hye_x_variant":[
        "\u053e\u0561\u0572\u056f\u0578\u0582\u0576\u0584"
    ],
    "wof:name":"Tsaghkunk'",
    "wof:placetype":"locality"
},
  "geometry": {"coordinates":[46.42081,39.98506],"type":"Point"}
}