{
  "type": "Feature",
  "properties": {
    "gn:admin1_code":"08",
    "gn:asciiname":"Reqloba",
    "gn:country_code":"AZ",
    "gn:dem":1084,
    "gn:feature_class":"P",
    "gn:feature_code":"PPL",
    "gn:name":"Reqloba",
    "gn:population":0,
    "gn:timezone":"Asia/Baku",
    "iso:country":"AZ",
    "name:aze_x_preferred":[
        "Reqloba"
    ],
    "name:und_x_variant":[
        "Yagul\u2019ba",
        "Ryglyba",
        "R\u0131qloba"
    ],
    "wof:name":"Reqloba",
    "wof:placetype":"locality"
},
  "geometry": {"coordinates":[48.59535,38.55046],"type":"Point"}
}