{
  "type": "Feature",
  "properties": {
    "gn:admin1_code":"08",
    "gn:asciiname":"Reqloba",
    "gn:country_code":"AZ",
    "gn:dem":1084,
    "gn:feature_class":"P",
    "gn:feature_code":"PPL",
    "gn:name":"Reqloba",
    "gn:population":0,
    "gn:timezone":"Asia/Baku",
    "iso:country":"AZ",
    "name:azb_x_preferred":[
        "\u0631\u0642\u0644\u0648\u0628\u0627"
    ],
    "name:aze_x_preferred":[
        "Reqloba"
    ],
    "name:ita_x_preferred":[
        "R\u0131qloba"
    ],
    "name:kat_x_preferred":[
        "\u10e0\u10d4\u10d2\u10da\u10dd\u10d1\u10d0"
    ],
    "name:msa_x_preferred":[
        "R\u0131qloba"
    ],
    "name:und_x_variant":[
        "Yagul\u2019ba",
        "Ryglyba"
    ],
    "wof:name":"Reqloba",
    "wof:placetype":"locality"
},
  "geometry": {"coordinates":[48.59535,38.55046],"type":"Point"}
}