{
  "type": "Feature",
  "properties": {
    "gn:admin1_code":"17",
    "gn:asciiname":"Yelekesan",
    "gn:country_code":"AZ",
    "gn:dem":276,
    "gn:feature_class":"P",
    "gn:feature_code":"PPL",
    "gn:name":"Yelekesan",
    "gn:population":0,
    "gn:timezone":"Asia/Baku",
    "iso:country":"AZ",
    "name:und_x_variant":[
        "Yel\u0259k\u0259s\u0259n"
    ],
    "wof:name":"Yelekesan",
    "wof:placetype":"locality"
},
  "geometry": {"coordinates":[48.88929,41.1661],"type":"Point"}
}