{
  "type": "Feature",
  "properties": {
    "gn:admin1_code":"66",
    "gn:asciiname":"Dzhardu",
    "gn:country_code":"AZ",
    "gn:dem":717,
    "gn:feature_class":"P",
    "gn:feature_code":"PPL",
    "gn:name":"Dzhardu",
    "gn:population":0,
    "gn:timezone":"Asia/Baku",
    "iso:country":"AZ",
    "wof:name":"Dzhardu",
    "wof:placetype":"locality"
},
  "geometry": {"coordinates":[48.43,39.03083],"type":"Point"}
}