{
  "type": "Feature",
  "properties": {
    "gn:admin1_code":"02",
    "gn:asciiname":"Kyurdlyar",
    "gn:country_code":"AZ",
    "gn:dem":149,
    "gn:feature_class":"P",
    "gn:feature_code":"PPL",
    "gn:name":"Kyurdlyar",
    "gn:population":0,
    "gn:timezone":"Asia/Baku",
    "iso:country":"AZ",
    "name:aze_x_preferred":[
        "K\u00fcrdl\u0259r"
    ],
    "name:hye_x_preferred":[
        "K\u2019urdlar"
    ],
    "name:hye_x_variant":[
        "\u0554\u0578\u0582\u0580\u0564\u056c\u0561\u0580"
    ],
    "name:rus_x_preferred":[
        "\u041a\u044e\u0440\u0434\u043b\u044f\u0440"
    ],
    "name:und_x_variant":[
        "\u041a\u044e\u0440\u0434\u043b\u044f\u0440"
    ],
    "wof:name":"Kyurdlyar",
    "wof:placetype":"locality"
},
  "geometry": {"coordinates":[47.16509,39.992],"type":"Point"}
}