{
  "type": "Feature",
  "properties": {
    "gn:admin1_code":"27",
    "gn:asciiname":"Topalgasanly",
    "gn:country_code":"AZ",
    "gn:dem":15,
    "gn:feature_class":"P",
    "gn:feature_code":"PPL",
    "gn:name":"Topalgasanly",
    "gn:population":0,
    "gn:timezone":"Asia/Baku",
    "iso:country":"AZ",
    "name:und_x_variant":[
        "Topalgasanli",
        "Topalgasanly",
        "Topalh\u0259s\u0259nli"
    ],
    "wof:name":"Topalgasanly",
    "wof:placetype":"locality"
},
  "geometry": {"coordinates":[48.19572,40.38449],"type":"Point"}
}