{
  "type": "Feature",
  "properties": {
    "gn:admin1_code":"21",
    "gn:asciiname":"Tap Qaraqoyunlu",
    "gn:country_code":"AZ",
    "gn:dem":503,
    "gn:feature_class":"P",
    "gn:feature_code":"PPL",
    "gn:name":"Tap Qaraqoyunlu",
    "gn:population":0,
    "gn:timezone":"Asia/Baku",
    "iso:country":"AZ",
    "name:aze_x_preferred":[
        "Tap Qaraqoyunlu"
    ],
    "name:eng_x_preferred":[
        "Tap Qaraqoyunlu"
    ],
    "name:hye_x_preferred":[
        "T\u2019ap\u2019gharakoyunlu"
    ],
    "name:hye_x_variant":[
        "\u0539\u0561\u0583\u0572\u0561\u0580\u0561\u056f\u0578\u0575\u0578\u0582\u0576\u056c\u0578\u0582",
        "T\u2019ap\u2019karakoyunlu",
        "\u0539\u0561\u0583\u056f\u0561\u0580\u0561\u056f\u0578\u0575\u0578\u0582\u0576\u056c\u0578\u0582"
    ],
    "name:rus_x_preferred":[
        "\u0422\u0430\u043f_\u043a\u0430\u0440\u0430\u043a\u043e\u044e\u043d\u043b\u0443"
    ],
    "name:rus_x_variant":[
        "\u0422\u0430\u043f\u043a\u0430\u0440\u0430\u043a\u043e\u044e\u043d\u043b\u0443"
    ],
    "name:und_x_variant":[
        "Top-Karakoyunlu",
        "Tapkarakoyunlu"
    ],
    "wof:name":"Tap Qaraqoyunlu",
    "wof:placetype":"locality"
},
  "geometry": {"coordinates":[46.77052,40.43119],"type":"Point"}
}