{
  "type": "Feature",
  "properties": {
    "iso:country":"AZ",
    "name:aze_x_preferred":[
        "A\u011fd\u0259r\u0259"
    ],
    "name:bel_x_preferred":[
        "\u0413\u043e\u0440\u0430\u0434 \u041c\u0430\u0440\u0434\u0430\u043a\u0435\u0440\u0442"
    ],
    "name:bxr_x_preferred":[
        "\u041c\u0430\u0440\u0434\u0430\u043a\u0435\u0440\u0442"
    ],
    "name:che_x_preferred":[
        "\u041c\u0430\u0440\u0434\u0430\u043a\u0435\u0440\u0442"
    ],
    "name:deu_x_preferred":[
        "Martakert"
    ],
    "name:eng_x_preferred":[
        "A\u011fd\u01ddr\u01dd"
    ],
    "name:eng_x_variant":[
        "Aghdara"
    ],
    "name:est_x_preferred":[
        "A\u011fd\u0259r\u0259"
    ],
    "name:fas_x_preferred":[
        "\u0622\u063a\u200c\u062f\u0631\u0647"
    ],
    "name:fin_x_preferred":[
        "Martakert"
    ],
    "name:fra_x_preferred":[
        "Martakert"
    ],
    "name:hsb_x_preferred":[
        "A\u011fd\u0259r\u0259"
    ],
    "name:hye_x_preferred":[
        "\u0544\u0561\u0580\u057f\u0561\u056f\u0565\u0580\u057f"
    ],
    "name:hye_x_variant":[
        "Martakert"
    ],
    "name:ita_x_preferred":[
        "Martakert"
    ],
    "name:jpn_x_preferred":[
        "\u30a2\u30b0\u30c0\u30e9"
    ],
    "name:lit_x_preferred":[
        "Mardakertas"
    ],
    "name:msa_x_preferred":[
        "Aghdara"
    ],
    "name:nld_x_preferred":[
        "Martakert"
    ],
    "name:pol_x_preferred":[
        "A\u011fd\u0259r\u0259"
    ],
    "name:rus_x_preferred":[
        "\u041c\u0430\u0440\u0434\u0430\u043a\u0435\u0440\u0442"
    ],
    "name:rus_x_variant":[
        "\u0410\u0433\u0434\u0435\u0440\u0435"
    ],
    "name:swe_x_preferred":[
        "Martakert"
    ],
    "name:ukr_x_preferred":[
        "\u041c\u0430\u0440\u0442\u0430\u043a\u0435\u0440\u0442"
    ],
    "name:unk_x_variant":[
        "Mardakert"
    ],
    "name:zho_x_preferred":[
        "\u99ac\u723e\u5854\u514b\u723e\u7279"
    ],
    "qs:gn_country":"AZ",
    "qs:gn_fcode":"PPL",
    "qs:gn_pop":10167,
    "qs:name":"Ak\u0327d\u00e4r\u00e4",
    "qs:name_adm0":"Azerbaijan",
    "qs:name_adm1":"Tartar",
    "qs:photos":0,
    "qs:photos_1k":0,
    "qs:photos_9k":1,
    "qs:photos_9r":1,
    "qs:photos_all":2,
    "qs:photos_sr":0,
    "qs:placetype":"Town",
    "qs:pop_sr":"6",
    "qs:woe_adm0":23424741,
    "wof:name":"Ak\u0327d\u00e4r\u00e4",
    "wof:placetype":"locality",
    "wof:population":10167
},
  "geometry": {"coordinates":[46.82097,40.2104],"type":"Point"}
}