{
  "type": "Feature",
  "properties": {
    "gn:admin1_code":"05",
    "gn:asciiname":"Saloglu",
    "gn:country_code":"AZ",
    "gn:dem":249,
    "gn:feature_class":"P",
    "gn:feature_code":"PPL",
    "gn:name":"Salo\u011flu",
    "gn:population":1581,
    "gn:timezone":"Asia/Baku",
    "iso:country":"AZ",
    "name:und_x_variant":[
        "Saloghly",
        "Salogly",
        "Salo\u011flu",
        "Kukheti",
        "Kukhety"
    ],
    "wof:name":"Saloglu",
    "wof:placetype":"locality",
    "wof:population":1581
},
  "geometry": {"coordinates":[45.35293,41.27524],"type":"Point"}
}