{
  "type": "Feature",
  "properties": {
    "gn:admin1_code":"05",
    "gn:asciiname":"Saloglu",
    "gn:country_code":"AZ",
    "gn:dem":249,
    "gn:feature_class":"P",
    "gn:feature_code":"PPL",
    "gn:name":"Salo\u011flu",
    "gn:population":1581,
    "gn:timezone":"Asia/Baku",
    "iso:country":"AZ",
    "name:azb_x_preferred":[
        "\u0633\u0627\u0644\u0648\u063a\u200c\u0644\u0648"
    ],
    "name:aze_x_preferred":[
        "Salo\u011flu"
    ],
    "name:ceb_x_preferred":[
        "Salo\u011flu"
    ],
    "name:hye_x_preferred":[
        "\u054d\u0561\u056c\u0585\u0572\u056c\u0578\u0582"
    ],
    "name:ita_x_preferred":[
        "Salo\u011flu"
    ],
    "name:kat_x_preferred":[
        "\u10e1\u10d0\u10da\u10dd\u10e6\u10da\u10e3"
    ],
    "name:msa_x_preferred":[
        "Salo\u011flu"
    ],
    "name:swe_x_preferred":[
        "Salo\u011flu"
    ],
    "name:und_x_variant":[
        "Saloghly",
        "Salogly",
        "Kukheti",
        "Kukhety"
    ],
    "wof:name":"Saloglu",
    "wof:placetype":"locality",
    "wof:population":1581
},
  "geometry": {"coordinates":[45.35293,41.27524],"type":"Point"}
}