{
  "type": "Feature",
  "properties": {
    "gn:admin1_code":"05",
    "gn:asciiname":"Geydzhally",
    "gn:country_code":"AZ",
    "gn:dem":455,
    "gn:feature_class":"P",
    "gn:feature_code":"PPL",
    "gn:name":"Geydzhally",
    "gn:population":0,
    "gn:timezone":"Asia/Baku",
    "iso:country":"AZ",
    "name:und_x_variant":[
        "G\u00ebydzhali",
        "G\u00f6yc\u0259li"
    ],
    "wof:name":"Geydzhally",
    "wof:placetype":"locality"
},
  "geometry": {"coordinates":[45.4756,41.0426],"type":"Point"}
}