{
  "type": "Feature",
  "properties": {
    "gn:admin1_code":"46",
    "gn:asciiname":"Kyurkendi",
    "gn:country_code":"AZ",
    "gn:dem":-14,
    "gn:feature_class":"P",
    "gn:feature_code":"PPL",
    "gn:name":"Kyurkendi",
    "gn:population":0,
    "gn:timezone":"Asia/Baku",
    "iso:country":"AZ",
    "name:azb_x_preferred":[
        "\u06a9\u0648\u0631 \u06a9\u0646\u062f\u06cc"
    ],
    "name:aze_x_preferred":[
        "K\u00fcrk\u0259ndi"
    ],
    "name:ceb_x_preferred":[
        "Kyurkendi"
    ],
    "name:ita_x_preferred":[
        "K\u00fcrk\u0259ndi"
    ],
    "name:msa_x_preferred":[
        "K\u00fcrk\u0259ndi"
    ],
    "name:swe_x_preferred":[
        "Kyurkendi"
    ],
    "wof:name":"Kyurkendi",
    "wof:placetype":"locality"
},
  "geometry": {"coordinates":[48.48211,40.02615],"type":"Point"}
}