{
  "type": "Feature",
  "properties": {
    "gn:admin1_code":"03",
    "gn:asciiname":"Acarli",
    "gn:country_code":"AZ",
    "gn:dem":284,
    "gn:feature_class":"P",
    "gn:feature_code":"PPL",
    "gn:name":"Acarl\u0131",
    "gn:population":0,
    "gn:timezone":"Asia/Baku",
    "iso:country":"AZ",
    "name:aze_x_preferred":[
        "Acanl\u0131"
    ],
    "name:aze_x_variant":[
        "Acarl\u0131"
    ],
    "name:und_x_variant":[
        "Adzharly"
    ],
    "wof:name":"Acarli",
    "wof:placetype":"locality"
},
  "geometry": {"coordinates":[47.01361,39.978],"type":"Point"}
}