{
  "type": "Feature",
  "properties": {
    "gn:admin1_code":"02",
    "gn:asciiname":"Allahgulubagi",
    "gn:country_code":"AZ",
    "gn:dem":-4,
    "gn:feature_class":"P",
    "gn:feature_code":"PPL",
    "gn:name":"Allahguluba\u011f\u0131",
    "gn:population":0,
    "gn:timezone":"Asia/Baku",
    "iso:country":"AZ",
    "name:aze_x_preferred":[
        "Allahguluba\u011f\u0131"
    ],
    "name:und_x_variant":[
        "Abyshbeyli",
        "Allakhkulubagy"
    ],
    "wof:name":"Allahgulubagi",
    "wof:placetype":"locality"
},
  "geometry": {"coordinates":[47.6688,40.19117],"type":"Point"}
}