{
  "type": "Feature",
  "properties": {
    "gn:admin1_code":"02",
    "gn:asciiname":"Allahgulubagi",
    "gn:country_code":"AZ",
    "gn:dem":-4,
    "gn:feature_class":"P",
    "gn:feature_code":"PPL",
    "gn:name":"Allahguluba\u011f\u0131",
    "gn:population":0,
    "gn:timezone":"Asia/Baku",
    "iso:country":"AZ",
    "name:azb_x_preferred":[
        "\u0627\u0628\u06cc\u0634\u0628\u06cc\u0644\u06cc"
    ],
    "name:aze_x_preferred":[
        "Allahguluba\u011f\u0131"
    ],
    "name:fas_x_preferred":[
        "\u0627\u0628\u06cc\u0634\u0628\u06cc\u0644\u06cc"
    ],
    "name:ita_x_preferred":[
        "Abyshbeyli"
    ],
    "name:kat_x_preferred":[
        "\u10d0\u10d1\u10d8\u10e8\u10d1\u10d4\u10d8\u10da\u10d8"
    ],
    "name:msa_x_preferred":[
        "Abyshbeyli"
    ],
    "name:und_x_variant":[
        "Allakhkulubagy"
    ],
    "wof:name":"Allahgulubagi",
    "wof:placetype":"locality"
},
  "geometry": {"coordinates":[47.6688,40.19117],"type":"Point"}
}