{
  "type": "Feature",
  "properties": {
    "gn:admin1_code":"45",
    "gn:asciiname":"Qaralar",
    "gn:country_code":"AZ",
    "gn:dem":-8,
    "gn:feature_class":"P",
    "gn:feature_code":"PPL",
    "gn:name":"Qaralar",
    "gn:population":0,
    "gn:timezone":"Asia/Baku",
    "iso:country":"AZ",
    "name:aze_x_preferred":[
        "Qaralar"
    ],
    "name:und_x_variant":[
        "Karalar",
        "Karaliar",
        "Qaracalar"
    ],
    "wof:name":"Qaralar",
    "wof:placetype":"locality"
},
  "geometry": {"coordinates":[48.26299,39.86668],"type":"Point"}
}