{
  "type": "Feature",
  "properties": {
    "gn:admin1_code":"21",
    "gn:asciiname":"Qarqucaq",
    "gn:country_code":"AZ",
    "gn:dem":445,
    "gn:feature_class":"P",
    "gn:feature_code":"PPL",
    "gn:name":"Qarqucaq",
    "gn:population":0,
    "gn:timezone":"Asia/Baku",
    "iso:country":"AZ",
    "name:aze_x_preferred":[
        "Qarqucaq"
    ],
    "name:ceb_x_preferred":[
        "Qarqucaq"
    ],
    "name:hye_x_preferred":[
        "K\u2019arkujak"
    ],
    "name:hye_x_variant":[
        "\u0554\u0561\u0580\u056f\u0578\u0582\u057b\u0561\u056f",
        "K\u2019ark\u2019ujak",
        "\u0554\u0561\u0580\u0584\u0578\u0582\u057b\u0561\u056f"
    ],
    "name:ita_x_preferred":[
        "Qarqucaq"
    ],
    "name:kat_x_preferred":[
        "\u10e7\u10d0\u10e0\u10e5\u10e3\u10ef\u10d0\u10ee\u10d8"
    ],
    "name:msa_x_preferred":[
        "Qarqucaq"
    ],
    "name:rus_x_preferred":[
        "\u041a\u0430\u0440\u043a\u0443\u0434\u0436\u0430\u043a"
    ],
    "name:und_x_variant":[
        "Karakudzhakh",
        "Karkudzhan",
        "Karakudzhak",
        "Karkudzhak"
    ],
    "wof:name":"Qarqucaq",
    "wof:placetype":"locality"
},
  "geometry": {"coordinates":[46.7233,40.49101],"type":"Point"}
}