{
  "type": "Feature",
  "properties": {
    "gn:admin1_code":"42",
    "gn:asciiname":"Atuc",
    "gn:country_code":"AZ",
    "gn:dem":1236,
    "gn:feature_class":"P",
    "gn:feature_code":"PPL",
    "gn:name":"Atuc",
    "gn:population":0,
    "gn:timezone":"Asia/Baku",
    "iso:country":"AZ",
    "name:und_x_variant":[
        "Atuch",
        "Atuc"
    ],
    "wof:name":"Atuc",
    "wof:placetype":"locality"
},
  "geometry": {"coordinates":[48.61173,41.10973],"type":"Point"}
}