{
  "type": "Feature",
  "properties": {
    "gn:admin1_code":"05",
    "gn:asciiname":"Beyazatly",
    "gn:country_code":"AZ",
    "gn:dem":474,
    "gn:feature_class":"P",
    "gn:feature_code":"PPL",
    "gn:name":"Beyazatly",
    "gn:population":0,
    "gn:timezone":"Asia/Baku",
    "iso:country":"AZ",
    "name:und_x_variant":[
        "Bayazatly",
        "Beyazatly",
        "B\u0259yazatl\u0131"
    ],
    "wof:name":"Beyazatly",
    "wof:placetype":"locality"
},
  "geometry": {"coordinates":[45.46667,41.05],"type":"Point"}
}