{
  "type": "Feature",
  "properties": {
    "gn:admin1_code":"42",
    "gn:asciiname":"Gyuneymakhla",
    "gn:country_code":"AZ",
    "gn:dem":626,
    "gn:feature_class":"P",
    "gn:feature_code":"PPL",
    "gn:name":"Gyuneymakhla",
    "gn:population":0,
    "gn:timezone":"Asia/Baku",
    "iso:country":"AZ",
    "name:aze_x_preferred":[
        "G\u00fcneym\u0259hl\u0259"
    ],
    "wof:name":"Gyuneymakhla",
    "wof:placetype":"locality"
},
  "geometry": {"coordinates":[48.58197,41.26174],"type":"Point"}
}