{
  "type": "Feature",
  "properties": {
    "gn:admin1_code":"14",
    "gn:asciiname":"Horovlu",
    "gn:country_code":"AZ",
    "gn:dem":432,
    "gn:feature_class":"P",
    "gn:feature_code":"PPL",
    "gn:name":"Horovlu",
    "gn:population":0,
    "gn:timezone":"Asia/Baku",
    "iso:country":"AZ",
    "name:azb_x_preferred":[
        "\u0647\u0648\u0631\u0648\u0648\u0644\u0648"
    ],
    "name:aze_x_preferred":[
        "Horovlu"
    ],
    "name:hye_x_preferred":[
        "\u053d\u0578\u0580\u0578\u057e\u056c\u0578\u0582"
    ],
    "name:min_x_preferred":[
        "Horovlu"
    ],
    "name:msa_x_preferred":[
        "Horovlu"
    ],
    "name:rus_x_preferred":[
        "\u0425\u043e\u0440\u043e\u0432\u043b\u0443"
    ],
    "name:und_x_variant":[
        "Gorovlu",
        "Goravly",
        "Khorovlu"
    ],
    "wof:name":"Horovlu",
    "wof:placetype":"locality"
},
  "geometry": {"coordinates":[47.09662,39.40171],"type":"Point"}
}