{
  "type": "Feature",
  "properties": {
    "gn:admin1_code":"40",
    "gn:asciiname":"Yukhary Askipara",
    "gn:country_code":"AZ",
    "gn:dem":808,
    "gn:feature_class":"P",
    "gn:feature_code":"PPL",
    "gn:name":"Yukhary Askipara",
    "gn:population":0,
    "gn:timezone":"Asia/Baku",
    "iso:country":"AZ",
    "name:und_x_variant":[
        "Okari-Eskipara",
        "Yukhary Askipara",
        "Yuxar\u0131 \u018fskipara"
    ],
    "wof:name":"Yukhary Askipara",
    "wof:placetype":"locality"
},
  "geometry": {"coordinates":[45.02625,41.06407],"type":"Point"}
}