{
  "type": "Feature",
  "properties": {
    "gn:admin1_code":"14",
    "gn:asciiname":"Nekhaly",
    "gn:country_code":"AZ",
    "gn:dem":357,
    "gn:feature_class":"P",
    "gn:feature_code":"PPL",
    "gn:name":"Nekhaly",
    "gn:population":0,
    "gn:timezone":"Asia/Baku",
    "iso:country":"AZ",
    "name:rus_x_preferred":[
        "\u041d\u0435\u0439\u0445\u0430\u043b\u0438"
    ],
    "wof:name":"Nekhaly",
    "wof:placetype":"locality"
},
  "geometry": {"coordinates":[46.94995,39.28149000000001],"type":"Point"}
}