{
  "type": "Feature",
  "properties": {
    "gn:admin1_code":"21",
    "gn:asciiname":"Sarov",
    "gn:country_code":"AZ",
    "gn:dem":199,
    "gn:feature_class":"P",
    "gn:feature_code":"PPL",
    "gn:name":"Sarov",
    "gn:population":0,
    "gn:timezone":"Asia/Baku",
    "iso:country":"AZ",
    "name:azb_x_preferred":[
        "\u0633\u0627\u0631\u0648\u0648\u0644\u0648"
    ],
    "name:aze_x_preferred":[
        "Sarovlu"
    ],
    "name:ceb_x_preferred":[
        "Sarov"
    ],
    "name:ita_x_preferred":[
        "Sarovlu"
    ],
    "name:kat_x_preferred":[
        "\u10e1\u10d0\u10e0\u10dd\u10d5\u10da\u10e3"
    ],
    "name:msa_x_preferred":[
        "Sarovlu"
    ],
    "name:und_x_variant":[
        "Saroylu",
        "Sarov",
        "Sarovlu"
    ],
    "wof:name":"Sarov",
    "wof:placetype":"locality"
},
  "geometry": {"coordinates":[46.5906,40.72661],"type":"Point"}
}