{
  "type": "Feature",
  "properties": {
    "gn:admin1_code":"21",
    "gn:asciiname":"Sarov",
    "gn:country_code":"AZ",
    "gn:dem":199,
    "gn:feature_class":"P",
    "gn:feature_code":"PPL",
    "gn:name":"Sarov",
    "gn:population":0,
    "gn:timezone":"Asia/Baku",
    "iso:country":"AZ",
    "name:und_x_variant":[
        "Saroylu",
        "Sarov",
        "Sarovlu"
    ],
    "wof:name":"Sarov",
    "wof:placetype":"locality"
},
  "geometry": {"coordinates":[46.5906,40.72661],"type":"Point"}
}