{
  "type": "Feature",
  "properties": {
    "gn:admin1_code":"69",
    "gn:asciiname":"Agakishilyar",
    "gn:country_code":"AZ",
    "gn:dem":522,
    "gn:feature_class":"P",
    "gn:feature_code":"PPL",
    "gn:name":"Agakishilyar",
    "gn:population":0,
    "gn:timezone":"Asia/Baku",
    "iso:country":"AZ",
    "name:aze_x_preferred":[
        "A\u011faki\u015fil\u0259r"
    ],
    "name:rus_x_preferred":[
        "\u0410\u0433\u0430\u043a\u0438\u0448\u0438\u043b\u044f\u0440"
    ],
    "wof:name":"Agakishilyar",
    "wof:placetype":"locality"
},
  "geometry": {"coordinates":[46.65836,39.22112],"type":"Point"}
}