{
  "type": "Feature",
  "properties": {
    "gn:admin1_code":"36",
    "gn:asciiname":"Ikinci Qarali",
    "gn:country_code":"AZ",
    "gn:dem":-25,
    "gn:feature_class":"P",
    "gn:feature_code":"PPL",
    "gn:name":"\u0130kinci Qaral\u0131",
    "gn:population":0,
    "gn:timezone":"Asia/Baku",
    "iso:country":"AZ",
    "name:und_x_variant":[
        "\u0130kinci Qaral\u0131"
    ],
    "wof:name":"Ikinci Qarali",
    "wof:placetype":"locality"
},
  "geometry": {"coordinates":[49.0325,39.45444000000001],"type":"Point"}
}