{
  "type": "Feature",
  "properties": {
    "gn:admin1_code":"36",
    "gn:asciiname":"Ikinci Qarali",
    "gn:country_code":"AZ",
    "gn:dem":-25,
    "gn:feature_class":"P",
    "gn:feature_code":"PPL",
    "gn:name":"\u0130kinci Qaral\u0131",
    "gn:population":0,
    "gn:timezone":"Asia/Baku",
    "iso:country":"AZ",
    "name:azb_x_preferred":[
        "\u0627\u06cc\u06a9\u06cc\u0646\u062c\u06cc \u0642\u0627\u0631\u0627\u0644\u06cc"
    ],
    "name:aze_x_preferred":[
        "\u0130kinci Qaral\u0131"
    ],
    "name:msa_x_preferred":[
        "\u0130kinci Qaral\u0131"
    ],
    "wof:name":"Ikinci Qarali",
    "wof:placetype":"locality"
},
  "geometry": {"coordinates":[49.0325,39.45444000000001],"type":"Point"}
}