{
  "type": "Feature",
  "properties": {
    "gn:admin1_code":"35",
    "gn:admin2_code":"147212.0",
    "gn:asciiname":"Mezre",
    "gn:country_code":"AZ",
    "gn:dem":1071,
    "gn:feature_class":"P",
    "gn:feature_code":"PPL",
    "gn:name":"Mezre",
    "gn:population":0,
    "gn:timezone":"Asia/Baku",
    "iso:country":"AZ",
    "name:aze_x_preferred":[
        "M\u0259zr\u0259"
    ],
    "name:eng_x_preferred":[
        "Mazra"
    ],
    "wof:name":"Mezre",
    "wof:placetype":"locality"
},
  "geometry": {"coordinates":[45.47842,39.33447],"type":"Point"}
}