{
  "type": "Feature",
  "properties": {
    "gn:admin1_code":"35",
    "gn:admin2_code":"7669114.0",
    "gn:asciiname":"Qahab",
    "gn:country_code":"AZ",
    "gn:dem":1022,
    "gn:feature_class":"P",
    "gn:feature_code":"PPL",
    "gn:name":"Qahab",
    "gn:population":0,
    "gn:timezone":"Asia/Baku",
    "iso:country":"AZ",
    "name:aze_x_preferred":[
        "Qahab"
    ],
    "name:und_x_variant":[
        "Kakhab",
        "Kagab"
    ],
    "wof:name":"Qahab",
    "wof:placetype":"locality"
},
  "geometry": {"coordinates":[45.51638,39.25138],"type":"Point"}
}