{
  "type": "Feature",
  "properties": {
    "gn:admin1_code":"44",
    "gn:asciiname":"Laza",
    "gn:country_code":"AZ",
    "gn:dem":1631,
    "gn:feature_class":"P",
    "gn:feature_code":"PPL",
    "gn:name":"Laza",
    "gn:population":0,
    "gn:timezone":"Asia/Baku",
    "iso:country":"AZ",
    "name:azb_x_preferred":[
        "\u0644\u0627\u0632\u0627"
    ],
    "name:aze_x_preferred":[
        "Laza"
    ],
    "name:eng_x_preferred":[
        "Laza"
    ],
    "name:ita_x_preferred":[
        "Laza"
    ],
    "name:kat_x_preferred":[
        "\u10da\u10d0\u10d6\u10d0"
    ],
    "name:lez_x_preferred":[
        "\u041b\u0430\u0446\u0430\u0440"
    ],
    "name:msa_x_preferred":[
        "Laza"
    ],
    "name:rus_x_preferred":[
        "\u041b\u0430\u0437\u0430"
    ],
    "wof:name":"Laza",
    "wof:placetype":"locality"
},
  "geometry": {"coordinates":[48.11161,41.29913],"type":"Point"}
}