{
  "type": "Feature",
  "properties": {
    "gn:admin1_code":"53",
    "gn:asciiname":"Qaragoz",
    "gn:country_code":"AZ",
    "gn:dem":619,
    "gn:feature_class":"P",
    "gn:feature_code":"PPL",
    "gn:name":"Qarag\u00f6z",
    "gn:population":0,
    "gn:timezone":"Asia/Baku",
    "iso:country":"AZ",
    "name:und_x_variant":[
        "Karag\u00ebz",
        "Qarag\u00f6z"
    ],
    "wof:name":"Qaragoz",
    "wof:placetype":"locality"
},
  "geometry": {"coordinates":[48.9856,40.95],"type":"Point"}
}