{
  "type": "Feature",
  "properties": {
    "gn:admin1_code":"02",
    "gn:asciiname":"Randzhbarlyar",
    "gn:country_code":"AZ",
    "gn:dem":67,
    "gn:feature_class":"P",
    "gn:feature_code":"PPL",
    "gn:name":"Randzhbarlyar",
    "gn:population":0,
    "gn:timezone":"Asia/Baku",
    "iso:country":"AZ",
    "name:azb_x_preferred":[
        "\u0631\u0646\u062c\u0628\u0631\u0644\u0631"
    ],
    "name:aze_x_preferred":[
        "R\u0259ncb\u0259rl\u0259r"
    ],
    "name:ceb_x_preferred":[
        "Randzhbarlyar"
    ],
    "name:fas_x_preferred":[
        "\u0631\u0646\u062c\u0628\u0631\u0644\u0631"
    ],
    "name:ita_x_preferred":[
        "R\u0259ncb\u0259rl\u0259r"
    ],
    "name:kat_x_preferred":[
        "\u10e0\u10d0\u10dc\u10ef\u10d1\u10d0\u10e0\u10da\u10d0\u10e0\u10d8"
    ],
    "name:msa_x_preferred":[
        "R\u0259ncb\u0259rl\u0259r"
    ],
    "name:rus_x_preferred":[
        "\u0420\u0430\u043d\u0434\u0436\u0431\u0430\u0440\u043b\u0430\u0440"
    ],
    "name:swe_x_preferred":[
        "Randzhbarlyar"
    ],
    "name:und_x_variant":[
        "Randzhbarlar"
    ],
    "wof:name":"Randzhbarlyar",
    "wof:placetype":"locality"
},
  "geometry": {"coordinates":[47.29937,40.05433],"type":"Point"}
}