{
  "type": "Feature",
  "properties": {
    "gn:admin1_code":"02",
    "gn:asciiname":"Randzhbarlyar",
    "gn:country_code":"AZ",
    "gn:dem":67,
    "gn:feature_class":"P",
    "gn:feature_code":"PPL",
    "gn:name":"Randzhbarlyar",
    "gn:population":0,
    "gn:timezone":"Asia/Baku",
    "iso:country":"AZ",
    "name:aze_x_preferred":[
        "R\u0259ncb\u0259rl\u0259r"
    ],
    "name:und_x_variant":[
        "Randzhbarlar",
        "Randzhbarlyar"
    ],
    "wof:name":"Randzhbarlyar",
    "wof:placetype":"locality"
},
  "geometry": {"coordinates":[47.29937,40.05433],"type":"Point"}
}