{
  "type": "Feature",
  "properties": {
    "gn:admin1_code":"26",
    "gn:asciiname":"Orta Surtan",
    "gn:country_code":"AZ",
    "gn:dem":1959,
    "gn:feature_class":"P",
    "gn:feature_code":"PPL",
    "gn:name":"Orta \u015eurtan",
    "gn:population":0,
    "gn:timezone":"Asia/Baku",
    "iso:country":"AZ",
    "name:aze_x_preferred":[
        "Orta \u015eurtan"
    ],
    "name:aze_x_variant":[
        "\u015eurtan"
    ],
    "name:rus_x_preferred":[
        "\u041e\u0440\u0442\u0430-\u0428\u0443\u0440\u0442\u0430\u043d"
    ],
    "name:und_x_variant":[
        "Orta-Shurtan"
    ],
    "wof:name":"Orta Surtan",
    "wof:placetype":"locality"
},
  "geometry": {"coordinates":[45.98542,39.99094],"type":"Point"}
}