{
  "type": "Feature",
  "properties": {
    "gn:admin1_code":"04",
    "gn:asciiname":"Yukhary Zeynaddin",
    "gn:country_code":"AZ",
    "gn:dem":46,
    "gn:feature_class":"P",
    "gn:feature_code":"PPL",
    "gn:name":"Yukhary Zeynaddin",
    "gn:population":0,
    "gn:timezone":"Asia/Baku",
    "iso:country":"AZ",
    "name:und_x_variant":[
        "Yuxar\u0131 Zeyn\u0259ddin"
    ],
    "wof:name":"Yukhary Zeynaddin",
    "wof:placetype":"locality"
},
  "geometry": {"coordinates":[47.47361,40.65694000000001],"type":"Point"}
}