{
  "type": "Feature",
  "properties": {
    "gn:admin1_code":"35",
    "gn:admin2_code":"147212.0",
    "gn:asciiname":"Selesyuz",
    "gn:country_code":"AZ",
    "gn:dem":1135,
    "gn:feature_class":"P",
    "gn:feature_code":"PPL",
    "gn:name":"Selesyuz",
    "gn:population":0,
    "gn:timezone":"Asia/Baku",
    "iso:country":"AZ",
    "name:aze_x_preferred":[
        "S\u0259l\u0259s\u00fcz"
    ],
    "name:ceb_x_preferred":[
        "Selesyuz"
    ],
    "name:hye_x_preferred":[
        "\u054d\u0561\u0572\u0578\u0582\u0561\u057d\u0578\u0576\u0584"
    ],
    "name:ita_x_preferred":[
        "S\u0259l\u0259s\u00fcz"
    ],
    "name:kat_x_preferred":[
        "\u10e1\u10d4\u10da\u10d4\u10e1\u10d8\u10e3\u10d6\u10d8"
    ],
    "name:msa_x_preferred":[
        "S\u0259l\u0259s\u00fcz"
    ],
    "name:swe_x_preferred":[
        "Selesyuz"
    ],
    "wof:name":"Selesyuz",
    "wof:placetype":"locality"
},
  "geometry": {"coordinates":[45.50451,39.39563],"type":"Point"}
}