{
  "type": "Feature",
  "properties": {
    "gn:admin1_code":"49",
    "gn:asciiname":"Sorsulu",
    "gn:country_code":"AZ",
    "gn:dem":-23,
    "gn:feature_class":"P",
    "gn:feature_code":"PPL",
    "gn:name":"\u015eorsulu",
    "gn:population":0,
    "gn:timezone":"Asia/Baku",
    "iso:country":"AZ",
    "name:und_x_variant":[
        "Shorsuli",
        "Shorsuly",
        "Shorsulu",
        "\u015eorsulu"
    ],
    "wof:name":"Sorsulu",
    "wof:placetype":"locality"
},
  "geometry": {"coordinates":[48.8246,39.42359],"type":"Point"}
}