{
  "type": "Feature",
  "properties": {
    "gn:admin1_code":"46",
    "gn:asciiname":"Malyy Talysh",
    "gn:country_code":"AZ",
    "gn:dem":-17,
    "gn:feature_class":"P",
    "gn:feature_code":"PPL",
    "gn:name":"Malyy Talysh",
    "gn:population":0,
    "gn:timezone":"Asia/Baku",
    "iso:country":"AZ",
    "name:ita_x_preferred":[
        "Malyy Talysh"
    ],
    "name:msa_x_preferred":[
        "Malyy Talysh"
    ],
    "name:und_x_variant":[
        "Kichik-Talysh",
        "Malyy Talysh"
    ],
    "wof:name":"Malyy Talysh",
    "wof:placetype":"locality"
},
  "geometry": {"coordinates":[48.70639,40.04667],"type":"Point"}
}