{
  "type": "Feature",
  "properties": {
    "gn:admin1_code":"65",
    "gn:asciiname":"Hesan",
    "gn:country_code":"AZ",
    "gn:dem":745,
    "gn:feature_class":"P",
    "gn:feature_code":"PPL",
    "gn:name":"He\u015fan",
    "gn:population":0,
    "gn:timezone":"Asia/Baku",
    "iso:country":"AZ",
    "name:azb_x_preferred":[
        "\u0647\u0634\u0627\u0646"
    ],
    "name:aze_x_preferred":[
        "He\u015fan"
    ],
    "name:bel_x_preferred":[
        "\u0410\u0448\u0430\u043d"
    ],
    "name:ceb_x_preferred":[
        "He\u015fan"
    ],
    "name:fra_x_preferred":[
        "Ashan"
    ],
    "name:hye_x_preferred":[
        "\u0531\u0577\u0561\u0576"
    ],
    "name:ita_x_preferred":[
        "Ashan"
    ],
    "name:msa_x_preferred":[
        "He\u015fan"
    ],
    "name:rus_x_preferred":[
        "\u0410\u0448\u0430\u043d"
    ],
    "name:swe_x_preferred":[
        "He\u015fan"
    ],
    "name:ukr_x_preferred":[
        "\u0410\u0448\u0430\u043d"
    ],
    "name:und_x_variant":[
        "A\u015fan"
    ],
    "wof:name":"Hesan",
    "wof:placetype":"locality"
},
  "geometry": {"coordinates":[46.99515,39.84658],"type":"Point"}
}