{
  "type": "Feature",
  "properties": {
    "gn:admin1_code":"25",
    "gn:asciiname":"Eyubbeyli",
    "gn:country_code":"AZ",
    "gn:dem":283,
    "gn:feature_class":"P",
    "gn:feature_code":"PPL",
    "gn:name":"Eyubbeyli",
    "gn:population":0,
    "gn:timezone":"Asia/Baku",
    "iso:country":"AZ",
    "name:aze_x_preferred":[
        "\u018fyyubb\u0259yli"
    ],
    "name:und_x_variant":[
        "\u018fyyubb\u0259li"
    ],
    "wof:name":"Eyubbeyli",
    "wof:placetype":"locality"
},
  "geometry": {"coordinates":[48.23157,40.62635],"type":"Point"}
}