{
  "type": "Feature",
  "properties": {
    "gn:admin1_code":"69",
    "gn:asciiname":"Ashaga Agaly",
    "gn:country_code":"AZ",
    "gn:dem":325,
    "gn:feature_class":"P",
    "gn:feature_code":"PPL",
    "gn:name":"Ashaga Agaly",
    "gn:population":0,
    "gn:timezone":"Asia/Baku",
    "iso:country":"AZ",
    "name:aze_x_preferred":[
        "\u00dc\u00e7\u00fcnc\u00fc A\u011fal\u0131"
    ],
    "name:bel_x_preferred":[
        "\u0410\u0445\u0430\u0434\u0437\u043e\u0440"
    ],
    "name:fas_x_preferred":[
        "\u0622\u063a\u0627\u062f\u0632\u0648\u0631"
    ],
    "name:hye_x_preferred":[
        "Aghadzor"
    ],
    "name:hye_x_variant":[
        "\u0531\u0572\u0561\u0571\u0578\u0580"
    ],
    "name:kat_x_preferred":[
        "\u10d8\u10e3\u10e9\u10d8\u10e3\u10dc\u10ef\u10d8-\u10d0\u10e6\u10d0\u10da\u10d8"
    ],
    "name:msa_x_preferred":[
        "\u00dc\u00e7\u00fcnc\u00fc A\u011fal\u0131"
    ],
    "name:rus_x_preferred":[
        "Agaly Tret\u2019ye"
    ],
    "name:rus_x_variant":[
        "\u0410\u0433\u0430\u043b\u044b \u0422\u0440\u0435\u0442\u044c\u0435"
    ],
    "name:ukr_x_preferred":[
        "\u0410\u0445\u0430\u0434\u0437\u043e\u0440"
    ],
    "name:urd_x_preferred":[
        "\u0627\u0686\u0648\u0646\u06a9\u0648 \u0622\u063a\u0644\u06cc"
    ],
    "wof:name":"Ashaga Agaly",
    "wof:placetype":"locality"
},
  "geometry": {"coordinates":[46.77466,39.17555],"type":"Point"}
}