{
  "type": "Feature",
  "properties": {
    "gn:admin1_code":"69",
    "gn:asciiname":"Ashaga Agaly",
    "gn:country_code":"AZ",
    "gn:dem":325,
    "gn:feature_class":"P",
    "gn:feature_code":"PPL",
    "gn:name":"Ashaga Agaly",
    "gn:population":0,
    "gn:timezone":"Asia/Baku",
    "iso:country":"AZ",
    "name:aze_x_preferred":[
        "\u00dc\u00e7\u00fcnc\u00fc A\u011fal\u0131"
    ],
    "name:hye_x_preferred":[
        "Aghadzor"
    ],
    "name:hye_x_variant":[
        "\u0531\u0572\u0561\u0571\u0578\u0580"
    ],
    "name:rus_x_preferred":[
        "Agaly Tret\u2019ye"
    ],
    "name:rus_x_variant":[
        "\u0410\u0433\u0430\u043b\u044b \u0422\u0440\u0435\u0442\u044c\u0435"
    ],
    "wof:name":"Ashaga Agaly",
    "wof:placetype":"locality"
},
  "geometry": {"coordinates":[46.77466,39.17555],"type":"Point"}
}