{
  "type": "Feature",
  "properties": {
    "gn:admin1_code":"16",
    "gn:asciiname":"Verin-Karagat",
    "gn:country_code":"AZ",
    "gn:dem":1791,
    "gn:feature_class":"P",
    "gn:feature_code":"PPL",
    "gn:name":"Verin-Karagat",
    "gn:population":0,
    "gn:timezone":"Asia/Baku",
    "iso:country":"AZ",
    "wof:name":"Verin-Karagat",
    "wof:placetype":"locality"
},
  "geometry": {"coordinates":[46.08333,40.48333],"type":"Point"}
}