{
  "type": "Feature",
  "properties": {
    "gn:admin1_code":"65",
    "gn:asciiname":"Kert",
    "gn:country_code":"AZ",
    "gn:dem":815,
    "gn:feature_class":"P",
    "gn:feature_code":"PPL",
    "gn:name":"Kert",
    "gn:population":0,
    "gn:timezone":"Asia/Baku",
    "iso:country":"AZ",
    "name:aze_x_preferred":[
        "Quzumk\u0259nd"
    ],
    "name:hye_x_preferred":[
        "K\u2019ert\u2019"
    ],
    "name:hye_x_variant":[
        "\u0554\u0565\u0580\u0569"
    ],
    "name:rus_x_preferred":[
        "\u041a\u0435\u0440\u0442"
    ],
    "name:und_x_variant":[
        "\u041a\u0435\u0440\u0442"
    ],
    "wof:name":"Kert",
    "wof:placetype":"locality"
},
  "geometry": {"coordinates":[46.99249,39.74408],"type":"Point"}
}