{
  "type": "Feature",
  "properties": {
    "gn:admin1_code":"42",
    "gn:asciiname":"Leyti-Kazma",
    "gn:country_code":"AZ",
    "gn:dem":285,
    "gn:feature_class":"P",
    "gn:feature_code":"PPL",
    "gn:name":"Leyti-Kazma",
    "gn:population":0,
    "gn:timezone":"Asia/Baku",
    "iso:country":"AZ",
    "wof:name":"Leyti-Kazma",
    "wof:placetype":"locality"
},
  "geometry": {"coordinates":[48.81667,41.25],"type":"Point"}
}