{
  "type": "Feature",
  "properties": {
    "gn:admin1_code":"42",
    "gn:asciiname":"Leyti-Kazma",
    "gn:country_code":"AZ",
    "gn:dem":285,
    "gn:feature_class":"P",
    "gn:feature_code":"PPL",
    "gn:name":"Leyti-Kazma",
    "gn:population":0,
    "gn:timezone":"Asia/Baku",
    "iso:country":"AZ",
    "name:ell_x_preferred":[
        "\u039b\u03ad\u03b9\u03c4\u03b9-\u039a\u03ac\u03b6\u03bc\u03b1"
    ],
    "name:ita_x_preferred":[
        "Leyti-Kazma"
    ],
    "name:msa_x_preferred":[
        "Leyti-Kazma"
    ],
    "wof:name":"Leyti-Kazma",
    "wof:placetype":"locality"
},
  "geometry": {"coordinates":[48.81667,41.25],"type":"Point"}
}