{
  "type": "Feature",
  "properties": {
    "gn:admin1_code":"60",
    "gn:asciiname":"Qaradagli",
    "gn:country_code":"AZ",
    "gn:dem":64,
    "gn:feature_class":"P",
    "gn:feature_code":"PPL",
    "gn:name":"Qarada\u011fl\u0131",
    "gn:population":0,
    "gn:timezone":"Asia/Baku",
    "iso:country":"AZ",
    "name:und_x_variant":[
        "Karadagly",
        "Qarada\u011fl\u0131"
    ],
    "wof:name":"Qaradagli",
    "wof:placetype":"locality"
},
  "geometry": {"coordinates":[48.83216,41.40415],"type":"Point"}
}