{
  "type": "Feature",
  "properties": {
    "iso:country":"AZ",
    "name:aze_x_preferred":[
        "\u015e\u0259ki"
    ],
    "name:bel_x_variant":[
        "\u0428\u044d\u043a\u0456"
    ],
    "name:rus_x_preferred":[
        "\u0428\u0435\u043a\u0438"
    ],
    "name:tur_x_preferred":[
        "\u015eeki"
    ],
    "name:unk_x_variant":[
        "Shekili"
    ],
    "qs:gn_country":"AZ",
    "qs:gn_fcode":"PPL",
    "qs:gn_pop":0,
    "qs:name":"Sheki",
    "qs:name_adm0":"Azerbaijan",
    "qs:name_adm1":"Saki",
    "qs:photos":504,
    "qs:photos_1k":102,
    "qs:photos_9k":2,
    "qs:photos_9r":5,
    "qs:photos_all":504,
    "qs:photos_sr":7,
    "qs:placetype":"Town",
    "qs:pop_sr":"0",
    "qs:woe_adm0":23424741,
    "wd:wordcount":41,
    "wof:name":"Sheki",
    "wof:placetype":"locality"
},
  "geometry": {"coordinates":[47.39472,40.70972],"type":"Point"}
}