{
  "type": "Feature",
  "properties": {
    "gn:admin1_code":"32",
    "gn:asciiname":"Yusifli",
    "gn:country_code":"AZ",
    "gn:dem":-3,
    "gn:feature_class":"P",
    "gn:feature_code":"PPL",
    "gn:name":"Yusifli",
    "gn:population":0,
    "gn:timezone":"Asia/Baku",
    "iso:country":"AZ",
    "name:aze_x_preferred":[
        "Yusifli"
    ],
    "wof:name":"Yusifli",
    "wof:placetype":"locality"
},
  "geometry": {"coordinates":[48.66432,38.98146],"type":"Point"}
}