{
  "type": "Feature",
  "properties": {
    "gn:admin1_code":"66",
    "gn:asciiname":"Jiy",
    "gn:country_code":"AZ",
    "gn:dem":738,
    "gn:feature_class":"P",
    "gn:feature_code":"PPL",
    "gn:name":"Jiy",
    "gn:population":0,
    "gn:timezone":"Asia/Baku",
    "iso:country":"AZ",
    "name:aze_x_preferred":[
        "Jiy"
    ],
    "name:und_x_variant":[
        "Zhiy"
    ],
    "wof:name":"Jiy",
    "wof:placetype":"locality"
},
  "geometry": {"coordinates":[48.36449,38.96225],"type":"Point"}
}