{
  "type": "Feature",
  "properties": {
    "gn:admin1_code":"11",
    "gn:asciiname":"Kasymbeyli",
    "gn:country_code":"AZ",
    "gn:dem":114,
    "gn:feature_class":"P",
    "gn:feature_code":"PPL",
    "gn:name":"Kasymbeyli",
    "gn:population":0,
    "gn:timezone":"Asia/Baku",
    "iso:country":"AZ",
    "name:aze_x_preferred":[
        "Qasimb\u0259yli"
    ],
    "name:aze_x_variant":[
        "Qas\u0131mb\u0259yli"
    ],
    "name:und_x_variant":[
        "Kasumbegly",
        "Kasymbeyli"
    ],
    "wof:name":"Kasymbeyli",
    "wof:placetype":"locality"
},
  "geometry": {"coordinates":[47.07621,40.36542],"type":"Point"}
}