{
  "type": "Feature",
  "properties": {
    "gn:admin1_code":"01",
    "gn:asciiname":"Novxani",
    "gn:country_code":"AZ",
    "gn:dem":41,
    "gn:feature_class":"P",
    "gn:feature_code":"PPL",
    "gn:name":"Novxan\u0131",
    "gn:population":0,
    "gn:timezone":"Asia/Baku",
    "iso:country":"AZ",
    "name:azb_x_preferred":[
        "\u0646\u0648\u0648\u062e\u0627\u0646\u06cc"
    ],
    "name:aze_x_preferred":[
        "Novxan\u0131"
    ],
    "name:che_x_preferred":[
        "\u041d\u043e\u0432\u0445\u0430\u043d\u044b"
    ],
    "name:eng_x_preferred":[
        "Novxan\u0131"
    ],
    "name:fas_x_preferred":[
        "\u0646\u0648\u062e\u0627\u0646\u06cc"
    ],
    "name:hye_x_preferred":[
        "\u0546\u0578\u057e\u056d\u0561\u0576\u056b"
    ],
    "name:ita_x_preferred":[
        "Novxan\u0131"
    ],
    "name:kat_x_preferred":[
        "\u10dc\u10dd\u10d5\u10ee\u10d0\u10dc\u10d8"
    ],
    "name:msa_x_preferred":[
        "Novxan\u0131"
    ],
    "name:pol_x_preferred":[
        "Novxan\u0131"
    ],
    "name:rus_x_preferred":[
        "\u041d\u043e\u0432\u0445\u0430\u043d\u0430"
    ],
    "name:rus_x_variant":[
        "\u041d\u043e\u0432\u0445\u0430\u043d\u044b"
    ],
    "name:und_x_variant":[
        "Novkhany",
        "Novkhana",
        "Nobkhana"
    ],
    "wof:name":"Novxani",
    "wof:placetype":"locality"
},
  "geometry": {"coordinates":[49.78188,40.52914000000001],"type":"Point"}
}