{
  "type": "Feature",
  "properties": {
    "gn:admin1_code":"26",
    "gn:asciiname":"Qizilqaya",
    "gn:country_code":"AZ",
    "gn:dem":903,
    "gn:feature_class":"P",
    "gn:feature_code":"PPL",
    "gn:name":"Q\u0131z\u0131lqaya",
    "gn:population":0,
    "gn:timezone":"Asia/Baku",
    "iso:country":"AZ",
    "name:aze_x_preferred":[
        "Arutunaqomer"
    ],
    "name:hye_x_preferred":[
        "Harut\u2019yunagomer"
    ],
    "name:hye_x_variant":[
        "\u0540\u0561\u0580\u0578\u0582\u0569\u0575\u0578\u0582\u0576\u0561\u0563\u0578\u0574\u0565\u0580"
    ],
    "name:rus_x_preferred":[
        "\u0410\u0440\u0443\u0442\u044e\u043d\u0430\u0433\u043e\u043c\u0435\u0440"
    ],
    "name:und_x_variant":[
        "Arutyunagomer",
        "Haroutiuounagomer",
        "Arutunagomer",
        "Arutyunagamer",
        "K\u2019armir K\u2019ar",
        "Q\u0131z\u0131lqaya"
    ],
    "wof:name":"Qizilqaya",
    "wof:placetype":"locality"
},
  "geometry": {"coordinates":[46.51449,40.12286],"type":"Point"}
}