{
  "type": "Feature",
  "properties": {
    "gn:admin1_code":"58",
    "gn:asciiname":"Meshadilyar",
    "gn:country_code":"AZ",
    "gn:dem":612,
    "gn:feature_class":"P",
    "gn:feature_code":"PPL",
    "gn:name":"Meshadilyar",
    "gn:population":0,
    "gn:timezone":"Asia/Baku",
    "iso:country":"AZ",
    "name:azb_x_preferred":[
        "\u0645\u0634\u0647\u062f\u06cc\u0644\u06cc\u06cc\u0631"
    ],
    "name:fas_x_preferred":[
        "\u0645\u0634\u0647\u062f\u06cc\u0644\u06cc\u200c\u06cc\u0631"
    ],
    "name:msa_x_preferred":[
        "Meshadilyar"
    ],
    "name:und_x_variant":[
        "M\u0259\u015f\u0259dil\u0259r"
    ],
    "wof:name":"Meshadilyar",
    "wof:placetype":"locality"
},
  "geometry": {"coordinates":[45.70626,40.8469],"type":"Point"}
}