{
  "type": "Feature",
  "properties": {
    "gn:admin1_code":"65",
    "gn:asciiname":"Arpagyadyuk",
    "gn:country_code":"AZ",
    "gn:dem":1604,
    "gn:feature_class":"P",
    "gn:feature_code":"PPL",
    "gn:name":"Arpagyadyuk",
    "gn:population":0,
    "gn:timezone":"Asia/Baku",
    "iso:country":"AZ",
    "name:aze_x_preferred":[
        "Arpag\u0259dik"
    ],
    "name:hye_x_preferred":[
        "Arp\u2019agetik"
    ],
    "name:hye_x_variant":[
        "\u0531\u0580\u0583\u0561\u0584\u0565\u057f\u056b\u056f",
        "\u0554\u0561\u0580\u056b\u0576\u0563",
        "Arp\u2019ak\u2019etik",
        "\u0531\u0580\u0583\u0561\u0563\u0565\u057f\u056b\u056f"
    ],
    "name:rus_x_preferred":[
        "\u0410\u0440\u043f\u0430\u0433\u044f\u0434\u0438\u043a"
    ],
    "name:und_x_variant":[
        "K\u2019aring",
        "Arpaguetik",
        "Arpagyadyuk",
        "Arpagyadik",
        "\u0410\u0440\u043f\u0430\u0433\u044f\u0434\u0438\u043a"
    ],
    "wof:name":"Arpagyadyuk",
    "wof:placetype":"locality"
},
  "geometry": {"coordinates":[46.70532,39.55889000000001],"type":"Point"}
}