{
  "type": "Feature",
  "properties": {
    "gn:admin1_code":"02",
    "gn:asciiname":"Karavelli",
    "gn:country_code":"AZ",
    "gn:dem":47,
    "gn:feature_class":"P",
    "gn:feature_code":"PPL",
    "gn:name":"Karavelli",
    "gn:population":0,
    "gn:timezone":"Asia/Baku",
    "iso:country":"AZ",
    "name:aze_x_preferred":[
        "Qarav\u0259lili"
    ],
    "wof:name":"Karavelli",
    "wof:placetype":"locality"
},
  "geometry": {"coordinates":[47.24449,40.18583],"type":"Point"}
}