{
  "type": "Feature",
  "properties": {
    "gn:admin1_code":"16",
    "gn:asciiname":"Qaraqullar",
    "gn:country_code":"AZ",
    "gn:dem":1651,
    "gn:feature_class":"P",
    "gn:feature_code":"PPL",
    "gn:name":"Qaraqullar",
    "gn:population":0,
    "gn:timezone":"Asia/Baku",
    "iso:country":"AZ",
    "name:azb_x_preferred":[
        "\u0642\u0627\u0631\u0627\u0642\u0648\u0644\u0644\u0627\u0631"
    ],
    "name:aze_x_preferred":[
        "Qaraqullar"
    ],
    "name:ceb_x_preferred":[
        "Qaraqullar"
    ],
    "name:hye_x_preferred":[
        "\u0542\u0561\u0580\u0561\u0572\u0578\u0582\u056c\u056c\u0561\u0580"
    ],
    "name:ita_x_preferred":[
        "Qaraqullar"
    ],
    "name:kat_x_preferred":[
        "\u10e7\u10d0\u10e0\u10d0\u10d2\u10e3\u10da\u10d0\u10e0\u10d8"
    ],
    "name:msa_x_preferred":[
        "Qaraqullar"
    ],
    "name:swe_x_preferred":[
        "Qaraqullar"
    ],
    "name:und_x_variant":[
        "Karakollar",
        "Karakullar",
        "Karagullar",
        "Qaraqullar"
    ],
    "wof:name":"Qaraqullar",
    "wof:placetype":"locality"
},
  "geometry": {"coordinates":[46.08879,40.42904],"type":"Point"}
}