{
  "type": "Feature",
  "properties": {
    "gn:admin1_code":"16",
    "gn:asciiname":"Qaraqullar",
    "gn:country_code":"AZ",
    "gn:dem":1651,
    "gn:feature_class":"P",
    "gn:feature_code":"PPL",
    "gn:name":"Qaraqullar",
    "gn:population":0,
    "gn:timezone":"Asia/Baku",
    "iso:country":"AZ",
    "name:und_x_variant":[
        "Karakollar",
        "Karakullar",
        "Karagullar",
        "Qaraqullar"
    ],
    "wof:name":"Qaraqullar",
    "wof:placetype":"locality"
},
  "geometry": {"coordinates":[46.08879,40.42904],"type":"Point"}
}