{
  "type": "Feature",
  "properties": {
    "gn:admin1_code":"06",
    "gn:asciiname":"Gyurzhyuvan",
    "gn:country_code":"AZ",
    "gn:dem":742,
    "gn:feature_class":"P",
    "gn:feature_code":"PPL",
    "gn:name":"Gyurzhyuvan",
    "gn:population":0,
    "gn:timezone":"Asia/Baku",
    "iso:country":"AZ",
    "name:eng_x_preferred":[
        "G\u00fcrc\u00fcvan"
    ],
    "name:rus_x_preferred":[
        "\u0413\u044e\u0440\u0434\u0436\u044e\u0432\u0430\u043d"
    ],
    "name:und_x_variant":[
        "Gyurdzhyuvan",
        "Gyurzhyuvan",
        "Gyurdzhivan",
        "G\u00fcrc\u00fcvan"
    ],
    "wof:name":"Gyurzhyuvan",
    "wof:placetype":"locality"
},
  "geometry": {"coordinates":[48.35176,40.64017],"type":"Point"}
}