{
  "type": "Feature",
  "properties": {
    "gn:admin1_code":"06",
    "gn:asciiname":"Gyurzhyuvan",
    "gn:country_code":"AZ",
    "gn:dem":742,
    "gn:feature_class":"P",
    "gn:feature_code":"PPL",
    "gn:name":"Gyurzhyuvan",
    "gn:population":0,
    "gn:timezone":"Asia/Baku",
    "iso:country":"AZ",
    "name:azb_x_preferred":[
        "\u06af\u0648\u0631\u062c\u0648\u0648\u0627\u0646"
    ],
    "name:ceb_x_preferred":[
        "Gyurzhyuvan"
    ],
    "name:ell_x_preferred":[
        "\u0393\u03ba\u03b9\u03bf\u03c5\u03c1\u03c4\u03c3\u03b9\u03bf\u03c5\u03b2\u03ac\u03bd"
    ],
    "name:eng_x_preferred":[
        "G\u00fcrc\u00fcvan"
    ],
    "name:fas_x_preferred":[
        "\u06af\u0631\u062c\u06cc\u200c\u0648\u0627\u0646"
    ],
    "name:ita_x_preferred":[
        "G\u00fcrc\u00fcvan"
    ],
    "name:kat_x_preferred":[
        "\u10d2\u10d8\u10e3\u10e0\u10ef\u10d8\u10e3\u10d5\u10d0\u10dc\u10d8"
    ],
    "name:msa_x_preferred":[
        "G\u00fcrc\u00fcvan"
    ],
    "name:rus_x_preferred":[
        "\u0413\u044e\u0440\u0434\u0436\u044e\u0432\u0430\u043d"
    ],
    "name:swe_x_preferred":[
        "Gyurzhyuvan"
    ],
    "name:und_x_variant":[
        "Gyurdzhyuvan",
        "Gyurzhyuvan",
        "Gyurdzhivan",
        "G\u00fcrc\u00fcvan"
    ],
    "wof:name":"Gyurzhyuvan",
    "wof:placetype":"locality"
},
  "geometry": {"coordinates":[48.35176,40.64017],"type":"Point"}
}