{
  "type": "Feature",
  "properties": {
    "gn:admin1_code":"26",
    "gn:asciiname":"Copurlu",
    "gn:country_code":"AZ",
    "gn:dem":1043,
    "gn:feature_class":"P",
    "gn:feature_code":"PPL",
    "gn:name":"\u00c7opurlu",
    "gn:population":0,
    "gn:timezone":"Asia/Baku",
    "iso:country":"AZ",
    "name:aze_x_preferred":[
        "Zardaxa\u00e7"
    ],
    "name:aze_x_variant":[
        "\u00c7opurlu"
    ],
    "name:hye_x_preferred":[
        "Zardakhach"
    ],
    "name:hye_x_variant":[
        "\u0536\u0561\u0580\u0564\u0561\u056d\u0561\u0579"
    ],
    "name:rus_x_preferred":[
        "\u0417\u0430\u0440\u0434\u0430\u0445\u0430\u0447"
    ],
    "name:und_x_variant":[
        "Dzardakhach\u2019",
        "Zardakhan",
        "Zardakhach\u2019"
    ],
    "wof:name":"Copurlu",
    "wof:placetype":"locality"
},
  "geometry": {"coordinates":[46.47308,40.15441],"type":"Point"}
}