{
  "type": "Feature",
  "properties": {
    "gn:admin1_code":"70",
    "gn:asciiname":"Chokakoba",
    "gn:country_code":"AZ",
    "gn:dem":480,
    "gn:feature_class":"P",
    "gn:feature_code":"PPL",
    "gn:name":"Chokakoba",
    "gn:population":0,
    "gn:timezone":"Asia/Baku",
    "iso:country":"AZ",
    "name:und_x_variant":[
        "\u00c7\u00f6k\u0259koba"
    ],
    "wof:name":"Chokakoba",
    "wof:placetype":"locality"
},
  "geometry": {"coordinates":[46.64458,41.61793],"type":"Point"}
}