{
  "type": "Feature",
  "properties": {
    "gn:admin1_code":"70",
    "gn:asciiname":"Chokakoba",
    "gn:country_code":"AZ",
    "gn:dem":480,
    "gn:feature_class":"P",
    "gn:feature_code":"PPL",
    "gn:name":"Chokakoba",
    "gn:population":0,
    "gn:timezone":"Asia/Baku",
    "iso:country":"AZ",
    "name:ava_x_preferred":[
        "\u0427\u0443\u043a\u0430\u043a"
    ],
    "name:azb_x_preferred":[
        "\u0686\u0624\u06a9\u06a9 \u0627\u0648\u0628\u0627"
    ],
    "name:aze_x_preferred":[
        "\u00c7\u00f6k\u0259koba"
    ],
    "name:ell_x_preferred":[
        "\u03a4\u03c3\u03bf\u03ba\u03ad\u03ba\u03bf\u03bc\u03c0\u03b1"
    ],
    "name:ita_x_preferred":[
        "\u00c7\u00f6k\u0259koba"
    ],
    "name:kat_x_preferred":[
        "\u10e9\u10d8\u10dd\u10e5\u10d0\u10e5\u10dd\u10d1\u10d0"
    ],
    "name:msa_x_preferred":[
        "\u00c7\u00f6k\u0259koba"
    ],
    "name:und_x_variant":[
        "\u00c7\u00f6k\u0259koba"
    ],
    "wof:name":"Chokakoba",
    "wof:placetype":"locality"
},
  "geometry": {"coordinates":[46.64458,41.61793],"type":"Point"}
}