{
  "type": "Feature",
  "properties": {
    "gn:admin1_code":"18",
    "gn:asciiname":"Dosulu",
    "gn:country_code":"AZ",
    "gn:dem":783,
    "gn:feature_class":"P",
    "gn:feature_code":"PPL",
    "gn:name":"Do\u015fulu",
    "gn:population":0,
    "gn:timezone":"Asia/Baku",
    "iso:country":"AZ",
    "name:azb_x_preferred":[
        "\u062f\u0648\u0634\u0648\u0644\u0648"
    ],
    "name:aze_x_preferred":[
        "Doshulu"
    ],
    "name:aze_x_variant":[
        "Do\u015fulu"
    ],
    "name:ita_x_preferred":[
        "Doshulu"
    ],
    "name:kat_x_preferred":[
        "\u10d3\u10dd\u10e1\u10f0\u10e3\u10da\u10e3"
    ],
    "name:msa_x_preferred":[
        "Doshulu"
    ],
    "name:rus_x_preferred":[
        "\u0414\u043e\u0448\u0443\u043b\u0443"
    ],
    "wof:name":"Dosulu",
    "wof:placetype":"locality"
},
  "geometry": {"coordinates":[47.07603,39.48024],"type":"Point"}
}