{
  "type": "Feature",
  "properties": {
    "gn:admin1_code":"02",
    "gn:asciiname":"Kandabil",
    "gn:country_code":"AZ",
    "gn:dem":-15,
    "gn:feature_class":"P",
    "gn:feature_code":"PPL",
    "gn:name":"K\u0259nd\u0259bil",
    "gn:population":0,
    "gn:timezone":"Asia/Baku",
    "iso:country":"AZ",
    "name:azb_x_preferred":[
        "\u06a9\u0646\u062f\u0628\u06cc\u0644"
    ],
    "name:ceb_x_preferred":[
        "K\u0259nd\u0259bil"
    ],
    "name:eng_x_preferred":[
        "K\u01ddnd\u01ddbil"
    ],
    "name:fas_x_preferred":[
        "\u06a9\u0646\u062f\u0628\u06cc\u0644"
    ],
    "name:ita_x_preferred":[
        "K\u0259nd\u0259bil"
    ],
    "name:kat_x_preferred":[
        "\u10e5\u10d0\u10dc\u10d3\u10d0\u10d1\u10d8\u10da\u10d8"
    ],
    "name:msa_x_preferred":[
        "K\u0259nd\u0259bil"
    ],
    "name:rus_x_preferred":[
        "\u0413\u0435\u043d\u0434\u0430\u0431\u0438\u043b\u044c"
    ],
    "name:swe_x_preferred":[
        "K\u0259nd\u0259bil"
    ],
    "name:und_x_variant":[
        "Gendabil\u2019",
        "Gendebil\u2019",
        "K\u0259nd\u0259bil"
    ],
    "wof:name":"Kandabil",
    "wof:placetype":"locality"
},
  "geometry": {"coordinates":[47.79988,40.11662000000001],"type":"Point"}
}