{
  "type": "Feature",
  "properties": {
    "gn:admin1_code":"19",
    "gn:asciiname":"Poladli",
    "gn:country_code":"AZ",
    "gn:dem":1274,
    "gn:feature_class":"P",
    "gn:feature_code":"PPL",
    "gn:name":"Poladl\u0131",
    "gn:population":0,
    "gn:timezone":"Asia/Baku",
    "iso:country":"AZ",
    "name:aze_x_preferred":[
        "Poladl\u0131"
    ],
    "name:und_x_variant":[
        "Poladly",
        "Polad\u0131"
    ],
    "wof:name":"Poladli",
    "wof:placetype":"locality"
},
  "geometry": {"coordinates":[45.65422,40.57008],"type":"Point"}
}