{
  "type": "Feature",
  "properties": {
    "gn:admin1_code":"32",
    "gn:asciiname":"Nazaruba",
    "gn:country_code":"AZ",
    "gn:dem":41,
    "gn:feature_class":"P",
    "gn:feature_code":"PPL",
    "gn:name":"Nazaruba",
    "gn:population":0,
    "gn:timezone":"Asia/Baku",
    "iso:country":"AZ",
    "name:azb_x_preferred":[
        "\u0646\u0638\u0631 \u0627\u0648\u0628\u0627"
    ],
    "name:aze_x_preferred":[
        "N\u0259z\u0259roba"
    ],
    "name:ceb_x_preferred":[
        "Nazaruba"
    ],
    "name:ita_x_preferred":[
        "N\u0259z\u0259roba"
    ],
    "name:msa_x_preferred":[
        "N\u0259z\u0259roba"
    ],
    "name:swe_x_preferred":[
        "Nazaruba"
    ],
    "name:und_x_variant":[
        "Nazaroba"
    ],
    "wof:name":"Nazaruba",
    "wof:placetype":"locality"
},
  "geometry": {"coordinates":[48.66403,38.88555],"type":"Point"}
}