{
  "type": "Feature",
  "properties": {
    "gn:admin1_code":"32",
    "gn:asciiname":"Nazaruba",
    "gn:country_code":"AZ",
    "gn:dem":41,
    "gn:feature_class":"P",
    "gn:feature_code":"PPL",
    "gn:name":"Nazaruba",
    "gn:population":0,
    "gn:timezone":"Asia/Baku",
    "iso:country":"AZ",
    "name:und_x_variant":[
        "N\u0259z\u0259roba",
        "Nazaroba"
    ],
    "wof:name":"Nazaruba",
    "wof:placetype":"locality"
},
  "geometry": {"coordinates":[48.66403,38.88555],"type":"Point"}
}