{
  "type": "Feature",
  "properties": {
    "gn:admin1_code":"26",
    "gn:asciiname":"Tezakend",
    "gn:country_code":"AZ",
    "gn:dem":1688,
    "gn:feature_class":"P",
    "gn:feature_code":"PPL",
    "gn:name":"Tezakend",
    "gn:population":0,
    "gn:timezone":"Asia/Baku",
    "iso:country":"AZ",
    "name:aze_x_preferred":[
        "T\u0259z\u0259k\u0259nd"
    ],
    "name:rus_x_preferred":[
        "\u0422\u0435\u0437\u0430\u043a\u0435\u043d\u0434"
    ],
    "wof:name":"Tezakend",
    "wof:placetype":"locality"
},
  "geometry": {"coordinates":[46.39334,40.01857],"type":"Point"}
}