{
  "type": "Feature",
  "properties": {
    "gn:admin1_code":"39",
    "gn:asciiname":"Qipcaq",
    "gn:cc2":"AZ",
    "gn:country_code":"AZ",
    "gn:dem":221,
    "gn:feature_class":"P",
    "gn:feature_code":"PPL",
    "gn:name":"Q\u0131p\u00e7aq",
    "gn:population":0,
    "gn:timezone":"Asia/Baku",
    "iso:country":"AZ",
    "name:eng_x_preferred":[
        "Q\u0131p\u00e7aq"
    ],
    "name:rus_x_preferred":[
        "\u041a\u044b\u043f\u0447\u0430\u043a"
    ],
    "name:und_x_variant":[
        "Kypchag",
        "Kypchakh",
        "Kypchak",
        "Q\u0131p\u00e7aq"
    ],
    "wof:name":"Qipcaq",
    "wof:placetype":"locality"
},
  "geometry": {"coordinates":[46.82806,41.3025],"type":"Point"}
}