{
  "type": "Feature",
  "properties": {
    "gn:admin1_code":"65",
    "gn:asciiname":"Kochbek",
    "gn:country_code":"AZ",
    "gn:dem":580,
    "gn:feature_class":"P",
    "gn:feature_code":"PPL",
    "gn:name":"Kochbek",
    "gn:population":0,
    "gn:timezone":"Asia/Baku",
    "iso:country":"AZ",
    "name:azb_x_preferred":[
        "\u0642\u0648\u0686 \u0628\u06cc\u200c\u0644\u06cc"
    ],
    "name:aze_x_preferred":[
        "Qo\u00e7b\u0259yli"
    ],
    "name:aze_x_variant":[
        "Qo\u00e7bek"
    ],
    "name:hye_x_preferred":[
        "\u0531\u0575\u0563\u0565\u057d\u057f\u0561\u0576"
    ],
    "name:ita_x_preferred":[
        "Qo\u00e7b\u0259yli"
    ],
    "name:kat_x_preferred":[
        "\u10e7\u10dd\u10e9\u10d1\u10d4\u10d8\u10da\u10d8"
    ],
    "name:msa_x_preferred":[
        "Qo\u00e7b\u0259yli"
    ],
    "name:rus_x_preferred":[
        "\u0410\u0439\u0433\u0435\u0441\u0442\u0430\u043d"
    ],
    "name:und_x_variant":[
        "Koch\u2019bek\u2019",
        "Kochbek",
        "Aygestan"
    ],
    "wof:name":"Kochbek",
    "wof:placetype":"locality"
},
  "geometry": {"coordinates":[47.06718,39.50657],"type":"Point"}
}