{
  "type": "Feature",
  "properties": {
    "gn:admin1_code":"50",
    "gn:asciiname":"Demirchi",
    "gn:country_code":"AZ",
    "gn:dem":1484,
    "gn:feature_class":"P",
    "gn:feature_code":"PPL",
    "gn:name":"Demirchi",
    "gn:population":0,
    "gn:timezone":"Asia/Baku",
    "iso:country":"AZ",
    "name:eng_x_preferred":[
        "D\u01ddmir\u00e7i"
    ],
    "name:rus_x_preferred":[
        "\u0414\u0435\u043c\u0438\u0440\u0447\u0438"
    ],
    "name:und_x_variant":[
        "Damerchi",
        "D\u0259mir\u00e7i"
    ],
    "wof:name":"Demirchi",
    "wof:placetype":"locality"
},
  "geometry": {"coordinates":[48.56187,40.83965],"type":"Point"}
}