{
  "type": "Feature",
  "properties": {
    "gn:admin1_code":"03",
    "gn:asciiname":"Orta Giounepaia",
    "gn:country_code":"AZ",
    "gn:dem":857,
    "gn:feature_class":"P",
    "gn:feature_code":"PPL",
    "gn:name":"Orta Giounepaia",
    "gn:population":0,
    "gn:timezone":"Asia/Baku",
    "iso:country":"AZ",
    "name:aze_x_preferred":[
        "Orta G\u00fcn\u0259yp\u0259y\u0259"
    ],
    "name:aze_x_variant":[
        "Orta G\u00fcneyt\u0259p\u0259",
        "Orta G\u00fcneyp\u0259y\u0259"
    ],
    "name:hye_x_preferred":[
        "Ort\u2019a"
    ],
    "name:hye_x_variant":[
        "\u0548\u0580\u0569\u0561"
    ],
    "name:kat_x_preferred":[
        "\u10dd\u10e0\u10d7\u10d0-\u10d2\u10d8\u10e3\u10dc\u10d4\u10e4\u10d0\u10d8\u10d0"
    ],
    "name:min_x_preferred":[
        "Orta G\u00fcn\u0259yp\u0259y\u0259"
    ],
    "name:msa_x_preferred":[
        "Orta G\u00fcn\u0259yp\u0259y\u0259"
    ],
    "name:rus_x_preferred":[
        "\u041e\u0440\u0442\u0430 \u0413\u044e\u043d\u0435\u0439\u043b\u0435\u044f"
    ],
    "name:und_x_variant":[
        "Orta Gyunep\u2019aya",
        "Orta Gyuneyleya"
    ],
    "wof:name":"Orta Giounepaia",
    "wof:placetype":"locality"
},
  "geometry": {"coordinates":[46.72716,40.09206],"type":"Point"}
}