{
  "type": "Feature",
  "properties": {
    "gn:admin1_code":"69",
    "gn:asciiname":"Dzhafarkuluushagy",
    "gn:country_code":"AZ",
    "gn:dem":503,
    "gn:feature_class":"P",
    "gn:feature_code":"PPL",
    "gn:name":"Dzhafarkuluushagy",
    "gn:population":0,
    "gn:timezone":"Asia/Baku",
    "iso:country":"AZ",
    "name:azb_x_preferred":[
        "\u062c\u0639\u0641\u0631\u0642\u0648\u0644\u06cc\u200c\u0627\u0648\u0634\u0627\u063a\u06cc"
    ],
    "name:fas_x_preferred":[
        "\u062c\u0639\u0641\u0631\u0642\u0644\u06cc\u200c\u0627\u0648\u0634\u0627\u063a\u06cc"
    ],
    "name:kat_x_preferred":[
        "\u10ef\u10d0\u10e4\u10d0\u10e0\u10e5\u10e3\u10da\u10d8\u10d8\u10e8\u10d0\u10d2\u10d8"
    ],
    "name:msa_x_preferred":[
        "Dzhafarkuluushagy"
    ],
    "name:und_x_variant":[
        "Dzhafargulu-Ushagy"
    ],
    "wof:name":"Dzhafarkuluushagy",
    "wof:placetype":"locality"
},
  "geometry": {"coordinates":[46.65141,39.16719000000001],"type":"Point"}
}