{
  "type": "Feature",
  "properties": {
    "gn:admin1_code":"69",
    "gn:asciiname":"Dzhafarkuluushagy",
    "gn:country_code":"AZ",
    "gn:dem":503,
    "gn:feature_class":"P",
    "gn:feature_code":"PPL",
    "gn:name":"Dzhafarkuluushagy",
    "gn:population":0,
    "gn:timezone":"Asia/Baku",
    "iso:country":"AZ",
    "name:und_x_variant":[
        "Dzhafargulu-Ushagy",
        "Dzhafarkuluushagy"
    ],
    "wof:name":"Dzhafarkuluushagy",
    "wof:placetype":"locality"
},
  "geometry": {"coordinates":[46.65141,39.16719000000001],"type":"Point"}
}