{
  "type": "Feature",
  "properties": {
    "gn:admin1_code":"46",
    "gn:asciiname":"Khalfali",
    "gn:country_code":"AZ",
    "gn:dem":-18,
    "gn:feature_class":"P",
    "gn:feature_code":"PPL",
    "gn:name":"Khalfali",
    "gn:population":0,
    "gn:timezone":"Asia/Baku",
    "iso:country":"AZ",
    "name:und_x_variant":[
        "X\u0259lf\u0259li"
    ],
    "wof:name":"Khalfali",
    "wof:placetype":"locality"
},
  "geometry": {"coordinates":[48.67817,39.95589],"type":"Point"}
}