{
  "type": "Feature",
  "properties": {
    "gn:admin1_code":"17",
    "gn:asciiname":"Khalfalar",
    "gn:country_code":"AZ",
    "gn:dem":245,
    "gn:feature_class":"P",
    "gn:feature_code":"PPL",
    "gn:name":"Khalfalar",
    "gn:population":0,
    "gn:timezone":"Asia/Baku",
    "iso:country":"AZ",
    "name:und_x_variant":[
        "X\u0259lf\u0259l\u0259r"
    ],
    "wof:name":"Khalfalar",
    "wof:placetype":"locality"
},
  "geometry": {"coordinates":[48.89599000000001,41.17173],"type":"Point"}
}