{
  "type": "Feature",
  "properties": {
    "gn:population":66686,
    "iso:country":"AZ",
    "name:ara_x_preferred":[
        "\u0628\u0627\u0643\u064a\u0633\u0646\u0648\u0641"
    ],
    "name:arz_x_preferred":[
        "\u0628\u0627\u0643\u064a\u0633\u0646\u0648\u0641"
    ],
    "name:ast_x_preferred":[
        "Bakikhanov"
    ],
    "name:azb_x_preferred":[
        "\u0628\u0627\u06a9\u06cc \u062e\u0627\u0646\u0648\u0648"
    ],
    "name:aze_x_preferred":[
        "Bak\u0131xanov"
    ],
    "name:ceb_x_preferred":[
        "Bak\u0131xanov"
    ],
    "name:ces_x_preferred":[
        "Bak\u0131xanov"
    ],
    "name:ces_x_variant":[
        "Bakichanov"
    ],
    "name:che_x_preferred":[
        "\u0411\u0430\u043a\u0438\u0445\u0430\u043d\u043e\u0432"
    ],
    "name:deu_x_preferred":[
        "Bak\u0131xanov"
    ],
    "name:ell_x_preferred":[
        "\u039c\u03c0\u03b1\u03ba\u03b9\u03c7\u03ac\u03bd\u03bf\u03c6"
    ],
    "name:eng_x_preferred":[
        "Bak\u0131xanov"
    ],
    "name:eng_x_variant":[
        "Bakikhanov"
    ],
    "name:fas_x_preferred":[
        "\u0628\u0627\u06a9\u06cc\u062e\u0627\u0646\u0648\u0641"
    ],
    "name:fra_x_preferred":[
        "Bakixanov"
    ],
    "name:fra_x_variant":[
        "Bak\u0131xanov"
    ],
    "name:jpn_x_preferred":[
        "\u30d0\u30ad\u30cf\u30ce\u30f4"
    ],
    "name:mlg_x_preferred":[
        "Bak\u0131xanov"
    ],
    "name:nld_x_preferred":[
        "Bak\u0131xanov"
    ],
    "name:nob_x_preferred":[
        "Bak\u0131xanov"
    ],
    "name:pol_x_preferred":[
        "Bak\u0131xanov"
    ],
    "name:por_x_preferred":[
        "Bak\u0131xanov"
    ],
    "name:ron_x_preferred":[
        "Bak\u00eehanov"
    ],
    "name:rus_x_preferred":[
        "\u0411\u0430\u043a\u0438\u0445\u0430\u043d\u043e\u0432"
    ],
    "name:rus_x_variant":[
        "\u0411\u0430\u043a\u0438\u0445\u0430\u043d\u043e\u0432\u0430"
    ],
    "name:sco_x_preferred":[
        "Bak\u0131xanov"
    ],
    "name:swe_x_preferred":[
        "Bak\u0131xanov"
    ],
    "name:tur_x_preferred":[
        "Bak\u0131hanov"
    ],
    "name:und_x_colloquial":[
        "Bakixanov"
    ],
    "name:und_x_variant":[
        "Bak\u1e2fxanov",
        "Bakikhanov"
    ],
    "qs:gn_adm0_cc":"AZ",
    "qs:gn_fcode":"PPLX",
    "qs:gn_local":587084,
    "qs:gn_nam_loc":"Baku, Baki, AZ",
    "qs:gn_namadm1":"09",
    "qs:gn_name":"Bak\u0131xanov",
    "qs:local_max":2231,
    "qs:local_sum":3804,
    "qs:localhoods":2,
    "qs:name":"Bak\u1e2fxanov",
    "qs:name_adm0":"Azerbaijan",
    "qs:name_adm1":"Baki",
    "qs:name_local":"Baku",
    "qs:photo_max":199,
    "qs:photo_sum":1573,
    "qs:placetype":"Suburb",
    "qs:quad_count":72,
    "qs:woe_adm0":23424741,
    "qs:woe_adm1":20070218,
    "qs:woe_adm2":0,
    "qs:woe_lau":0,
    "qs:woe_local":1951874,
    "qs:woe_ver":"7.10.0",
    "wof:lang":[
        "unk"
    ],
    "wof:name":"Bak\u1e2fxanov",
    "wof:placetype":"neighbourhood",
    "wof:population":66686
},
  "geometry": {"coordinates":[49.859729,40.381382],"type":"Point"}
}