{
  "type": "Feature",
  "properties": {
    "gn:admin1_code":"14",
    "gn:asciiname":"Yarakhmedli",
    "gn:country_code":"AZ",
    "gn:dem":680,
    "gn:feature_class":"P",
    "gn:feature_code":"PPL",
    "gn:name":"Yarakhmedli",
    "gn:population":0,
    "gn:timezone":"Asia/Baku",
    "iso:country":"AZ",
    "name:azb_x_preferred":[
        "\u06cc\u0627\u0631\u0627\u062d\u0645\u062f\u0644\u06cc"
    ],
    "name:aze_x_preferred":[
        "Yar\u0259hm\u0259dli"
    ],
    "name:hye_x_preferred":[
        "Yarahmedli"
    ],
    "name:hye_x_variant":[
        "\u0545\u0561\u0580\u0561\u0570\u0574\u0565\u0564\u056c\u056b"
    ],
    "name:min_x_preferred":[
        "Yar\u0259hm\u0259dli"
    ],
    "name:msa_x_preferred":[
        "Yar\u0259hm\u0259dli"
    ],
    "name:rus_x_preferred":[
        "\u042f\u0440\u0430\u0445\u043c\u0435\u0434\u043b\u0438"
    ],
    "name:urd_x_preferred":[
        "\u06cc\u0627\u0631\u06cc\u06c1\u0645\u06cc\u062f\u0644\u06cc"
    ],
    "wof:name":"Yarakhmedli",
    "wof:placetype":"locality"
},
  "geometry": {"coordinates":[46.97429,39.37929000000001],"type":"Point"}
}