{
  "type": "Feature",
  "properties": {
    "gn:admin1_code":"15",
    "gn:asciiname":"Bassiz",
    "gn:country_code":"AZ",
    "gn:dem":53,
    "gn:feature_class":"P",
    "gn:feature_code":"PPL",
    "gn:name":"Ba\u015fs\u0131z",
    "gn:population":0,
    "gn:timezone":"Asia/Baku",
    "iso:country":"AZ",
    "name:aze_x_preferred":[
        "Ba\u015fs\u0131z"
    ],
    "name:und_x_variant":[
        "Bashyz",
        "Bashsyz"
    ],
    "wof:name":"Bassiz",
    "wof:placetype":"locality"
},
  "geometry": {"coordinates":[48.45757,39.20088],"type":"Point"}
}