{
  "type": "Feature",
  "properties": {
    "gn:admin1_code":"17",
    "gn:asciiname":"Karblyuk",
    "gn:country_code":"AZ",
    "gn:dem":1156,
    "gn:feature_class":"P",
    "gn:feature_code":"PPL",
    "gn:name":"Karblyuk",
    "gn:population":0,
    "gn:timezone":"Asia/Baku",
    "iso:country":"AZ",
    "name:und_x_variant":[
        "Gariblik",
        "Q\u0259riblik"
    ],
    "wof:name":"Karblyuk",
    "wof:placetype":"locality"
},
  "geometry": {"coordinates":[48.78708,40.95046],"type":"Point"}
}