{
  "type": "Feature",
  "properties": {
    "gn:admin1_code":"52",
    "gn:asciiname":"Alyushagy",
    "gn:country_code":"AZ",
    "gn:dem":286,
    "gn:feature_class":"P",
    "gn:feature_code":"PPL",
    "gn:name":"Alyushagy",
    "gn:population":0,
    "gn:timezone":"Asia/Baku",
    "iso:country":"AZ",
    "name:azb_x_preferred":[
        "\u0622\u0644\u06cc\u0648\u0634\u0627\u063a\u06cc"
    ],
    "name:aze_x_preferred":[
        "Al\u0131u\u015fa\u011f\u0131"
    ],
    "name:ceb_x_preferred":[
        "Alyushagy"
    ],
    "name:fas_x_preferred":[
        "\u0627\u0644\u06cc\u0648\u0634\u0627\u06af\u06cc"
    ],
    "name:ita_x_preferred":[
        "Al\u0131u\u015fa\u011f\u0131"
    ],
    "name:msa_x_preferred":[
        "Al\u0131u\u015fa\u011f\u0131"
    ],
    "name:swe_x_preferred":[
        "Alyushagy"
    ],
    "name:und_x_variant":[
        "Aliushagy",
        "\u018fliu\u015fa\u011f\u0131"
    ],
    "wof:name":"Alyushagy",
    "wof:placetype":"locality"
},
  "geometry": {"coordinates":[46.47672,40.69434],"type":"Point"}
}