{
  "type": "Feature",
  "properties": {
    "gn:admin1_code":"52",
    "gn:asciiname":"Alyushagy",
    "gn:country_code":"AZ",
    "gn:dem":286,
    "gn:feature_class":"P",
    "gn:feature_code":"PPL",
    "gn:name":"Alyushagy",
    "gn:population":0,
    "gn:timezone":"Asia/Baku",
    "iso:country":"AZ",
    "name:aze_x_preferred":[
        "Al\u0131u\u015fa\u011f\u0131"
    ],
    "name:und_x_variant":[
        "Aliushagy",
        "\u018fliu\u015fa\u011f\u0131"
    ],
    "wof:name":"Alyushagy",
    "wof:placetype":"locality"
},
  "geometry": {"coordinates":[46.47672,40.69434],"type":"Point"}
}