{
  "type": "Feature",
  "properties": {
    "gn:admin1_code":"60",
    "gn:asciiname":"Khazarli",
    "gn:country_code":"AZ",
    "gn:dem":-14,
    "gn:feature_class":"P",
    "gn:feature_code":"PPL",
    "gn:name":"Khazarli",
    "gn:population":0,
    "gn:timezone":"Asia/Baku",
    "iso:country":"AZ",
    "name:aze_x_preferred":[
        "X\u0259z\u0259rli"
    ],
    "wof:name":"Khazarli",
    "wof:placetype":"locality"
},
  "geometry": {"coordinates":[48.84993,41.56841],"type":"Point"}
}