{
  "type": "Feature",
  "properties": {
    "gn:admin1_code":"14",
    "gn:asciiname":"Yuxari Maralyan",
    "gn:country_code":"AZ",
    "gn:dem":177,
    "gn:feature_class":"P",
    "gn:feature_code":"PPL",
    "gn:name":"Yuxar\u0131 Maralyan",
    "gn:population":0,
    "gn:timezone":"Asia/Baku",
    "iso:country":"AZ",
    "name:azb_x_preferred":[
        "\u06cc\u0648\u062e\u0627\u0631\u06cc \u0645\u0627\u0631\u0627\u0644\u06cc\u0627\u0646"
    ],
    "name:aze_x_preferred":[
        "Yuxar\u0131 Maralyan"
    ],
    "name:min_x_preferred":[
        "Yuxar\u0131 Maralyan"
    ],
    "name:msa_x_preferred":[
        "Yuxar\u0131 Maralyan"
    ],
    "name:rus_x_preferred":[
        "\u042e\u0445\u0430\u0440\u0438-\u041c\u0430\u0440\u0430\u043b\u044c\u044f\u043d"
    ],
    "name:rus_x_variant":[
        "Yukhary-Maral\u2019yan"
    ],
    "name:und_x_variant":[
        "Yukhary Maralyan"
    ],
    "name:urd_x_preferred":[
        "\u06cc\u06a9\u0634\u0627\u0631\u06cc \u0645\u0631\u0627\u0644\u06cc\u0627\u0646"
    ],
    "wof:name":"Yuxari Maralyan",
    "wof:placetype":"locality"
},
  "geometry": {"coordinates":[47.19485,39.33287],"type":"Point"}
}