{
  "type": "Feature",
  "properties": {
    "gn:admin1_code":"35",
    "gn:admin2_code":"147997.0",
    "gn:asciiname":"Alyaklu",
    "gn:country_code":"AZ",
    "gn:dem":806,
    "gn:feature_class":"P",
    "gn:feature_code":"PPL",
    "gn:name":"Alyaklu",
    "gn:population":0,
    "gn:timezone":"Asia/Baku",
    "iso:country":"AZ",
    "name:aze_x_preferred":[
        "\u018fl\u0259kli"
    ],
    "name:und_x_variant":[
        "Alakli"
    ],
    "wof:name":"Alyaklu",
    "wof:placetype":"locality"
},
  "geometry": {"coordinates":[45.01272,39.50518],"type":"Point"}
}