{
  "type": "Feature",
  "properties": {
    "gn:admin1_code":"43",
    "gn:asciiname":"Delyalimyuskanly",
    "gn:country_code":"AZ",
    "gn:dem":444,
    "gn:feature_class":"P",
    "gn:feature_code":"PPL",
    "gn:name":"Delyalimyuskanly",
    "gn:population":0,
    "gn:timezone":"Asia/Baku",
    "iso:country":"AZ",
    "name:aze_x_preferred":[
        "Dil\u0259lim\u00fcsk\u0259nli"
    ],
    "name:aze_x_variant":[
        "Dil\u0259li M\u00fcsk\u0259nli"
    ],
    "name:hye_x_preferred":[
        "Janfida"
    ],
    "name:hye_x_variant":[
        "\u054b\u0561\u0576\u0586\u0315\u056b\u0564\u0561"
    ],
    "name:rus_x_preferred":[
        "\u0414\u0438\u043b\u044f\u043b\u0438\u043c\u0438\u0443\u0441\u043a\u0430\u043d\u043b\u044b"
    ],
    "name:und_x_variant":[
        "Dilyalimyuskanly"
    ],
    "wof:name":"Delyalimyuskanly",
    "wof:placetype":"locality"
},
  "geometry": {"coordinates":[46.64541,39.30586],"type":"Point"}
}