{
  "type": "Feature",
  "properties": {
    "gn:admin1_code":"03",
    "gn:asciiname":"Ballar",
    "gn:country_code":"AZ",
    "gn:dem":150,
    "gn:feature_class":"P",
    "gn:feature_code":"PPL",
    "gn:name":"Ballar",
    "gn:population":0,
    "gn:timezone":"Asia/Baku",
    "iso:country":"AZ",
    "name:aze_x_preferred":[
        "Ballar"
    ],
    "name:che_x_preferred":[
        "\u0411\u0430\u043b\u043b\u0430\u0440"
    ],
    "name:kat_x_preferred":[
        "\u10d1\u10d0\u10da\u10d0\u10e0\u10d8"
    ],
    "name:min_x_preferred":[
        "Ballar"
    ],
    "name:msa_x_preferred":[
        "Ballar"
    ],
    "name:rus_x_preferred":[
        "\u0411\u0430\u043b\u043b\u0430\u0440"
    ],
    "name:tur_x_preferred":[
        "Ballar"
    ],
    "wof:name":"Ballar",
    "wof:placetype":"locality"
},
  "geometry": {"coordinates":[47.10455,40.10064000000001],"type":"Point"}
}