{
  "type": "Feature",
  "properties": {
    "gn:admin1_code":"39",
    "gn:asciiname":"Amanli",
    "gn:country_code":"AZ",
    "gn:dem":211,
    "gn:feature_class":"P",
    "gn:feature_code":"PPL",
    "gn:name":"Amanl\u0131",
    "gn:population":0,
    "gn:timezone":"Asia/Baku",
    "iso:country":"AZ",
    "name:ava_x_preferred":[
        "\u0410\u0432\u0430\u0445I\u0438\u0431"
    ],
    "name:aze_x_preferred":[
        "Amanl\u0131"
    ],
    "name:ceb_x_preferred":[
        "Amanl\u0131"
    ],
    "name:ita_x_preferred":[
        "Amanl\u0131"
    ],
    "name:kat_x_preferred":[
        "\u10d0\u10db\u10d0\u10dc\u10da\u10d8"
    ],
    "name:msa_x_preferred":[
        "Amanl\u0131"
    ],
    "name:swe_x_preferred":[
        "Amanl\u0131"
    ],
    "name:und_x_variant":[
        "Amanly",
        "Amonly"
    ],
    "wof:name":"Amanli",
    "wof:placetype":"locality"
},
  "geometry": {"coordinates":[46.84712,41.28944],"type":"Point"}
}