{
  "type": "Feature",
  "properties": {
    "gn:admin1_code":"39",
    "gn:asciiname":"Amanli",
    "gn:country_code":"AZ",
    "gn:dem":211,
    "gn:feature_class":"P",
    "gn:feature_code":"PPL",
    "gn:name":"Amanl\u0131",
    "gn:population":0,
    "gn:timezone":"Asia/Baku",
    "iso:country":"AZ",
    "name:und_x_variant":[
        "Amanly",
        "Amonly",
        "Amanl\u0131"
    ],
    "wof:name":"Amanli",
    "wof:placetype":"locality"
},
  "geometry": {"coordinates":[46.84712,41.28944],"type":"Point"}
}