{
  "type": "Feature",
  "properties": {
    "gn:admin1_code":"26",
    "gn:asciiname":"Imeret-Gerevend",
    "gn:country_code":"AZ",
    "gn:dem":1066,
    "gn:feature_class":"P",
    "gn:feature_code":"PPL",
    "gn:name":"Imeret-Gerevend",
    "gn:population":0,
    "gn:timezone":"Asia/Baku",
    "iso:country":"AZ",
    "name:aze_x_preferred":[
        "\u0130mar\u0259t Q\u0259rv\u0259nd"
    ],
    "name:aze_x_variant":[
        "K\u0259m\u0259rli",
        "K\u0259r\u0259mli"
    ],
    "name:hye_x_preferred":[
        "Imeret\u2019-Herevend"
    ],
    "name:hye_x_variant":[
        "\u053b\u0574\u0565\u0580\u0565\u0569-\u0540\u0565\u0580\u0565\u057e\u0565\u0576\u0564",
        "K\u2019arvand",
        "\u0554\u0561\u0580\u057e\u0561\u0576\u0564"
    ],
    "name:rus_x_preferred":[
        "\u0418\u043c\u0435\u0440\u0435\u0442-\u0413\u0435\u0440\u0435\u0432\u0435\u043d\u0434"
    ],
    "name:und_x_variant":[
        "Imarat-Karvend",
        "Imaret-Geravend",
        "Imarat\u2019 K\u2019arvand",
        "Giaravand",
        "Imeret-Gerevend"
    ],
    "wof:name":"Imeret-Gerevend",
    "wof:placetype":"locality"
},
  "geometry": {"coordinates":[46.43304000000001,40.16302],"type":"Point"}
}