{
  "type": "Feature",
  "properties": {
    "gn:admin1_code":"47",
    "gn:asciiname":"Goybulaq",
    "gn:country_code":"AZ",
    "gn:dem":366,
    "gn:feature_class":"P",
    "gn:feature_code":"PPL",
    "gn:name":"G\u00f6ybulaq",
    "gn:population":0,
    "gn:timezone":"Asia/Baku",
    "iso:country":"AZ",
    "name:aze_x_preferred":[
        "G\u00f6ybulaq"
    ],
    "name:ceb_x_preferred":[
        "G\u00f6ybulaq"
    ],
    "name:ita_x_preferred":[
        "G\u00f6ybulaq"
    ],
    "name:msa_x_preferred":[
        "G\u00f6ybulaq"
    ],
    "name:swe_x_preferred":[
        "G\u00f6ybulaq"
    ],
    "name:und_x_variant":[
        "G\u00ebybulak",
        "Geybulag",
        "G\u00f6ybulaq"
    ],
    "wof:name":"Goybulaq",
    "wof:placetype":"locality"
},
  "geometry": {"coordinates":[47.14818,41.04743],"type":"Point"}
}