{
  "type": "Feature",
  "properties": {
    "gn:admin1_code":"02",
    "gn:asciiname":"Mehrabli",
    "gn:country_code":"AZ",
    "gn:dem":47,
    "gn:feature_class":"P",
    "gn:feature_code":"PPL",
    "gn:name":"Mehrabl\u0131",
    "gn:population":0,
    "gn:timezone":"Asia/Baku",
    "iso:country":"AZ",
    "name:aze_x_preferred":[
        "Mehrabl\u0131"
    ],
    "name:ceb_x_preferred":[
        "Mehrabl\u0131"
    ],
    "name:ita_x_preferred":[
        "Mehrabl\u0131"
    ],
    "name:kat_x_preferred":[
        "\u10db\u10d4\u10f0\u10e0\u10d0\u10d1\u10da\u10d8"
    ],
    "name:msa_x_preferred":[
        "Mehrabl\u0131"
    ],
    "name:rus_x_preferred":[
        "\u041c\u0435\u0445\u0440\u0430\u0431\u043b\u044b"
    ],
    "name:swe_x_preferred":[
        "Mehrabl\u0131"
    ],
    "name:und_x_variant":[
        "Mekhrably"
    ],
    "wof:name":"Mehrabli",
    "wof:placetype":"locality"
},
  "geometry": {"coordinates":[47.47042,39.89789],"type":"Point"}
}