{
  "type": "Feature",
  "properties": {
    "gn:admin1_code":"45",
    "gn:asciiname":"Dzhafarkhan",
    "gn:country_code":"AZ",
    "gn:dem":-15,
    "gn:feature_class":"P",
    "gn:feature_code":"PPL",
    "gn:name":"Dzhafarkhan",
    "gn:population":0,
    "gn:timezone":"Asia/Baku",
    "iso:country":"AZ",
    "name:aze_x_preferred":[
        "C\u0259f\u0259rxan"
    ],
    "wof:name":"Dzhafarkhan",
    "wof:placetype":"locality"
},
  "geometry": {"coordinates":[48.5376,39.939],"type":"Point"}
}