{
  "type": "Feature",
  "properties": {
    "gn:admin1_code":"26",
    "gn:asciiname":"Demirchidam",
    "gn:country_code":"AZ",
    "gn:dem":1822,
    "gn:feature_class":"P",
    "gn:feature_code":"PPL",
    "gn:name":"Demirchidam",
    "gn:population":0,
    "gn:timezone":"Asia/Baku",
    "iso:country":"AZ",
    "name:azb_x_preferred":[
        "\u062f\u0645\u06cc\u0631\u0686\u06cc\u062f\u0627\u0645"
    ],
    "name:aze_x_preferred":[
        "D\u0259mir\u00e7idam"
    ],
    "name:msa_x_preferred":[
        "D\u0259mir\u00e7idam"
    ],
    "name:rus_x_preferred":[
        "\u0414\u0435\u043c\u0438\u0440\u0447\u0438\u0434\u0430\u043c"
    ],
    "wof:name":"Demirchidam",
    "wof:placetype":"locality"
},
  "geometry": {"coordinates":[46.07468,40.21616],"type":"Point"}
}