{
  "type": "Feature",
  "properties": {
    "gn:admin1_code":"67",
    "gn:asciiname":"Xanabad",
    "gn:country_code":"AZ",
    "gn:dem":83,
    "gn:feature_class":"P",
    "gn:feature_code":"PPL",
    "gn:name":"Xanabad",
    "gn:population":0,
    "gn:timezone":"Asia/Baku",
    "iso:country":"AZ",
    "name:eng_x_preferred":[
        "Xanabad"
    ],
    "name:rus_x_preferred":[
        "\u0425\u0430\u043d\u0430\u0431\u0430\u0434"
    ],
    "name:und_x_variant":[
        "Khanabad",
        "Xanabad"
    ],
    "wof:name":"Xanabad",
    "wof:placetype":"locality"
},
  "geometry": {"coordinates":[47.17908,40.79288],"type":"Point"}
}