{
  "type": "Feature",
  "properties": {
    "gn:admin1_code":"47",
    "gn:asciiname":"Qozlubulaq",
    "gn:country_code":"AZ",
    "gn:dem":293,
    "gn:feature_class":"P",
    "gn:feature_code":"PPL",
    "gn:name":"Qozlubulaq",
    "gn:population":0,
    "gn:timezone":"Asia/Baku",
    "iso:country":"AZ",
    "name:aze_x_preferred":[
        "Qozlubulaq"
    ],
    "name:aze_x_variant":[
        "G\u00f6zlubulaq"
    ],
    "name:ell_x_preferred":[
        "\u039a\u03bf\u03b6\u03bb\u03bf\u03c5\u03bc\u03c0\u03bf\u03c5\u03bb\u03ac\u03ba"
    ],
    "name:ita_x_preferred":[
        "Qozlubulaq"
    ],
    "name:msa_x_preferred":[
        "Qozlubulaq"
    ],
    "name:und_x_variant":[
        "Kozlu-Budzhakh",
        "Kozlubudzhak",
        "Kozlubulak"
    ],
    "wof:name":"Qozlubulaq",
    "wof:placetype":"locality"
},
  "geometry": {"coordinates":[47.30441,40.91956],"type":"Point"}
}