{
  "type": "Feature",
  "properties": {
    "gn:admin1_code":"47",
    "gn:asciiname":"Dzheiyrli",
    "gn:country_code":"AZ",
    "gn:dem":224,
    "gn:feature_class":"P",
    "gn:feature_code":"PPL",
    "gn:name":"Dzheiyrli",
    "gn:population":0,
    "gn:timezone":"Asia/Baku",
    "iso:country":"AZ",
    "name:eng_x_preferred":[
        "C\u01ddyirli"
    ],
    "name:rus_x_preferred":[
        "\u0414\u0436\u0435\u0438\u0440\u043b\u0438"
    ],
    "name:und_x_variant":[
        "Dzheirli",
        "Dzheiyrli",
        "C\u0259yirli"
    ],
    "wof:name":"Dzheiyrli",
    "wof:placetype":"locality"
},
  "geometry": {"coordinates":[47.27081,40.88617],"type":"Point"}
}