{
  "type": "Feature",
  "properties": {
    "gn:admin1_code":"28",
    "gn:asciiname":"Sus",
    "gn:country_code":"AZ",
    "gn:dem":1124,
    "gn:feature_class":"P",
    "gn:feature_code":"PPL",
    "gn:name":"Sus",
    "gn:population":0,
    "gn:timezone":"Asia/Baku",
    "iso:country":"AZ",
    "name:aze_x_preferred":[
        "Sus"
    ],
    "name:hye_x_preferred":[
        "\u054d\u0578\u0582\u057d"
    ],
    "name:rus_x_preferred":[
        "\u0421\u0443\u0441"
    ],
    "name:und_x_variant":[
        "Suse"
    ],
    "wof:name":"Sus",
    "wof:placetype":"locality"
},
  "geometry": {"coordinates":[46.51443,39.62537],"type":"Point"}
}