{
  "type": "Feature",
  "properties": {
    "gn:admin1_code":"15",
    "gn:asciiname":"Etchelyar",
    "gn:country_code":"AZ",
    "gn:dem":93,
    "gn:feature_class":"P",
    "gn:feature_code":"PPL",
    "gn:name":"Etchelyar",
    "gn:population":0,
    "gn:timezone":"Asia/Baku",
    "iso:country":"AZ",
    "name:aze_x_preferred":[
        "\u018ftc\u0259l\u0259r"
    ],
    "name:und_x_variant":[
        "Echelyar",
        "Etchelyar",
        "Etcheler"
    ],
    "wof:name":"Etchelyar",
    "wof:placetype":"locality"
},
  "geometry": {"coordinates":[48.34562,39.30524000000001],"type":"Point"}
}