{
  "type": "Feature",
  "properties": {
    "gn:admin1_code":"52",
    "gn:asciiname":"Sabira",
    "gn:country_code":"AZ",
    "gn:dem":243,
    "gn:feature_class":"P",
    "gn:feature_code":"PPL",
    "gn:name":"Sabira",
    "gn:population":0,
    "gn:timezone":"Asia/Baku",
    "iso:country":"AZ",
    "name:azb_x_preferred":[
        "\u0635\u0627\u0628\u06cc\u0631\u0627"
    ],
    "name:ita_x_preferred":[
        "Sabira"
    ],
    "name:msa_x_preferred":[
        "Sabira"
    ],
    "wof:name":"Sabira",
    "wof:placetype":"locality"
},
  "geometry": {"coordinates":[46.41111,40.77],"type":"Point"}
}