{
  "type": "Feature",
  "properties": {
    "gn:admin1_code":"28",
    "gn:asciiname":"Alikulu",
    "gn:country_code":"AZ",
    "gn:dem":1428,
    "gn:feature_class":"P",
    "gn:feature_code":"PPL",
    "gn:name":"Alikulu",
    "gn:population":0,
    "gn:timezone":"Asia/Baku",
    "iso:country":"AZ",
    "name:aze_x_preferred":[
        "\u018fliqulu"
    ],
    "name:aze_x_variant":[
        "Al\u0131qulu"
    ],
    "name:bel_x_preferred":[
        "\u0413\u0430\u0437\u0430\u0440\u0430\u043f\u0430\u0442"
    ],
    "name:hye_x_preferred":[
        "Alik\u2019ulu"
    ],
    "name:hye_x_variant":[
        "\u0531\u056c\u056b\u0584\u0578\u0582\u056c\u0578\u0582",
        "Ghazarapat",
        "\u0542\u0561\u0566\u0561\u0580\u0561\u057a\u0561\u057f"
    ],
    "name:kat_x_preferred":[
        "\u10d0\u10da\u10d8\u10e5\u10e3\u10da\u10e3"
    ],
    "name:msa_x_preferred":[
        "\u018fliqulu"
    ],
    "name:rus_x_preferred":[
        "\u0410\u043b\u0438\u043a\u0443\u043b\u0443"
    ],
    "name:ukr_x_preferred":[
        "\u0413\u0430\u0437\u0430\u0440\u0430\u043f\u0430\u0442"
    ],
    "name:und_x_variant":[
        "Alikulikend",
        "Alikulu",
        "\u0410\u043b\u0438\u043a\u0443\u043b\u0443"
    ],
    "wof:name":"Alikulu",
    "wof:placetype":"locality"
},
  "geometry": {"coordinates":[46.40998,39.74858],"type":"Point"}
}