{
  "type": "Feature",
  "properties": {
    "gn:admin1_code":"26",
    "gn:asciiname":"Zar",
    "gn:country_code":"AZ",
    "gn:dem":2050,
    "gn:feature_class":"P",
    "gn:feature_code":"PPL",
    "gn:name":"Zar",
    "gn:population":0,
    "gn:timezone":"Asia/Baku",
    "iso:country":"AZ",
    "name:azb_x_preferred":[
        "\u0632\u0627\u0631"
    ],
    "name:aze_x_preferred":[
        "Zar"
    ],
    "name:bel_x_preferred":[
        "\u0426\u0430\u0440"
    ],
    "name:cat_x_preferred":[
        "Tsar"
    ],
    "name:epo_x_preferred":[
        "Zar"
    ],
    "name:fas_x_preferred":[
        "\u062a\u0633\u0627\u0631"
    ],
    "name:hye_x_preferred":[
        "Tsar"
    ],
    "name:hye_x_variant":[
        "\u053e\u0561\u0580"
    ],
    "name:ita_x_preferred":[
        "Tzar"
    ],
    "name:msa_x_preferred":[
        "Zar"
    ],
    "name:nld_x_preferred":[
        "Tsar"
    ],
    "name:rus_x_preferred":[
        "\u0417\u0430\u0440"
    ],
    "name:ukr_x_preferred":[
        "\u0426\u0430\u0440"
    ],
    "wof:name":"Zar",
    "wof:placetype":"locality"
},
  "geometry": {"coordinates":[45.95321,40.0027],"type":"Point"}
}