{
  "type": "Feature",
  "properties": {
    "gn:admin1_code":"43",
    "gn:asciiname":"Chayzami",
    "gn:country_code":"AZ",
    "gn:dem":1247,
    "gn:feature_class":"P",
    "gn:feature_code":"PPL",
    "gn:name":"Chayzami",
    "gn:population":0,
    "gn:timezone":"Asia/Yerevan",
    "iso:country":"AZ",
    "name:aze_x_preferred":[
        "\u00c7ayz\u0259mi"
    ],
    "name:rus_x_preferred":[
        "\u0427\u0430\u0439\u0437\u0430\u043c\u0438"
    ],
    "wof:name":"Chayzami",
    "wof:placetype":"locality"
},
  "geometry": {"coordinates":[46.45065,39.33863],"type":"Point"}
}