{
  "type": "Feature",
  "properties": {
    "gn:admin1_code":"38",
    "gn:asciiname":"Kyurt",
    "gn:country_code":"AZ",
    "gn:dem":332,
    "gn:feature_class":"P",
    "gn:feature_code":"PPL",
    "gn:name":"Kyurt",
    "gn:population":0,
    "gn:timezone":"Asia/Baku",
    "iso:country":"AZ",
    "name:eng_x_preferred":[
        "K\u00fcrd"
    ],
    "name:rus_x_preferred":[
        "\u041a\u044e\u0440\u0434"
    ],
    "name:und_x_variant":[
        "Kyurd",
        "Kyurt",
        "K\u00fcrd"
    ],
    "wof:name":"Kyurt",
    "wof:placetype":"locality"
},
  "geometry": {"coordinates":[47.68958,40.80631],"type":"Point"}
}