{
  "type": "Feature",
  "properties": {
    "gn:admin1_code":"21",
    "gn:asciiname":"Todan",
    "gn:country_code":"AZ",
    "gn:dem":1103,
    "gn:feature_class":"P",
    "gn:feature_code":"PPL",
    "gn:name":"Todan",
    "gn:population":0,
    "gn:timezone":"Asia/Baku",
    "iso:country":"AZ",
    "name:aze_x_preferred":[
        "Todan"
    ],
    "name:hye_x_preferred":[
        "T\u2019odan"
    ],
    "name:hye_x_variant":[
        "\u0539\u0578\u0564\u0561\u0576"
    ],
    "wof:name":"Todan",
    "wof:placetype":"locality"
},
  "geometry": {"coordinates":[46.44865,40.47152],"type":"Point"}
}