{
  "type": "Feature",
  "properties": {
    "gn:admin1_code":"31",
    "gn:asciiname":"Yuxari Bradi",
    "gn:country_code":"AZ",
    "gn:dem":1008,
    "gn:feature_class":"P",
    "gn:feature_code":"PPL",
    "gn:name":"Yuxar\u0131 Bradi",
    "gn:population":0,
    "gn:timezone":"Asia/Baku",
    "iso:country":"AZ",
    "name:und_x_variant":[
        "Yukhary-Burady",
        "Yuxar\u0131 Bradi"
    ],
    "wof:name":"Yuxari Bradi",
    "wof:placetype":"locality"
},
  "geometry": {"coordinates":[48.59331,38.65379],"type":"Point"}
}