{
  "type": "Feature",
  "properties": {
    "gn:admin1_code":"31",
    "gn:asciiname":"Yuxari Bradi",
    "gn:country_code":"AZ",
    "gn:dem":1008,
    "gn:feature_class":"P",
    "gn:feature_code":"PPL",
    "gn:name":"Yuxar\u0131 Bradi",
    "gn:population":0,
    "gn:timezone":"Asia/Baku",
    "iso:country":"AZ",
    "name:ell_x_preferred":[
        "\u0393\u03b9\u03bf\u03c5\u03c7\u03ac\u03c1\u03b9 \u039c\u03c0\u03c1\u03ac\u03bd\u03c4\u03b9"
    ],
    "name:ita_x_preferred":[
        "Yuxar\u0131 Bradi"
    ],
    "name:msa_x_preferred":[
        "Yuxar\u0131 Bradi"
    ],
    "name:und_x_variant":[
        "Yukhary-Burady"
    ],
    "name:urd_x_preferred":[
        "\u06cc\u06a9\u0634\u0627\u0631\u06cc \u0628\u0631\u0627\u062f\u06cc"
    ],
    "wof:name":"Yuxari Bradi",
    "wof:placetype":"locality"
},
  "geometry": {"coordinates":[48.59331,38.65379],"type":"Point"}
}