{
  "type": "Feature",
  "properties": {
    "gn:admin1_code":"69",
    "gn:asciiname":"Qarqulu",
    "gn:country_code":"AZ",
    "gn:dem":442,
    "gn:feature_class":"P",
    "gn:feature_code":"PPL",
    "gn:name":"Qarqulu",
    "gn:population":0,
    "gn:timezone":"Asia/Baku",
    "iso:country":"AZ",
    "name:aze_x_preferred":[
        "Qarqulu"
    ],
    "name:kat_x_preferred":[
        "\u10e7\u10d0\u10e0\u10d2\u10e3\u10da\u10e3"
    ],
    "name:msa_x_preferred":[
        "Qarqulu"
    ],
    "name:rus_x_preferred":[
        "\u041a\u0430\u0440\u0433\u0443\u043b\u0443"
    ],
    "name:und_x_variant":[
        "Kargulu"
    ],
    "wof:name":"Qarqulu",
    "wof:placetype":"locality"
},
  "geometry": {"coordinates":[46.64131,38.97618],"type":"Point"}
}