{
  "type": "Feature",
  "properties": {
    "iso:country":"AZ",
    "name:rus_x_preferred":[
        "\u0421\u0442\u0435\u043f\u0430\u043d\u0430\u043a\u0435\u0440\u0442"
    ],
    "name:unk_x_variant":[
        "Khankendi"
    ],
    "qs:gn_country":"AZ",
    "qs:gn_fcode":"PPL",
    "qs:gn_pop":0,
    "qs:name":"Xank\u00e4ndi",
    "qs:name_adm0":"Azerbaijan",
    "qs:name_adm1":"Ismayilli",
    "qs:photos":66,
    "qs:photos_1k":13,
    "qs:photos_9k":1,
    "qs:photos_9r":2,
    "qs:photos_all":66,
    "qs:photos_sr":2,
    "qs:placetype":"Town",
    "qs:pop_sr":"0",
    "qs:woe_adm0":23424741,
    "wof:name":"Xank\u00e4ndi",
    "wof:placetype":"locality"
},
  "geometry": {"coordinates":[48.41517,40.75728],"type":"Point"}
}