{
  "type": "Feature",
  "properties": {
    "gn:country":"AZ",
    "gn:fcode":"PPL",
    "gn:population":8624,
    "iso:country":"AZ",
    "name:azb_x_preferred":[
        "\u062c\u0648\u0631\u0627\u062a"
    ],
    "name:aze_x_preferred":[
        "Corat"
    ],
    "name:ceb_x_preferred":[
        "Corat"
    ],
    "name:ell_x_preferred":[
        "\u03a4\u03c3\u03bf\u03c1\u03ac\u03c4"
    ],
    "name:eng_x_preferred":[
        "Corat"
    ],
    "name:fas_x_preferred":[
        "\u062c\u0648\u0631\u0627\u062a"
    ],
    "name:fra_x_preferred":[
        "Corat"
    ],
    "name:kat_x_preferred":[
        "\u10ef\u10dd\u10e0\u10d0\u10d7\u10d8"
    ],
    "name:nld_x_preferred":[
        "Corat"
    ],
    "name:rus_x_preferred":[
        "\u0414\u0436\u043e\u0440\u0430\u0442"
    ],
    "name:spa_x_preferred":[
        "Corat"
    ],
    "name:swe_x_preferred":[
        "Corat"
    ],
    "name:und_x_variant":[
        "Dzhorat"
    ],
    "qs:name":"Corat",
    "qs:photos_9r":0,
    "qs:photos_sr":0,
    "qs:pop_sr":"5",
    "wd:wordcount":44,
    "wof:name":"Corat",
    "wof:placetype":"locality",
    "wof:population":8624
},
  "geometry": {"coordinates":[49.70639,40.5725],"type":"Point"}
}