{
  "type": "Feature",
  "properties": {
    "gn:admin1_code":"42",
    "gn:asciiname":"Nokhurdyuzyu",
    "gn:country_code":"AZ",
    "gn:dem":1122,
    "gn:feature_class":"P",
    "gn:feature_code":"PPL",
    "gn:name":"Nokhurdyuzyu",
    "gn:population":0,
    "gn:timezone":"Asia/Baku",
    "iso:country":"AZ",
    "name:aze_x_preferred":[
        "Nohurd\u00fcz\u00fc"
    ],
    "name:ell_x_preferred":[
        "\u039d\u03bf\u03c7\u03bf\u03c5\u03c1\u03bd\u03c4\u03bf\u03c5\u03b6\u03bf\u03cd"
    ],
    "name:ita_x_preferred":[
        "Nohurd\u00fcz\u00fc"
    ],
    "name:msa_x_preferred":[
        "Nohurd\u00fcz\u00fc"
    ],
    "name:und_x_variant":[
        "Nokhurdyuzi",
        "Nokhurdyuzyu",
        "Nohurd\u00fcz\u00fc"
    ],
    "wof:name":"Nokhurdyuzyu",
    "wof:placetype":"locality"
},
  "geometry": {"coordinates":[48.53025,41.08936],"type":"Point"}
}