{
  "type": "Feature",
  "properties": {
    "gn:admin1_code":"58",
    "gn:asciiname":"Alagel-Myulkyulyu",
    "gn:country_code":"AZ",
    "gn:dem":355,
    "gn:feature_class":"P",
    "gn:feature_code":"PPL",
    "gn:name":"Alagel-Myulkyulyu",
    "gn:population":0,
    "gn:timezone":"Asia/Baku",
    "iso:country":"AZ",
    "name:azb_x_preferred":[
        "\u0622\u0634\u0627\u063a\u06cc \u0645\u0648\u0644\u06a9\u0648\u0644\u0648"
    ],
    "name:aze_x_preferred":[
        "A\u015fa\u011f\u0131 M\u00fclk\u00fcl\u00fc"
    ],
    "name:ceb_x_preferred":[
        "Alagel-Myulkyulyu"
    ],
    "name:ita_x_preferred":[
        "A\u015fa\u011f\u0131 M\u00fclk\u00fcl\u00fc"
    ],
    "name:kat_x_preferred":[
        "\u10d0\u10e8\u10d0\u10e6\u10d8-\u10db\u10d8\u10e3\u10da\u10e5\u10d8\u10e3\u10da\u10d8\u10e3"
    ],
    "name:msa_x_preferred":[
        "A\u015fa\u011f\u0131 M\u00fclk\u00fcl\u00fc"
    ],
    "name:rus_x_preferred":[
        "Ashagy Myul\u2019kyulyu"
    ],
    "name:swe_x_preferred":[
        "Alagel-Myulkyulyu"
    ],
    "name:und_x_variant":[
        "M\u00fclk\u00fcl\u00fc",
        "Myulkyulyu",
        "Ashaga-Myul\u2019kyuli"
    ],
    "wof:name":"Alagel-Myulkyulyu",
    "wof:placetype":"locality"
},
  "geometry": {"coordinates":[45.61646,41.05487],"type":"Point"}
}