{
  "type": "Feature",
  "properties": {
    "gn:admin1_code":"58",
    "gn:asciiname":"Alagel-Myulkyulyu",
    "gn:country_code":"AZ",
    "gn:dem":355,
    "gn:feature_class":"P",
    "gn:feature_code":"PPL",
    "gn:name":"Alagel-Myulkyulyu",
    "gn:population":0,
    "gn:timezone":"Asia/Baku",
    "iso:country":"AZ",
    "name:aze_x_preferred":[
        "A\u015fa\u011f\u0131 M\u00fclk\u00fcl\u00fc"
    ],
    "name:rus_x_preferred":[
        "Ashagy Myul\u2019kyulyu"
    ],
    "name:und_x_variant":[
        "M\u00fclk\u00fcl\u00fc",
        "Myulkyulyu",
        "Ashaga-Myul\u2019kyuli",
        "Alagel-Myulkyulyu"
    ],
    "wof:name":"Alagel-Myulkyulyu",
    "wof:placetype":"locality"
},
  "geometry": {"coordinates":[45.61646,41.05487],"type":"Point"}
}