{
  "type": "Feature",
  "properties": {
    "gn:admin1_code":"13",
    "gn:asciiname":"Agayri",
    "gn:country_code":"AZ",
    "gn:dem":-1,
    "gn:feature_class":"P",
    "gn:feature_code":"PPL",
    "gn:name":"A\u011fayr\u0131",
    "gn:population":0,
    "gn:timezone":"Asia/Baku",
    "iso:country":"AZ",
    "name:azb_x_preferred":[
        "\u0622\u063a\u0627\u06cc\u0631\u06cc"
    ],
    "name:aze_x_preferred":[
        "A\u011fayr\u0131"
    ],
    "name:ceb_x_preferred":[
        "A\u011fayr\u0131"
    ],
    "name:ita_x_preferred":[
        "A\u011fayr\u0131"
    ],
    "name:kat_x_preferred":[
        "\u10d0\u10e6\u10d0\u10d8\u10e0\u10d8"
    ],
    "name:msa_x_preferred":[
        "A\u011fayr\u0131"
    ],
    "name:swe_x_preferred":[
        "A\u011fayr\u0131"
    ],
    "name:und_x_variant":[
        "Agayry"
    ],
    "wof:name":"Agayri",
    "wof:placetype":"locality"
},
  "geometry": {"coordinates":[48.49498,39.52533],"type":"Point"}
}