{
  "type": "Feature",
  "properties": {
    "gn:admin1_code":"58",
    "gn:asciiname":"Baqqalli",
    "gn:country_code":"AZ",
    "gn:dem":1655,
    "gn:feature_class":"P",
    "gn:feature_code":"PPL",
    "gn:name":"Baqqall\u0131",
    "gn:population":0,
    "gn:timezone":"Asia/Baku",
    "iso:country":"AZ",
    "name:aze_x_preferred":[
        "Baqqall\u0131"
    ],
    "name:ceb_x_preferred":[
        "Baqqall\u0131"
    ],
    "name:ita_x_preferred":[
        "Baqqall\u0131"
    ],
    "name:kat_x_preferred":[
        "\u10d1\u10d0\u10e5\u10d0\u10da\u10d8"
    ],
    "name:msa_x_preferred":[
        "Baqqall\u0131"
    ],
    "name:swe_x_preferred":[
        "Baqqall\u0131"
    ],
    "name:und_x_variant":[
        "Bakkally",
        "Baqqall\u0131"
    ],
    "wof:name":"Baqqalli",
    "wof:placetype":"locality"
},
  "geometry": {"coordinates":[45.61467,40.73569000000001],"type":"Point"}
}