{
  "type": "Feature",
  "properties": {
    "gn:admin1_code":"58",
    "gn:asciiname":"Qaraxanli",
    "gn:country_code":"AZ",
    "gn:dem":354,
    "gn:feature_class":"P",
    "gn:feature_code":"PPL",
    "gn:name":"Qaraxanl\u0131",
    "gn:population":3166,
    "gn:timezone":"Asia/Baku",
    "iso:country":"AZ",
    "name:azb_x_preferred":[
        "\u0642\u0627\u0631\u0627\u062e\u0627\u0646\u0644\u06cc"
    ],
    "name:aze_x_preferred":[
        "Qaraxanl\u0131"
    ],
    "name:ceb_x_preferred":[
        "Qaraxanl\u0131"
    ],
    "name:ita_x_preferred":[
        "Qaraxanl\u0131"
    ],
    "name:kat_x_preferred":[
        "\u10e5\u10d0\u10e0\u10d0\u10ee\u10d0\u10dc\u10da\u10d8"
    ],
    "name:msa_x_preferred":[
        "Qaraxanl\u0131"
    ],
    "name:swe_x_preferred":[
        "Qaraxanl\u0131"
    ],
    "name:und_x_variant":[
        "Karakhanly"
    ],
    "wof:name":"Qaraxanli",
    "wof:placetype":"locality",
    "wof:population":3166
},
  "geometry": {"coordinates":[45.65527,41.04358],"type":"Point"}
}