{
  "type": "Feature",
  "properties": {
    "gn:admin1_code":"12",
    "gn:asciiname":"Kagramanly",
    "gn:country_code":"AZ",
    "gn:dem":60,
    "gn:feature_class":"P",
    "gn:feature_code":"PPL",
    "gn:name":"Kagramanly",
    "gn:population":0,
    "gn:timezone":"Asia/Baku",
    "iso:country":"AZ",
    "name:aze_x_preferred":[
        "Q\u0259hr\u0259manl\u0131"
    ],
    "name:und_x_variant":[
        "Moshkara",
        "Kagramanli"
    ],
    "wof:name":"Kagramanly",
    "wof:placetype":"locality"
},
  "geometry": {"coordinates":[47.69103,39.69865],"type":"Point"}
}