{
  "type": "Feature",
  "properties": {
    "gn:admin1_code":"12",
    "gn:asciiname":"Kagramanly",
    "gn:country_code":"AZ",
    "gn:dem":60,
    "gn:feature_class":"P",
    "gn:feature_code":"PPL",
    "gn:name":"Kagramanly",
    "gn:population":0,
    "gn:timezone":"Asia/Baku",
    "iso:country":"AZ",
    "name:azb_x_preferred":[
        "\u0642\u0647\u0631\u0645\u0627\u0646\u0644\u06cc"
    ],
    "name:aze_x_preferred":[
        "Q\u0259hr\u0259manl\u0131"
    ],
    "name:ceb_x_preferred":[
        "Kagramanly"
    ],
    "name:ell_x_preferred":[
        "\u039a\u03b5\u03c7\u03c1\u03b5\u03bc\u03b1\u03bd\u03bb\u03af"
    ],
    "name:ita_x_preferred":[
        "Kagramanly"
    ],
    "name:kat_x_preferred":[
        "\u10e7\u10d0\u10f0\u10e0\u10d0\u10db\u10d0\u10dc\u10da\u10d8"
    ],
    "name:msa_x_preferred":[
        "Q\u0259hr\u0259manl\u0131"
    ],
    "name:rus_x_preferred":[
        "\u041a\u0430\u0433\u0440\u0430\u043c\u0430\u043d\u043b\u044b"
    ],
    "name:swe_x_preferred":[
        "Kagramanly"
    ],
    "name:und_x_variant":[
        "Moshkara",
        "Kagramanli"
    ],
    "wof:name":"Kagramanly",
    "wof:placetype":"locality"
},
  "geometry": {"coordinates":[47.69103,39.69865],"type":"Point"}
}