{
  "type": "Feature",
  "properties": {
    "gn:admin1_code":"01",
    "gn:asciiname":"Ramazan",
    "gn:country_code":"AZ",
    "gn:dem":224,
    "gn:feature_class":"P",
    "gn:feature_code":"PPL",
    "gn:name":"Ramazan",
    "gn:population":0,
    "gn:timezone":"Asia/Baku",
    "iso:country":"AZ",
    "name:azb_x_preferred":[
        "\u0631\u0645\u0636\u0627\u0646"
    ],
    "name:ita_x_preferred":[
        "Ramazan"
    ],
    "name:kat_x_preferred":[
        "\u10e0\u10d0\u10db\u10d0\u10d6\u10d0\u10dc\u10d8"
    ],
    "name:msa_x_preferred":[
        "Ramazan"
    ],
    "name:pol_x_preferred":[
        "Ramazan"
    ],
    "wof:name":"Ramazan",
    "wof:placetype":"locality"
},
  "geometry": {"coordinates":[49.21028,40.28556],"type":"Point"}
}