{
  "type": "Feature",
  "properties": {
    "gn:admin1_code":"38",
    "gn:asciiname":"Laza",
    "gn:country_code":"AZ",
    "gn:dem":1357,
    "gn:feature_class":"P",
    "gn:feature_code":"PPL",
    "gn:name":"Laza",
    "gn:population":0,
    "gn:timezone":"Asia/Baku",
    "iso:country":"AZ",
    "name:eng_x_preferred":[
        "Laza"
    ],
    "name:rus_x_preferred":[
        "\u041b\u0430\u0437\u0430"
    ],
    "wof:name":"Laza",
    "wof:placetype":"locality"
},
  "geometry": {"coordinates":[47.91392000000001,41.04683],"type":"Point"}
}