{
  "type": "Feature",
  "properties": {
    "gn:admin1_code":"28",
    "gn:asciiname":"Kazidara",
    "gn:country_code":"AZ",
    "gn:dem":815,
    "gn:feature_class":"P",
    "gn:feature_code":"PPL",
    "gn:name":"Kazidara",
    "gn:population":0,
    "gn:timezone":"Asia/Baku",
    "iso:country":"AZ",
    "name:azb_x_preferred":[
        "\u0642\u0627\u0636\u06cc \u062f\u0631\u0647"
    ],
    "name:aze_x_preferred":[
        "Qaz\u0131d\u0259r\u0259"
    ],
    "name:fas_x_preferred":[
        "\u0642\u0627\u0636\u06cc\u200c\u062f\u0631\u0647"
    ],
    "name:hye_x_preferred":[
        "Ghazydere"
    ],
    "name:hye_x_variant":[
        "\u0542\u0561\u0566\u0568\u0564\u0565\u0580\u0565"
    ],
    "name:kat_x_preferred":[
        "\u10e7\u10d0\u10d6\u10d8\u10d3\u10d0\u10e0\u10d0"
    ],
    "name:msa_x_preferred":[
        "Qaz\u0131d\u0259r\u0259"
    ],
    "name:rus_x_preferred":[
        "\u0413\u0430\u0437\u044b\u0434\u0435\u0440\u0435"
    ],
    "name:und_x_variant":[
        "Gazydere",
        "Kazidara"
    ],
    "wof:name":"Kazidara",
    "wof:placetype":"locality"
},
  "geometry": {"coordinates":[46.56567,39.52809],"type":"Point"}
}