{
  "type": "Feature",
  "properties": {
    "gn:admin1_code":"26",
    "gn:asciiname":"Dasbulaq",
    "gn:country_code":"AZ",
    "gn:dem":2112,
    "gn:feature_class":"P",
    "gn:feature_code":"PPL",
    "gn:name":"Da\u015fbulaq",
    "gn:population":0,
    "gn:timezone":"Asia/Baku",
    "iso:country":"AZ",
    "name:aze_x_preferred":[
        "Da\u015fbulaq"
    ],
    "wof:name":"Dasbulaq",
    "wof:placetype":"locality"
},
  "geometry": {"coordinates":[46.03904,40.14565],"type":"Point"}
}