{
  "type": "Feature",
  "properties": {
    "gn:admin1_code":"22",
    "gn:asciiname":"Asagi Qaramaryam",
    "gn:country_code":"AZ",
    "gn:dem":70,
    "gn:feature_class":"P",
    "gn:feature_code":"PPL",
    "gn:name":"A\u015fa\u011f\u0131 Qaram\u0259ry\u0259m",
    "gn:population":0,
    "gn:timezone":"Asia/Baku",
    "iso:country":"AZ",
    "name:aze_x_preferred":[
        "A\u015fa\u011f\u0131 Qaram\u0259ry\u0259m"
    ],
    "name:ita_x_preferred":[
        "A\u015fa\u011f\u0131 Qaram\u0259ryam"
    ],
    "name:kat_x_preferred":[
        "\u10d0\u10e8\u10d0\u10e6\u10d8-\u10e7\u10d0\u10e0\u10d0\u10db\u10d0\u10e0\u10d8\u10d0\u10db\u10d8"
    ],
    "name:msa_x_preferred":[
        "A\u015fa\u011f\u0131 Qaram\u0259ryam"
    ],
    "name:und_x_variant":[
        "Ashagy Karamar\u2019yam",
        "Karamar\u2019yam"
    ],
    "wof:name":"Asagi Qaramaryam",
    "wof:placetype":"locality"
},
  "geometry": {"coordinates":[47.98439000000001,40.57487],"type":"Point"}
}