{
  "type": "Feature",
  "properties": {
    "gn:admin1_code":"15",
    "gn:asciiname":"Shorbachy",
    "gn:country_code":"AZ",
    "gn:dem":146,
    "gn:feature_class":"P",
    "gn:feature_code":"PPL",
    "gn:name":"Shorbachy",
    "gn:population":0,
    "gn:timezone":"Asia/Baku",
    "iso:country":"AZ",
    "name:und_x_variant":[
        "Shorbachi",
        "Shorbachy",
        "\u015eorba\u00e7\u0131"
    ],
    "wof:name":"Shorbachy",
    "wof:placetype":"locality"
},
  "geometry": {"coordinates":[48.32386,39.25781],"type":"Point"}
}