{
  "type": "Feature",
  "properties": {
    "gn:admin1_code":"31",
    "gn:asciiname":"Anzolu",
    "gn:country_code":"AZ",
    "gn:dem":1610,
    "gn:feature_class":"P",
    "gn:feature_code":"PPL",
    "gn:name":"Anzolu",
    "gn:population":0,
    "gn:timezone":"Asia/Baku",
    "iso:country":"AZ",
    "name:und_x_variant":[
        "Anzoli",
        "Anzolu"
    ],
    "wof:name":"Anzolu",
    "wof:placetype":"locality"
},
  "geometry": {"coordinates":[48.4843,38.69314],"type":"Point"}
}