{
  "type": "Feature",
  "properties": {
    "gn:admin1_code":"35",
    "gn:admin2_code":"147365.0",
    "gn:asciiname":"Urmis",
    "gn:country_code":"AZ",
    "gn:dem":2139,
    "gn:feature_class":"P",
    "gn:feature_code":"PPL",
    "gn:name":"Urmis",
    "gn:population":0,
    "gn:timezone":"Asia/Baku",
    "iso:country":"AZ",
    "name:aze_x_preferred":[
        "Urmis"
    ],
    "name:und_x_variant":[
        "Urumys"
    ],
    "wof:name":"Urmis",
    "wof:placetype":"locality"
},
  "geometry": {"coordinates":[45.9741,39.07277],"type":"Point"}
}