{
  "type": "Feature",
  "properties": {
    "gn:admin1_code":"53",
    "gn:asciiname":"Chandakhar",
    "gn:country_code":"AZ",
    "gn:dem":-14,
    "gn:feature_class":"P",
    "gn:feature_code":"PPL",
    "gn:name":"Chandakhar",
    "gn:population":0,
    "gn:timezone":"Asia/Baku",
    "iso:country":"AZ",
    "name:aze_x_preferred":[
        "C\u0259nd\u0259har"
    ],
    "wof:name":"Chandakhar",
    "wof:placetype":"locality"
},
  "geometry": {"coordinates":[49.23729,40.9856],"type":"Point"}
}