{
  "type": "Feature",
  "properties": {
    "gn:admin1_code":"31",
    "gn:asciiname":"Rvarud",
    "gn:country_code":"AZ",
    "gn:dem":1622,
    "gn:feature_class":"P",
    "gn:feature_code":"PPL",
    "gn:name":"Rvarud",
    "gn:population":0,
    "gn:timezone":"Asia/Baku",
    "iso:country":"AZ",
    "name:und_x_variant":[
        "Revarut",
        "Rivarud",
        "Rvarud"
    ],
    "wof:name":"Rvarud",
    "wof:placetype":"locality"
},
  "geometry": {"coordinates":[48.49347,38.69518],"type":"Point"}
}