{
  "type": "Feature",
  "properties": {
    "gn:admin1_code":"64",
    "gn:asciiname":"Qaybali",
    "gn:country_code":"AZ",
    "gn:dem":1045,
    "gn:feature_class":"P",
    "gn:feature_code":"PPL",
    "gn:name":"Qaybal\u0131",
    "gn:population":0,
    "gn:timezone":"Asia/Baku",
    "iso:country":"AZ",
    "name:aze_x_preferred":[
        "Qeybal\u0131"
    ],
    "name:aze_x_variant":[
        "Qaybal\u0131"
    ],
    "name:hye_x_preferred":[
        "K\u2019eybaly"
    ],
    "name:hye_x_variant":[
        "\u0554\u0565\u0575\u0562\u0561\u056c\u0568",
        "Gaylabun",
        "\u0533\u0561\u0575\u056c\u0561\u0562\u0578\u0582\u0576",
        "Ghaybalishen",
        "\u0542\u0561\u0575\u0562\u0561\u056c\u056b\u0577\u0565\u0576"
    ],
    "name:msa_x_preferred":[
        "Qeybal\u0131"
    ],
    "name:rus_x_preferred":[
        "\u041a\u0435\u0439\u0431\u0430\u043b\u0438"
    ],
    "name:rus_x_variant":[
        "\u041a\u0435\u0439\u0431\u0430\u043b\u044b"
    ],
    "name:und_x_variant":[
        "Ghaibalou",
        "Keybaly"
    ],
    "wof:name":"Qaybali",
    "wof:placetype":"locality"
},
  "geometry": {"coordinates":[46.72778,39.77639],"type":"Point"}
}