{
  "type": "Feature",
  "properties": {
    "gn:admin1_code":"49",
    "gn:asciiname":"Boranykend",
    "gn:country_code":"AZ",
    "gn:dem":-24,
    "gn:feature_class":"P",
    "gn:feature_code":"PPL",
    "gn:name":"Boranykend",
    "gn:population":0,
    "gn:timezone":"Asia/Baku",
    "iso:country":"AZ",
    "name:azb_x_preferred":[
        "\u0628\u0648\u0631\u0627\u0646\u06cc \u06a9\u0646\u062f"
    ],
    "name:aze_x_preferred":[
        "Boran\u0131k\u0259nd"
    ],
    "name:ceb_x_preferred":[
        "Boranykend"
    ],
    "name:fas_x_preferred":[
        "\u0628\u0648\u0631\u0627\u0646\u06cc\u200c\u06a9\u0646\u062f"
    ],
    "name:ita_x_preferred":[
        "Boran\u0131k\u0259nd"
    ],
    "name:msa_x_preferred":[
        "Boran\u0131k\u0259nd"
    ],
    "name:swe_x_preferred":[
        "Boranykend"
    ],
    "name:und_x_variant":[
        "Boran\u0131k\u0259nd"
    ],
    "wof:name":"Boranykend",
    "wof:placetype":"locality"
},
  "geometry": {"coordinates":[48.83575,39.42943],"type":"Point"}
}