{
  "type": "Feature",
  "properties": {
    "gn:admin1_code":"49",
    "gn:asciiname":"Boranykend",
    "gn:country_code":"AZ",
    "gn:dem":-24,
    "gn:feature_class":"P",
    "gn:feature_code":"PPL",
    "gn:name":"Boranykend",
    "gn:population":0,
    "gn:timezone":"Asia/Baku",
    "iso:country":"AZ",
    "name:und_x_variant":[
        "Boran\u0131k\u0259nd"
    ],
    "wof:name":"Boranykend",
    "wof:placetype":"locality"
},
  "geometry": {"coordinates":[48.83575,39.42943],"type":"Point"}
}