{
  "type": "Feature",
  "properties": {
    "gn:admin1_code":"25",
    "gn:asciiname":"Myudryuse",
    "gn:country_code":"AZ",
    "gn:dem":1251,
    "gn:feature_class":"P",
    "gn:feature_code":"PPL",
    "gn:name":"Myudryuse",
    "gn:population":0,
    "gn:timezone":"Asia/Baku",
    "iso:country":"AZ",
    "name:aze_x_preferred":[
        "M\u00fcdris\u0259"
    ],
    "name:ceb_x_preferred":[
        "Myudryuse"
    ],
    "name:ita_x_preferred":[
        "M\u00fcdr\u0259s\u0259"
    ],
    "name:kat_x_preferred":[
        "\u10db\u10d8\u10e3\u10d3\u10e0\u10d8\u10e1\u10d0"
    ],
    "name:msa_x_preferred":[
        "M\u00fcdr\u0259s\u0259"
    ],
    "name:swe_x_preferred":[
        "Myudryuse"
    ],
    "name:und_x_variant":[
        "Myudresa",
        "Myudryuse",
        "M\u00fcdr\u0259s\u0259"
    ],
    "wof:name":"Myudryuse",
    "wof:placetype":"locality"
},
  "geometry": {"coordinates":[48.31775,40.86091],"type":"Point"}
}