{
  "type": "Feature",
  "properties": {
    "gn:admin1_code":"64",
    "gn:asciiname":"Quscubaba",
    "gn:country_code":"AZ",
    "gn:dem":1153,
    "gn:feature_class":"P",
    "gn:feature_code":"PPL",
    "gn:name":"Qu\u015f\u00e7ubaba",
    "gn:population":0,
    "gn:timezone":"Asia/Baku",
    "iso:country":"AZ",
    "name:azb_x_preferred":[
        "\u0642\u0648\u0634\u0686\u0648\u0628\u0627\u0628\u0627"
    ],
    "name:aze_x_preferred":[
        "Qu\u015f\u00e7ubaba"
    ],
    "name:aze_x_variant":[
        "Mo\u015fxmhat"
    ],
    "name:bel_x_preferred":[
        "\u041c\u0430\u0448\u0445\u043c\u0433\u0430\u0442"
    ],
    "name:fas_x_preferred":[
        "\u0645\u0648\u0634\u062e\u0645\u0647\u0627\u062a"
    ],
    "name:fra_x_preferred":[
        "Moshkhmgat"
    ],
    "name:hye_x_preferred":[
        "\u0544\u0578\u0577\u056d\u0574\u0570\u0561\u057f"
    ],
    "name:hye_x_variant":[
        "Moshkhmhat",
        "Moshkhmahat",
        "\u0544\u0578\u0577\u056d\u0574\u0561\u0570\u0561\u057f"
    ],
    "name:ita_x_preferred":[
        "Moshkhmhat"
    ],
    "name:msa_x_preferred":[
        "Mo\u015fxmhat"
    ],
    "name:rus_x_preferred":[
        "\u041c\u043e\u0448\u0445\u043c\u0430\u0430\u0442"
    ],
    "name:ukr_x_preferred":[
        "\u041c\u043e\u0448\u0445\u043c\u0433\u0430\u0442"
    ],
    "name:und_x_variant":[
        "Moshkhmhat",
        "Moshkhmaat"
    ],
    "wof:name":"Quscubaba",
    "wof:placetype":"locality"
},
  "geometry": {"coordinates":[46.85407,39.68464],"type":"Point"}
}