{
  "type": "Feature",
  "properties": {
    "gn:admin1_code":"31",
    "gn:asciiname":"Laman",
    "gn:country_code":"AZ",
    "gn:dem":745,
    "gn:feature_class":"P",
    "gn:feature_code":"PPL",
    "gn:name":"Laman",
    "gn:population":0,
    "gn:timezone":"Asia/Baku",
    "iso:country":"AZ",
    "name:azb_x_preferred":[
        "\u0644\u0627\u0645\u0627\u0646"
    ],
    "name:ceb_x_preferred":[
        "Laman"
    ],
    "name:ita_x_preferred":[
        "Laman"
    ],
    "name:msa_x_preferred":[
        "Laman"
    ],
    "name:urd_x_preferred":[
        "\u0644\u0627\u0645\u0627\u0646"
    ],
    "wof:name":"Laman",
    "wof:placetype":"locality"
},
  "geometry": {"coordinates":[48.42528,38.86138],"type":"Point"}
}