{
  "type": "Feature",
  "properties": {
    "iso:country":"AZ",
    "name:azb_x_preferred":[
        "\u0644\u0627\u0647\u06cc\u062c"
    ],
    "name:aze_x_preferred":[
        "Lah\u0131c"
    ],
    "name:ceb_x_preferred":[
        "Lah\u0131c"
    ],
    "name:ceb_x_variant":[
        "Lahic"
    ],
    "name:che_x_preferred":[
        "\u041b\u0430\u0445\u04c0\u0438\u0434\u0436"
    ],
    "name:deu_x_preferred":[
        "Lah\u0131c"
    ],
    "name:eng_x_preferred":[
        "Lah\u0131c"
    ],
    "name:fas_x_preferred":[
        "\u0644\u0627\u0647\u06cc\u062c"
    ],
    "name:fin_x_preferred":[
        "Lah\u0131c"
    ],
    "name:fra_x_preferred":[
        "Lahidj"
    ],
    "name:ita_x_preferred":[
        "Lah\u0131c"
    ],
    "name:jpn_x_preferred":[
        "\u30e9\u30d5\u30b8"
    ],
    "name:kat_x_preferred":[
        "\u10da\u10d0\u10f0\u10d8\u10ef\u10d8"
    ],
    "name:msa_x_preferred":[
        "Lah\u0131c"
    ],
    "name:nld_x_preferred":[
        "Lah\u0131c"
    ],
    "name:pol_x_preferred":[
        "Lah\u0131c"
    ],
    "name:rus_x_preferred":[
        "\u041b\u0430\u0433\u0438\u0447"
    ],
    "name:swe_x_preferred":[
        "Lah\u0131c"
    ],
    "name:swe_x_variant":[
        "Lahic"
    ],
    "name:tur_x_preferred":[
        "Lah\u0131c"
    ],
    "name:und_x_variant":[
        "Lagich"
    ],
    "name:uzb_x_preferred":[
        "Lah\u0131c(Ismailli"
    ],
    "name:zho_x_preferred":[
        "\u62c9\u8d6b\u5b63\u5730\u533a"
    ],
    "qs:gn_country":"AZ",
    "qs:gn_fcode":"PPL",
    "qs:gn_pop":925,
    "qs:name":"Lah\u1e2fc",
    "qs:name_adm0":"Azerbaijan",
    "qs:name_adm1":"Ismayilli",
    "qs:photos":54,
    "qs:photos_1k":11,
    "qs:photos_9k":1,
    "qs:photos_9r":2,
    "qs:photos_all":54,
    "qs:photos_sr":2,
    "qs:placetype":"Town",
    "qs:pop_sr":"2",
    "qs:woe_adm0":23424741,
    "wof:name":"Lah\u1e2fc",
    "wof:placetype":"locality",
    "wof:population":925
},
  "geometry": {"coordinates":[48.39306,40.85306],"type":"Point"}
}