{
  "type": "Feature",
  "properties": {
    "gn:admin1_code":"39",
    "gn:asciiname":"Lekit Malakh",
    "gn:country_code":"AZ",
    "gn:dem":547,
    "gn:feature_class":"P",
    "gn:feature_code":"PPL",
    "gn:name":"Lekit Malakh",
    "gn:population":0,
    "gn:timezone":"Asia/Baku",
    "iso:country":"AZ",
    "name:ava_x_preferred":[
        "\u041b\u0435\u043aI\u0438\u043a\u044c \u041c\u0430\u043b\u0430\u0445\u044a"
    ],
    "name:aze_x_preferred":[
        "L\u0259kit Malax"
    ],
    "name:ceb_x_preferred":[
        "Lekit Malakh"
    ],
    "name:ell_x_preferred":[
        "\u039b\u03b5\u03ba\u03af\u03c4 \u039c\u03b1\u03bb\u03ac\u03c7"
    ],
    "name:ita_x_preferred":[
        "L\u0259kit Malax"
    ],
    "name:kat_x_preferred":[
        "\u10da\u10d4\u10e5\u10d4\u10d7\u10d8-\u10db\u10d0\u10da\u10d0\u10ee\u10d8"
    ],
    "name:msa_x_preferred":[
        "L\u0259kit Malax"
    ],
    "name:swe_x_preferred":[
        "Lekit Malakh"
    ],
    "name:und_x_variant":[
        "L\u0259kit Malax"
    ],
    "wof:name":"Lekit Malakh",
    "wof:placetype":"locality"
},
  "geometry": {"coordinates":[46.86491,41.47318],"type":"Point"}
}