{
  "type": "Feature",
  "properties": {
    "gn:admin1_code":"06",
    "gn:asciiname":"Qirlar",
    "gn:country_code":"AZ",
    "gn:dem":693,
    "gn:feature_class":"P",
    "gn:feature_code":"PPL",
    "gn:name":"Q\u0131rlar",
    "gn:population":0,
    "gn:timezone":"Asia/Baku",
    "iso:country":"AZ",
    "name:aze_x_preferred":[
        "Q\u0131rlar"
    ],
    "name:ell_x_preferred":[
        "\u039a\u03b9\u03c1\u03bb\u03ac\u03c1"
    ],
    "name:ita_x_preferred":[
        "Q\u0131rlar"
    ],
    "name:kat_x_preferred":[
        "\u10e5\u10d8\u10e0\u10da\u10d0\u10e0\u10d8"
    ],
    "name:msa_x_preferred":[
        "Q\u0131rlar"
    ],
    "name:und_x_variant":[
        "Kyrlar",
        "Gyrlar",
        "Q\u0131rlar",
        "Kyvrak"
    ],
    "wof:name":"Qirlar",
    "wof:placetype":"locality"
},
  "geometry": {"coordinates":[48.46865,40.67998],"type":"Point"}
}