{
  "type": "Feature",
  "properties": {
    "gn:admin1_code":"41",
    "gn:asciiname":"Derekend",
    "gn:country_code":"AZ",
    "gn:dem":693,
    "gn:feature_class":"P",
    "gn:feature_code":"PPL",
    "gn:name":"Derekend",
    "gn:population":0,
    "gn:timezone":"Asia/Baku",
    "iso:country":"AZ",
    "name:und_x_variant":[
        "Darakend",
        "D\u0259r\u0259k\u0259nd"
    ],
    "wof:name":"Derekend",
    "wof:placetype":"locality"
},
  "geometry": {"coordinates":[48.93736,40.4999],"type":"Point"}
}