{
  "type": "Feature",
  "properties": {
    "gn:admin1_code":"46",
    "gn:asciiname":"Yenikend",
    "gn:country_code":"AZ",
    "gn:dem":-17,
    "gn:feature_class":"P",
    "gn:feature_code":"PPL",
    "gn:name":"Yenikend",
    "gn:population":0,
    "gn:timezone":"Asia/Baku",
    "iso:country":"AZ",
    "name:und_x_variant":[
        "Yenik\u0259nd"
    ],
    "wof:name":"Yenikend",
    "wof:placetype":"locality"
},
  "geometry": {"coordinates":[48.58023,40.10386],"type":"Point"}
}