{
  "type": "Feature",
  "properties": {
    "gn:admin1_code":"28",
    "gn:asciiname":"Ircan",
    "gn:country_code":"AZ",
    "gn:dem":1545,
    "gn:feature_class":"P",
    "gn:feature_code":"PPL",
    "gn:name":"\u0130r\u00e7an",
    "gn:population":0,
    "gn:timezone":"Asia/Baku",
    "iso:country":"AZ",
    "name:azb_x_preferred":[
        "\u0627\u06cc\u0631\u0686\u0627\u0646"
    ],
    "name:aze_x_preferred":[
        "\u0130r\u00e7an"
    ],
    "name:hye_x_preferred":[
        "Irchan"
    ],
    "name:hye_x_variant":[
        "\u053b\u0580\u0579\u0561\u0576"
    ],
    "name:kat_x_preferred":[
        "\u10d8\u10e0\u10e9\u10d0\u10dc\u10d8"
    ],
    "name:msa_x_preferred":[
        "\u0130r\u00e7an"
    ],
    "name:rus_x_preferred":[
        "Irch\u2019an"
    ],
    "name:rus_x_variant":[
        "\u0418\u0440\u0447\u0430\u043d"
    ],
    "wof:name":"Ircan",
    "wof:placetype":"locality"
},
  "geometry": {"coordinates":[46.66871,39.63359000000001],"type":"Point"}
}