{
  "type": "Feature",
  "properties": {
    "gn:admin1_code":"40",
    "gn:asciiname":"Quscu Ayrim",
    "gn:country_code":"AZ",
    "gn:dem":862,
    "gn:feature_class":"P",
    "gn:feature_code":"PPL",
    "gn:name":"Qu\u015f\u00e7u Ayr\u0131m",
    "gn:population":0,
    "gn:timezone":"Asia/Baku",
    "iso:country":"AZ",
    "name:azb_x_preferred":[
        "\u0642\u0648\u0634\u0686\u0648 \u0622\u06cc\u0631\u06cc\u0645"
    ],
    "name:aze_x_preferred":[
        "Qu\u015f\u00e7u Ayr\u0131m"
    ],
    "name:hye_x_preferred":[
        "\u0542\u0578\u0582\u0577\u0579\u0578\u0582 \u0531\u0575\u0580\u0578\u0582\u0574"
    ],
    "name:kat_x_preferred":[
        "\u10e5\u10e3\u10e8\u10e9\u10e3-\u10d0\u10d8\u10e0\u10d8\u10db\u10d8"
    ],
    "name:msa_x_preferred":[
        "Qu\u015f\u00e7u Ayr\u0131m"
    ],
    "name:rus_x_preferred":[
        "\u041a\u0443\u0448\u0447\u0443-\u0410\u0439\u0440\u0443\u043c"
    ],
    "name:und_x_variant":[
        "Kushchu Ayrum",
        "Kushchi-Ayrum",
        "Qu\u015f\u00e7u Ayr\u0131m"
    ],
    "wof:name":"Quscu Ayrim",
    "wof:placetype":"locality"
},
  "geometry": {"coordinates":[45.102,41.09378],"type":"Point"}
}