{
  "type": "Feature",
  "properties": {
    "gn:admin1_code":"40",
    "gn:asciiname":"Quscu Ayrim",
    "gn:country_code":"AZ",
    "gn:dem":862,
    "gn:feature_class":"P",
    "gn:feature_code":"PPL",
    "gn:name":"Qu\u015f\u00e7u Ayr\u0131m",
    "gn:population":0,
    "gn:timezone":"Asia/Baku",
    "iso:country":"AZ",
    "name:und_x_variant":[
        "Kushchu Ayrum",
        "Kushchi-Ayrum",
        "Qu\u015f\u00e7u Ayr\u0131m"
    ],
    "wof:name":"Quscu Ayrim",
    "wof:placetype":"locality"
},
  "geometry": {"coordinates":[45.102,41.09378],"type":"Point"}
}