{
  "type": "Feature",
  "properties": {
    "gn:admin1_code":"04",
    "gn:asciiname":"Pirkend",
    "gn:country_code":"AZ",
    "gn:dem":35,
    "gn:feature_class":"P",
    "gn:feature_code":"PPL",
    "gn:name":"Pirkend",
    "gn:population":0,
    "gn:timezone":"Asia/Baku",
    "iso:country":"AZ",
    "name:aze_x_preferred":[
        "Pirk\u0259k\u0259"
    ],
    "name:und_x_variant":[
        "Pirk\u0259nd",
        "Pirkekya"
    ],
    "wof:name":"Pirkend",
    "wof:placetype":"locality"
},
  "geometry": {"coordinates":[47.39498,40.71261],"type":"Point"}
}