{
  "type": "Feature",
  "properties": {
    "gn:admin1_code":"06",
    "gn:asciiname":"Dzhalair",
    "gn:country_code":"AZ",
    "gn:dem":16,
    "gn:feature_class":"P",
    "gn:feature_code":"PPL",
    "gn:name":"Dzhalair",
    "gn:population":0,
    "gn:timezone":"Asia/Baku",
    "iso:country":"AZ",
    "name:aze_x_preferred":[
        "C\u0259lay\u0131r"
    ],
    "name:eng_x_preferred":[
        "C\u01ddlayir"
    ],
    "name:rus_x_preferred":[
        "\u0414\u0436\u0430\u043b\u0430\u0438\u0440"
    ],
    "name:und_x_variant":[
        "C\u0259layir"
    ],
    "wof:name":"Dzhalair",
    "wof:placetype":"locality"
},
  "geometry": {"coordinates":[48.42056,40.35835],"type":"Point"}
}