{
  "type": "Feature",
  "properties": {
    "gn:admin1_code":"36",
    "gn:asciiname":"Nord-Ost Qultuq",
    "gn:country_code":"AZ",
    "gn:dem":-27,
    "gn:feature_class":"P",
    "gn:feature_code":"PPL",
    "gn:name":"Nord-Ost Qultuq",
    "gn:population":0,
    "gn:timezone":"Asia/Baku",
    "iso:country":"AZ",
    "name:aze_x_preferred":[
        "Nord-Ost Qultuq"
    ],
    "name:aze_x_variant":[
        "Z\u00fcd-Ost Qoltuq"
    ],
    "name:msa_x_preferred":[
        "Nord-Ost-Kultuk"
    ],
    "name:und_x_variant":[
        "Kul\u2019tuk",
        "Nordostovyy Kultuk",
        "Nord-Ost-Kultuk"
    ],
    "wof:name":"Nord-Ost Qultuq",
    "wof:placetype":"locality"
},
  "geometry": {"coordinates":[49.2668,39.4924],"type":"Point"}
}