{
  "type": "Feature",
  "properties": {
    "gn:admin1_code":"52",
    "gn:asciiname":"Cirdaxan",
    "gn:country_code":"AZ",
    "gn:dem":255,
    "gn:feature_class":"P",
    "gn:feature_code":"PPL",
    "gn:name":"C\u0131rdaxan",
    "gn:population":0,
    "gn:timezone":"Asia/Baku",
    "iso:country":"AZ",
    "wof:name":"Cirdaxan",
    "wof:placetype":"locality"
},
  "geometry": {"coordinates":[46.31917,40.78806],"type":"Point"}
}