{
  "type": "Feature",
  "properties": {
    "gn:admin1_code":"19",
    "gn:asciiname":"Arisu",
    "gn:country_code":"AZ",
    "gn:dem":1500,
    "gn:feature_class":"P",
    "gn:feature_code":"PPL",
    "gn:name":"Ar\u0131su",
    "gn:population":0,
    "gn:timezone":"Asia/Baku",
    "iso:country":"AZ",
    "name:aze_x_preferred":[
        "Ar\u0131su"
    ],
    "name:ita_x_preferred":[
        "Ar\u0131su"
    ],
    "name:kat_x_preferred":[
        "\u10d0\u10e0\u10d8\u10e1\u10e3"
    ],
    "name:msa_x_preferred":[
        "Ar\u0131su"
    ],
    "name:und_x_variant":[
        "Arysu",
        "Ayrysu"
    ],
    "wof:name":"Arisu",
    "wof:placetype":"locality"
},
  "geometry": {"coordinates":[45.72861,40.49096],"type":"Point"}
}