{
  "type": "Feature",
  "properties": {
    "gn:admin1_code":"53",
    "gn:asciiname":"Eynibulaq",
    "gn:country_code":"AZ",
    "gn:dem":165,
    "gn:feature_class":"P",
    "gn:feature_code":"PPL",
    "gn:name":"Eynibulaq",
    "gn:population":0,
    "gn:timezone":"Asia/Baku",
    "iso:country":"AZ",
    "name:eng_x_preferred":[
        "Eynibulaq"
    ],
    "name:rus_x_preferred":[
        "\u042d\u0439\u043d\u0438\u0431\u0443\u043b\u0430\u043a"
    ],
    "name:und_x_variant":[
        "Eyni-Bulagi",
        "Eynibulak",
        "Eynibulag",
        "Eynibulaq"
    ],
    "wof:name":"Eynibulaq",
    "wof:placetype":"locality"
},
  "geometry": {"coordinates":[49.03712,41.10551],"type":"Point"}
}