{
  "type": "Feature",
  "properties": {
    "gn:admin1_code":"46",
    "gn:asciiname":"Kovlar",
    "gn:country_code":"AZ",
    "gn:dem":-18,
    "gn:feature_class":"P",
    "gn:feature_code":"PPL",
    "gn:name":"Kovlar",
    "gn:population":0,
    "gn:timezone":"Asia/Baku",
    "iso:country":"AZ",
    "name:eng_x_preferred":[
        "Qovlar"
    ],
    "name:rus_x_preferred":[
        "\u041a\u043e\u0432\u043b\u0430\u0440"
    ],
    "name:und_x_variant":[
        "Bol\u2019shoy Kovlyar",
        "Kovlyar",
        "Beyuk Kovlar",
        "Kovlar",
        "Qovlar"
    ],
    "wof:name":"Kovlar",
    "wof:placetype":"locality"
},
  "geometry": {"coordinates":[48.5558,40.11232],"type":"Point"}
}