{
  "type": "Feature",
  "properties": {
    "gn:admin1_code":"26",
    "gn:asciiname":"Kiliselli",
    "gn:country_code":"AZ",
    "gn:dem":1701,
    "gn:feature_class":"P",
    "gn:feature_code":"PPL",
    "gn:name":"Kiliselli",
    "gn:population":0,
    "gn:timezone":"Asia/Baku",
    "iso:country":"AZ",
    "name:aze_x_preferred":[
        "G\u00fcn\u0259\u015fli"
    ],
    "name:hye_x_preferred":[
        "Yeghts\u2019ategh"
    ],
    "name:hye_x_variant":[
        "\u0535\u0572\u0581\u0561\u057f\u0565\u0572"
    ],
    "name:rus_x_preferred":[
        "\u041a\u0438\u043b\u044c\u0441\u044f\u043b\u0438"
    ],
    "name:und_x_variant":[
        "Kil\u2019syali",
        "Kiliselli",
        "Kilisali",
        "Kils\u0259li"
    ],
    "wof:name":"Kiliselli",
    "wof:placetype":"locality"
},
  "geometry": {"coordinates":[46.19245,40.1157],"type":"Point"}
}