{
  "type": "Feature",
  "properties": {
    "gn:admin1_code":"64",
    "gn:asciiname":"Ballica",
    "gn:country_code":"AZ",
    "gn:dem":781,
    "gn:feature_class":"P",
    "gn:feature_code":"PPL",
    "gn:name":"Ball\u0131ca",
    "gn:population":0,
    "gn:timezone":"Asia/Baku",
    "iso:country":"AZ",
    "name:aze_x_preferred":[
        "Ball\u0131ca"
    ],
    "name:hye_x_preferred":[
        "\u0531\u0575\u0563\u0565\u057d\u057f\u0561\u0576"
    ],
    "name:hye_x_variant":[
        "Aygestan"
    ],
    "name:rus_x_preferred":[
        "\u0411\u0430\u043b\u043b\u044b\u0434\u0436\u0430"
    ],
    "name:tur_x_preferred":[
        "Ball\u0131ca"
    ],
    "name:und_x_variant":[
        "Balludzha",
        "Baloudga",
        "Baludzha",
        "Ballydzha",
        "Aygestan",
        "Boludzha"
    ],
    "wof:name":"Ballica",
    "wof:placetype":"locality"
},
  "geometry": {"coordinates":[46.72749,39.86918],"type":"Point"}
}