{
  "type": "Feature",
  "properties": {
    "gn:admin1_code":"59",
    "gn:asciiname":"Tyurkachi",
    "gn:country_code":"AZ",
    "gn:dem":10,
    "gn:feature_class":"P",
    "gn:feature_code":"PPL",
    "gn:name":"Tyurkachi",
    "gn:population":0,
    "gn:timezone":"Asia/Baku",
    "iso:country":"AZ",
    "name:azb_x_preferred":[
        "\u062a\u0648\u0631\u06a9\u0647\u200c\u0686\u06cc"
    ],
    "name:aze_x_preferred":[
        "T\u00fcrk\u0259\u00e7i"
    ],
    "name:ceb_x_preferred":[
        "Tyurkachi"
    ],
    "name:fas_x_preferred":[
        "\u062a\u0648\u0631\u06a9\u0686\u06cc"
    ],
    "name:ita_x_preferred":[
        "T\u00fcrk\u0259\u00e7i"
    ],
    "name:msa_x_preferred":[
        "T\u00fcrk\u0259\u00e7i"
    ],
    "name:swe_x_preferred":[
        "Tyurkachi"
    ],
    "name:und_x_variant":[
        "Tyuri-Gadzhi",
        "Tyurkachi",
        "T\u00fcrk\u0259\u00e7i"
    ],
    "wof:name":"Tyurkachi",
    "wof:placetype":"locality"
},
  "geometry": {"coordinates":[47.78078,40.47265],"type":"Point"}
}