{
  "type": "Feature",
  "properties": {
    "gn:admin1_code":"55",
    "gn:asciiname":"Koynashen",
    "gn:country_code":"AZ",
    "gn:dem":1549,
    "gn:feature_class":"P",
    "gn:feature_code":"PPL",
    "gn:name":"Koynashen",
    "gn:population":0,
    "gn:timezone":"Asia/Baku",
    "iso:country":"AZ",
    "name:aze_x_preferred":[
        "Kirov"
    ],
    "name:aze_x_variant":[
        "Qalad\u0259r\u0259si",
        "Ki\u00e7ik Qalad\u0259r\u0259si"
    ],
    "name:hye_x_preferred":[
        "\u0540\u056b\u0576\u0577\u0565\u0576"
    ],
    "name:rus_x_preferred":[
        "\u041a\u0438\u0440\u043e\u0432"
    ],
    "name:und_x_variant":[
        "Hinshen",
        "Koynashen"
    ],
    "wof:name":"Koynashen",
    "wof:placetype":"locality"
},
  "geometry": {"coordinates":[46.60734,39.63929],"type":"Point"}
}