{
  "type": "Feature",
  "properties": {
    "gn:admin1_code":"55",
    "gn:asciiname":"Koynashen",
    "gn:country_code":"AZ",
    "gn:dem":1549,
    "gn:feature_class":"P",
    "gn:feature_code":"PPL",
    "gn:name":"Koynashen",
    "gn:population":0,
    "gn:timezone":"Asia/Baku",
    "iso:country":"AZ",
    "name:azb_x_preferred":[
        "\u06a9\u06cc\u0631\u0648\u0648"
    ],
    "name:aze_x_preferred":[
        "Kirov"
    ],
    "name:aze_x_variant":[
        "Qalad\u0259r\u0259si",
        "Ki\u00e7ik Qalad\u0259r\u0259si"
    ],
    "name:bel_x_preferred":[
        "\u0425\u0456\u043d\u0448\u044d\u043d"
    ],
    "name:ceb_x_preferred":[
        "Koynashen"
    ],
    "name:fas_x_preferred":[
        "\u0647\u06cc\u0646\u0634\u0646"
    ],
    "name:fra_x_preferred":[
        "Hinshen"
    ],
    "name:hye_x_preferred":[
        "\u0540\u056b\u0576\u0577\u0565\u0576"
    ],
    "name:ita_x_preferred":[
        "Hinshen"
    ],
    "name:msa_x_preferred":[
        "Kirov"
    ],
    "name:rus_x_preferred":[
        "\u041a\u0438\u0440\u043e\u0432"
    ],
    "name:swe_x_preferred":[
        "Koynashen"
    ],
    "name:ukr_x_preferred":[
        "\u0425\u0456\u043d\u0448\u0435\u043d"
    ],
    "name:und_x_variant":[
        "Hinshen",
        "Koynashen"
    ],
    "wof:name":"Koynashen",
    "wof:placetype":"locality"
},
  "geometry": {"coordinates":[46.60734,39.63929],"type":"Point"}
}