{
  "type": "Feature",
  "properties": {
    "gn:admin1_code":"50",
    "gn:asciiname":"Kelakhany",
    "gn:country_code":"AZ",
    "gn:dem":650,
    "gn:feature_class":"P",
    "gn:feature_code":"PPL",
    "gn:name":"Kelakhany",
    "gn:population":0,
    "gn:timezone":"Asia/Baku",
    "iso:country":"AZ",
    "name:und_x_variant":[
        "Kelakhana",
        "Kelakhan",
        "K\u0259l\u0259xana"
    ],
    "wof:name":"Kelakhany",
    "wof:placetype":"locality"
},
  "geometry": {"coordinates":[48.60634,40.59085],"type":"Point"}
}