{
  "type": "Feature",
  "properties": {
    "gn:admin1_code":"50",
    "gn:asciiname":"Kelakhany",
    "gn:country_code":"AZ",
    "gn:dem":650,
    "gn:feature_class":"P",
    "gn:feature_code":"PPL",
    "gn:name":"Kelakhany",
    "gn:population":0,
    "gn:timezone":"Asia/Baku",
    "iso:country":"AZ",
    "name:azb_x_preferred":[
        "\u0634\u0647\u0631\u06cc\u0627\u0631"
    ],
    "name:aze_x_preferred":[
        "\u015e\u0259hriyar q\u0259s\u0259b\u0259si"
    ],
    "name:ceb_x_preferred":[
        "Kelakhany"
    ],
    "name:fas_x_preferred":[
        "\u0634\u0647\u0631\u06cc\u0627\u0631"
    ],
    "name:ita_x_preferred":[
        "\u015e\u0259hriyar"
    ],
    "name:kat_x_preferred":[
        "\u10e8\u10d0\u10f0\u10e0\u10d8\u10d0\u10e0\u10d8"
    ],
    "name:min_x_preferred":[
        "\u015e\u0259hriyar"
    ],
    "name:msa_x_preferred":[
        "\u015e\u0259hriyar"
    ],
    "name:swe_x_preferred":[
        "Kelakhany"
    ],
    "name:und_x_variant":[
        "Kelakhana",
        "Kelakhan",
        "K\u0259l\u0259xana"
    ],
    "wof:name":"Kelakhany",
    "wof:placetype":"locality"
},
  "geometry": {"coordinates":[48.60634,40.59085],"type":"Point"}
}