{
  "type": "Feature",
  "properties": {
    "gn:admin1_code":"17",
    "gn:asciiname":"Uqah",
    "gn:country_code":"AZ",
    "gn:dem":1123,
    "gn:feature_class":"P",
    "gn:feature_code":"PPL",
    "gn:name":"Uqah",
    "gn:population":0,
    "gn:timezone":"Asia/Baku",
    "iso:country":"AZ",
    "name:und_x_variant":[
        "Uchakh",
        "Ugakh",
        "Uga",
        "Uqah"
    ],
    "wof:name":"Uqah",
    "wof:placetype":"locality"
},
  "geometry": {"coordinates":[48.86073,41.08956],"type":"Point"}
}