{
  "type": "Feature",
  "properties": {
    "gn:admin1_code":"60",
    "gn:asciiname":"Mollaburhanli",
    "gn:country_code":"AZ",
    "gn:dem":175,
    "gn:feature_class":"P",
    "gn:feature_code":"PPL",
    "gn:name":"Mollab\u00fcrhanl\u0131",
    "gn:population":0,
    "gn:timezone":"Asia/Baku",
    "iso:country":"AZ",
    "name:aze_x_preferred":[
        "Mollab\u00fcrhanl\u0131"
    ],
    "name:ceb_x_preferred":[
        "Mollab\u00fcrhanl\u0131"
    ],
    "name:ita_x_preferred":[
        "Mollab\u00fcrhanl\u0131"
    ],
    "name:lez_x_preferred":[
        "\u041c\u043e\u043b\u043b\u0430\u0431\u0443\u044c\u0440\u0433\u044c\u0430\u043d\u043b\u044b"
    ],
    "name:msa_x_preferred":[
        "Mollab\u00fcrhanl\u0131"
    ],
    "name:swe_x_preferred":[
        "Mollab\u00fcrhanl\u0131"
    ],
    "name:und_x_variant":[
        "Mollaburkhanly",
        "Mollabyurkhanly"
    ],
    "wof:name":"Mollaburhanli",
    "wof:placetype":"locality"
},
  "geometry": {"coordinates":[48.71377,41.44642],"type":"Point"}
}