{
  "type": "Feature",
  "properties": {
    "gn:admin1_code":"70",
    "gn:asciiname":"Qimir",
    "gn:country_code":"AZ",
    "gn:dem":374,
    "gn:feature_class":"P",
    "gn:feature_code":"PPL",
    "gn:name":"Q\u0131m\u0131r",
    "gn:population":0,
    "gn:timezone":"Asia/Baku",
    "iso:country":"AZ",
    "name:und_x_variant":[
        "Kymyr",
        "Q\u0131m\u0131r"
    ],
    "wof:name":"Qimir",
    "wof:placetype":"locality"
},
  "geometry": {"coordinates":[46.67783,41.52926],"type":"Point"}
}