{
  "type": "Feature",
  "properties": {
    "gn:admin1_code":"70",
    "gn:asciiname":"Qimir",
    "gn:country_code":"AZ",
    "gn:dem":374,
    "gn:feature_class":"P",
    "gn:feature_code":"PPL",
    "gn:name":"Q\u0131m\u0131r",
    "gn:population":0,
    "gn:timezone":"Asia/Baku",
    "iso:country":"AZ",
    "name:ava_x_preferred":[
        "\u041aI\u0443\u043c\u0443\u0440"
    ],
    "name:aze_x_preferred":[
        "Q\u0131m\u0131r"
    ],
    "name:ita_x_preferred":[
        "Q\u0131m\u0131r"
    ],
    "name:kat_x_preferred":[
        "\u10e7\u10d8\u10db\u10d8\u10e0\u10d8"
    ],
    "name:msa_x_preferred":[
        "Q\u0131m\u0131r"
    ],
    "name:und_x_variant":[
        "Kymyr"
    ],
    "wof:name":"Qimir",
    "wof:placetype":"locality"
},
  "geometry": {"coordinates":[46.67783,41.52926],"type":"Point"}
}