{
  "type": "Feature",
  "properties": {
    "gn:admin1_code":"37",
    "gn:asciiname":"Top",
    "gn:country_code":"AZ",
    "gn:dem":401,
    "gn:feature_class":"P",
    "gn:feature_code":"PPL",
    "gn:name":"Top",
    "gn:population":0,
    "gn:timezone":"Asia/Baku",
    "iso:country":"AZ",
    "name:aze_x_preferred":[
        "Top"
    ],
    "wof:name":"Top",
    "wof:placetype":"locality"
},
  "geometry": {"coordinates":[47.42678,40.9407],"type":"Point"}
}