{
  "type": "Feature",
  "properties": {
    "gn:admin1_code":"67",
    "gn:asciiname":"Khuruushagy",
    "gn:country_code":"AZ",
    "gn:dem":27,
    "gn:feature_class":"P",
    "gn:feature_code":"PPL",
    "gn:name":"Khuruushagy",
    "gn:population":0,
    "gn:timezone":"Asia/Baku",
    "iso:country":"AZ",
    "name:azb_x_preferred":[
        "\u0647\u0648\u0631\u0648 \u0627\u0648\u0634\u0627\u063a\u06cc"
    ],
    "name:aze_x_preferred":[
        "H\u00fcr\u00fcu\u015fa\u011f\u0131"
    ],
    "name:ceb_x_preferred":[
        "Khuruushagy"
    ],
    "name:ita_x_preferred":[
        "H\u00fcr\u00fcu\u015fa\u011f\u0131"
    ],
    "name:kat_x_preferred":[
        "\u10f0\u10d8\u10e3\u10e0\u10d8\u10e3\u10e3\u10e8\u10d0\u10e6\u10d8"
    ],
    "name:msa_x_preferred":[
        "H\u00fcr\u00fcu\u015fa\u011f\u0131"
    ],
    "name:swe_x_preferred":[
        "Khuruushagy"
    ],
    "name:und_x_variant":[
        "Guruushagy",
        "Khuruushagy",
        "H\u00fcr\u00fcu\u015fa\u011f\u0131",
        "Gyuryuushagy"
    ],
    "wof:name":"Khuruushagy",
    "wof:placetype":"locality"
},
  "geometry": {"coordinates":[47.0206,40.72044],"type":"Point"}
}