{
  "type": "Feature",
  "properties": {
    "gn:admin1_code":"36",
    "gn:asciiname":"Dortlyar",
    "gn:country_code":"AZ",
    "gn:dem":-26,
    "gn:feature_class":"P",
    "gn:feature_code":"PPL",
    "gn:name":"Dortlyar",
    "gn:population":0,
    "gn:timezone":"Asia/Baku",
    "iso:country":"AZ",
    "name:aze_x_preferred":[
        "D\u00f6rdl\u0259r"
    ],
    "name:und_x_variant":[
        "Dortlar",
        "Dortlyar"
    ],
    "wof:name":"Dortlyar",
    "wof:placetype":"locality"
},
  "geometry": {"coordinates":[49.08346,39.43019],"type":"Point"}
}