{
  "type": "Feature",
  "properties": {
    "gn:admin1_code":"18",
    "gn:asciiname":"Dortcinar",
    "gn:country_code":"AZ",
    "gn:dem":290,
    "gn:feature_class":"P",
    "gn:feature_code":"PPL",
    "gn:name":"D\u00f6rt\u00e7inar",
    "gn:population":0,
    "gn:timezone":"Asia/Baku",
    "iso:country":"AZ",
    "name:aze_x_preferred":[
        "D\u00f6rt\u00e7inar"
    ],
    "name:aze_x_variant":[
        "D\u00f6rd\u00e7inar"
    ],
    "name:hye_x_preferred":[
        "\u0534\u0578\u0580\u0569\u0579\u056b\u0576\u0561\u0580"
    ],
    "name:hye_x_variant":[
        "Dort\u2019chinar"
    ],
    "name:rus_x_preferred":[
        "\u0414\u043e\u0440\u0442\u0447\u0438\u043d\u0430\u0440"
    ],
    "name:und_x_variant":[
        "Dortchinar",
        "\u0414\u043e\u0440\u0442\u0447\u0438\u043d\u0430\u0440"
    ],
    "wof:name":"Dortcinar",
    "wof:placetype":"locality"
},
  "geometry": {"coordinates":[47.21254,39.46214000000001],"type":"Point"}
}