{
  "type": "Feature",
  "properties": {
    "gn:admin1_code":"18",
    "gn:asciiname":"Qorqan",
    "gn:country_code":"AZ",
    "gn:dem":276,
    "gn:feature_class":"P",
    "gn:feature_code":"PPL",
    "gn:name":"Qorqan",
    "gn:population":0,
    "gn:timezone":"Asia/Baku",
    "iso:country":"AZ",
    "name:aze_x_preferred":[
        "Qorqan"
    ],
    "name:hye_x_preferred":[
        "Korghan"
    ],
    "name:hye_x_variant":[
        "\u053f\u0578\u0580\u0572\u0561\u0576"
    ],
    "name:rus_x_preferred":[
        "\u041a\u043e\u0440\u0433\u0430\u043d"
    ],
    "name:und_x_variant":[
        "Korgan",
        "\u041a\u043e\u0440\u0433\u0430\u043d"
    ],
    "wof:name":"Qorqan",
    "wof:placetype":"locality"
},
  "geometry": {"coordinates":[47.28313,39.56081],"type":"Point"}
}