{
  "type": "Feature",
  "properties": {
    "iso:country":"AZ",
    "name:aze_x_preferred":[
        "Ba\u011fbanlar"
    ],
    "name:unk_x_variant":[
        "Bagmanlyar"
    ],
    "qs:gn_country":"AZ",
    "qs:gn_fcode":"PPLX",
    "qs:gn_pop":0,
    "qs:name":"Bagbanlar",
    "qs:name_adm0":"Azerbaijan",
    "qs:name_adm1":"Ganca",
    "qs:photos":1,
    "qs:photos_1k":1,
    "qs:photos_9k":1,
    "qs:photos_9r":1,
    "qs:photos_all":1,
    "qs:photos_sr":1,
    "qs:placetype":"Suburb",
    "qs:pop_sr":"0",
    "qs:woe_adm0":23424741,
    "wd:wordcount":13,
    "wof:name":"Bagbanlar",
    "wof:placetype":"neighbourhood"
},
  "geometry": {"coordinates":[46.31667,40.65],"type":"Point"}
}