{
  "type": "Feature",
  "properties": {
    "gn:admin1_code":"21",
    "gn:asciiname":"Tap",
    "gn:country_code":"AZ",
    "gn:dem":502,
    "gn:feature_class":"P",
    "gn:feature_code":"PPL",
    "gn:name":"Tap",
    "gn:population":0,
    "gn:timezone":"Asia/Baku",
    "iso:country":"AZ",
    "name:aze_x_preferred":[
        "Tap"
    ],
    "name:cat_x_preferred":[
        "Tap"
    ],
    "name:ceb_x_preferred":[
        "Tap"
    ],
    "name:dan_x_preferred":[
        "Tap"
    ],
    "name:deu_x_preferred":[
        "Tap"
    ],
    "name:kat_x_preferred":[
        "\u10d7\u10d0\u10e4\u10d8"
    ],
    "name:nld_x_preferred":[
        "Tap"
    ],
    "name:pol_x_preferred":[
        "Tap"
    ],
    "name:por_x_preferred":[
        "Tap"
    ],
    "name:rus_x_preferred":[
        "\u0422\u0430\u043f"
    ],
    "name:swe_x_preferred":[
        "Tap"
    ],
    "wof:name":"Tap",
    "wof:placetype":"locality"
},
  "geometry": {"coordinates":[46.77849000000001,40.42377000000001],"type":"Point"}
}