{
  "type": "Feature",
  "properties": {
    "gn:admin1_code":"31",
    "gn:asciiname":"Khalifa",
    "gn:country_code":"AZ",
    "gn:dem":1742,
    "gn:feature_class":"P",
    "gn:feature_code":"PPL",
    "gn:name":"Khalifa",
    "gn:population":0,
    "gn:timezone":"Asia/Baku",
    "iso:country":"AZ",
    "name:und_x_variant":[
        "Khalfalikend",
        "X\u0259lf\u0259lik\u0259nd"
    ],
    "wof:name":"Khalifa",
    "wof:placetype":"locality"
},
  "geometry": {"coordinates":[48.41728,38.65223],"type":"Point"}
}