{
  "type": "Feature",
  "properties": {
    "gn:admin1_code":"17",
    "gn:asciiname":"Nizhniye Kushchi",
    "gn:country_code":"AZ",
    "gn:dem":-14,
    "gn:feature_class":"P",
    "gn:feature_code":"PPL",
    "gn:name":"Nizhniye Kushchi",
    "gn:population":0,
    "gn:timezone":"Asia/Baku",
    "iso:country":"AZ",
    "name:aze_x_preferred":[
        "\u00c7\u00f6l Qu\u015f\u00e7u"
    ],
    "name:eng_x_preferred":[
        "\u00c7\u00f6l Qu\u015f\u00e7u"
    ],
    "name:rus_x_preferred":[
        "\u0427\u0435\u043b\u044c \u041a\u0443\u0448\u0447\u0443"
    ],
    "name:und_x_variant":[
        "Cholkushchi",
        "Cholkushchu",
        "Ch\u00ebl\u2019 Kushchu"
    ],
    "wof:name":"Nizhniye Kushchi",
    "wof:placetype":"locality"
},
  "geometry": {"coordinates":[49.00653,41.33525],"type":"Point"}
}