{
  "type": "Feature",
  "properties": {
    "gn:admin1_code":"29",
    "gn:asciiname":"Istisu",
    "gn:country_code":"AZ",
    "gn:dem":9,
    "gn:feature_class":"P",
    "gn:feature_code":"PPL",
    "gn:name":"\u0130stisu",
    "gn:population":0,
    "gn:timezone":"Asia/Baku",
    "iso:country":"AZ",
    "name:aze_x_preferred":[
        "\u0130stisu"
    ],
    "name:und_x_variant":[
        "Khibinogorsk",
        "Kirovsk",
        "Kirov"
    ],
    "wof:name":"Istisu",
    "wof:placetype":"locality"
},
  "geometry": {"coordinates":[48.73597,38.79403],"type":"Point"}
}