{
  "type": "Feature",
  "properties": {
    "gn:admin1_code":"46",
    "gn:asciiname":"Qalagayin",
    "gn:country_code":"AZ",
    "gn:dem":-12,
    "gn:feature_class":"P",
    "gn:feature_code":"PPL",
    "gn:name":"Qala\u011fay\u0131n",
    "gn:population":0,
    "gn:timezone":"Asia/Baku",
    "iso:country":"AZ",
    "name:und_x_variant":[
        "Kalagayny",
        "Kalagain",
        "Qala\u011fay\u0131n"
    ],
    "wof:name":"Qalagayin",
    "wof:placetype":"locality"
},
  "geometry": {"coordinates":[48.47962,39.98119000000001],"type":"Point"}
}