{
  "type": "Feature",
  "properties": {
    "iso:country":"AZ",
    "name:bxr_x_preferred":[
        "\u0410\u0441\u0442\u0430\u0440\u0430"
    ],
    "name:che_x_preferred":[
        "\u0410\u0441\u0442\u0430\u0440\u0430"
    ],
    "name:fas_x_preferred":[
        "\u0622\u0633\u062a\u0627\u0631\u0627"
    ],
    "name:hye_x_preferred":[
        "\u0531\u057d\u057f\u0561\u0580\u0561"
    ],
    "name:kat_x_preferred":[
        "\u10d0\u10e1\u10e2\u10d0\u10e0\u10d0"
    ],
    "name:kor_x_preferred":[
        "\uc544\uc2a4\ud0c0\ub77c"
    ],
    "name:mon_x_preferred":[
        "\u0410\u0441\u0442\u0430\u0440\u0430"
    ],
    "name:rus_x_preferred":[
        "\u0410\u0441\u0442\u0430\u0440\u0430"
    ],
    "name:ukr_x_preferred":[
        "\u0410\u0441\u0442\u0430\u0440\u0430"
    ],
    "name:unk_x_variant":[
        "Azerbaydzhanskaya Astara"
    ],
    "name:urd_x_preferred":[
        "\u0622\u0633\u062a\u0627\u0631\u0627"
    ],
    "name:zho_x_preferred":[
        "\u963f\u65af\u5854\u62c9"
    ],
    "qs:gn_country":"AZ",
    "qs:gn_fcode":"PPLA",
    "qs:gn_pop":15190,
    "qs:name":"Astara",
    "qs:name_adm0":"Azerbaijan",
    "qs:name_adm1":"Astara",
    "qs:photos":0,
    "qs:photos_1k":0,
    "qs:photos_9k":1,
    "qs:photos_9r":1,
    "qs:photos_all":3,
    "qs:photos_sr":0,
    "qs:placetype":"Town",
    "qs:pop_sr":"6",
    "qs:woe_adm0":23424741,
    "wof:name":"Astara",
    "wof:placetype":"locality",
    "wof:population":15190
},
  "geometry": {"coordinates":[48.87498,38.45598],"type":"Point"}
}