{
  "type": "Feature",
  "properties": {
    "iso:country":"AZ",
    "name:ara_x_preferred":[
        "\u0622\u0633\u062a\u0627\u0631\u0627"
    ],
    "name:azb_x_preferred":[
        "\u0622\u0633\u062a\u0627\u0631\u0627"
    ],
    "name:aze_x_preferred":[
        "Astara"
    ],
    "name:bel_x_preferred":[
        "\u0410\u0441\u0442\u0430\u0440\u0430"
    ],
    "name:bxr_x_preferred":[
        "\u0410\u0441\u0442\u0430\u0440\u0430"
    ],
    "name:cat_x_preferred":[
        "Astara"
    ],
    "name:ceb_x_preferred":[
        "Astara"
    ],
    "name:ces_x_preferred":[
        "Astara"
    ],
    "name:che_x_preferred":[
        "\u0410\u0441\u0442\u0430\u0440\u0430"
    ],
    "name:deu_x_preferred":[
        "Astara"
    ],
    "name:eng_x_preferred":[
        "Astara"
    ],
    "name:epo_x_preferred":[
        "Astara"
    ],
    "name:est_x_preferred":[
        "Astara"
    ],
    "name:fas_x_preferred":[
        "\u0622\u0633\u062a\u0627\u0631\u0627"
    ],
    "name:fas_x_variant":[
        "\u0634\u0647\u0631 \u0622\u0633\u062a\u0627\u0631\u0627"
    ],
    "name:fin_x_preferred":[
        "Astara"
    ],
    "name:fra_x_preferred":[
        "Astara"
    ],
    "name:heb_x_preferred":[
        "\u05d0\u05e1\u05ea\u05d0\u05e8\u05d0"
    ],
    "name:hsb_x_preferred":[
        "Astara"
    ],
    "name:hye_x_preferred":[
        "\u0531\u057d\u057f\u0561\u0580\u0561"
    ],
    "name:ind_x_preferred":[
        "Astara"
    ],
    "name:isl_x_preferred":[
        "Astara"
    ],
    "name:ita_x_preferred":[
        "Astara"
    ],
    "name:jpn_x_preferred":[
        "\u30a2\u30b9\u30bf\u30e9"
    ],
    "name:kat_x_preferred":[
        "\u10d0\u10e1\u10e2\u10d0\u10e0\u10d0"
    ],
    "name:kor_x_preferred":[
        "\uc544\uc2a4\ud0c0\ub77c"
    ],
    "name:kur_x_preferred":[
        "Astara"
    ],
    "name:lit_x_preferred":[
        "Astara"
    ],
    "name:mon_x_preferred":[
        "\u0410\u0441\u0442\u0430\u0440\u0430"
    ],
    "name:msa_x_preferred":[
        "Astara"
    ],
    "name:nld_x_preferred":[
        "Astara"
    ],
    "name:pol_x_preferred":[
        "Astara"
    ],
    "name:ron_x_preferred":[
        "Astara"
    ],
    "name:rus_x_preferred":[
        "\u0410\u0441\u0442\u0430\u0440\u0430"
    ],
    "name:sco_x_preferred":[
        "Astara"
    ],
    "name:spa_x_preferred":[
        "Astara"
    ],
    "name:swe_x_preferred":[
        "Astara"
    ],
    "name:tat_x_preferred":[
        "\u0410\u0441\u0442\u0430\u0440\u0430"
    ],
    "name:tur_x_preferred":[
        "Astara"
    ],
    "name:ukr_x_preferred":[
        "\u0410\u0441\u0442\u0430\u0440\u0430"
    ],
    "name:unk_x_variant":[
        "Azerbaydzhanskaya Astara"
    ],
    "name:urd_x_preferred":[
        "\u0622\u0633\u062a\u0627\u0631\u0627"
    ],
    "name:uzb_x_preferred":[
        "Astara"
    ],
    "name:zho_x_preferred":[
        "\u963f\u65af\u5854\u62c9"
    ],
    "qs:gn_country":"AZ",
    "qs:gn_fcode":"PPLA",
    "qs:gn_pop":15190,
    "qs:name":"Astara",
    "qs:name_adm0":"Azerbaijan",
    "qs:name_adm1":"Astara",
    "qs:photos":0,
    "qs:photos_1k":0,
    "qs:photos_9k":1,
    "qs:photos_9r":1,
    "qs:photos_all":3,
    "qs:photos_sr":0,
    "qs:placetype":"Town",
    "qs:pop_sr":"6",
    "qs:woe_adm0":23424741,
    "wof:name":"Astara",
    "wof:placetype":"locality",
    "wof:population":15190
},
  "geometry": {"coordinates":[48.87498,38.45598],"type":"Point"}
}