{
  "type": "Feature",
  "properties": {
    "gn:admin1_code":"06",
    "gn:asciiname":"Talis",
    "gn:country_code":"AZ",
    "gn:dem":802,
    "gn:feature_class":"P",
    "gn:feature_code":"PPL",
    "gn:name":"Tal\u0131\u015f",
    "gn:population":0,
    "gn:timezone":"Asia/Baku",
    "iso:country":"AZ",
    "name:fra_x_preferred":[
        "Talis"
    ],
    "name:lit_x_preferred":[
        "Talis"
    ],
    "name:und_x_variant":[
        "Talysh",
        "Tal\u0131\u015f"
    ],
    "wof:name":"Talis",
    "wof:placetype":"locality"
},
  "geometry": {"coordinates":[48.43546,40.6073],"type":"Point"}
}