{
  "type": "Feature",
  "properties": {
    "gn:admin1_code":"06",
    "gn:asciiname":"Tazanovdzhi",
    "gn:country_code":"AZ",
    "gn:dem":46,
    "gn:feature_class":"P",
    "gn:feature_code":"PPL",
    "gn:name":"Tazanovdzhi",
    "gn:population":0,
    "gn:timezone":"Asia/Baku",
    "iso:country":"AZ",
    "name:ita_x_preferred":[
        "Tazanovdzhi"
    ],
    "name:kat_x_preferred":[
        "\u10d7\u10d0\u10d6\u10d0\u10dc\u10dd\u10d5\u10ef\u10d8"
    ],
    "name:msa_x_preferred":[
        "Tazanovdzhi"
    ],
    "wof:name":"Tazanovdzhi",
    "wof:placetype":"locality"
},
  "geometry": {"coordinates":[48.25417,40.49194],"type":"Point"}
}