{
  "type": "Feature",
  "properties": {
    "gn:admin1_code":"69",
    "gn:asciiname":"Ichari Mushlan",
    "gn:country_code":"AZ",
    "gn:dem":381,
    "gn:feature_class":"P",
    "gn:feature_code":"PPL",
    "gn:name":"Ichari Mushlan",
    "gn:population":0,
    "gn:timezone":"Asia/Baku",
    "iso:country":"AZ",
    "name:azb_x_preferred":[
        "\u0627\u06cc\u0686\u0631\u06cc \u0645\u0648\u0634\u0644\u0627\u0646"
    ],
    "name:aze_x_preferred":[
        "\u0130\u00e7\u0259ri M\u00fc\u015flan"
    ],
    "name:kat_x_preferred":[
        "\u10d8\u10e9\u10d0\u10e0\u10d8-\u10db\u10e3\u10e8\u10da\u10d0\u10dc\u10d8"
    ],
    "name:msa_x_preferred":[
        "\u0130\u00e7\u0259ri M\u00fc\u015flan"
    ],
    "name:rus_x_preferred":[
        "\u0418\u0447\u0430\u0440\u0438 \u041c\u0443\u0448\u043b\u0430\u043d"
    ],
    "name:und_x_variant":[
        "\u0130\u00e7\u0259ri Mu\u015flan"
    ],
    "wof:name":"Ichari Mushlan",
    "wof:placetype":"locality"
},
  "geometry": {"coordinates":[46.69998,39.07274],"type":"Point"}
}