{
  "type": "Feature",
  "properties": {
    "gn:admin1_code":"31",
    "gn:asciiname":"Conu",
    "gn:country_code":"AZ",
    "gn:dem":1365,
    "gn:feature_class":"P",
    "gn:feature_code":"PPL",
    "gn:name":"Conu",
    "gn:population":0,
    "gn:timezone":"Asia/Baku",
    "iso:country":"AZ",
    "name:aze_x_preferred":[
        "Conu"
    ],
    "name:ceb_x_preferred":[
        "Conu"
    ],
    "name:ita_x_preferred":[
        "Conu"
    ],
    "name:msa_x_preferred":[
        "Conu"
    ],
    "name:swe_x_preferred":[
        "Conu"
    ],
    "name:und_x_variant":[
        "Dzhoni",
        "Coni"
    ],
    "wof:name":"Conu",
    "wof:placetype":"locality"
},
  "geometry": {"coordinates":[48.50773,38.61661],"type":"Point"}
}