{
  "type": "Feature",
  "properties": {
    "gn:admin1_code":"70",
    "gn:asciiname":"Ali-Bayramly",
    "gn:country_code":"AZ",
    "gn:dem":236,
    "gn:feature_class":"P",
    "gn:feature_code":"PPL",
    "gn:name":"Ali-Bayramly",
    "gn:population":0,
    "gn:timezone":"Asia/Baku",
    "iso:country":"AZ",
    "name:und_x_variant":[
        "\u018fli Bayraml\u0131"
    ],
    "wof:name":"Ali-Bayramly",
    "wof:placetype":"locality"
},
  "geometry": {"coordinates":[46.53168,41.52414],"type":"Point"}
}