{
  "type": "Feature",
  "properties": {
    "gn:admin1_code":"06",
    "gn:asciiname":"Novdzhu",
    "gn:country_code":"AZ",
    "gn:dem":77,
    "gn:feature_class":"P",
    "gn:feature_code":"PPL",
    "gn:name":"Novdzhu",
    "gn:population":0,
    "gn:timezone":"Asia/Baku",
    "iso:country":"AZ",
    "name:eng_x_preferred":[
        "N\u00f6vc\u00fc"
    ],
    "name:rus_x_preferred":[
        "\u041d\u0435\u0432\u0434\u0436\u0443"
    ],
    "name:rus_x_variant":[
        "N\u00ebvdzhu"
    ],
    "name:und_x_variant":[
        "N\u00f6vc\u00fc"
    ],
    "wof:name":"Novdzhu",
    "wof:placetype":"locality"
},
  "geometry": {"coordinates":[48.25948,40.51874],"type":"Point"}
}