{
  "type": "Feature",
  "properties": {
    "gn:admin1_code":"03",
    "gn:asciiname":"Xindiristan",
    "gn:country_code":"AZ",
    "gn:dem":145,
    "gn:feature_class":"P",
    "gn:feature_code":"PPL",
    "gn:name":"X\u0131nd\u0131r\u0131stan",
    "gn:population":0,
    "gn:timezone":"Asia/Baku",
    "iso:country":"AZ",
    "name:azb_x_preferred":[
        "\u062e\u06cc\u0646\u062f\u06cc\u0631\u06cc\u0633\u062a\u0627\u0646"
    ],
    "name:aze_x_preferred":[
        "X\u0131nd\u0131r\u0131stan"
    ],
    "name:ceb_x_preferred":[
        "X\u0131nd\u0131r\u0131stan"
    ],
    "name:ell_x_preferred":[
        "\u03a7\u03b9\u03bd\u03c4\u03b9\u03c1\u03b9\u03c3\u03c4\u03ac\u03bd"
    ],
    "name:eng_x_preferred":[
        "X\u0131nd\u0131r\u0131stan"
    ],
    "name:fas_x_preferred":[
        "\u062e\u0646\u062f\u0631\u0633\u062a\u0627\u0646"
    ],
    "name:kat_x_preferred":[
        "\u10ee\u10d8\u10dc\u10d3\u10d8\u10e0\u10d8\u10e1\u10d7\u10d0\u10dc\u10d8"
    ],
    "name:min_x_preferred":[
        "X\u0131nd\u0131r\u0131stan"
    ],
    "name:msa_x_preferred":[
        "X\u0131nd\u0131r\u0131stan"
    ],
    "name:rus_x_preferred":[
        "\u0425\u044b\u043d\u0434\u0440\u044b\u0441\u0442\u0430\u043d"
    ],
    "name:swe_x_preferred":[
        "X\u0131nd\u0131r\u0131stan"
    ],
    "name:und_x_variant":[
        "Khykdrystan",
        "X\u0131nd\u0131r\u0131star",
        "Khindristan",
        "Khyndrystan",
        "Khyndyrystan"
    ],
    "wof:name":"Xindiristan",
    "wof:placetype":"locality"
},
  "geometry": {"coordinates":[47.10258,40.12501],"type":"Point"}
}