{
  "type": "Feature",
  "properties": {
    "gn:admin1_code":"03",
    "gn:asciiname":"Xindiristan",
    "gn:country_code":"AZ",
    "gn:dem":145,
    "gn:feature_class":"P",
    "gn:feature_code":"PPL",
    "gn:name":"X\u0131nd\u0131r\u0131stan",
    "gn:population":0,
    "gn:timezone":"Asia/Baku",
    "iso:country":"AZ",
    "name:aze_x_preferred":[
        "X\u0131nd\u0131r\u0131stan"
    ],
    "name:eng_x_preferred":[
        "X\u0131nd\u0131r\u0131stan"
    ],
    "name:rus_x_preferred":[
        "\u0425\u044b\u043d\u0434\u0440\u044b\u0441\u0442\u0430\u043d"
    ],
    "name:und_x_variant":[
        "Khykdrystan",
        "X\u0131nd\u0131r\u0131star",
        "Khindristan",
        "Khyndrystan",
        "Khyndyrystan"
    ],
    "wof:name":"Xindiristan",
    "wof:placetype":"locality"
},
  "geometry": {"coordinates":[47.10258,40.12501],"type":"Point"}
}