{
  "type": "Feature",
  "properties": {
    "gn:admin1_code":"25",
    "gn:asciiname":"Burovdal",
    "gn:country_code":"AZ",
    "gn:dem":1634,
    "gn:feature_class":"P",
    "gn:feature_code":"PPL",
    "gn:name":"Burovdal",
    "gn:population":0,
    "gn:timezone":"Asia/Baku",
    "iso:country":"AZ",
    "name:aze_x_preferred":[
        "Burovdal"
    ],
    "name:ceb_x_preferred":[
        "Burovdal"
    ],
    "name:eng_x_preferred":[
        "Burovdal"
    ],
    "name:ita_x_preferred":[
        "Burovdal"
    ],
    "name:kat_x_preferred":[
        "\u10d1\u10e3\u10e0\u10dd\u10d5\u10d3\u10d0\u10da\u10d8"
    ],
    "name:lez_x_preferred":[
        "\u0411\u0443\u0440\u043e\u0432\u0434\u0430\u043b"
    ],
    "name:msa_x_preferred":[
        "Burovdal"
    ],
    "name:rus_x_preferred":[
        "\u0411\u0443\u0440\u043e\u0432\u0434\u0430\u043b"
    ],
    "name:swe_x_preferred":[
        "Burovdal"
    ],
    "name:und_x_variant":[
        "Bruydal",
        "Buravdal"
    ],
    "wof:name":"Burovdal",
    "wof:placetype":"locality"
},
  "geometry": {"coordinates":[48.37072,40.94076],"type":"Point"}
}