{
  "type": "Feature",
  "properties": {
    "gn:admin1_code":"17",
    "gn:asciiname":"Aygyunli",
    "gn:country_code":"AZ",
    "gn:dem":76,
    "gn:feature_class":"P",
    "gn:feature_code":"PPL",
    "gn:name":"Aygyunli",
    "gn:population":0,
    "gn:timezone":"Asia/Baku",
    "iso:country":"AZ",
    "name:und_x_variant":[
        "Ayg\u00fcnl\u00fc"
    ],
    "wof:name":"Aygyunli",
    "wof:placetype":"locality"
},
  "geometry": {"coordinates":[48.85622,41.29831],"type":"Point"}
}