{
  "type": "Feature",
  "properties": {
    "gn:admin1_code":"17",
    "gn:asciiname":"Aygyunli",
    "gn:country_code":"AZ",
    "gn:dem":76,
    "gn:feature_class":"P",
    "gn:feature_code":"PPL",
    "gn:name":"Aygyunli",
    "gn:population":0,
    "gn:timezone":"Asia/Baku",
    "iso:country":"AZ",
    "name:azb_x_preferred":[
        "\u0622\u06cc \u06af\u0648\u0646\u200c\u0644\u0648"
    ],
    "name:aze_x_preferred":[
        "Ayg\u00fcnl\u00fc"
    ],
    "name:ceb_x_preferred":[
        "Aygyunli"
    ],
    "name:ita_x_preferred":[
        "Ayg\u00fcnl\u00fc"
    ],
    "name:msa_x_preferred":[
        "Ayg\u00fcnl\u00fc"
    ],
    "name:swe_x_preferred":[
        "Aygyunli"
    ],
    "wof:name":"Aygyunli",
    "wof:placetype":"locality"
},
  "geometry": {"coordinates":[48.85622,41.29831],"type":"Point"}
}