{
  "type": "Feature",
  "properties": {
    "gn:admin1_code":"18",
    "gn:asciiname":"Qobu Dilagarda",
    "gn:country_code":"AZ",
    "gn:dem":273,
    "gn:feature_class":"P",
    "gn:feature_code":"PPL",
    "gn:name":"Qobu Dila\u011farda",
    "gn:population":0,
    "gn:timezone":"Asia/Baku",
    "iso:country":"AZ",
    "name:aze_x_preferred":[
        "Qobu Dila\u011farda"
    ],
    "name:hye_x_preferred":[
        "\u053f\u0578\u0562\u0578\u0582 \u0534\u056b\u056c\u0561\u0563\u0561\u0580\u0564\u0561"
    ],
    "name:rus_x_preferred":[
        "\u041a\u043e\u0431\u0443-\u0414\u0438\u043b\u0430\u0433\u0430\u0440\u0434\u0430"
    ],
    "name:und_x_variant":[
        "Kobu-Dilagarda",
        "\u041a\u043e\u0431\u0443-\u0414\u0438\u043b\u0430\u0433\u0430\u0440\u0434\u0430"
    ],
    "wof:name":"Qobu Dilagarda",
    "wof:placetype":"locality"
},
  "geometry": {"coordinates":[47.17838,39.68153],"type":"Point"}
}