{
  "type": "Feature",
  "properties": {
    "gn:admin1_code":"55",
    "gn:asciiname":"Yengibar",
    "gn:country_code":"AZ",
    "gn:dem":1335,
    "gn:feature_class":"P",
    "gn:feature_code":"PPL",
    "gn:name":"Yengibar",
    "gn:population":0,
    "gn:timezone":"Asia/Baku",
    "iso:country":"AZ",
    "name:aze_x_preferred":[
        "Yengibar"
    ],
    "name:hye_x_preferred":[
        "Kanach\u2019 T\u2019ala"
    ],
    "name:hye_x_variant":[
        "\u053f\u0561\u0576\u0561\u0579 \u0539\u0561\u056c\u0561"
    ],
    "name:rus_x_preferred":[
        "\u0415\u043d\u0433\u0438\u0432\u0430\u0440"
    ],
    "name:und_x_variant":[
        "Yengivar"
    ],
    "wof:name":"Yengibar",
    "wof:placetype":"locality"
},
  "geometry": {"coordinates":[46.60489000000001,39.67472],"type":"Point"}
}