{
  "type": "Feature",
  "properties": {
    "gn:admin1_code":"42",
    "gn:asciiname":"Vladimirovka",
    "gn:country_code":"AZ",
    "gn:dem":486,
    "gn:feature_class":"P",
    "gn:feature_code":"PPL",
    "gn:name":"Vladimirovka",
    "gn:population":0,
    "gn:timezone":"Asia/Baku",
    "iso:country":"AZ",
    "wof:name":"Vladimirovka",
    "wof:placetype":"locality"
},
  "geometry": {"coordinates":[48.54826,41.39829],"type":"Point"}
}