{
  "type": "Feature",
  "properties": {
    "gn:admin1_code":"42",
    "gn:asciiname":"Vladimirovka",
    "gn:country_code":"AZ",
    "gn:dem":486,
    "gn:feature_class":"P",
    "gn:feature_code":"PPL",
    "gn:name":"Vladimirovka",
    "gn:population":0,
    "gn:timezone":"Asia/Baku",
    "iso:country":"AZ",
    "name:azb_x_preferred":[
        "\u0648\u0644\u0627\u062f\u06cc\u0645\u06cc\u0631\u0648\u0648\u06a9\u0627"
    ],
    "name:aze_x_preferred":[
        "Vladimirovka"
    ],
    "name:ceb_x_preferred":[
        "Vladimirovka"
    ],
    "name:ell_x_preferred":[
        "\u0392\u03bb\u03b1\u03bd\u03c4\u03b9\u03bc\u03b9\u03c1\u03cc\u03b2\u03ba\u03b1"
    ],
    "name:ita_x_preferred":[
        "Vladimirovka"
    ],
    "name:msa_x_preferred":[
        "Vladimirovka"
    ],
    "wof:name":"Vladimirovka",
    "wof:placetype":"locality"
},
  "geometry": {"coordinates":[48.54826,41.39829],"type":"Point"}
}