{
  "type": "Feature",
  "properties": {
    "gn:admin1_code":"66",
    "gn:asciiname":"Arvana",
    "gn:country_code":"AZ",
    "gn:dem":1758,
    "gn:feature_class":"P",
    "gn:feature_code":"PPL",
    "gn:name":"Arvana",
    "gn:population":0,
    "gn:timezone":"Asia/Baku",
    "iso:country":"AZ",
    "name:azb_x_preferred":[
        "\u0622\u0631\u0648\u0627\u0646\u0627"
    ],
    "name:aze_x_preferred":[
        "Arvana"
    ],
    "name:ceb_x_preferred":[
        "Arvana"
    ],
    "name:fas_x_preferred":[
        "\u0627\u0631\u0648\u0627\u0646\u0647"
    ],
    "name:ita_x_preferred":[
        "Arvana"
    ],
    "name:kat_x_preferred":[
        "\u10d0\u10e0\u10d5\u10d0\u10dc\u10d0"
    ],
    "name:msa_x_preferred":[
        "Arvana"
    ],
    "name:sqi_x_preferred":[
        "Arvana"
    ],
    "name:swe_x_preferred":[
        "Arvana"
    ],
    "name:tur_x_preferred":[
        "Arvana"
    ],
    "wof:name":"Arvana",
    "wof:placetype":"locality"
},
  "geometry": {"coordinates":[48.12042,38.82813],"type":"Point"}
}