{
  "type": "Feature",
  "properties": {
    "gn:admin1_code":"64",
    "gn:asciiname":"Signaq",
    "gn:country_code":"AZ",
    "gn:dem":1302,
    "gn:feature_class":"P",
    "gn:feature_code":"PPL",
    "gn:name":"S\u0131\u011fnaq",
    "gn:population":0,
    "gn:timezone":"Asia/Baku",
    "iso:country":"AZ",
    "name:azb_x_preferred":[
        "\u0633\u06cc\u063a\u0646\u0627\u062e"
    ],
    "name:aze_x_preferred":[
        "Si\u011fnax"
    ],
    "name:aze_x_variant":[
        "S\u0131\u011fnaq",
        "S\u0131\u011fnax"
    ],
    "name:bel_x_preferred":[
        "\u0421\u0445\u043d\u0430\u0445"
    ],
    "name:ceb_x_preferred":[
        "Si\u011fnax"
    ],
    "name:fra_x_preferred":[
        "Skhnakh"
    ],
    "name:hye_x_preferred":[
        "\u054d\u0572\u0576\u0561\u056d"
    ],
    "name:hye_x_variant":[
        "Sghnakh"
    ],
    "name:ita_x_preferred":[
        "Sghnakh"
    ],
    "name:msa_x_preferred":[
        "S\u0131\u011fnax"
    ],
    "name:rus_x_preferred":[
        "\u0421\u0438\u0433\u043d\u0430\u0445"
    ],
    "name:swe_x_preferred":[
        "Si\u011fnax"
    ],
    "name:ukr_x_preferred":[
        "\u0421\u0445\u043d\u0430\u0445"
    ],
    "name:und_x_variant":[
        "Sghnakh",
        "Sygnakh",
        "Signakh"
    ],
    "wof:name":"Signaq",
    "wof:placetype":"locality"
},
  "geometry": {"coordinates":[46.80022,39.72284000000001],"type":"Point"}
}