{
  "type": "Feature",
  "properties": {
    "gn:admin1_code":"32",
    "gn:asciiname":"Amirturba",
    "gn:country_code":"AZ",
    "gn:dem":92,
    "gn:feature_class":"P",
    "gn:feature_code":"PPL",
    "gn:name":"Amirturba",
    "gn:population":0,
    "gn:timezone":"Asia/Baku",
    "iso:country":"AZ",
    "name:aze_x_preferred":[
        "\u018fmirturba"
    ],
    "name:aze_x_variant":[
        "\u018fmirt\u00fcrb\u0259"
    ],
    "wof:name":"Amirturba",
    "wof:placetype":"locality"
},
  "geometry": {"coordinates":[48.56737,39.03882],"type":"Point"}
}