{
  "type": "Feature",
  "properties": {
    "gn:admin1_code":"11",
    "gn:asciiname":"Mustafaagali",
    "gn:cc2":"AZ",
    "gn:country_code":"AZ",
    "gn:dem":30,
    "gn:feature_class":"P",
    "gn:feature_code":"PPL",
    "gn:name":"Mustafaa\u011fal\u0131",
    "gn:population":0,
    "gn:timezone":"Asia/Baku",
    "iso:country":"AZ",
    "name:azb_x_preferred":[
        "\u0645\u0635\u0637\u0641\u06cc \u0622\u063a\u0627\u0644\u06cc"
    ],
    "name:aze_x_preferred":[
        "Mustafaa\u011fal\u0131"
    ],
    "name:ceb_x_preferred":[
        "Mustafaa\u011fal\u0131"
    ],
    "name:ell_x_preferred":[
        "\u039c\u03bf\u03c5\u03c3\u03c4\u03b1\u03c6\u03b1\u03b1\u03b3\u03ba\u03ac\u03bb\u03b9"
    ],
    "name:eng_x_preferred":[
        "Mustafaa\u011fal\u0131"
    ],
    "name:ita_x_preferred":[
        "Mustafaa\u011fal\u0131"
    ],
    "name:kat_x_preferred":[
        "\u10db\u10e3\u10e1\u10d7\u10d0\u10e4\u10d0\u10d0\u10e6\u10d0\u10da\u10d8"
    ],
    "name:msa_x_preferred":[
        "Mustafaa\u011fal\u0131"
    ],
    "name:rus_x_preferred":[
        "\u041c\u0443\u0441\u0442\u0430\u0444\u0430\u0430\u0433\u0430\u043b\u044b"
    ],
    "name:swe_x_preferred":[
        "Mustafaa\u011fal\u0131"
    ],
    "name:und_x_variant":[
        "Mustafaagaly"
    ],
    "wof:name":"Mustafaagali",
    "wof:placetype":"locality"
},
  "geometry": {"coordinates":[47.27333,40.31972],"type":"Point"}
}