{
  "type": "Feature",
  "properties": {
    "gn:admin1_code":"11",
    "gn:asciiname":"Mustafaagali",
    "gn:cc2":"AZ",
    "gn:country_code":"AZ",
    "gn:dem":30,
    "gn:feature_class":"P",
    "gn:feature_code":"PPL",
    "gn:name":"Mustafaa\u011fal\u0131",
    "gn:population":0,
    "gn:timezone":"Asia/Baku",
    "iso:country":"AZ",
    "name:aze_x_preferred":[
        "Mustafaa\u011fal\u0131"
    ],
    "name:eng_x_preferred":[
        "Mustafaa\u011fal\u0131"
    ],
    "name:rus_x_preferred":[
        "\u041c\u0443\u0441\u0442\u0430\u0444\u0430\u0430\u0433\u0430\u043b\u044b"
    ],
    "name:und_x_variant":[
        "Mustafaagaly"
    ],
    "wof:name":"Mustafaagali",
    "wof:placetype":"locality"
},
  "geometry": {"coordinates":[47.27333,40.31972],"type":"Point"}
}