{
  "type": "Feature",
  "properties": {
    "gn:admin1_code":"19",
    "gn:asciiname":"Dortlyar",
    "gn:country_code":"AZ",
    "gn:dem":1603,
    "gn:feature_class":"P",
    "gn:feature_code":"PPL",
    "gn:name":"Dortlyar",
    "gn:population":0,
    "gn:timezone":"Asia/Baku",
    "iso:country":"AZ",
    "name:aze_x_preferred":[
        "D\u00f6rdl\u0259r"
    ],
    "name:und_x_variant":[
        "D\u00f6rtl\u0259r"
    ],
    "wof:name":"Dortlyar",
    "wof:placetype":"locality"
},
  "geometry": {"coordinates":[45.45831,40.61683],"type":"Point"}
}