{
  "type": "Feature",
  "properties": {
    "gn:admin1_code":"17",
    "gn:asciiname":"Ashagy Emirkhanly",
    "gn:country_code":"AZ",
    "gn:dem":279,
    "gn:feature_class":"P",
    "gn:feature_code":"PPL",
    "gn:name":"Ashagy Emirkhanly",
    "gn:population":0,
    "gn:timezone":"Asia/Baku",
    "iso:country":"AZ",
    "name:ell_x_preferred":[
        "\u0391\u03c3\u03ac\u03b3\u03ba\u03b9 \u0395\u03bc\u03b9\u03c1\u03c7\u03b1\u03bd\u03bb\u03af"
    ],
    "name:msa_x_preferred":[
        "A\u015fa\u011f\u0131 \u018fmirxanl\u0131"
    ],
    "wof:name":"Ashagy Emirkhanly",
    "wof:placetype":"locality"
},
  "geometry": {"coordinates":[48.94407,41.13257],"type":"Point"}
}