{
  "type": "Feature",
  "properties": {
    "iso:country":"AZ",
    "name:azb_x_preferred":[
        "\u0632\u0627\u0628\u0631\u0627\u062a"
    ],
    "name:aze_x_preferred":[
        "Zabrat"
    ],
    "name:ceb_x_preferred":[
        "Zabrat"
    ],
    "name:che_x_preferred":[
        "\u0417\u0430\u0431\u0440\u0430\u0442"
    ],
    "name:eng_x_preferred":[
        "Zabrat"
    ],
    "name:fas_x_preferred":[
        "\u0632\u0628\u0631\u0627\u062a"
    ],
    "name:fra_x_preferred":[
        "Zabrat"
    ],
    "name:jpn_x_preferred":[
        "\u30b6\u30d6\u30e9\u30c8"
    ],
    "name:nld_x_preferred":[
        "Zabrat"
    ],
    "name:pol_x_preferred":[
        "Zabrat"
    ],
    "name:rus_x_preferred":[
        "\u0417\u0430\u0431\u0440\u0430\u0442"
    ],
    "name:swe_x_preferred":[
        "Zabrat"
    ],
    "name:und_x_variant":[
        "Sabrat"
    ],
    "name:urd_x_preferred":[
        "\u0632\u0628\u0631\u062a"
    ],
    "qs:gn_country":"AZ",
    "qs:gn_fcode":"PPL",
    "qs:gn_pop":21396,
    "qs:name":"Zabrat",
    "qs:name_adm0":"Azerbaijan",
    "qs:name_adm1":"Baki",
    "qs:photos":17,
    "qs:photos_1k":3,
    "qs:photos_9k":1,
    "qs:photos_9r":1,
    "qs:photos_all":17,
    "qs:photos_sr":1,
    "qs:placetype":"Town",
    "qs:pop_sr":"7",
    "qs:woe_adm0":23424741,
    "wd:wordcount":39,
    "wof:name":"Zabrat",
    "wof:placetype":"locality",
    "wof:population":21396
},
  "geometry": {"coordinates":[49.94158,40.4761],"type":"Point"}
}