{
  "type": "Feature",
  "properties": {
    "gn:admin1_code":"14",
    "gn:asciiname":"Chakhyrly",
    "gn:country_code":"AZ",
    "gn:dem":168,
    "gn:feature_class":"P",
    "gn:feature_code":"PPL",
    "gn:name":"Chakhyrly",
    "gn:population":0,
    "gn:timezone":"Asia/Baku",
    "iso:country":"AZ",
    "name:aze_x_preferred":[
        "\u00c7ax\u0131rl\u0131"
    ],
    "name:rus_x_preferred":[
        "\u0427\u0430\u0445\u044b\u0440\u043b\u044b"
    ],
    "wof:name":"Chakhyrly",
    "wof:placetype":"locality"
},
  "geometry": {"coordinates":[47.26885,39.36913],"type":"Point"}
}