{
  "type": "Feature",
  "properties": {
    "gn:admin1_code":"19",
    "gn:asciiname":"Parakend",
    "gn:country_code":"AZ",
    "gn:dem":1451,
    "gn:feature_class":"P",
    "gn:feature_code":"PPL",
    "gn:name":"Parakend",
    "gn:population":0,
    "gn:timezone":"Asia/Baku",
    "iso:country":"AZ",
    "name:aze_x_preferred":[
        "Parak\u0259nd"
    ],
    "wof:name":"Parakend",
    "wof:placetype":"locality"
},
  "geometry": {"coordinates":[45.69316,40.53164],"type":"Point"}
}