{
  "type": "Feature",
  "properties": {
    "gn:admin1_code":"02",
    "gn:asciiname":"Gyusyulyu",
    "gn:country_code":"AZ",
    "gn:dem":62,
    "gn:feature_class":"P",
    "gn:feature_code":"PPL",
    "gn:name":"Gyusyulyu",
    "gn:population":0,
    "gn:timezone":"Asia/Baku",
    "iso:country":"AZ",
    "name:aze_x_preferred":[
        "H\u00fcs\u00fcl\u00fc"
    ],
    "name:und_x_variant":[
        "Gusyulyu",
        "Gyusyulyu"
    ],
    "wof:name":"Gyusyulyu",
    "wof:placetype":"locality"
},
  "geometry": {"coordinates":[47.29955,40.06935],"type":"Point"}
}