{
  "type": "Feature",
  "properties": {
    "gn:admin1_code":"37",
    "gn:asciiname":"Deymedagyly",
    "gn:country_code":"AZ",
    "gn:dem":391,
    "gn:feature_class":"P",
    "gn:feature_code":"PPL",
    "gn:name":"Deymedagyly",
    "gn:population":0,
    "gn:timezone":"Asia/Baku",
    "iso:country":"AZ",
    "name:und_x_variant":[
        "Daymadagly",
        "Deymedagyly",
        "D\u0259ym\u0259da\u011fl\u0131"
    ],
    "wof:name":"Deymedagyly",
    "wof:placetype":"locality"
},
  "geometry": {"coordinates":[47.60986,40.9446],"type":"Point"}
}