{
  "type": "Feature",
  "properties": {
    "gn:admin1_code":"58",
    "gn:asciiname":"Alimardanly",
    "gn:country_code":"AZ",
    "gn:dem":363,
    "gn:feature_class":"P",
    "gn:feature_code":"PPL",
    "gn:name":"Alimardanly",
    "gn:population":0,
    "gn:timezone":"Asia/Baku",
    "iso:country":"AZ",
    "name:azb_x_preferred":[
        "\u0639\u0644\u06cc\u0645\u0631\u062f\u0627\u0646\u0644\u06cc"
    ],
    "name:aze_x_preferred":[
        "\u018flim\u0259rdanl\u0131"
    ],
    "name:ceb_x_preferred":[
        "Alimardanly"
    ],
    "name:eng_x_preferred":[
        "\u018flim\u01ddrdanl\u0131"
    ],
    "name:fas_x_preferred":[
        "\u0639\u0644\u06cc\u0645\u0631\u062f\u0627\u0646\u0644\u06cc"
    ],
    "name:ita_x_preferred":[
        "\u018flim\u0259rdanl\u0131"
    ],
    "name:kat_x_preferred":[
        "\u10d0\u10da\u10d8\u10db\u10d0\u10e0\u10d3\u10d0\u10dc\u10da\u10d8"
    ],
    "name:msa_x_preferred":[
        "\u018flim\u0259rdanl\u0131"
    ],
    "name:rus_x_preferred":[
        "\u0410\u043b\u0438\u043c\u0430\u0440\u0434\u0430\u043d\u043b\u044b"
    ],
    "name:swe_x_preferred":[
        "Alimardanly"
    ],
    "wof:name":"Alimardanly",
    "wof:placetype":"locality"
},
  "geometry": {"coordinates":[45.67297,41.03982],"type":"Point"}
}