{
  "type": "Feature",
  "properties": {
    "gn:admin1_code":"15",
    "gn:asciiname":"Mamed-Dzhanly",
    "gn:country_code":"AZ",
    "gn:dem":92,
    "gn:feature_class":"P",
    "gn:feature_code":"PPL",
    "gn:name":"Mamed-Dzhanly",
    "gn:population":0,
    "gn:timezone":"Asia/Baku",
    "iso:country":"AZ",
    "name:aze_x_preferred":[
        "M\u0259mm\u0259dcanl\u0131"
    ],
    "name:und_x_variant":[
        "Mameddzhanly"
    ],
    "wof:name":"Mamed-Dzhanly",
    "wof:placetype":"locality"
},
  "geometry": {"coordinates":[48.3551,39.30055],"type":"Point"}
}