{
  "type": "Feature",
  "properties": {
    "gn:admin1_code":"03",
    "gn:asciiname":"Sixbabali",
    "gn:country_code":"AZ",
    "gn:dem":373,
    "gn:feature_class":"P",
    "gn:feature_code":"PPL",
    "gn:name":"S\u0131xbabal\u0131",
    "gn:population":0,
    "gn:timezone":"Asia/Baku",
    "iso:country":"AZ",
    "name:azb_x_preferred":[
        "\u0634\u06cc\u062e\u200c\u0628\u0627\u0628\u0627\u0644\u06cc"
    ],
    "name:aze_x_preferred":[
        "S\u0131xbabal\u0131"
    ],
    "name:aze_x_variant":[
        "\u015e\u0131xbabal\u0131"
    ],
    "name:fas_x_preferred":[
        "\u0634\u06cc\u062e\u200c\u0628\u0627\u0628\u0627\u0644\u06cc"
    ],
    "name:kat_x_preferred":[
        "\u10e1\u10d8\u10ee\u10d1\u10d0\u10d1\u10d0\u10da\u10d8"
    ],
    "name:min_x_preferred":[
        "S\u0131xbabal\u0131"
    ],
    "name:msa_x_preferred":[
        "S\u0131xbabal\u0131"
    ],
    "name:rus_x_preferred":[
        "\u0428\u044b\u0445\u0431\u0430\u0431\u0430\u043b\u044b"
    ],
    "name:und_x_variant":[
        "Shikhbabaly",
        "Shykhbabaly"
    ],
    "wof:name":"Sixbabali",
    "wof:placetype":"locality"
},
  "geometry": {"coordinates":[46.93547,39.95843],"type":"Point"}
}