{
  "type": "Feature",
  "properties": {
    "gn:asciiname":"Qilincli",
    "gn:country_code":"AZ",
    "gn:dem":1247,
    "gn:feature_class":"P",
    "gn:feature_code":"PPL",
    "gn:name":"Qilincli",
    "gn:population":0,
    "gn:timezone":"Asia/Baku",
    "iso:country":"AZ",
    "wof:name":"Qilincli",
    "wof:placetype":"locality"
},
  "geometry": {"coordinates":[46.13644,40.16185],"type":"Point"}
}