{
  "type": "Feature",
  "properties": {
    "gn:admin1_code":"66",
    "gn:asciiname":"Golyeri",
    "gn:country_code":"AZ",
    "gn:dem":683,
    "gn:feature_class":"P",
    "gn:feature_code":"PPL",
    "gn:name":"G\u00f6lyeri",
    "gn:population":0,
    "gn:timezone":"Asia/Baku",
    "iso:country":"AZ",
    "name:azb_x_preferred":[
        "\u0646\u0642\u0648\u0631"
    ],
    "name:aze_x_preferred":[
        "Nequr"
    ],
    "name:ceb_x_preferred":[
        "G\u00f6lyeri"
    ],
    "name:ita_x_preferred":[
        "G\u00f6lyeri"
    ],
    "name:kat_x_preferred":[
        "\u10dc\u10d4\u10e5\u10e3\u10e0\u10d8"
    ],
    "name:msa_x_preferred":[
        "G\u00f6lyeri"
    ],
    "name:rus_x_preferred":[
        "Gyol\u2019eri"
    ],
    "name:swe_x_preferred":[
        "G\u00f6lyeri"
    ],
    "name:tur_x_preferred":[
        "Nekur"
    ],
    "wof:name":"Golyeri",
    "wof:placetype":"locality"
},
  "geometry": {"coordinates":[48.38781,39.00972],"type":"Point"}
}