{
  "type": "Feature",
  "properties": {
    "gn:admin1_code":"55",
    "gn:asciiname":"Mirzalar",
    "gn:country_code":"AZ",
    "gn:dem":1371,
    "gn:feature_class":"P",
    "gn:feature_code":"PPL",
    "gn:name":"Mirzalar",
    "gn:population":0,
    "gn:timezone":"Asia/Baku",
    "iso:country":"AZ",
    "name:aze_x_preferred":[
        "Mirz\u0259l\u0259r"
    ],
    "name:hye_x_preferred":[
        "\u0544\u056b\u0580\u0566\u0561\u056c\u0561\u0580"
    ],
    "name:msa_x_preferred":[
        "Mirz\u0259l\u0259r"
    ],
    "name:rus_x_preferred":[
        "\u041c\u0438\u0440\u0437\u0430\u043b\u0430\u0440"
    ],
    "wof:name":"Mirzalar",
    "wof:placetype":"locality"
},
  "geometry": {"coordinates":[46.65998,39.77749],"type":"Point"}
}