{
  "type": "Feature",
  "properties": {
    "gn:admin1_code":"08",
    "gn:asciiname":"Sigaloni",
    "gn:country_code":"AZ",
    "gn:dem":39,
    "gn:feature_class":"P",
    "gn:feature_code":"PPL",
    "gn:name":"S\u0131\u011faloni",
    "gn:population":0,
    "gn:timezone":"Asia/Baku",
    "iso:country":"AZ",
    "name:aze_x_preferred":[
        "S\u0131\u011faloni"
    ],
    "name:ceb_x_preferred":[
        "S\u0131qalonu"
    ],
    "name:ita_x_preferred":[
        "S\u0131qalonu"
    ],
    "name:kat_x_preferred":[
        "\u10e1\u10d8\u10e6\u10d0\u10da\u10dd\u10dc\u10d8"
    ],
    "name:msa_x_preferred":[
        "S\u0131qalonu"
    ],
    "name:swe_x_preferred":[
        "S\u0131qalonu"
    ],
    "name:und_x_variant":[
        "S\u0131qalonu",
        "Sygalonu"
    ],
    "wof:name":"Sigaloni",
    "wof:placetype":"locality"
},
  "geometry": {"coordinates":[48.78713,38.60508],"type":"Point"}
}