{
  "type": "Feature",
  "properties": {
    "gn:admin1_code":"03",
    "gn:asciiname":"Cullu",
    "gn:country_code":"AZ",
    "gn:dem":465,
    "gn:feature_class":"P",
    "gn:feature_code":"PPL",
    "gn:name":"\u00c7ullu",
    "gn:population":0,
    "gn:timezone":"Asia/Baku",
    "iso:country":"AZ",
    "name:aze_x_preferred":[
        "\u00c7ullu"
    ],
    "name:hye_x_preferred":[
        "\u0549\u0578\u0582\u056c\u056c\u0578\u0582"
    ],
    "name:rus_x_preferred":[
        "\u0427\u0443\u043b\u043b\u0443"
    ],
    "name:und_x_variant":[
        "Chullu Vtoroye",
        "Chullu"
    ],
    "wof:name":"Cullu",
    "wof:placetype":"locality"
},
  "geometry": {"coordinates":[46.87414,40.04698],"type":"Point"}
}