{
  "type": "Feature",
  "properties": {
    "gn:admin1_code":"10",
    "gn:asciiname":"Qazma",
    "gn:country_code":"AZ",
    "gn:dem":300,
    "gn:feature_class":"P",
    "gn:feature_code":"PPL",
    "gn:name":"Qazma",
    "gn:population":0,
    "gn:timezone":"Asia/Baku",
    "iso:country":"AZ",
    "name:azb_x_preferred":[
        "\u0642\u0627\u0632\u0645\u0627"
    ],
    "name:aze_x_preferred":[
        "Qazma"
    ],
    "name:ceb_x_preferred":[
        "Qazma"
    ],
    "name:eng_x_preferred":[
        "Qazma"
    ],
    "name:ita_x_preferred":[
        "Qazma"
    ],
    "name:kat_x_preferred":[
        "\u10e7\u10d0\u10d6\u10db\u10d0"
    ],
    "name:msa_x_preferred":[
        "Qazma"
    ],
    "name:rus_x_preferred":[
        "\u041a\u0430\u0437\u043c\u0430"
    ],
    "name:swe_x_preferred":[
        "Qazma"
    ],
    "name:und_x_variant":[
        "Kazma",
        "Kazmatabun"
    ],
    "wof:name":"Qazma",
    "wof:placetype":"locality"
},
  "geometry": {"coordinates":[46.38597,41.6942],"type":"Point"}
}