{
  "type": "Feature",
  "properties": {
    "gn:admin1_code":"60",
    "gn:asciiname":"Ilkhychy",
    "gn:country_code":"AZ",
    "gn:dem":-6,
    "gn:feature_class":"P",
    "gn:feature_code":"PPL",
    "gn:name":"Ilkhychy",
    "gn:population":0,
    "gn:timezone":"Asia/Baku",
    "iso:country":"AZ",
    "name:aze_x_preferred":[
        "\u0130lx\u0131\u00e7\u0131"
    ],
    "name:aze_x_variant":[
        "\u0130lx\u0131\u00e7\u0131 H\u0259s\u0259n \u018ff\u0259ndi"
    ],
    "name:und_x_variant":[
        "Il\u2019khychy-Gasanefendi",
        "Gasan Efendi",
        "Il\u2019kichi-Kazeya",
        "H\u0259s\u0259n \u018ff\u0259ndi",
        "Ilkhychy"
    ],
    "wof:name":"Ilkhychy",
    "wof:placetype":"locality"
},
  "geometry": {"coordinates":[48.91878,41.46009],"type":"Point"}
}