{
  "type": "Feature",
  "properties": {
    "gn:admin1_code":"14",
    "gn:asciiname":"Kovshutlu",
    "gn:country_code":"AZ",
    "gn:dem":217,
    "gn:feature_class":"P",
    "gn:feature_code":"PPL",
    "gn:name":"Kovshutlu",
    "gn:population":0,
    "gn:timezone":"Asia/Baku",
    "iso:country":"AZ",
    "wof:name":"Kovshutlu",
    "wof:placetype":"locality"
},
  "geometry": {"coordinates":[47.05,39.25],"type":"Point"}
}