{
  "type": "Feature",
  "properties": {
    "gn:admin1_code":"23",
    "gn:asciiname":"Pirxana",
    "gn:country_code":"AZ",
    "gn:dem":79,
    "gn:feature_class":"P",
    "gn:feature_code":"PPL",
    "gn:name":"Pirxana",
    "gn:population":0,
    "gn:timezone":"Asia/Baku",
    "iso:country":"AZ",
    "name:und_x_variant":[
        "Pirkhana"
    ],
    "wof:name":"Pirxana",
    "wof:placetype":"locality"
},
  "geometry": {"coordinates":[49.01845,40.15342],"type":"Point"}
}