{
  "type": "Feature",
  "properties": {
    "iso:country":"AZ",
    "name:azb_x_preferred":[
        "\u0635\u0627\u0628\u0648\u0646\u0686\u0648"
    ],
    "name:aze_x_preferred":[
        "Sabun\u00e7u"
    ],
    "name:ceb_x_preferred":[
        "Sabun\u00e7u"
    ],
    "name:che_x_preferred":[
        "\u0421\u0430\u0431\u0443\u043d\u0447\u0443"
    ],
    "name:eng_x_preferred":[
        "Sabun\u00e7u"
    ],
    "name:fas_x_preferred":[
        "\u0635\u0627\u0628\u0648\u0646\u0686\u06cc"
    ],
    "name:fra_x_preferred":[
        "Sabun\u00e7u"
    ],
    "name:hun_x_preferred":[
        "Sabun\u00e7u"
    ],
    "name:hye_x_preferred":[
        "\u054d\u0561\u0562\u0578\u0582\u0576\u0579\u056b"
    ],
    "name:jpn_x_preferred":[
        "\u30b5\u30d6\u30f3\u30c1\u30e5"
    ],
    "name:kaz_x_preferred":[
        "\u0421\u0430\u0431\u0443\u043d\u0447\u0443"
    ],
    "name:nld_x_preferred":[
        "Sabun\u00e7u"
    ],
    "name:pol_x_preferred":[
        "Sabun\u00e7u"
    ],
    "name:rus_x_preferred":[
        "\u0421\u0430\u0431\u0443\u043d\u0447\u0438"
    ],
    "name:swe_x_preferred":[
        "Sabun\u00e7u"
    ],
    "name:ukr_x_preferred":[
        "\u0421\u0430\u0431\u0443\u043d\u0447\u0443"
    ],
    "name:und_x_variant":[
        "Sabunchi"
    ],
    "name:urd_x_preferred":[
        "\u0633\u0628\u0627\u0646\u06a9\u0648\u060c \u0628\u0627\u06a9\u0648"
    ],
    "name:urd_x_variant":[
        "\u0633\u0628\u0627\u0646\u06a9\u0648"
    ],
    "name:zho_x_preferred":[
        "\u85a9\u672c\u5947"
    ],
    "qs:gn_country":"AZ",
    "qs:gn_fcode":"PPL",
    "qs:gn_pop":20996,
    "qs:name":"Sabun\u00e7u",
    "qs:name_adm0":"Azerbaijan",
    "qs:name_adm1":"Baki",
    "qs:photos":47,
    "qs:photos_1k":10,
    "qs:photos_9k":1,
    "qs:photos_9r":2,
    "qs:photos_all":47,
    "qs:photos_sr":2,
    "qs:placetype":"Town",
    "qs:pop_sr":"7",
    "qs:woe_adm0":23424741,
    "wd:wordcount":172,
    "wof:name":"Sabun\u00e7u",
    "wof:placetype":"locality",
    "wof:population":20996
},
  "geometry": {"coordinates":[49.94806,40.4425],"type":"Point"}
}