{
  "type": "Feature",
  "properties": {
    "gn:admin1_code":"28",
    "gn:asciiname":"Tyurklyar",
    "gn:country_code":"AZ",
    "gn:dem":912,
    "gn:feature_class":"P",
    "gn:feature_code":"PPL",
    "gn:name":"Tyurklyar",
    "gn:population":0,
    "gn:timezone":"Asia/Baku",
    "iso:country":"AZ",
    "name:aze_x_preferred":[
        "T\u00fcrkl\u0259r"
    ],
    "name:rus_x_preferred":[
        "\u0422\u044e\u0440\u043a\u043b\u044f\u0440"
    ],
    "wof:name":"Tyurklyar",
    "wof:placetype":"locality"
},
  "geometry": {"coordinates":[46.61425,39.51669],"type":"Point"}
}