{
  "type": "Feature",
  "properties": {
    "gn:admin1_code":"25",
    "gn:asciiname":"Akhan",
    "gn:country_code":"AZ",
    "gn:dem":1540,
    "gn:feature_class":"P",
    "gn:feature_code":"PPL",
    "gn:name":"Akhan",
    "gn:population":0,
    "gn:timezone":"Asia/Baku",
    "iso:country":"AZ",
    "name:und_x_variant":[
        "Agan",
        "\u018fh\u0259n"
    ],
    "wof:name":"Akhan",
    "wof:placetype":"locality"
},
  "geometry": {"coordinates":[48.41604,40.85256],"type":"Point"}
}