{
  "type": "Feature",
  "properties": {
    "gn:admin1_code":"46",
    "gn:asciiname":"Rustamly",
    "gn:country_code":"AZ",
    "gn:dem":-21,
    "gn:feature_class":"P",
    "gn:feature_code":"PPL",
    "gn:name":"Rustamly",
    "gn:population":0,
    "gn:timezone":"Asia/Baku",
    "iso:country":"AZ",
    "name:aze_x_preferred":[
        "R\u00fcst\u0259mli"
    ],
    "name:und_x_variant":[
        "Rustam",
        "Rustamly",
        "R\u00fcst\u0259ml\u0131"
    ],
    "wof:name":"Rustamly",
    "wof:placetype":"locality"
},
  "geometry": {"coordinates":[48.71616,39.86295],"type":"Point"}
}