{
  "type": "Feature",
  "properties": {
    "gn:admin1_code":"46",
    "gn:asciiname":"Rustamly",
    "gn:country_code":"AZ",
    "gn:dem":-21,
    "gn:feature_class":"P",
    "gn:feature_code":"PPL",
    "gn:name":"Rustamly",
    "gn:population":0,
    "gn:timezone":"Asia/Baku",
    "iso:country":"AZ",
    "name:azb_x_preferred":[
        "\u0631\u0648\u0633\u062a\u0645\u0644\u06cc"
    ],
    "name:aze_x_preferred":[
        "R\u00fcst\u0259mli"
    ],
    "name:ceb_x_preferred":[
        "Rustamly"
    ],
    "name:ita_x_preferred":[
        "R\u00fcst\u0259ml\u0131"
    ],
    "name:msa_x_preferred":[
        "R\u00fcst\u0259ml\u0131"
    ],
    "name:swe_x_preferred":[
        "Rustamly"
    ],
    "name:und_x_variant":[
        "Rustam"
    ],
    "wof:name":"Rustamly",
    "wof:placetype":"locality"
},
  "geometry": {"coordinates":[48.71616,39.86295],"type":"Point"}
}