{
  "type": "Feature",
  "properties": {
    "gn:admin1_code":"15",
    "gn:asciiname":"Boyxanli",
    "gn:country_code":"AZ",
    "gn:dem":269,
    "gn:feature_class":"P",
    "gn:feature_code":"PPL",
    "gn:name":"Boyxanl\u0131",
    "gn:population":0,
    "gn:timezone":"Asia/Baku",
    "iso:country":"AZ",
    "name:azb_x_preferred":[
        "\u0628\u0648\u06cc\u062e\u0627\u0646\u0644\u06cc"
    ],
    "name:aze_x_preferred":[
        "Boyxanl\u0131"
    ],
    "name:ceb_x_preferred":[
        "Boyxanl\u0131"
    ],
    "name:ita_x_preferred":[
        "Boyxanl\u0131"
    ],
    "name:msa_x_preferred":[
        "Boyxanl\u0131"
    ],
    "name:swe_x_preferred":[
        "Boyxanl\u0131"
    ],
    "name:und_x_variant":[
        "Boykhanly",
        "Bayankhanly"
    ],
    "wof:name":"Boyxanli",
    "wof:placetype":"locality"
},
  "geometry": {"coordinates":[48.23557,39.2458],"type":"Point"}
}