{
  "type": "Feature",
  "properties": {
    "gn:admin1_code":"15",
    "gn:asciiname":"Boyxanli",
    "gn:country_code":"AZ",
    "gn:dem":269,
    "gn:feature_class":"P",
    "gn:feature_code":"PPL",
    "gn:name":"Boyxanl\u0131",
    "gn:population":0,
    "gn:timezone":"Asia/Baku",
    "iso:country":"AZ",
    "name:und_x_variant":[
        "Boykhanly",
        "Bayankhanly",
        "Boyxanl\u0131"
    ],
    "wof:name":"Boyxanli",
    "wof:placetype":"locality"
},
  "geometry": {"coordinates":[48.23557,39.2458],"type":"Point"}
}