{
  "type": "Feature",
  "properties": {
    "gn:admin1_code":"66",
    "gn:asciiname":"Gilar",
    "gn:country_code":"AZ",
    "gn:dem":1230,
    "gn:feature_class":"P",
    "gn:feature_code":"PPL",
    "gn:name":"Gilar",
    "gn:population":0,
    "gn:timezone":"Asia/Baku",
    "iso:country":"AZ",
    "name:aze_x_preferred":[
        "Gilar"
    ],
    "name:ita_x_preferred":[
        "Gilar"
    ],
    "name:msa_x_preferred":[
        "Gilar"
    ],
    "name:tur_x_preferred":[
        "Gilar"
    ],
    "wof:name":"Gilar",
    "wof:placetype":"locality"
},
  "geometry": {"coordinates":[48.14626,38.91827],"type":"Point"}
}