{
  "type": "Feature",
  "properties": {
    "gn:admin1_code":"69",
    "gn:asciiname":"Velikulubeyli",
    "gn:country_code":"AZ",
    "gn:dem":311,
    "gn:feature_class":"P",
    "gn:feature_code":"PPL",
    "gn:name":"Velikulubeyli",
    "gn:population":0,
    "gn:timezone":"Asia/Tehran",
    "iso:country":"AZ",
    "name:rus_x_preferred":[
        "\u0412\u0435\u043b\u0438\u043a\u0443\u043b\u0443\u0431\u0435\u0439\u043b\u0438"
    ],
    "wof:name":"Velikulubeyli",
    "wof:placetype":"locality"
},
  "geometry": {"coordinates":[46.74416,39.02812],"type":"Point"}
}