{
  "type": "Feature",
  "properties": {
    "gn:admin1_code":"08",
    "gn:asciiname":"Dul'myadi",
    "gn:country_code":"AZ",
    "gn:dem":379,
    "gn:feature_class":"P",
    "gn:feature_code":"PPL",
    "gn:name":"Dul\u2019myadi",
    "gn:population":0,
    "gn:timezone":"Asia/Baku",
    "iso:country":"AZ",
    "name:rus_x_preferred":[
        "Dul\u2019myadi"
    ],
    "name:und_x_variant":[
        "Dil\u2019mady",
        "Dyl\u2019mady"
    ],
    "wof:name":"Dul'myadi",
    "wof:placetype":"locality"
},
  "geometry": {"coordinates":[48.67027,38.45747],"type":"Point"}
}