{
  "type": "Feature",
  "properties": {
    "gn:admin1_code":"35",
    "gn:admin2_code":"7669114.0",
    "gn:asciiname":"Kizilvank",
    "gn:country_code":"AZ",
    "gn:dem":777,
    "gn:feature_class":"P",
    "gn:feature_code":"PPL",
    "gn:name":"Kizilvank",
    "gn:population":0,
    "gn:timezone":"Asia/Baku",
    "iso:country":"AZ",
    "name:aze_x_preferred":[
        "Q\u0131z\u0131lv\u0259ng"
    ],
    "wof:name":"Kizilvank",
    "wof:placetype":"locality"
},
  "geometry": {"coordinates":[45.41325,39.10857],"type":"Point"}
}