{
  "type": "Feature",
  "properties": {
    "gn:admin1_code":"14",
    "gn:asciiname":"Lchashen",
    "gn:country_code":"AZ",
    "gn:dem":783,
    "gn:feature_class":"P",
    "gn:feature_code":"PPL",
    "gn:name":"Lchashen",
    "gn:population":0,
    "gn:timezone":"Asia/Baku",
    "iso:country":"AZ",
    "name:aze_x_preferred":[
        "\u00d6rd\u0259kli"
    ],
    "name:ceb_x_preferred":[
        "Lchashen"
    ],
    "name:ces_x_preferred":[
        "Lchashen"
    ],
    "name:deu_x_preferred":[
        "Ltschaschen"
    ],
    "name:fas_x_preferred":[
        "\u0644\u0686\u0627\u0634\u0646"
    ],
    "name:fra_x_preferred":[
        "Lchashen"
    ],
    "name:hye_x_preferred":[
        "Lchashen"
    ],
    "name:hye_x_variant":[
        "\u053c\u0573\u0561\u0577\u0565\u0576"
    ],
    "name:ita_x_preferred":[
        "Lchashen"
    ],
    "name:kat_x_preferred":[
        "\u10da\u10ed\u10d0\u10e8\u10d4\u10dc\u10d8"
    ],
    "name:msa_x_preferred":[
        "Lchashen"
    ],
    "name:rus_x_preferred":[
        "\u041b\u0447\u0430\u0448\u0435\u043d"
    ],
    "name:sco_x_preferred":[
        "Lchashen"
    ],
    "name:spa_x_preferred":[
        "Lchashen"
    ],
    "name:swe_x_preferred":[
        "Lchashen"
    ],
    "name:ukr_x_preferred":[
        "\u041b\u0447\u0430\u0448\u0435\u043d"
    ],
    "name:vie_x_preferred":[
        "Lchashen"
    ],
    "wof:name":"Lchashen",
    "wof:placetype":"locality"
},
  "geometry": {"coordinates":[46.70151,39.40995],"type":"Point"}
}