{
  "type": "Feature",
  "properties": {
    "gn:admin1_code":"14",
    "gn:asciiname":"Lchashen",
    "gn:country_code":"AZ",
    "gn:dem":783,
    "gn:feature_class":"P",
    "gn:feature_code":"PPL",
    "gn:name":"Lchashen",
    "gn:population":0,
    "gn:timezone":"Asia/Baku",
    "iso:country":"AZ",
    "name:hye_x_preferred":[
        "Lchashen"
    ],
    "name:hye_x_variant":[
        "\u053c\u0573\u0561\u0577\u0565\u0576"
    ],
    "wof:name":"Lchashen",
    "wof:placetype":"locality"
},
  "geometry": {"coordinates":[46.70151,39.40995],"type":"Point"}
}