{
  "type": "Feature",
  "properties": {
    "gn:admin1_code":"31",
    "gn:asciiname":"Piyakyudzha",
    "gn:country_code":"AZ",
    "gn:dem":1598,
    "gn:feature_class":"P",
    "gn:feature_code":"PPL",
    "gn:name":"Piyakyudzha",
    "gn:population":0,
    "gn:timezone":"Asia/Baku",
    "iso:country":"AZ",
    "name:aze_x_preferred":[
        "Piy\u0259k\u00fcc\u0259"
    ],
    "wof:name":"Piyakyudzha",
    "wof:placetype":"locality"
},
  "geometry": {"coordinates":[48.48343,38.70951],"type":"Point"}
}