{
  "type": "Feature",
  "properties": {
    "gn:admin1_code":"60",
    "gn:asciiname":"Manafoba",
    "gn:country_code":"AZ",
    "gn:dem":118,
    "gn:feature_class":"P",
    "gn:feature_code":"PPL",
    "gn:name":"Manafoba",
    "gn:population":0,
    "gn:timezone":"Asia/Baku",
    "iso:country":"AZ",
    "wof:name":"Manafoba",
    "wof:placetype":"locality"
},
  "geometry": {"coordinates":[48.69207,41.54065],"type":"Point"}
}