{
  "type": "Feature",
  "properties": {
    "gn:admin1_code":"60",
    "gn:asciiname":"Manafoba",
    "gn:country_code":"AZ",
    "gn:dem":118,
    "gn:feature_class":"P",
    "gn:feature_code":"PPL",
    "gn:name":"Manafoba",
    "gn:population":0,
    "gn:timezone":"Asia/Baku",
    "iso:country":"AZ",
    "name:azb_x_preferred":[
        "\u0645\u0627\u0646\u0627\u0641 \u0627\u0648\u0628\u0627"
    ],
    "name:aze_x_preferred":[
        "Manafoba"
    ],
    "name:ell_x_preferred":[
        "\u039c\u03b1\u03bd\u03b1\u03c6\u03cc\u03bc\u03c0\u03b1"
    ],
    "name:ita_x_preferred":[
        "Manafoba"
    ],
    "name:kat_x_preferred":[
        "\u10db\u10d0\u10dc\u10d0\u10e4\u10dd\u10d1\u10d0"
    ],
    "name:lez_x_preferred":[
        "\u041c\u0430\u043d\u0430\u0444\u0443\u0431\u0430"
    ],
    "name:msa_x_preferred":[
        "Manafoba"
    ],
    "wof:name":"Manafoba",
    "wof:placetype":"locality"
},
  "geometry": {"coordinates":[48.69207,41.54065],"type":"Point"}
}