{
  "type": "Feature",
  "properties": {
    "gn:country":"AZ",
    "gn:fcode":"PPL",
    "gn:population":1853,
    "iso:country":"AZ",
    "name:arg_x_preferred":[
        "Sadarak"
    ],
    "name:azb_x_preferred":[
        "\u0633\u062f\u0647\u200c\u0631\u06a9 \u0642\u0635\u0628\u0647\u200c\u0633\u06cc"
    ],
    "name:aze_x_colloquial":[
        "S\u0259d\u0259r\u0259k"
    ],
    "name:aze_x_historical":[
        "S\u0259d\u0259r\u0259k"
    ],
    "name:aze_x_preferred":[
        "S\u0259d\u0259r\u0259k"
    ],
    "name:ceb_x_preferred":[
        "Sedarak"
    ],
    "name:eng_x_preferred":[
        "S\u0259d\u0259r\u0259k"
    ],
    "name:hye_x_preferred":[
        "\u054d\u0561\u0576\u0564\u0580\u0578\u0582\u0584"
    ],
    "name:jpn_x_preferred":[
        "\u30b5\u30c0\u30e9\u30af"
    ],
    "name:kat_x_preferred":[
        "\u10e1\u10d0\u10d3\u10d0\u10e0\u10d0\u10e5\u10d8"
    ],
    "name:msa_x_preferred":[
        "S\u0259d\u0259r\u0259k"
    ],
    "name:nld_x_preferred":[
        "S\u0259d\u0259r\u0259k"
    ],
    "name:rus_x_preferred":[
        "\u0421\u0430\u0434\u0430\u0440\u0430\u043a"
    ],
    "name:swe_x_preferred":[
        "Sedarak"
    ],
    "name:tur_x_historical":[
        "Sederek"
    ],
    "name:tur_x_preferred":[
        "Sederek"
    ],
    "name:urd_x_preferred":[
        "\u0633\u062f\u0631\u06a9"
    ],
    "qs_pg:aaroncc":"AZ",
    "qs_pg:gn_country":"AZ",
    "qs_pg:gn_fcode":"PPL",
    "qs_pg:gn_pop":1853,
    "qs_pg:name":"Sedarak",
    "qs_pg:photos_9r":0,
    "qs_pg:photos_sr":0,
    "qs_pg:pop_sr":3,
    "qs_pg:qs_pg_placetype":"locality",
    "wof:name":"Sedarak",
    "wof:placetype":"locality",
    "wof:population":1853
},
  "geometry": {"coordinates":[44.88805,39.71144],"type":"Point"}
}