{
  "type": "Feature",
  "properties": {
    "gn:admin1_code":"12",
    "gn:asciiname":"Lekino",
    "gn:country_code":"AZ",
    "gn:dem":62,
    "gn:feature_class":"P",
    "gn:feature_code":"PPL",
    "gn:name":"Lekino",
    "gn:population":0,
    "gn:timezone":"Asia/Baku",
    "iso:country":"AZ",
    "name:ita_x_preferred":[
        "Lekino"
    ],
    "name:kat_x_preferred":[
        "\u10da\u10d4\u10e5\u10d8\u10dc\u10dd"
    ],
    "name:msa_x_preferred":[
        "Lekino"
    ],
    "wof:name":"Lekino",
    "wof:placetype":"locality"
},
  "geometry": {"coordinates":[47.61667,39.76667],"type":"Point"}
}