{
  "type": "Feature",
  "properties": {
    "gn:admin1_code":"32",
    "gn:asciiname":"Sygdash",
    "gn:country_code":"AZ",
    "gn:dem":67,
    "gn:feature_class":"P",
    "gn:feature_code":"PPL",
    "gn:name":"Sygdash",
    "gn:population":0,
    "gn:timezone":"Asia/Baku",
    "iso:country":"AZ",
    "name:azb_x_preferred":[
        "\u0633\u06cc\u063a\u062f\u0627\u0634"
    ],
    "name:aze_x_preferred":[
        "S\u0131\u011fda\u015f"
    ],
    "name:ceb_x_preferred":[
        "Sygdash"
    ],
    "name:ita_x_preferred":[
        "S\u0131\u011fda\u015f"
    ],
    "name:msa_x_preferred":[
        "S\u0131\u011fda\u015f"
    ],
    "name:swe_x_preferred":[
        "Sygdash"
    ],
    "name:und_x_variant":[
        "Sigdash"
    ],
    "wof:name":"Sygdash",
    "wof:placetype":"locality"
},
  "geometry": {"coordinates":[48.61556,38.95625],"type":"Point"}
}