{
  "type": "Feature",
  "properties": {
    "gn:admin1_code":"25",
    "gn:asciiname":"Mulux",
    "gn:country_code":"AZ",
    "gn:dem":1410,
    "gn:feature_class":"P",
    "gn:feature_code":"PPL",
    "gn:name":"Mulux",
    "gn:population":0,
    "gn:timezone":"Asia/Baku",
    "iso:country":"AZ",
    "name:und_x_variant":[
        "Mulukh",
        "Mulux"
    ],
    "wof:name":"Mulux",
    "wof:placetype":"locality"
},
  "geometry": {"coordinates":[48.29922,40.86928],"type":"Point"}
}