{
  "type": "Feature",
  "properties": {
    "gn:admin1_code":"21",
    "gn:asciiname":"Hacalli",
    "gn:country_code":"AZ",
    "gn:dem":439,
    "gn:feature_class":"P",
    "gn:feature_code":"PPL",
    "gn:name":"Hacall\u0131",
    "gn:population":0,
    "gn:timezone":"Asia/Baku",
    "iso:country":"AZ",
    "name:aze_x_preferred":[
        "Hacall\u0131"
    ],
    "name:hye_x_preferred":[
        "Hajaly"
    ],
    "name:hye_x_variant":[
        "\u0540\u0561\u057b\u0561\u056c\u0568",
        "Hajali",
        "\u0540\u0561\u057b\u0561\u056c\u056b"
    ],
    "name:rus_x_preferred":[
        "\u0413\u0430\u0434\u0436\u0430\u043b\u043b\u044b"
    ],
    "name:und_x_variant":[
        "Gadzhialilu",
        "Gadzhally"
    ],
    "wof:name":"Hacalli",
    "wof:placetype":"locality"
},
  "geometry": {"coordinates":[46.73954000000001,40.483],"type":"Point"}
}