{
  "type": "Feature",
  "properties": {
    "gn:admin1_code":"60",
    "gn:asciiname":"Myurshyudoba",
    "gn:country_code":"AZ",
    "gn:dem":77,
    "gn:feature_class":"P",
    "gn:feature_code":"PPL",
    "gn:name":"Myurshyudoba",
    "gn:population":0,
    "gn:timezone":"Asia/Baku",
    "iso:country":"AZ",
    "name:azb_x_preferred":[
        "\u0645\u0648\u0631\u0634\u0648\u062f \u0627\u0648\u0628\u0627"
    ],
    "name:aze_x_preferred":[
        "M\u00fcr\u015f\u00fcdoba"
    ],
    "name:ceb_x_preferred":[
        "Myurshyudoba"
    ],
    "name:fas_x_preferred":[
        "\u0645\u0631\u0634\u062f\u0627\u0648\u0628\u0647"
    ],
    "name:ita_x_preferred":[
        "M\u00fcr\u015f\u00fcdoba"
    ],
    "name:kat_x_preferred":[
        "\u10db\u10e3\u10e0\u10e8\u10e3\u10d3\u10dd\u10d1\u10d0"
    ],
    "name:lez_x_preferred":[
        "\u041c\u0443\u044c\u0440\u0448\u0443\u044c\u0434\u0443\u0431\u0430"
    ],
    "name:msa_x_preferred":[
        "M\u00fcr\u015f\u00fcdoba"
    ],
    "name:swe_x_preferred":[
        "Myurshyudoba"
    ],
    "name:und_x_variant":[
        "Murshudoba",
        "M\u00fcr\u015f\u00fcdoba"
    ],
    "wof:name":"Myurshyudoba",
    "wof:placetype":"locality"
},
  "geometry": {"coordinates":[48.75611,41.50917000000001],"type":"Point"}
}