{
  "type": "Feature",
  "properties": {
    "gn:admin1_code":"60",
    "gn:asciiname":"Myurshyudoba",
    "gn:country_code":"AZ",
    "gn:dem":77,
    "gn:feature_class":"P",
    "gn:feature_code":"PPL",
    "gn:name":"Myurshyudoba",
    "gn:population":0,
    "gn:timezone":"Asia/Baku",
    "iso:country":"AZ",
    "name:und_x_variant":[
        "Murshudoba",
        "M\u00fcr\u015f\u00fcdoba"
    ],
    "wof:name":"Myurshyudoba",
    "wof:placetype":"locality"
},
  "geometry": {"coordinates":[48.75611,41.50917000000001],"type":"Point"}
}