{
  "type": "Feature",
  "properties": {
    "gn:admin1_code":"17",
    "gn:asciiname":"Qalagah",
    "gn:country_code":"AZ",
    "gn:dem":390,
    "gn:feature_class":"P",
    "gn:feature_code":"PPL",
    "gn:name":"Qalagah",
    "gn:population":0,
    "gn:timezone":"Asia/Baku",
    "iso:country":"AZ",
    "name:und_x_variant":[
        "Kelagyakh",
        "Kalagyakh",
        "Qalagah"
    ],
    "wof:name":"Qalagah",
    "wof:placetype":"locality"
},
  "geometry": {"coordinates":[48.86696,41.21824],"type":"Point"}
}