{
  "type": "Feature",
  "properties": {
    "gn:admin1_code":"12",
    "gn:asciiname":"Bolsulu",
    "gn:country_code":"AZ",
    "gn:dem":57,
    "gn:feature_class":"P",
    "gn:feature_code":"PPL",
    "gn:name":"Bolsulu",
    "gn:population":0,
    "gn:timezone":"Asia/Baku",
    "iso:country":"AZ",
    "name:aze_x_preferred":[
        "Bolsulu"
    ],
    "name:ceb_x_preferred":[
        "Bolsulu"
    ],
    "name:ita_x_preferred":[
        "Bolsulu"
    ],
    "name:kat_x_preferred":[
        "\u10d1\u10dd\u10da\u10e1\u10e3\u10da\u10e3"
    ],
    "name:msa_x_preferred":[
        "Bolsulu"
    ],
    "name:swe_x_preferred":[
        "Bolsulu"
    ],
    "wof:name":"Bolsulu",
    "wof:placetype":"locality"
},
  "geometry": {"coordinates":[47.57707,39.80028],"type":"Point"}
}