{
  "type": "Feature",
  "properties": {
    "gn:admin1_code":"21",
    "gn:asciiname":"Goran",
    "gn:country_code":"AZ",
    "gn:dem":95,
    "gn:feature_class":"P",
    "gn:feature_code":"PPL",
    "gn:name":"Goran",
    "gn:population":0,
    "gn:timezone":"Asia/Baku",
    "iso:country":"AZ",
    "name:und_x_variant":[
        "G\u00ebran",
        "G\u00f6ran"
    ],
    "wof:name":"Goran",
    "wof:placetype":"locality"
},
  "geometry": {"coordinates":[46.85248,40.65876],"type":"Point"}
}