{
  "type": "Feature",
  "properties": {
    "gn:admin1_code":"37",
    "gn:asciiname":"Asagi Filfili",
    "gn:country_code":"AZ",
    "gn:dem":1009,
    "gn:feature_class":"P",
    "gn:feature_code":"PPL",
    "gn:name":"A\u015fa\u011f\u0131 Filfili",
    "gn:population":0,
    "gn:timezone":"Asia/Baku",
    "iso:country":"AZ",
    "name:und_x_variant":[
        "Ashagy Fil\u2019filli",
        "Ashagy Fil\u2019fili",
        "A\u015fa\u011f\u0131 Filfili"
    ],
    "wof:name":"Asagi Filfili",
    "wof:placetype":"locality"
},
  "geometry": {"coordinates":[47.58274,41.09502],"type":"Point"}
}