{
  "type": "Feature",
  "properties": {
    "gn:admin1_code":"23",
    "gn:asciiname":"Navahi",
    "gn:country_code":"AZ",
    "gn:dem":33,
    "gn:feature_class":"P",
    "gn:feature_code":"PPL",
    "gn:name":"Navah\u0131",
    "gn:population":0,
    "gn:timezone":"Asia/Baku",
    "iso:country":"AZ",
    "name:aze_x_preferred":[
        "Navah\u0131"
    ],
    "name:eng_x_preferred":[
        "N\u01ddvah\u0131"
    ],
    "name:rus_x_preferred":[
        "\u041d\u0430\u0432\u0430\u0433\u0438"
    ],
    "name:und_x_variant":[
        "Navagi",
        "N\u0259vah\u0131"
    ],
    "wof:name":"Navahi",
    "wof:placetype":"locality"
},
  "geometry": {"coordinates":[49.09952,40.04031],"type":"Point"}
}