{
  "type": "Feature",
  "properties": {
    "gn:admin1_code":"10",
    "gn:asciiname":"Gyulyuzanbina",
    "gn:country_code":"AZ",
    "gn:dem":220,
    "gn:feature_class":"P",
    "gn:feature_code":"PPL",
    "gn:name":"Gyulyuzanbina",
    "gn:population":0,
    "gn:timezone":"Asia/Baku",
    "iso:country":"AZ",
    "name:aze_x_preferred":[
        "G\u00fcl\u00fczanbin\u0259"
    ],
    "name:und_x_variant":[
        "Gyuluzanbina",
        "Gyulyuzanbina",
        "Gyulyuzambina",
        "Guluzan-Bina",
        "G\u00fcl\u00fcz\u0259nbin\u0259"
    ],
    "wof:name":"Gyulyuzanbina",
    "wof:placetype":"locality"
},
  "geometry": {"coordinates":[46.33999,41.64804],"type":"Point"}
}