{
  "type": "Feature",
  "properties": {
    "gn:admin1_code":"19",
    "gn:asciiname":"Yenikend",
    "gn:country_code":"AZ",
    "gn:dem":1293,
    "gn:feature_class":"P",
    "gn:feature_code":"PPL",
    "gn:name":"Yenikend",
    "gn:population":0,
    "gn:timezone":"Asia/Baku",
    "iso:country":"AZ",
    "name:und_x_variant":[
        "Yenik\u0259nd"
    ],
    "wof:name":"Yenikend",
    "wof:placetype":"locality"
},
  "geometry": {"coordinates":[45.59201,40.57401],"type":"Point"}
}