{
  "type": "Feature",
  "properties": {
    "gn:admin1_code":"19",
    "gn:asciiname":"Yenikend",
    "gn:country_code":"AZ",
    "gn:dem":1293,
    "gn:feature_class":"P",
    "gn:feature_code":"PPL",
    "gn:name":"Yenikend",
    "gn:population":0,
    "gn:timezone":"Asia/Baku",
    "iso:country":"AZ",
    "name:aze_x_preferred":[
        "Yenik\u0259nd"
    ],
    "name:ceb_x_preferred":[
        "Yenikend"
    ],
    "name:ita_x_preferred":[
        "Yenik\u0259nd"
    ],
    "name:kat_x_preferred":[
        "\u10d8\u10d4\u10dc\u10d8\u10e5\u10d4\u10dc\u10d3\u10d8"
    ],
    "name:swe_x_preferred":[
        "Yenikend"
    ],
    "wof:name":"Yenikend",
    "wof:placetype":"locality"
},
  "geometry": {"coordinates":[45.59201,40.57401],"type":"Point"}
}