{
  "type": "Feature",
  "properties": {
    "gn:admin1_code":"24",
    "gn:asciiname":"Gobektala",
    "gn:country_code":"AZ",
    "gn:dem":4,
    "gn:feature_class":"P",
    "gn:feature_code":"PPL",
    "gn:name":"Gobektala",
    "gn:population":0,
    "gn:timezone":"Asia/Baku",
    "iso:country":"AZ",
    "name:aze_x_preferred":[
        "G\u00f6b\u0259ktala"
    ],
    "name:ceb_x_preferred":[
        "Gobektala"
    ],
    "name:ita_x_preferred":[
        "G\u00f6b\u0259ktala"
    ],
    "name:kat_x_preferred":[
        "\u10d2\u10d8\u10dd\u10d1\u10d0\u10e5\u10d7\u10d0\u10da\u10d0"
    ],
    "name:msa_x_preferred":[
        "G\u00f6b\u0259ktala"
    ],
    "name:rus_x_preferred":[
        "\u0413\u043e\u0431\u0435\u043a\u0442\u0430\u043b\u0430"
    ],
    "name:swe_x_preferred":[
        "Gobektala"
    ],
    "name:und_x_variant":[
        "Gebektala",
        "Gobektala",
        "G\u00f6b\u0259ktala"
    ],
    "wof:name":"Gobektala",
    "wof:placetype":"locality"
},
  "geometry": {"coordinates":[48.00724,39.81021],"type":"Point"}
}