{
  "type": "Feature",
  "properties": {
    "gn:admin1_code":"24",
    "gn:asciiname":"Bodzherevan",
    "gn:country_code":"AZ",
    "gn:dem":-7,
    "gn:feature_class":"P",
    "gn:feature_code":"PPL",
    "gn:name":"Bodzherevan",
    "gn:population":0,
    "gn:timezone":"Asia/Baku",
    "iso:country":"AZ",
    "name:und_x_variant":[
        "Badzhiravan",
        "B\u0259cir\u0259van"
    ],
    "wof:name":"Bodzherevan",
    "wof:placetype":"locality"
},
  "geometry": {"coordinates":[48.17818,39.90702],"type":"Point"}
}