{
  "type": "Feature",
  "properties": {
    "gn:admin1_code":"06",
    "gn:asciiname":"Kalagayli",
    "gn:country_code":"AZ",
    "gn:dem":254,
    "gn:feature_class":"P",
    "gn:feature_code":"PPL",
    "gn:name":"Kala\u011fayl\u0131",
    "gn:population":0,
    "gn:timezone":"Asia/Baku",
    "iso:country":"AZ",
    "name:aze_x_preferred":[
        "Kala\u011fayl\u0131"
    ],
    "name:ceb_x_preferred":[
        "Kala\u011fayl\u0131"
    ],
    "name:ita_x_preferred":[
        "Kala\u011fayl\u0131"
    ],
    "name:kat_x_preferred":[
        "\u10e5\u10d0\u10da\u10d0\u10e6\u10d0\u10e3\u10da\u10d8"
    ],
    "name:msa_x_preferred":[
        "Kala\u011fayl\u0131"
    ],
    "name:swe_x_preferred":[
        "Kala\u011fayl\u0131"
    ],
    "name:und_x_variant":[
        "Kalageyli",
        "Kalagayly",
        "Kalagayni",
        "Kala\u011fayl\u0131",
        "Kalabeyli"
    ],
    "wof:name":"Kalagayli",
    "wof:placetype":"locality"
},
  "geometry": {"coordinates":[48.28975,40.60311],"type":"Point"}
}