{
  "type": "Feature",
  "properties": {
    "gn:admin1_code":"06",
    "gn:asciiname":"Kasymbeyli",
    "gn:country_code":"AZ",
    "gn:dem":67,
    "gn:feature_class":"P",
    "gn:feature_code":"PPL",
    "gn:name":"Kasymbeyli",
    "gn:population":0,
    "gn:timezone":"Asia/Baku",
    "iso:country":"AZ",
    "name:aze_x_preferred":[
        "Qas\u0131mb\u0259yli"
    ],
    "name:und_x_variant":[
        "Kasumbeyli",
        "Kasymbeyli",
        "Qas\u0131mbeyli"
    ],
    "wof:name":"Kasymbeyli",
    "wof:placetype":"locality"
},
  "geometry": {"coordinates":[48.19877,40.53524],"type":"Point"}
}