{
  "type": "Feature",
  "properties": {
    "gn:admin1_code":"65",
    "gn:asciiname":"Arysh",
    "gn:country_code":"AZ",
    "gn:dem":604,
    "gn:feature_class":"P",
    "gn:feature_code":"PPL",
    "gn:name":"Arysh",
    "gn:population":0,
    "gn:timezone":"Asia/Baku",
    "iso:country":"AZ",
    "name:aze_x_preferred":[
        "Ar\u0131\u015f"
    ],
    "name:aze_x_variant":[
        "Aru\u015f"
    ],
    "name:hye_x_preferred":[
        "Aresh"
    ],
    "name:hye_x_variant":[
        "\u0531\u0580\u0565\u0577"
    ],
    "name:msa_x_preferred":[
        "Arysh"
    ],
    "name:rus_x_preferred":[
        "\u0410\u0440\u044b\u0448"
    ],
    "wof:name":"Arysh",
    "wof:placetype":"locality"
},
  "geometry": {"coordinates":[47.1029,39.53259],"type":"Point"}
}