{
  "type": "Feature",
  "properties": {
    "gn:admin1_code":"43",
    "gn:asciiname":"Qaragac",
    "gn:country_code":"AZ",
    "gn:dem":562,
    "gn:feature_class":"P",
    "gn:feature_code":"PPL",
    "gn:name":"Qara\u011fac",
    "gn:population":0,
    "gn:timezone":"Asia/Baku",
    "iso:country":"AZ",
    "name:aze_x_preferred":[
        "Qara\u011fac"
    ],
    "name:aze_x_variant":[
        "Qaraa\u011fac"
    ],
    "name:hye_x_preferred":[
        "K\u2019araaghach"
    ],
    "name:hye_x_variant":[
        "\u0554\u0561\u0580\u0561\u0561\u0572\u0561\u0579",
        "Getap\u2019",
        "\u0533\u0565\u057f\u0561\u0583"
    ],
    "name:rus_x_preferred":[
        "\u041a\u0430\u0440\u0430\u0430\u0433\u0430\u0447"
    ],
    "name:und_x_variant":[
        "Karaagach",
        "\u041a\u0430\u0440\u0430\u0430\u0433\u0430\u0447"
    ],
    "wof:name":"Qaragac",
    "wof:placetype":"locality"
},
  "geometry": {"coordinates":[46.6514,39.39489],"type":"Point"}
}