{
  "type": "Feature",
  "properties": {
    "gn:admin1_code":"46",
    "gn:asciiname":"Khankechan",
    "gn:country_code":"AZ",
    "gn:dem":-21,
    "gn:feature_class":"P",
    "gn:feature_code":"PPL",
    "gn:name":"Khankechan",
    "gn:population":0,
    "gn:timezone":"Asia/Baku",
    "iso:country":"AZ",
    "name:aze_x_preferred":[
        "Xanke\u00e7\u0259n"
    ],
    "wof:name":"Khankechan",
    "wof:placetype":"locality"
},
  "geometry": {"coordinates":[48.91481,39.756],"type":"Point"}
}