{
  "type": "Feature",
  "properties": {
    "gn:admin1_code":"69",
    "gn:asciiname":"Sobu",
    "gn:country_code":"AZ",
    "gn:dem":827,
    "gn:feature_class":"P",
    "gn:feature_code":"PPL",
    "gn:name":"Sobu",
    "gn:population":0,
    "gn:timezone":"Asia/Baku",
    "iso:country":"AZ",
    "name:aze_x_preferred":[
        "Sobu"
    ],
    "name:hye_x_preferred":[
        "Tzobi"
    ],
    "name:hye_x_variant":[
        "\u053e\u0578\u0562\u056b"
    ],
    "name:rus_x_preferred":[
        "\u0421\u043e\u0431\u0443"
    ],
    "wof:name":"Sobu",
    "wof:placetype":"locality"
},
  "geometry": {"coordinates":[46.58323,39.02514],"type":"Point"}
}