{
  "type": "Feature",
  "properties": {
    "gn:admin1_code":"03",
    "gn:asciiname":"Poladli",
    "gn:country_code":"AZ",
    "gn:dem":390,
    "gn:feature_class":"P",
    "gn:feature_code":"PPL",
    "gn:name":"Poladl\u0131",
    "gn:population":0,
    "gn:timezone":"Asia/Baku",
    "iso:country":"AZ",
    "name:aze_x_preferred":[
        "Poladl\u0131"
    ],
    "name:hye_x_preferred":[
        "\u0553\u0578\u056c\u0561\u0564\u056c\u0568"
    ],
    "name:hye_x_variant":[
        "P\u2019uladly"
    ],
    "name:rus_x_preferred":[
        "\u041f\u043e\u043b\u0430\u0434\u043b\u044b"
    ],
    "name:und_x_variant":[
        "Polatlu",
        "Poladly"
    ],
    "wof:name":"Poladli",
    "wof:placetype":"locality"
},
  "geometry": {"coordinates":[46.91517,39.96994],"type":"Point"}
}