{
  "type": "Feature",
  "properties": {
    "gn:admin1_code":"39",
    "gn:asciiname":"Baydarli",
    "gn:country_code":"AZ",
    "gn:dem":213,
    "gn:feature_class":"P",
    "gn:feature_code":"PPL",
    "gn:name":"Baydarl\u0131",
    "gn:population":0,
    "gn:timezone":"Asia/Baku",
    "iso:country":"AZ",
    "name:ava_x_preferred":[
        "\u0411\u0430\u0439\u0434\u0430\u0440"
    ],
    "name:aze_x_preferred":[
        "Baydarl\u0131"
    ],
    "name:ceb_x_preferred":[
        "Baydarl\u0131"
    ],
    "name:ita_x_preferred":[
        "Baydarl\u0131"
    ],
    "name:kat_x_preferred":[
        "\u10d1\u10d0\u10d8\u10d3\u10d0\u10e0\u10da\u10d8"
    ],
    "name:msa_x_preferred":[
        "Baydarl\u0131"
    ],
    "name:rus_x_preferred":[
        "\u0411\u0430\u0439\u0434\u0430\u0440\u043b\u044b"
    ],
    "name:swe_x_preferred":[
        "Baydarl\u0131"
    ],
    "name:und_x_variant":[
        "Baydarly"
    ],
    "wof:name":"Baydarli",
    "wof:placetype":"locality"
},
  "geometry": {"coordinates":[46.86805,41.27807],"type":"Point"}
}