{
  "type": "Feature",
  "properties": {
    "gn:admin1_code":"15",
    "gn:asciiname":"Tatlar",
    "gn:country_code":"AZ",
    "gn:dem":166,
    "gn:feature_class":"P",
    "gn:feature_code":"PPL",
    "gn:name":"Tatlar",
    "gn:population":0,
    "gn:timezone":"Asia/Baku",
    "iso:country":"AZ",
    "name:azb_x_preferred":[
        "\u062a\u0627\u062a\u0644\u0627\u0631"
    ],
    "name:fas_x_preferred":[
        "\u062a\u0627\u062a\u200c\u0644\u0627\u0631"
    ],
    "name:msa_x_preferred":[
        "Tatlar"
    ],
    "wof:name":"Tatlar",
    "wof:placetype":"locality"
},
  "geometry": {"coordinates":[48.30583,39.29111],"type":"Point"}
}