{
  "type": "Feature",
  "properties": {
    "gn:admin1_code":"65",
    "gn:asciiname":"Peretes",
    "gn:country_code":"AZ",
    "gn:dem":755,
    "gn:feature_class":"P",
    "gn:feature_code":"PPL",
    "gn:name":"Peretes",
    "gn:population":0,
    "gn:timezone":"Asia/Baku",
    "iso:country":"AZ",
    "name:hye_x_preferred":[
        "Peretes"
    ],
    "name:hye_x_variant":[
        "\u054a\u0565\u0580\u0565\u057f\u0565\u057d"
    ],
    "wof:name":"Peretes",
    "wof:placetype":"locality"
},
  "geometry": {"coordinates":[46.94754,39.73957],"type":"Point"}
}