{
  "type": "Feature",
  "properties": {
    "gn:admin1_code":"29",
    "gn:asciiname":"Alazalin",
    "gn:country_code":"AZ",
    "gn:dem":917,
    "gn:feature_class":"P",
    "gn:feature_code":"PPL",
    "gn:name":"Alazalin",
    "gn:population":0,
    "gn:timezone":"Asia/Baku",
    "iso:country":"AZ",
    "name:und_x_variant":[
        "\u018fl\u0259z\u0259pin",
        "Alazalin"
    ],
    "wof:name":"Alazalin",
    "wof:placetype":"locality"
},
  "geometry": {"coordinates":[48.64972,38.62006],"type":"Point"}
}