{
  "type": "Feature",
  "properties": {
    "gn:admin1_code":"28",
    "gn:asciiname":"Alakchi",
    "gn:country_code":"AZ",
    "gn:dem":1679,
    "gn:feature_class":"P",
    "gn:feature_code":"PPL",
    "gn:name":"Alakchi",
    "gn:population":0,
    "gn:timezone":"Asia/Baku",
    "iso:country":"AZ",
    "name:aze_x_preferred":[
        "\u018fl\u0259k\u00e7i"
    ],
    "name:hye_x_preferred":[
        "Alyak\u2019chi"
    ],
    "name:hye_x_variant":[
        "\u0531\u056c\u0575\u0561\u0584\u0579\u056b"
    ],
    "name:kat_x_preferred":[
        "\u10d0\u10da\u10d0\u10e5\u10e9\u10d8"
    ],
    "name:msa_x_preferred":[
        "\u018fl\u0259k\u00e7i"
    ],
    "name:rus_x_preferred":[
        "\u0410\u043b\u044f\u043a\u0447\u0438"
    ],
    "name:und_x_variant":[
        "Alyakchi"
    ],
    "wof:name":"Alakchi",
    "wof:placetype":"locality"
},
  "geometry": {"coordinates":[46.40474,39.90005],"type":"Point"}
}