{
  "type": "Feature",
  "properties": {
    "gn:admin1_code":"11",
    "gn:asciiname":"Kerimbeyli",
    "gn:country_code":"AZ",
    "gn:dem":20,
    "gn:feature_class":"P",
    "gn:feature_code":"PPL",
    "gn:name":"Kerimbeyli",
    "gn:population":0,
    "gn:timezone":"Asia/Baku",
    "iso:country":"AZ",
    "name:aze_x_preferred":[
        "K\u0259rimb\u0259yli"
    ],
    "wof:name":"Kerimbeyli",
    "wof:placetype":"locality"
},
  "geometry": {"coordinates":[47.25031,40.44961],"type":"Point"}
}