{
  "type": "Feature",
  "properties": {
    "gn:admin1_code":"41",
    "gn:asciiname":"Narimankend",
    "gn:country_code":"AZ",
    "gn:dem":776,
    "gn:feature_class":"P",
    "gn:feature_code":"PPL",
    "gn:name":"Narimankend",
    "gn:population":0,
    "gn:timezone":"Asia/Baku",
    "iso:country":"AZ",
    "name:eng_x_preferred":[
        "N\u01ddrimank\u01ddnd"
    ],
    "name:rus_x_preferred":[
        "\u041d\u0430\u0440\u0438\u043c\u0430\u043d\u043a\u0435\u043d\u0434"
    ],
    "name:und_x_variant":[
        "N\u0259rimank\u0259nd"
    ],
    "wof:name":"Narimankend",
    "wof:placetype":"locality"
},
  "geometry": {"coordinates":[48.93976,40.51606],"type":"Point"}
}