{
  "type": "Feature",
  "properties": {
    "gn:admin1_code":"17",
    "gn:asciiname":"Nohurlar",
    "gn:country_code":"AZ",
    "gn:dem":1283,
    "gn:feature_class":"P",
    "gn:feature_code":"PPL",
    "gn:name":"Nohurlar",
    "gn:population":0,
    "gn:timezone":"Asia/Baku",
    "iso:country":"AZ",
    "name:aze_x_preferred":[
        "Nohurlar"
    ],
    "name:eng_x_preferred":[
        "Nohurlar"
    ],
    "name:ita_x_preferred":[
        "Nohurlar"
    ],
    "name:msa_x_preferred":[
        "Nohurlar"
    ],
    "name:rus_x_preferred":[
        "\u041d\u043e\u0445\u0443\u0440\u043b\u0430\u0440"
    ],
    "name:und_x_variant":[
        "Nokhurlar",
        "Nohurlar"
    ],
    "wof:name":"Nohurlar",
    "wof:placetype":"locality"
},
  "geometry": {"coordinates":[48.77189,41.10356],"type":"Point"}
}