{
  "type": "Feature",
  "properties": {
    "gn:admin1_code":"28",
    "gn:asciiname":"Daygyan",
    "gn:country_code":"AZ",
    "gn:dem":1160,
    "gn:feature_class":"P",
    "gn:feature_code":"PPL",
    "gn:name":"Daygyan",
    "gn:population":0,
    "gn:timezone":"Asia/Baku",
    "iso:country":"AZ",
    "name:azb_x_preferred":[
        "\u062f\u06cc\u0647\u0627\u0646"
    ],
    "name:aze_x_preferred":[
        "D\u0259yhan"
    ],
    "name:fas_x_preferred":[
        "\u062f\u0647\u0642\u0627\u0646"
    ],
    "name:kat_x_preferred":[
        "\u10d3\u10d0\u10d8\u10f0\u10d0\u10dc\u10d8"
    ],
    "name:msa_x_preferred":[
        "D\u0259yhan"
    ],
    "name:rus_x_preferred":[
        "\u0414\u0435\u0439\u0445\u0430\u043d"
    ],
    "name:und_x_variant":[
        "Deykhan",
        "Daygyan",
        "\u0414\u0435\u0439\u0445\u0430\u043d"
    ],
    "wof:name":"Daygyan",
    "wof:placetype":"locality"
},
  "geometry": {"coordinates":[46.64467,39.5915],"type":"Point"}
}