{
  "type": "Feature",
  "properties": {
    "gn:admin1_code":"27",
    "gn:asciiname":"Melikumud",
    "gn:country_code":"AZ",
    "gn:dem":6,
    "gn:feature_class":"P",
    "gn:feature_code":"PPL",
    "gn:name":"Melikumud",
    "gn:population":0,
    "gn:timezone":"Asia/Baku",
    "iso:country":"AZ",
    "name:azb_x_preferred":[
        "\u0645\u0644\u06cc\u06a9 \u0627\u0648\u0645\u0648\u062f"
    ],
    "name:msa_x_preferred":[
        "Melikumud"
    ],
    "name:und_x_variant":[
        "Melikumu",
        "Melikumud"
    ],
    "wof:name":"Melikumud",
    "wof:placetype":"locality"
},
  "geometry": {"coordinates":[48.09603,40.44279],"type":"Point"}
}