{
  "type": "Feature",
  "properties": {
    "gn:admin1_code":"22",
    "gn:asciiname":"Incha",
    "gn:country_code":"AZ",
    "gn:dem":28,
    "gn:feature_class":"P",
    "gn:feature_code":"PPL",
    "gn:name":"Incha",
    "gn:population":0,
    "gn:timezone":"Asia/Baku",
    "iso:country":"AZ",
    "name:aze_x_preferred":[
        "\u0130n\u00e7\u0259"
    ],
    "name:eng_x_preferred":[
        "\u0130nc\u01dd"
    ],
    "name:rus_x_preferred":[
        "\u0418\u043d\u0447\u0430"
    ],
    "name:und_x_variant":[
        "\u0130nc\u0259"
    ],
    "wof:name":"Incha",
    "wof:placetype":"locality"
},
  "geometry": {"coordinates":[47.97416,40.55555],"type":"Point"}
}