{
  "type": "Feature",
  "properties": {
    "gn:admin1_code":"25",
    "gn:asciiname":"Arakit",
    "gn:country_code":"AZ",
    "gn:dem":1252,
    "gn:feature_class":"P",
    "gn:feature_code":"PPL",
    "gn:name":"Arakit",
    "gn:population":0,
    "gn:timezone":"Asia/Baku",
    "iso:country":"AZ",
    "name:azb_x_preferred":[
        "\u0627\u0631\u06a9\u06cc\u062a"
    ],
    "name:aze_x_preferred":[
        "\u018fr\u0259kit"
    ],
    "name:ceb_x_preferred":[
        "Arakit"
    ],
    "name:ell_x_preferred":[
        "\u0395\u03c1\u03b5\u03ba\u03af\u03c4"
    ],
    "name:fas_x_preferred":[
        "\u0627\u0631\u06a9\u06cc\u062a"
    ],
    "name:ita_x_preferred":[
        "\u018fr\u0259kit"
    ],
    "name:kat_x_preferred":[
        "\u10d0\u10e0\u10d0\u10e5\u10d8\u10d7\u10d8"
    ],
    "name:msa_x_preferred":[
        "\u018fr\u0259kit"
    ],
    "name:swe_x_preferred":[
        "Arakit"
    ],
    "wof:name":"Arakit",
    "wof:placetype":"locality"
},
  "geometry": {"coordinates":[48.39184,40.85212],"type":"Point"}
}