{
  "type": "Feature",
  "properties": {
    "gn:admin1_code":"25",
    "gn:asciiname":"Arakit",
    "gn:country_code":"AZ",
    "gn:dem":1252,
    "gn:feature_class":"P",
    "gn:feature_code":"PPL",
    "gn:name":"Arakit",
    "gn:population":0,
    "gn:timezone":"Asia/Baku",
    "iso:country":"AZ",
    "name:und_x_variant":[
        "\u018fr\u0259kit",
        "Arakit"
    ],
    "wof:name":"Arakit",
    "wof:placetype":"locality"
},
  "geometry": {"coordinates":[48.39184,40.85212],"type":"Point"}
}