{
  "type": "Feature",
  "properties": {
    "gn:admin1_code":"69",
    "gn:asciiname":"Kuyuderekheshtab",
    "gn:country_code":"AZ",
    "gn:dem":767,
    "gn:feature_class":"P",
    "gn:feature_code":"PPL",
    "gn:name":"Kuyuderekheshtab",
    "gn:population":0,
    "gn:timezone":"Asia/Baku",
    "iso:country":"AZ",
    "name:aze_x_preferred":[
        "Quyud\u0259r\u0259x\u0259\u015ftab"
    ],
    "name:rus_x_preferred":[
        "\u041a\u0443\u044e\u0434\u0435\u0440\u0435\u0445\u0435\u0448\u0442\u0430\u0431"
    ],
    "name:und_x_variant":[
        "Guydara Khashtab",
        "Kuyuderekheshtab"
    ],
    "wof:name":"Kuyuderekheshtab",
    "wof:placetype":"locality"
},
  "geometry": {"coordinates":[46.55989,39.17334],"type":"Point"}
}