{
  "type": "Feature",
  "properties": {
    "gn:country":"AZ",
    "gn:fcode":"PPL",
    "gn:pop":13340,
    "iso:country":"AZ",
    "name:aze_x_preferred":[
        "Pri\u015fib"
    ],
    "name:che_x_preferred":[
        "\u0413\u0451\u0439\u0442\u0435\u043f\u0435"
    ],
    "name:eng_x_preferred":[
        "G\u00f6yt\u0259p\u0259"
    ],
    "name:fin_x_preferred":[
        "G\u00f6yt\u0259p\u0259"
    ],
    "name:hye_x_preferred":[
        "\u0533\u0575\u0578\u0575\u0569\u0565\u0583\u0565"
    ],
    "name:msa_x_preferred":[
        "G\u00f6yt\u0259p\u0259"
    ],
    "name:nld_x_preferred":[
        "G\u00f6yt\u0259p\u0259"
    ],
    "name:pol_x_preferred":[
        "G\u00f6yt\u0259p\u0259"
    ],
    "name:rus_x_preferred":[
        "\u0413\u0451\u0439\u0442\u0435\u043f\u0435"
    ],
    "name:swe_x_preferred":[
        "G\u00f6jt\u00e4p\u00e4"
    ],
    "name:ukr_x_preferred":[
        "\u0413\u0435\u0439\u0442\u0435\u043f\u0435"
    ],
    "name:unk_x_variant":[
        "Prishib"
    ],
    "qs:name":"Prishibinskoye",
    "qs:photos_9r":0,
    "qs:photos_sr":0,
    "qs:pop_sr":"6",
    "wof:name":"Prishibinskoye",
    "wof:placetype":"locality",
    "wof:population":13340
},
  "geometry": {"coordinates":[48.59255,39.11817],"type":"Point"}
}