{
  "type": "Feature",
  "properties": {
    "gn:country":"AZ",
    "gn:fcode":"PPL",
    "gn:population":13340,
    "iso:country":"AZ",
    "name:ast_x_preferred":[
        "G\u00f6yt\u0259p\u0259"
    ],
    "name:azb_x_preferred":[
        "\u06af\u0624\u06cc \u062a\u067e\u0647"
    ],
    "name:aze_x_preferred":[
        "Pri\u015fib"
    ],
    "name:aze_x_variant":[
        "G\u00f6yt\u0259p\u0259"
    ],
    "name:bel_x_preferred":[
        "\u0413\u0451\u0439\u0442\u044d\u043f\u044d"
    ],
    "name:ceb_x_preferred":[
        "Prishibinskoye"
    ],
    "name:che_x_preferred":[
        "\u0413\u0451\u0439\u0442\u0435\u043f\u0435"
    ],
    "name:che_x_variant":[
        "\u0413\u043e\u044c\u0439\u0442\u0430\u044c\u043f\u0430\u044c"
    ],
    "name:deu_x_preferred":[
        "G\u00f6yt\u0259p\u0259"
    ],
    "name:eng_x_preferred":[
        "G\u00f6yt\u0259p\u0259"
    ],
    "name:fas_x_preferred":[
        "\u06af\u0648\u06cc\u200c\u062a\u067e\u0647"
    ],
    "name:fin_x_preferred":[
        "G\u00f6yt\u0259p\u0259"
    ],
    "name:fra_x_preferred":[
        "G\u00f6ytepe"
    ],
    "name:hsb_x_preferred":[
        "G\u00f6yt\u0259p\u0259"
    ],
    "name:hye_x_preferred":[
        "\u0533\u0575\u0578\u0575\u0569\u0565\u0583\u0565"
    ],
    "name:msa_x_preferred":[
        "G\u00f6yt\u0259p\u0259"
    ],
    "name:nld_x_preferred":[
        "G\u00f6yt\u0259p\u0259"
    ],
    "name:pol_x_preferred":[
        "G\u00f6yt\u0259p\u0259"
    ],
    "name:rus_x_preferred":[
        "\u0413\u0451\u0439\u0442\u0435\u043f\u0435"
    ],
    "name:swe_x_preferred":[
        "G\u00f6jt\u00e4p\u00e4"
    ],
    "name:tat_x_preferred":[
        "\u041a\u04af\u043a\u0442\u04af\u0431\u04d9"
    ],
    "name:tgk_x_preferred":[
        "\u0413\u0451\u0439\u0442\u0435\u043f\u0430"
    ],
    "name:tur_x_preferred":[
        "G\u00f6ytepe"
    ],
    "name:ukr_x_preferred":[
        "\u0413\u0435\u0439\u0442\u0435\u043f\u0435"
    ],
    "name:und_x_variant":[
        "Prishib"
    ],
    "name:uzb_x_preferred":[
        "G\u00f6yt\u0259p\u0259"
    ],
    "name:zho_x_preferred":[
        "\u84cb\u7279\u4f69"
    ],
    "qs:name":"Prishibinskoye",
    "qs:photos_9r":0,
    "qs:photos_sr":0,
    "qs:pop_sr":"6",
    "wof:name":"Prishibinskoye",
    "wof:placetype":"locality",
    "wof:population":13340
},
  "geometry": {"coordinates":[48.59255,39.11817],"type":"Point"}
}