{
  "type": "Feature",
  "properties": {
    "gn:admin1_code":"03",
    "gn:asciiname":"Syrkhavend",
    "gn:country_code":"AZ",
    "gn:dem":830,
    "gn:feature_class":"P",
    "gn:feature_code":"PPL",
    "gn:name":"Syrkhavend",
    "gn:population":0,
    "gn:timezone":"Asia/Baku",
    "iso:country":"AZ",
    "name:azb_x_preferred":[
        "\u0633\u06cc\u0631\u062e\u0627\u0648\u0646\u062f"
    ],
    "name:aze_x_preferred":[
        "S\u0131rxav\u0259nd"
    ],
    "name:aze_x_variant":[
        "Srxav\u0259nd"
    ],
    "name:bel_x_preferred":[
        "\u041d\u043e\u0440-\u0413\u0430\u0437\u0430\u043d\u0447\u044b"
    ],
    "name:ceb_x_preferred":[
        "Syrkhavend"
    ],
    "name:fas_x_preferred":[
        "\u0633\u0631\u062e\u0627\u0646\u200c\u0648\u0646\u062f"
    ],
    "name:fra_x_preferred":[
        "Nor Ghazanchi"
    ],
    "name:hye_x_preferred":[
        "\u054d\u0580\u056d\u0561\u057e\u0565\u0576\u0564"
    ],
    "name:hye_x_variant":[
        "Srkhavend",
        "Srkhavand",
        "\u054d\u0580\u056d\u0561\u057e\u0561\u0576\u0564",
        "Nor Ghazanch\u2019i",
        "\u0546\u0578\u0580 \u0542\u0561\u0566\u0561\u0576\u0579\u056b"
    ],
    "name:ita_x_preferred":[
        "Nor Ghazanchi"
    ],
    "name:kat_x_preferred":[
        "\u10e1\u10d8\u10e0\u10ee\u10d0\u10d5\u10d4\u10dc\u10d3\u10d8"
    ],
    "name:min_x_preferred":[
        "S\u0131rxav\u0259nd"
    ],
    "name:msa_x_preferred":[
        "S\u0131rxav\u0259nd"
    ],
    "name:rus_x_preferred":[
        "\u0421\u044b\u0440\u0445\u0430\u0432\u0435\u043d\u0434"
    ],
    "name:swe_x_preferred":[
        "Syrkhavend"
    ],
    "name:ukr_x_preferred":[
        "\u041d\u043e\u0440-\u0413\u0430\u0437\u0430\u043d\u0447\u0456"
    ],
    "name:und_x_variant":[
        "Srkhavend",
        "Sarkhavend",
        "Syrkhavend",
        "Srkhanvend"
    ],
    "wof:name":"Syrkhavend",
    "wof:placetype":"locality"
},
  "geometry": {"coordinates":[46.68574,40.06268],"type":"Point"}
}