{
  "type": "Feature",
  "properties": {
    "gn:admin1_code":"03",
    "gn:asciiname":"Syrkhavend",
    "gn:country_code":"AZ",
    "gn:dem":830,
    "gn:feature_class":"P",
    "gn:feature_code":"PPL",
    "gn:name":"Syrkhavend",
    "gn:population":0,
    "gn:timezone":"Asia/Baku",
    "iso:country":"AZ",
    "name:aze_x_preferred":[
        "S\u0131rxav\u0259nd"
    ],
    "name:aze_x_variant":[
        "Srxav\u0259nd"
    ],
    "name:hye_x_preferred":[
        "\u054d\u0580\u056d\u0561\u057e\u0565\u0576\u0564"
    ],
    "name:hye_x_variant":[
        "Srkhavend",
        "Srkhavand",
        "\u054d\u0580\u056d\u0561\u057e\u0561\u0576\u0564",
        "Nor Ghazanch\u2019i",
        "\u0546\u0578\u0580 \u0542\u0561\u0566\u0561\u0576\u0579\u056b"
    ],
    "name:rus_x_preferred":[
        "\u0421\u044b\u0440\u0445\u0430\u0432\u0435\u043d\u0434"
    ],
    "name:und_x_variant":[
        "Srkhavend",
        "Sarkhavend",
        "Syrkhavend",
        "Srkhanvend"
    ],
    "wof:name":"Syrkhavend",
    "wof:placetype":"locality"
},
  "geometry": {"coordinates":[46.68574,40.06268],"type":"Point"}
}