{
  "type": "Feature",
  "properties": {
    "gn:admin1_code":"43",
    "gn:asciiname":"Sariyataq",
    "gn:country_code":"AZ",
    "gn:dem":546,
    "gn:feature_class":"P",
    "gn:feature_code":"PPL",
    "gn:name":"Sar\u0131yataq",
    "gn:population":0,
    "gn:timezone":"Asia/Baku",
    "iso:country":"AZ",
    "name:aze_x_preferred":[
        "Sar\u0131yataq"
    ],
    "name:hye_x_preferred":[
        "Sarriyat\u2019agh"
    ],
    "name:hye_x_variant":[
        "\u054d\u0561\u057c\u056b\u0575\u0561\u0569\u0561\u0572",
        "Saratak",
        "\u054d\u0561\u0580\u0561\u057f\u0561\u056f"
    ],
    "name:rus_x_preferred":[
        "\u0421\u0430\u0440\u044b\u044f\u0442\u0430\u0433"
    ],
    "name:und_x_variant":[
        "Saryyatag",
        "Saryyatakh",
        "\u0421\u0430\u0440\u044b\u044f\u0442\u0430\u0433"
    ],
    "wof:name":"Sariyataq",
    "wof:placetype":"locality"
},
  "geometry": {"coordinates":[46.65988,39.3786],"type":"Point"}
}