{
  "type": "Feature",
  "properties": {
    "gn:admin1_code":"12",
    "gn:asciiname":"Altanskiy",
    "gn:country_code":"AZ",
    "gn:dem":48,
    "gn:feature_class":"P",
    "gn:feature_code":"PPL",
    "gn:name":"Altanskiy",
    "gn:population":0,
    "gn:timezone":"Asia/Baku",
    "iso:country":"AZ",
    "wof:name":"Altanskiy",
    "wof:placetype":"locality"
},
  "geometry": {"coordinates":[47.78333,39.65],"type":"Point"}
}