{
  "type": "Feature",
  "properties": {
    "gn:admin1_code":"69",
    "gn:asciiname":"Udkun",
    "gn:country_code":"AZ",
    "gn:dem":368,
    "gn:feature_class":"P",
    "gn:feature_code":"PPL",
    "gn:name":"Udkun",
    "gn:population":0,
    "gn:timezone":"Asia/Baku",
    "iso:country":"AZ",
    "name:aze_x_preferred":[
        "Udkun"
    ],
    "name:rus_x_preferred":[
        "\u0423\u0434\u0433\u044e\u043d"
    ],
    "name:und_x_variant":[
        "Udgyun"
    ],
    "wof:name":"Udkun",
    "wof:placetype":"locality"
},
  "geometry": {"coordinates":[46.69126,39.05799],"type":"Point"}
}