{
  "type": "Feature",
  "properties": {
    "gn:admin1_code":"67",
    "gn:asciiname":"Kolani",
    "gn:country_code":"AZ",
    "gn:dem":58,
    "gn:feature_class":"P",
    "gn:feature_code":"PPL",
    "gn:name":"Kolan\u0131",
    "gn:population":0,
    "gn:timezone":"Asia/Baku",
    "iso:country":"AZ",
    "name:aze_x_preferred":[
        "Kolan\u0131"
    ],
    "name:ita_x_preferred":[
        "Kelanly"
    ],
    "name:kat_x_preferred":[
        "\u10e5\u10d4\u10da\u10d0\u10dc\u10da\u10d8"
    ],
    "name:msa_x_preferred":[
        "Kelanly"
    ],
    "name:und_x_variant":[
        "Kelanly",
        "Kelany"
    ],
    "wof:name":"Kolani",
    "wof:placetype":"locality"
},
  "geometry": {"coordinates":[47.10127,40.48894],"type":"Point"}
}