{
  "type": "Feature",
  "properties": {
    "gn:admin1_code":"28",
    "gn:asciiname":"Korcabulaq",
    "gn:country_code":"AZ",
    "gn:dem":1710,
    "gn:feature_class":"P",
    "gn:feature_code":"PPL",
    "gn:name":"Korcabulaq",
    "gn:population":0,
    "gn:timezone":"Asia/Baku",
    "iso:country":"AZ",
    "name:aze_x_preferred":[
        "Korcabulaq"
    ],
    "name:hye_x_preferred":[
        "Aghbradzor"
    ],
    "name:hye_x_variant":[
        "\u0531\u0572\u0562\u0580\u0561\u0571\u0578\u0580"
    ],
    "name:rus_x_preferred":[
        "\u041a\u043e\u0440\u0447\u0443\u0431\u0443\u043b\u0430\u043a"
    ],
    "name:und_x_variant":[
        "Korchubulak",
        "Kyurdzhabulag",
        "\u041a\u043e\u0440\u0447\u0443\u0431\u0443\u043b\u0430\u043a"
    ],
    "wof:name":"Korcabulaq",
    "wof:placetype":"locality"
},
  "geometry": {"coordinates":[46.36752,39.86778],"type":"Point"}
}