{
  "type": "Feature",
  "properties": {
    "gn:admin1_code":"28",
    "gn:asciiname":"Korcabulaq",
    "gn:country_code":"AZ",
    "gn:dem":1710,
    "gn:feature_class":"P",
    "gn:feature_code":"PPL",
    "gn:name":"Korcabulaq",
    "gn:population":0,
    "gn:timezone":"Asia/Baku",
    "iso:country":"AZ",
    "name:azb_x_preferred":[
        "\u06a9\u0648\u0631\u062c\u0627\u0628\u0648\u0644\u0627\u0642"
    ],
    "name:aze_x_preferred":[
        "Korcabulaq"
    ],
    "name:bel_x_preferred":[
        "\u0410\u0445\u0431\u0440\u0430\u0434\u0437\u043e\u0440"
    ],
    "name:hye_x_preferred":[
        "Aghbradzor"
    ],
    "name:hye_x_variant":[
        "\u0531\u0572\u0562\u0580\u0561\u0571\u0578\u0580"
    ],
    "name:kat_x_preferred":[
        "\u10e5\u10dd\u10e0\u10ef\u10d0\u10d1\u10e3\u10da\u10d0\u10e5\u10d8"
    ],
    "name:msa_x_preferred":[
        "Korcabulaq"
    ],
    "name:rus_x_preferred":[
        "\u041a\u043e\u0440\u0447\u0443\u0431\u0443\u043b\u0430\u043a"
    ],
    "name:ukr_x_preferred":[
        "\u0410\u0445\u0431\u0440\u0430\u0434\u0437\u043e\u0440"
    ],
    "name:und_x_variant":[
        "Korchubulak",
        "Kyurdzhabulag"
    ],
    "wof:name":"Korcabulaq",
    "wof:placetype":"locality"
},
  "geometry": {"coordinates":[46.36752,39.86778],"type":"Point"}
}