{
  "type": "Feature",
  "properties": {
    "gn:admin1_code":"43",
    "gn:asciiname":"Zilanli",
    "gn:country_code":"AZ",
    "gn:dem":363,
    "gn:feature_class":"P",
    "gn:feature_code":"PPL",
    "gn:name":"Zilanl\u0131",
    "gn:population":0,
    "gn:timezone":"Asia/Baku",
    "iso:country":"AZ",
    "name:aze_x_preferred":[
        "Zilanl\u0131"
    ],
    "name:kat_x_preferred":[
        "\u10d6\u10d8\u10da\u10d0\u10dc\u10da\u10d8"
    ],
    "name:kur_x_preferred":[
        "Z\u00eelanl\u00ee"
    ],
    "name:msa_x_preferred":[
        "Zilanl\u0131"
    ],
    "name:rus_x_preferred":[
        "\u0417\u0438\u043b\u0430\u043d\u043b\u044b"
    ],
    "name:und_x_variant":[
        "Zilanly"
    ],
    "wof:name":"Zilanli",
    "wof:placetype":"locality"
},
  "geometry": {"coordinates":[46.73599,39.20475],"type":"Point"}
}