{
  "type": "Feature",
  "properties": {
    "gn:admin1_code":"31",
    "gn:asciiname":"Qilqlov",
    "gn:country_code":"AZ",
    "gn:dem":679,
    "gn:feature_class":"P",
    "gn:feature_code":"PPL",
    "gn:name":"Q\u0131lqlov",
    "gn:population":0,
    "gn:timezone":"Asia/Baku",
    "iso:country":"AZ",
    "name:und_x_variant":[
        "Gylglov",
        "Gel\u2019glov",
        "Q\u0131lqlov"
    ],
    "wof:name":"Qilqlov",
    "wof:placetype":"locality"
},
  "geometry": {"coordinates":[48.62101,38.67482],"type":"Point"}
}