{
  "type": "Feature",
  "properties": {
    "gn:admin1_code":"31",
    "gn:asciiname":"Sonacola",
    "gn:country_code":"AZ",
    "gn:dem":1326,
    "gn:feature_class":"P",
    "gn:feature_code":"PPL",
    "gn:name":"\u015eonacola",
    "gn:population":0,
    "gn:timezone":"Asia/Baku",
    "iso:country":"AZ",
    "name:azb_x_preferred":[
        "\u0634\u0648\u0646\u0627\u0686\u0648\u0644\u0627"
    ],
    "name:aze_x_preferred":[
        "\u015eona\u00e7ola"
    ],
    "name:ceb_x_preferred":[
        "\u015eonacola"
    ],
    "name:ita_x_preferred":[
        "\u015eona\u00e7ola"
    ],
    "name:msa_x_preferred":[
        "\u015eona\u00e7ola"
    ],
    "name:swe_x_preferred":[
        "\u015eonacola"
    ],
    "name:und_x_variant":[
        "Shona-Chola",
        "Shonadzhola",
        "\u015eonacola"
    ],
    "wof:name":"Sonacola",
    "wof:placetype":"locality"
},
  "geometry": {"coordinates":[48.40503,38.69143],"type":"Point"}
}