{
  "type": "Feature",
  "properties": {
    "gn:admin1_code":"53",
    "gn:asciiname":"Yukhary Alyaz",
    "gn:country_code":"AZ",
    "gn:dem":812,
    "gn:feature_class":"P",
    "gn:feature_code":"PPL",
    "gn:name":"Yukhary Alyaz",
    "gn:population":0,
    "gn:timezone":"Asia/Baku",
    "iso:country":"AZ",
    "name:aze_x_preferred":[
        "Yuxar\u0131 \u018fl\u0259z"
    ],
    "name:und_x_variant":[
        "Yukhary Alayaz",
        "Yukhary Alyaz",
        "Yukharu-Alyaz",
        "Yuxar\u0131 Alayaz"
    ],
    "wof:name":"Yukhary Alyaz",
    "wof:placetype":"locality"
},
  "geometry": {"coordinates":[48.96249,40.963],"type":"Point"}
}