{
  "type": "Feature",
  "properties": {
    "gn:admin1_code":"18",
    "gn:asciiname":"Yuxari Aybasanli",
    "gn:country_code":"AZ",
    "gn:dem":402,
    "gn:feature_class":"P",
    "gn:feature_code":"PPL",
    "gn:name":"Yuxar\u0131 Aybasanl\u0131",
    "gn:population":0,
    "gn:timezone":"Asia/Baku",
    "iso:country":"AZ",
    "name:aze_x_preferred":[
        "Yuxar\u0131 Aybasanl\u0131"
    ],
    "name:hye_x_preferred":[
        "Yukhary Aybasanli"
    ],
    "name:hye_x_variant":[
        "\u0545\u0578\u0582\u056d\u0561\u0580\u0568 \u0531\u0575\u0562\u0561\u057d\u0561\u0576\u056c\u056b"
    ],
    "name:rus_x_preferred":[
        "\u042e\u0445\u0430\u0440\u044b \u0410\u0439\u0431\u0430\u0441\u0430\u043d\u043b\u044b"
    ],
    "name:und_x_variant":[
        "Aybasanly",
        "\u042e\u0445\u0430\u0440\u044b \u0410\u0439\u0431\u0430\u0441\u0430\u043d\u043b\u044b",
        "Yukhary-Ayybasanly",
        "Yukhary Aybasanly"
    ],
    "wof:name":"Yuxari Aybasanli",
    "wof:placetype":"locality"
},
  "geometry": {"coordinates":[47.1694,39.59631],"type":"Point"}
}