{
  "type": "Feature",
  "properties": {
    "gn:admin1_code":"51",
    "gn:asciiname":"Atabey",
    "gn:country_code":"AZ",
    "gn:dem":1373,
    "gn:feature_class":"P",
    "gn:feature_code":"PPL",
    "gn:name":"Atabey",
    "gn:population":0,
    "gn:timezone":"Asia/Baku",
    "iso:country":"AZ",
    "name:aze_x_preferred":[
        "Atab\u0259y"
    ],
    "name:ceb_x_preferred":[
        "Atabey"
    ],
    "name:eng_x_preferred":[
        "Atab\u01ddy"
    ],
    "name:hye_x_preferred":[
        "\u0531\u0569\u0561\u0562\u0565\u0575"
    ],
    "name:ita_x_preferred":[
        "Atab\u0259y"
    ],
    "name:kat_x_preferred":[
        "\u10d0\u10d7\u10d0\u10d1\u10d4\u10d8"
    ],
    "name:msa_x_preferred":[
        "Atab\u0259y"
    ],
    "name:rus_x_preferred":[
        "\u0410\u0442\u0430\u0431\u0435\u043a"
    ],
    "name:swe_x_preferred":[
        "Atabey"
    ],
    "name:und_x_variant":[
        "Atabek"
    ],
    "wof:name":"Atabey",
    "wof:placetype":"locality"
},
  "geometry": {"coordinates":[45.82218,40.75204],"type":"Point"}
}