{
  "type": "Feature",
  "properties": {
    "gn:admin1_code":"51",
    "gn:asciiname":"Atabey",
    "gn:country_code":"AZ",
    "gn:dem":1373,
    "gn:feature_class":"P",
    "gn:feature_code":"PPL",
    "gn:name":"Atabey",
    "gn:population":0,
    "gn:timezone":"Asia/Baku",
    "iso:country":"AZ",
    "name:eng_x_preferred":[
        "Atab\u01ddy"
    ],
    "name:rus_x_preferred":[
        "\u0410\u0442\u0430\u0431\u0435\u043a"
    ],
    "name:und_x_variant":[
        "Atabek",
        "Atab\u0259y"
    ],
    "wof:name":"Atabey",
    "wof:placetype":"locality"
},
  "geometry": {"coordinates":[45.82218,40.75204],"type":"Point"}
}