{
  "type": "Feature",
  "properties": {
    "gn:admin1_code":"39",
    "gn:asciiname":"Zarna",
    "gn:country_code":"AZ",
    "gn:dem":455,
    "gn:feature_class":"P",
    "gn:feature_code":"PPL",
    "gn:name":"Zarna",
    "gn:population":0,
    "gn:timezone":"Asia/Baku",
    "iso:country":"AZ",
    "name:und_x_variant":[
        "Z\u0259rn\u0259",
        "Zarna"
    ],
    "wof:name":"Zarna",
    "wof:placetype":"locality"
},
  "geometry": {"coordinates":[46.81864,41.51292],"type":"Point"}
}