{
  "type": "Feature",
  "properties": {
    "gn:admin1_code":"39",
    "gn:asciiname":"Zarna",
    "gn:country_code":"AZ",
    "gn:dem":455,
    "gn:feature_class":"P",
    "gn:feature_code":"PPL",
    "gn:name":"Zarna",
    "gn:population":0,
    "gn:timezone":"Asia/Baku",
    "iso:country":"AZ",
    "name:ava_x_preferred":[
        "\u0426I\u043e\u0440\u043e\u043d\u0443\u0431"
    ],
    "name:aze_x_preferred":[
        "Z\u0259rn\u0259"
    ],
    "name:ceb_x_preferred":[
        "Zarna"
    ],
    "name:ita_x_preferred":[
        "Z\u0259rn\u0259"
    ],
    "name:kat_x_preferred":[
        "\u10d6\u10d0\u10e0\u10dc\u10d0"
    ],
    "name:msa_x_preferred":[
        "Z\u0259rn\u0259"
    ],
    "name:swe_x_preferred":[
        "Zarna"
    ],
    "wof:name":"Zarna",
    "wof:placetype":"locality"
},
  "geometry": {"coordinates":[46.81864,41.51292],"type":"Point"}
}