{
  "type": "Feature",
  "properties": {
    "gn:admin1_code":"28",
    "gn:asciiname":"Velibeyli",
    "gn:country_code":"AZ",
    "gn:dem":1677,
    "gn:feature_class":"P",
    "gn:feature_code":"PPL",
    "gn:name":"Velibeyli",
    "gn:population":0,
    "gn:timezone":"Asia/Baku",
    "iso:country":"AZ",
    "name:azb_x_preferred":[
        "\u0648\u0644\u06cc \u0628\u06cc\u200c\u0644\u06cc"
    ],
    "name:aze_x_preferred":[
        "V\u0259lib\u0259yli"
    ],
    "name:bel_x_preferred":[
        "\u0412\u0435\u0440\u044b\u0448\u044d\u043d"
    ],
    "name:hye_x_preferred":[
        "\u054e\u0561\u056c\u056b\u0562\u0565\u0575\u056c\u056b"
    ],
    "name:hye_x_variant":[
        "Valibeyli",
        "Verishen",
        "\u054e\u0565\u0580\u056b\u0577\u0565\u0576",
        "Verin Shen",
        "\u054e\u0565\u0580\u056b\u0576 \u0547\u0565\u0576"
    ],
    "name:kat_x_preferred":[
        "\u10d5\u10d0\u10da\u10d8\u10d1\u10d4\u10d8\u10da\u10d8"
    ],
    "name:msa_x_preferred":[
        "V\u0259lib\u0259yli"
    ],
    "name:rus_x_preferred":[
        "\u0412\u0435\u043b\u0438\u0431\u0435\u0439\u043b\u0438"
    ],
    "name:ukr_x_preferred":[
        "\u0412\u0435\u0440\u0456\u0448\u0435\u043d"
    ],
    "name:und_x_variant":[
        "Belibeyli",
        "Velibeyli",
        "\u0412\u0435\u043b\u0438\u0431\u0435\u0439\u043b\u0438"
    ],
    "wof:name":"Velibeyli",
    "wof:placetype":"locality"
},
  "geometry": {"coordinates":[46.29618,39.82192],"type":"Point"}
}