{
  "type": "Feature",
  "properties": {
    "gn:admin1_code":"11",
    "gn:asciiname":"Kyarana",
    "gn:country_code":"AZ",
    "gn:dem":73,
    "gn:feature_class":"P",
    "gn:feature_code":"PPL",
    "gn:name":"Kyarana",
    "gn:population":0,
    "gn:timezone":"Asia/Baku",
    "iso:country":"AZ",
    "name:aze_x_preferred":[
        "G\u0259r\u0259n\u0259"
    ],
    "name:aze_x_variant":[
        "\u00c7\u0259r\u0259k\u0259"
    ],
    "name:eng_x_preferred":[
        "G\u01ddr\u01ddn\u01dd"
    ],
    "name:rus_x_preferred":[
        "\u0413\u0435\u0440\u0430\u043d\u0430"
    ],
    "name:und_x_variant":[
        "G\u00ebrana",
        "Kyarana",
        "Oto Kelanly"
    ],
    "wof:name":"Kyarana",
    "wof:placetype":"locality"
},
  "geometry": {"coordinates":[47.11037,40.42562],"type":"Point"}
}