{
  "type": "Feature",
  "properties": {
    "gn:admin1_code":"11",
    "gn:asciiname":"Kyarana",
    "gn:country_code":"AZ",
    "gn:dem":73,
    "gn:feature_class":"P",
    "gn:feature_code":"PPL",
    "gn:name":"Kyarana",
    "gn:population":0,
    "gn:timezone":"Asia/Baku",
    "iso:country":"AZ",
    "name:azb_x_preferred":[
        "\u06af\u0631\u0646\u0647"
    ],
    "name:aze_x_preferred":[
        "G\u0259r\u0259n\u0259"
    ],
    "name:aze_x_variant":[
        "\u00c7\u0259r\u0259k\u0259"
    ],
    "name:ceb_x_preferred":[
        "Kyarana"
    ],
    "name:eng_x_preferred":[
        "G\u01ddr\u01ddn\u01dd"
    ],
    "name:fas_x_preferred":[
        "\u06af\u06cc\u0631\u0627\u0646\u0647"
    ],
    "name:ita_x_preferred":[
        "G\u0259r\u0259n\u0259"
    ],
    "name:kat_x_preferred":[
        "\u10d2\u10d0\u10e0\u10d0\u10dc\u10d0"
    ],
    "name:msa_x_preferred":[
        "G\u0259r\u0259n\u0259"
    ],
    "name:rus_x_preferred":[
        "\u0413\u0435\u0440\u0430\u043d\u0430"
    ],
    "name:swe_x_preferred":[
        "Kyarana"
    ],
    "name:und_x_variant":[
        "G\u00ebrana",
        "Oto Kelanly"
    ],
    "wof:name":"Kyarana",
    "wof:placetype":"locality"
},
  "geometry": {"coordinates":[47.11037,40.42562],"type":"Point"}
}