{
  "type": "Feature",
  "properties": {
    "gn:admin1_code":"25",
    "gn:asciiname":"Zeyva",
    "gn:country_code":"AZ",
    "gn:dem":1024,
    "gn:feature_class":"P",
    "gn:feature_code":"PPL",
    "gn:name":"Zeyva",
    "gn:population":0,
    "gn:timezone":"Asia/Baku",
    "iso:country":"AZ",
    "name:aze_x_preferred":[
        "Zeyv\u0259"
    ],
    "name:ita_x_preferred":[
        "Zeyva"
    ],
    "name:kat_x_preferred":[
        "\u10d6\u10d4\u10d8\u10d5\u10d0"
    ],
    "name:rus_x_preferred":[
        "\u0417\u0435\u0439\u0432\u0430"
    ],
    "wof:name":"Zeyva",
    "wof:placetype":"locality"
},
  "geometry": {"coordinates":[48.40022,40.75115],"type":"Point"}
}