{
  "type": "Feature",
  "properties": {
    "gn:admin1_code":"35",
    "gn:admin2_code":"7669114.0",
    "gn:asciiname":"Sixmahmud",
    "gn:country_code":"AZ",
    "gn:dem":922,
    "gn:feature_class":"P",
    "gn:feature_code":"PPL",
    "gn:name":"\u015e\u0131xmahmud",
    "gn:population":0,
    "gn:timezone":"Asia/Baku",
    "iso:country":"AZ",
    "name:azb_x_preferred":[
        "\u0634\u06cc\u062e\u200c\u0645\u062d\u0645\u0648\u062f"
    ],
    "name:aze_x_preferred":[
        "\u015e\u0131xmahmud"
    ],
    "name:ceb_x_preferred":[
        "\u015e\u0131xmahmud"
    ],
    "name:fas_x_preferred":[
        "\u0634\u06cc\u062e\u200c\u0645\u062d\u0645\u0648\u062f"
    ],
    "name:hye_x_preferred":[
        "\u0547\u0574\u0580\u0569\u0561"
    ],
    "name:ita_x_preferred":[
        "\u015e\u0131xmahmud"
    ],
    "name:kat_x_preferred":[
        "\u10e8\u10d8\u10ee\u10db\u10d0\u10ee\u10db\u10e3\u10d3\u10d8"
    ],
    "name:msa_x_preferred":[
        "\u015e\u0131xmahmud"
    ],
    "name:swe_x_preferred":[
        "\u015e\u0131xmahmud"
    ],
    "name:und_x_variant":[
        "Shikhmakhmud",
        "Shykhmakhmud"
    ],
    "wof:name":"Sixmahmud",
    "wof:placetype":"locality"
},
  "geometry": {"coordinates":[45.42994,39.25313],"type":"Point"}
}