{
  "type": "Feature",
  "properties": {
    "gn:admin1_code":"35",
    "gn:admin2_code":"7669114.0",
    "gn:asciiname":"Sixmahmud",
    "gn:country_code":"AZ",
    "gn:dem":922,
    "gn:feature_class":"P",
    "gn:feature_code":"PPL",
    "gn:name":"\u015e\u0131xmahmud",
    "gn:population":0,
    "gn:timezone":"Asia/Baku",
    "iso:country":"AZ",
    "name:aze_x_preferred":[
        "\u015e\u0131xmahmud"
    ],
    "name:und_x_variant":[
        "Shikhmakhmud",
        "Shykhmakhmud"
    ],
    "wof:name":"Sixmahmud",
    "wof:placetype":"locality"
},
  "geometry": {"coordinates":[45.42994,39.25313],"type":"Point"}
}