{
  "type": "Feature",
  "properties": {
    "gn:admin1_code":"26",
    "gn:asciiname":"Quzeycirkin",
    "gn:country_code":"AZ",
    "gn:dem":1616,
    "gn:feature_class":"P",
    "gn:feature_code":"PPL",
    "gn:name":"Quzey\u00e7irkin",
    "gn:population":0,
    "gn:timezone":"Asia/Baku",
    "iso:country":"AZ",
    "name:aze_x_preferred":[
        "Guzey\u00e7irkin"
    ],
    "name:aze_x_variant":[
        "Quzey\u00e7irkin"
    ],
    "name:hye_x_preferred":[
        "Zovk\u2019"
    ],
    "name:hye_x_variant":[
        "\u0536\u0578\u057e\u0584"
    ],
    "name:rus_x_preferred":[
        "\u0413\u044e\u0437\u0435\u0439\u0447\u0438\u0440\u043a\u0438\u043d"
    ],
    "name:und_x_variant":[
        "Gezal-Chirkin",
        "Kyuzey-Chirkin",
        "Gyuzeychirkin"
    ],
    "wof:name":"Quzeycirkin",
    "wof:placetype":"locality"
},
  "geometry": {"coordinates":[46.12532,40.14785],"type":"Point"}
}