{
  "type": "Feature",
  "properties": {
    "gn:admin1_code":"29",
    "gn:asciiname":"Lyuvasar",
    "gn:country_code":"AZ",
    "gn:dem":7,
    "gn:feature_class":"P",
    "gn:feature_code":"PPL",
    "gn:name":"Lyuvasar",
    "gn:population":0,
    "gn:timezone":"Asia/Baku",
    "iso:country":"AZ",
    "name:und_x_variant":[
        "L\u00fcv\u0259s\u0259r",
        "Lyuvasar"
    ],
    "wof:name":"Lyuvasar",
    "wof:placetype":"locality"
},
  "geometry": {"coordinates":[48.79744,38.70934000000001],"type":"Point"}
}