{
  "type": "Feature",
  "properties": {
    "gn:admin1_code":"01",
    "gn:asciiname":"Goradil",
    "gn:country_code":"AZ",
    "gn:dem":39,
    "gn:feature_class":"P",
    "gn:feature_code":"PPL",
    "gn:name":"Goradil",
    "gn:population":0,
    "gn:timezone":"Asia/Baku",
    "iso:country":"AZ",
    "name:aze_x_preferred":[
        "Goradil"
    ],
    "name:rus_x_preferred":[
        "Goradil\u2019"
    ],
    "name:und_x_variant":[
        "Gerodil\u2019",
        "Gorodil\u2019"
    ],
    "wof:name":"Goradil",
    "wof:placetype":"locality"
},
  "geometry": {"coordinates":[49.82972,40.54861],"type":"Point"}
}