{
  "type": "Feature",
  "properties": {
    "gn:admin1_code":"01",
    "gn:asciiname":"Goradil",
    "gn:country_code":"AZ",
    "gn:dem":39,
    "gn:feature_class":"P",
    "gn:feature_code":"PPL",
    "gn:name":"Goradil",
    "gn:population":0,
    "gn:timezone":"Asia/Baku",
    "iso:country":"AZ",
    "name:aze_x_preferred":[
        "Goradil"
    ],
    "name:aze_x_variant":[
        "G\u00f6r\u0259dil"
    ],
    "name:ceb_x_preferred":[
        "Goradil"
    ],
    "name:che_x_preferred":[
        "\u0413\u043e\u0440\u0430\u0434\u0438\u043b"
    ],
    "name:kat_x_preferred":[
        "\u10d2\u10dd\u10e0\u10d0\u10d3\u10d8\u10da\u10d8"
    ],
    "name:pol_x_preferred":[
        "Goradil"
    ],
    "name:rus_x_preferred":[
        "Goradil\u2019"
    ],
    "name:swe_x_preferred":[
        "Goradil"
    ],
    "name:und_x_variant":[
        "Gerodil\u2019",
        "Gorodil\u2019"
    ],
    "wof:name":"Goradil",
    "wof:placetype":"locality"
},
  "geometry": {"coordinates":[49.82972,40.54861],"type":"Point"}
}