{
  "type": "Feature",
  "properties": {
    "gn:admin1_code":"44",
    "gn:asciiname":"Girik",
    "gn:country_code":"AZ",
    "gn:dem":468,
    "gn:feature_class":"P",
    "gn:feature_code":"PPL",
    "gn:name":"Girik",
    "gn:population":0,
    "gn:timezone":"Asia/Baku",
    "iso:country":"AZ",
    "name:aze_x_preferred":[
        "Girik"
    ],
    "name:ceb_x_preferred":[
        "Girik"
    ],
    "name:ita_x_preferred":[
        "Girik"
    ],
    "name:kat_x_preferred":[
        "\u10d2\u10d8\u10e0\u10d8\u10e5\u10d8"
    ],
    "name:lez_x_preferred":[
        "\u041a\u0438\u0440\u0438\u0433\u0430\u0440"
    ],
    "name:msa_x_preferred":[
        "Girik"
    ],
    "wof:name":"Girik",
    "wof:placetype":"locality"
},
  "geometry": {"coordinates":[48.2794,41.53674],"type":"Point"}
}