{
  "type": "Feature",
  "properties": {
    "gn:admin1_code":"44",
    "gn:asciiname":"Girik",
    "gn:country_code":"AZ",
    "gn:dem":468,
    "gn:feature_class":"P",
    "gn:feature_code":"PPL",
    "gn:name":"Girik",
    "gn:population":0,
    "gn:timezone":"Asia/Baku",
    "iso:country":"AZ",
    "wof:name":"Girik",
    "wof:placetype":"locality"
},
  "geometry": {"coordinates":[48.2794,41.53674],"type":"Point"}
}