{
  "type": "Feature",
  "properties": {
    "gn:admin1_code":"28",
    "gn:asciiname":"Farrash",
    "gn:country_code":"AZ",
    "gn:dem":1841,
    "gn:feature_class":"P",
    "gn:feature_code":"PPL",
    "gn:name":"Farrash",
    "gn:population":0,
    "gn:timezone":"Asia/Baku",
    "iso:country":"AZ",
    "name:azb_x_preferred":[
        "\u0641\u0631\u0627\u0634"
    ],
    "name:aze_x_preferred":[
        "F\u0259rra\u015f"
    ],
    "name:fas_x_preferred":[
        "\u0641\u0631\u0627\u0634"
    ],
    "name:hye_x_preferred":[
        "Faraj"
    ],
    "name:hye_x_variant":[
        "\u0556\u0561\u0580\u0561\u057b",
        "P\u2019arajants\u2019",
        "\u0553\u0561\u0580\u0561\u057b\u0561\u0576\u0581"
    ],
    "name:kat_x_preferred":[
        "\u10e4\u10d0\u10e0\u10d0\u10e8\u10d8"
    ],
    "name:msa_x_preferred":[
        "F\u0259rra\u015f"
    ],
    "name:rus_x_preferred":[
        "\u0424\u0430\u0440\u0440\u0430\u0434\u0436"
    ],
    "name:und_x_variant":[
        "Farradzh",
        "\u0424\u0430\u0440\u0440\u0430\u0434\u0436"
    ],
    "wof:name":"Farrash",
    "wof:placetype":"locality"
},
  "geometry": {"coordinates":[46.51575,39.84019],"type":"Point"}
}