{
  "type": "Feature",
  "properties": {
    "gn:asciiname":"Balabur",
    "gn:country_code":"AZ",
    "gn:dem":5,
    "gn:feature_class":"P",
    "gn:feature_code":"PPL",
    "gn:name":"Balabur",
    "gn:population":0,
    "gn:timezone":"Asia/Baku",
    "iso:country":"AZ",
    "wof:name":"Balabur",
    "wof:placetype":"locality"
},
  "geometry": {"coordinates":[48.80406,38.69958],"type":"Point"}
}