{
  "type": "Feature",
  "properties": {
    "gn:admin1_code":"67",
    "gn:asciiname":"Karamamedly",
    "gn:country_code":"AZ",
    "gn:dem":63,
    "gn:feature_class":"P",
    "gn:feature_code":"PPL",
    "gn:name":"Karamamedly",
    "gn:population":0,
    "gn:timezone":"Asia/Baku",
    "iso:country":"AZ",
    "name:aze_x_preferred":[
        "Qaram\u0259mm\u0259dli"
    ],
    "name:und_x_variant":[
        "Karamamedli",
        "Karamamedly"
    ],
    "wof:name":"Karamamedly",
    "wof:placetype":"locality"
},
  "geometry": {"coordinates":[47.03015,40.54186],"type":"Point"}
}