{
  "type": "Feature",
  "properties": {
    "gn:admin1_code":"45",
    "gn:asciiname":"Maztaly",
    "gn:country_code":"AZ",
    "gn:dem":-7,
    "gn:feature_class":"P",
    "gn:feature_code":"PPL",
    "gn:name":"Maztaly",
    "gn:population":0,
    "gn:timezone":"Asia/Baku",
    "iso:country":"AZ",
    "name:aze_x_preferred":[
        "M\u0259zr\u0259li"
    ],
    "name:aze_x_variant":[
        "M\u0259rz\u0259li",
        "Yuxar\u0131 Hac\u0131qas\u0131ml\u0131"
    ],
    "name:msa_x_preferred":[
        "Yuxar\u0131 Hac\u0131qas\u0131ml\u0131"
    ],
    "name:und_x_variant":[
        "Mazra",
        "Maztaly",
        "Mazrali",
        "Gadzhykasymly",
        "Gadzhikasymly",
        "Gadzhi-Kasumly",
        "Yukhary Gadzhykasymly"
    ],
    "name:urd_x_preferred":[
        "\u06cc\u06a9\u0634\u0627\u0631\u06cc \u06c1\u0627\u06a9\u06cc\u0642\u0635\u06cc\u0645\u0644\u06cc"
    ],
    "wof:name":"Maztaly",
    "wof:placetype":"locality"
},
  "geometry": {"coordinates":[48.23304,39.91357],"type":"Point"}
}