{
  "type": "Feature",
  "properties": {
    "gn:admin1_code":"47",
    "gn:asciiname":"Alyar",
    "gn:country_code":"AZ",
    "gn:dem":414,
    "gn:feature_class":"P",
    "gn:feature_code":"PPL",
    "gn:name":"Alyar",
    "gn:population":0,
    "gn:timezone":"Asia/Baku",
    "iso:country":"AZ",
    "name:eng_x_preferred":[
        "\u018fliyar"
    ],
    "name:rus_x_preferred":[
        "\u0410\u043b\u0438\u044f\u0440"
    ],
    "name:und_x_variant":[
        "\u018fliyar",
        "Aliyar"
    ],
    "wof:name":"Alyar",
    "wof:placetype":"locality"
},
  "geometry": {"coordinates":[47.25314,41.00624000000001],"type":"Point"}
}