{
  "type": "Feature",
  "properties": {
    "gn:admin1_code":"46",
    "gn:asciiname":"Col Dallak",
    "gn:country_code":"AZ",
    "gn:dem":-21,
    "gn:feature_class":"P",
    "gn:feature_code":"PPL",
    "gn:name":"\u00c7\u00f6l D\u0259ll\u0259k",
    "gn:population":0,
    "gn:timezone":"Asia/Baku",
    "iso:country":"AZ",
    "name:aze_x_preferred":[
        "\u00c7\u00f6l D\u0259ll\u0259k"
    ],
    "name:ceb_x_preferred":[
        "\u00c7\u00f6l D\u0259ll\u0259k"
    ],
    "name:ita_x_preferred":[
        "\u00c7\u00f6l D\u0259ll\u0259k"
    ],
    "name:msa_x_preferred":[
        "\u00c7\u00f6l D\u0259ll\u0259k"
    ],
    "name:swe_x_preferred":[
        "\u00c7\u00f6l D\u0259ll\u0259k"
    ],
    "name:und_x_variant":[
        "Ch\u00ebl\u2019dellyak",
        "Chol\u2019-Dallyak",
        "\u00c7\u00f6l D\u0259ll\u0259k"
    ],
    "wof:name":"Col Dallak",
    "wof:placetype":"locality"
},
  "geometry": {"coordinates":[48.79333,39.83598],"type":"Point"}
}