{
  "type": "Feature",
  "properties": {
    "gn:admin1_code":"28",
    "gn:asciiname":"Khanlanty",
    "gn:country_code":"AZ",
    "gn:dem":862,
    "gn:feature_class":"P",
    "gn:feature_code":"PPL",
    "gn:name":"Khanlanty",
    "gn:population":0,
    "gn:timezone":"Asia/Baku",
    "iso:country":"AZ",
    "wof:name":"Khanlanty",
    "wof:placetype":"locality"
},
  "geometry": {"coordinates":[46.52861,39.60144],"type":"Point"}
}