{
  "type": "Feature",
  "properties": {
    "gn:admin1_code":"11",
    "gn:asciiname":"Qaragaci",
    "gn:country_code":"AZ",
    "gn:dem":56,
    "gn:feature_class":"P",
    "gn:feature_code":"PPL",
    "gn:name":"Qara\u011fac\u0131",
    "gn:population":0,
    "gn:timezone":"Asia/Baku",
    "iso:country":"AZ",
    "name:aze_x_preferred":[
        "Harahac\u0131"
    ],
    "name:aze_x_variant":[
        "Qarahac\u0131",
        "Qara\u011fac\u0131"
    ],
    "name:und_x_variant":[
        "Karagaadzhi",
        "Karagadzhy"
    ],
    "wof:name":"Qaragaci",
    "wof:placetype":"locality"
},
  "geometry": {"coordinates":[47.14745,40.46375],"type":"Point"}
}