{
  "type": "Feature",
  "properties": {
    "gn:admin1_code":"04",
    "gn:asciiname":"Kakhay",
    "gn:country_code":"AZ",
    "gn:dem":5,
    "gn:feature_class":"P",
    "gn:feature_code":"PPL",
    "gn:name":"Kakhay",
    "gn:population":0,
    "gn:timezone":"Asia/Baku",
    "iso:country":"AZ",
    "name:ita_x_preferred":[
        "Kakhay"
    ],
    "name:kat_x_preferred":[
        "\u10e5\u10d0\u10ee\u10d0\u10d8"
    ],
    "name:msa_x_preferred":[
        "Kakhay"
    ],
    "wof:name":"Kakhay",
    "wof:placetype":"locality"
},
  "geometry": {"coordinates":[47.43333,40.33333],"type":"Point"}
}