{
  "type": "Feature",
  "properties": {
    "gn:admin1_code":"05",
    "gn:asciiname":"Pirili",
    "gn:country_code":"AZ",
    "gn:dem":306,
    "gn:feature_class":"P",
    "gn:feature_code":"PPL",
    "gn:name":"Pirili",
    "gn:population":0,
    "gn:timezone":"Asia/Baku",
    "iso:country":"AZ",
    "name:azb_x_preferred":[
        "\u067e\u06cc\u0631\u06cc\u0644\u06cc"
    ],
    "name:aze_x_preferred":[
        "Pirili"
    ],
    "name:ceb_x_preferred":[
        "Pirili"
    ],
    "name:hye_x_preferred":[
        "\u0553\u056b\u0580\u056b\u056c\u056b"
    ],
    "name:ita_x_preferred":[
        "Pirili"
    ],
    "name:kat_x_preferred":[
        "\u10e4\u10d8\u10e0\u10d8\u10da\u10d8"
    ],
    "name:msa_x_preferred":[
        "Pirili"
    ],
    "name:swe_x_preferred":[
        "Pirili"
    ],
    "wof:name":"Pirili",
    "wof:placetype":"locality"
},
  "geometry": {"coordinates":[45.39328,41.20447],"type":"Point"}
}