{
  "type": "Feature",
  "properties": {
    "gn:admin1_code":"25",
    "gn:asciiname":"Vank Pervyy",
    "gn:country_code":"AZ",
    "gn:dem":721,
    "gn:feature_class":"P",
    "gn:feature_code":"PPL",
    "gn:name":"Vank Pervyy",
    "gn:population":0,
    "gn:timezone":"Asia/Baku",
    "iso:country":"AZ",
    "name:eng_x_preferred":[
        "V\u01ddng"
    ],
    "name:rus_x_preferred":[
        "\u0412\u0430\u043d\u043a"
    ],
    "name:und_x_variant":[
        "Bank",
        "Vank Pervyy",
        "Vank",
        "V\u0259ng"
    ],
    "wof:name":"Vank Pervyy",
    "wof:placetype":"locality"
},
  "geometry": {"coordinates":[47.93492,40.81024],"type":"Point"}
}