{
  "type": "Feature",
  "properties": {
    "gn:admin1_code":"64",
    "gn:asciiname":"Xanyeri",
    "gn:country_code":"AZ",
    "gn:dem":931,
    "gn:feature_class":"P",
    "gn:feature_code":"PPL",
    "gn:name":"Xanyeri",
    "gn:population":0,
    "gn:timezone":"Asia/Baku",
    "iso:country":"AZ",
    "name:aze_x_preferred":[
        "Xanyeri"
    ],
    "name:hye_x_preferred":[
        "Khants\u2019k\u2019"
    ],
    "name:hye_x_variant":[
        "\u053d\u0561\u0576\u0581\u0584"
    ],
    "name:rus_x_preferred":[
        "\u0425\u0430\u043d\u0446\u043a"
    ],
    "name:und_x_variant":[
        "Khandzk\u2019",
        "Xantsk",
        "Khantsk",
        "\u0425\u0430\u043d\u0446\u043a"
    ],
    "wof:name":"Xanyeri",
    "wof:placetype":"locality"
},
  "geometry": {"coordinates":[46.6806,39.93668],"type":"Point"}
}