{
  "type": "Feature",
  "properties": {
    "gn:admin1_code":"49",
    "gn:asciiname":"Komsomol",
    "gn:country_code":"AZ",
    "gn:dem":-24,
    "gn:feature_class":"P",
    "gn:feature_code":"PPL",
    "gn:name":"Komsomol",
    "gn:population":0,
    "gn:timezone":"Asia/Baku",
    "iso:country":"AZ",
    "name:azb_x_preferred":[
        "\u06a9\u0648\u0645\u0633\u0648\u0645\u0648\u0644"
    ],
    "name:aze_x_preferred":[
        "\u018fr\u0259bqarda\u015fb\u0259yli"
    ],
    "name:ita_x_preferred":[
        "Komsomol"
    ],
    "name:msa_x_preferred":[
        "Komsomol"
    ],
    "name:und_x_variant":[
        "Arab-Kardashbeyli",
        "Komsomol"
    ],
    "wof:name":"Komsomol",
    "wof:placetype":"locality"
},
  "geometry": {"coordinates":[49.00334,39.52084],"type":"Point"}
}