{
  "type": "Feature",
  "properties": {
    "gn:admin1_code":"12",
    "gn:asciiname":"Yukhary-Chemenli",
    "gn:country_code":"AZ",
    "gn:dem":31,
    "gn:feature_class":"P",
    "gn:feature_code":"PPL",
    "gn:name":"Yukhary-Chemenli",
    "gn:population":0,
    "gn:timezone":"Asia/Baku",
    "iso:country":"AZ",
    "name:aze_x_preferred":[
        "Yuxar\u0131 \u00c7\u0259m\u0259nli"
    ],
    "wof:name":"Yukhary-Chemenli",
    "wof:placetype":"locality"
},
  "geometry": {"coordinates":[47.79381,39.6725],"type":"Point"}
}