{
  "type": "Feature",
  "properties": {
    "gn:admin1_code":"47",
    "gn:asciiname":"Qayabasi",
    "gn:country_code":"AZ",
    "gn:dem":283,
    "gn:feature_class":"P",
    "gn:feature_code":"PPL",
    "gn:name":"Qayaba\u015f\u0131",
    "gn:population":0,
    "gn:timezone":"Asia/Baku",
    "iso:country":"AZ",
    "name:azb_x_preferred":[
        "\u0642\u0627\u06cc\u0627\u0628\u0627\u0634\u06cc"
    ],
    "name:aze_x_preferred":[
        "Qayaba\u015f\u0131"
    ],
    "name:ceb_x_preferred":[
        "Qayaba\u015f\u0131"
    ],
    "name:ita_x_preferred":[
        "Qayaba\u015f\u0131"
    ],
    "name:msa_x_preferred":[
        "Qayaba\u015f\u0131"
    ],
    "name:swe_x_preferred":[
        "Qayaba\u015f\u0131"
    ],
    "name:und_x_variant":[
        "Kayabasby",
        "Kayabashy",
        "Qayabas\u0131"
    ],
    "wof:name":"Qayabasi",
    "wof:placetype":"locality"
},
  "geometry": {"coordinates":[47.35038,40.89188],"type":"Point"}
}