{
  "type": "Feature",
  "properties": {
    "gn:admin1_code":"28",
    "gn:asciiname":"Nizhneye Akh-Kerpi",
    "gn:country_code":"AZ",
    "gn:dem":1536,
    "gn:feature_class":"P",
    "gn:feature_code":"PPL",
    "gn:name":"Nizhneye Akh-Kerpi",
    "gn:population":0,
    "gn:timezone":"Asia/Baku",
    "iso:country":"AZ",
    "name:kat_x_preferred":[
        "\u10dc\u10d8\u10df\u10dc\u10d4\u10d4 \u10d0\u10ee-\u10e5\u10d4\u10e0\u10e4\u10d8"
    ],
    "name:msa_x_preferred":[
        "Nizhneye Akh-Kerpi"
    ],
    "wof:name":"Nizhneye Akh-Kerpi",
    "wof:placetype":"locality"
},
  "geometry": {"coordinates":[46.28944,39.77722],"type":"Point"}
}