{
  "type": "Feature",
  "properties": {
    "gn:admin1_code":"28",
    "gn:asciiname":"Nizhneye Akh-Kerpi",
    "gn:country_code":"AZ",
    "gn:dem":1536,
    "gn:feature_class":"P",
    "gn:feature_code":"PPL",
    "gn:name":"Nizhneye Akh-Kerpi",
    "gn:population":0,
    "gn:timezone":"Asia/Baku",
    "iso:country":"AZ",
    "wof:name":"Nizhneye Akh-Kerpi",
    "wof:placetype":"locality"
},
  "geometry": {"coordinates":[46.28944,39.77722],"type":"Point"}
}