{
  "type": "Feature",
  "properties": {
    "gn:admin1_code":"03",
    "gn:asciiname":"Qalaycilar",
    "gn:country_code":"AZ",
    "gn:dem":512,
    "gn:feature_class":"P",
    "gn:feature_code":"PPL",
    "gn:name":"Qalay\u00e7\u0131lar",
    "gn:population":0,
    "gn:timezone":"Asia/Baku",
    "iso:country":"AZ",
    "name:azb_x_preferred":[
        "\u0642\u0627\u0644\u0627\u06cc\u200c\u0686\u06cc\u0644\u0627\u0631"
    ],
    "name:aze_x_preferred":[
        "Qalay\u00e7\u0131lar"
    ],
    "name:hye_x_preferred":[
        "Gaylat\u2019agh"
    ],
    "name:hye_x_variant":[
        "\u0533\u0561\u0575\u056c\u0561\u0569\u0561\u0572"
    ],
    "name:kat_x_preferred":[
        "\u10e5\u10d0\u10da\u10d0\u10d8\u10e9\u10d8\u10da\u10d0\u10e0\u10d8"
    ],
    "name:min_x_preferred":[
        "Qalay\u00e7\u0131lar"
    ],
    "name:msa_x_preferred":[
        "Qalay\u00e7\u0131lar"
    ],
    "name:rus_x_preferred":[
        "\u0413\u0430\u043b\u0430\u0439\u0447\u044b\u043b\u0430\u0440"
    ],
    "name:und_x_variant":[
        "Kalaychylar",
        "Galaychylar"
    ],
    "wof:name":"Qalaycilar",
    "wof:placetype":"locality"
},
  "geometry": {"coordinates":[46.81934,40.12302],"type":"Point"}
}