{
  "type": "Feature",
  "properties": {
    "gn:admin1_code":"65",
    "gn:asciiname":"Norasen",
    "gn:country_code":"AZ",
    "gn:dem":721,
    "gn:feature_class":"P",
    "gn:feature_code":"PPL",
    "gn:name":"Nora\u015fen",
    "gn:population":0,
    "gn:timezone":"Asia/Baku",
    "iso:country":"AZ",
    "name:aze_x_preferred":[
        "G\u00fcne\u015fli"
    ],
    "name:hye_x_preferred":[
        "\u0546\u0578\u0580\u0561\u0577\u0565\u0576"
    ],
    "name:hye_x_variant":[
        "Norashen"
    ],
    "name:rus_x_preferred":[
        "\u041d\u043e\u0440\u0430\u0448\u0435\u043d"
    ],
    "name:und_x_variant":[
        "Nora\u015fen",
        "Norashen"
    ],
    "wof:name":"Norasen",
    "wof:placetype":"locality"
},
  "geometry": {"coordinates":[47.07778,39.4924],"type":"Point"}
}