{
  "type": "Feature",
  "properties": {
    "gn:admin1_code":"02",
    "gn:asciiname":"Yeni Qaradolaq",
    "gn:country_code":"AZ",
    "gn:dem":59,
    "gn:feature_class":"P",
    "gn:feature_code":"PPL",
    "gn:name":"Yeni Qaradolaq",
    "gn:population":0,
    "gn:timezone":"Asia/Baku",
    "iso:country":"AZ",
    "name:azb_x_preferred":[
        "\u06cc\u0626\u0646\u06cc \u0642\u0627\u0631\u0627\u062f\u0648\u0644\u0627\u0642"
    ],
    "name:aze_x_preferred":[
        "Yeni Qaradolaq"
    ],
    "name:ceb_x_preferred":[
        "Yeni Qaradolaq"
    ],
    "name:ita_x_preferred":[
        "Yeni Qaradolaq"
    ],
    "name:kat_x_preferred":[
        "\u10d8\u10d4\u10dc\u10d8-\u10e5\u10d0\u10e0\u10d0\u10d3\u10dd\u10da\u10d0\u10e5\u10d8"
    ],
    "name:msa_x_preferred":[
        "Yeni Qaradolaq"
    ],
    "name:rus_x_preferred":[
        "\u0415\u043d\u0438\u043a\u0430\u0440\u0430\u0434\u043e\u043b\u0430\u043a"
    ],
    "name:swe_x_preferred":[
        "Yeni Qaradolaq"
    ],
    "name:und_x_variant":[
        "Yenikaradolak"
    ],
    "name:urd_x_preferred":[
        "\u06cc\u0646\u06cc \u0642\u0631\u0627\u062f\u0648\u0644\u0642"
    ],
    "wof:name":"Yeni Qaradolaq",
    "wof:placetype":"locality"
},
  "geometry": {"coordinates":[47.41997,39.90612],"type":"Point"}
}