{
  "type": "Feature",
  "properties": {
    "gn:admin1_code":"02",
    "gn:asciiname":"Yeni Qaradolaq",
    "gn:country_code":"AZ",
    "gn:dem":59,
    "gn:feature_class":"P",
    "gn:feature_code":"PPL",
    "gn:name":"Yeni Qaradolaq",
    "gn:population":0,
    "gn:timezone":"Asia/Baku",
    "iso:country":"AZ",
    "name:aze_x_preferred":[
        "Yeni Qaradolaq"
    ],
    "name:und_x_variant":[
        "Yenikaradolak"
    ],
    "wof:name":"Yeni Qaradolaq",
    "wof:placetype":"locality"
},
  "geometry": {"coordinates":[47.41997,39.90612],"type":"Point"}
}