{
  "type": "Feature",
  "properties": {
    "gn:admin1_code":"04",
    "gn:asciiname":"Gyuvekend",
    "gn:country_code":"AZ",
    "gn:dem":19,
    "gn:feature_class":"P",
    "gn:feature_code":"PPL",
    "gn:name":"Gyuvekend",
    "gn:population":0,
    "gn:timezone":"Asia/Baku",
    "iso:country":"AZ",
    "name:azb_x_preferred":[
        "\u06af\u0648\u0648 \u06a9\u0646\u062f"
    ],
    "name:aze_x_preferred":[
        "G\u00fcv\u0259k\u0259nd"
    ],
    "name:ceb_x_preferred":[
        "Gyuvekend"
    ],
    "name:ell_x_preferred":[
        "\u0393\u03ba\u03b9\u03bf\u03c5\u03b2\u03b5\u03ba\u03ad\u03bd\u03c4"
    ],
    "name:ita_x_preferred":[
        "G\u00fcv\u0259k\u0259nd"
    ],
    "name:kat_x_preferred":[
        "\u10d2\u10d8\u10e3\u10d5\u10d4\u10e5\u10d4\u10dc\u10d3\u10d8"
    ],
    "name:msa_x_preferred":[
        "G\u00fcv\u0259k\u0259nd"
    ],
    "name:rus_x_preferred":[
        "\u0413\u044e\u0432\u0435\u043a\u0435\u043d\u0434"
    ],
    "name:swe_x_preferred":[
        "Gyuvekend"
    ],
    "wof:name":"Gyuvekend",
    "wof:placetype":"locality"
},
  "geometry": {"coordinates":[47.39423,40.55853],"type":"Point"}
}