{
  "type": "Feature",
  "properties": {
    "gn:admin1_code":"04",
    "gn:asciiname":"Gyuvekend",
    "gn:country_code":"AZ",
    "gn:dem":19,
    "gn:feature_class":"P",
    "gn:feature_code":"PPL",
    "gn:name":"Gyuvekend",
    "gn:population":0,
    "gn:timezone":"Asia/Baku",
    "iso:country":"AZ",
    "name:und_x_variant":[
        "G\u00fcv\u0259k\u0259nd"
    ],
    "wof:name":"Gyuvekend",
    "wof:placetype":"locality"
},
  "geometry": {"coordinates":[47.39423,40.55853],"type":"Point"}
}