{
  "type": "Feature",
  "properties": {
    "gn:admin1_code":"43",
    "gn:asciiname":"Melikakhmedli",
    "gn:country_code":"AZ",
    "gn:dem":904,
    "gn:feature_class":"P",
    "gn:feature_code":"PPL",
    "gn:name":"Melikakhmedli",
    "gn:population":0,
    "gn:timezone":"Asia/Baku",
    "iso:country":"AZ",
    "name:aze_x_preferred":[
        "M\u0259lik\u0259hm\u0259dli"
    ],
    "name:hye_x_preferred":[
        "Melik\u2019ahmedli"
    ],
    "name:hye_x_variant":[
        "\u0544\u0565\u056c\u056b\u0584\u0561\u0570\u0574\u0565\u0564\u056c\u056b",
        "Melik\u2019ashen",
        "\u0544\u0565\u056c\u056b\u0584\u0561\u0577\u0565\u0576"
    ],
    "name:rus_x_preferred":[
        "\u041c\u0435\u043b\u0438\u043a\u0430\u0445\u043c\u0435\u0434\u043b\u0438"
    ],
    "name:und_x_variant":[
        "\u041c\u0435\u043b\u0438\u043a\u0430\u0445\u043c\u0435\u0434\u043b\u0438"
    ],
    "wof:name":"Melikakhmedli",
    "wof:placetype":"locality"
},
  "geometry": {"coordinates":[46.51306,39.45295],"type":"Point"}
}