{
  "type": "Feature",
  "properties": {
    "gn:admin1_code":"42",
    "gn:asciiname":"Idrisqislaq",
    "gn:country_code":"AZ",
    "gn:dem":166,
    "gn:feature_class":"P",
    "gn:feature_code":"PPL",
    "gn:name":"\u0130drisq\u0131\u015flaq",
    "gn:population":0,
    "gn:timezone":"Asia/Baku",
    "iso:country":"AZ",
    "name:aze_x_preferred":[
        "\u0130drisiq\u0131\u015flaq"
    ],
    "name:ita_x_preferred":[
        "\u0130drisq\u0131\u015flaq"
    ],
    "name:msa_x_preferred":[
        "\u0130drisq\u0131\u015flaq"
    ],
    "name:und_x_variant":[
        "Idrisi",
        "\u0130drisq\u0131\u015flaq",
        "Idrisikyshlak"
    ],
    "wof:name":"Idrisqislaq",
    "wof:placetype":"locality"
},
  "geometry": {"coordinates":[48.80515,41.3253],"type":"Point"}
}