{
  "type": "Feature",
  "properties": {
    "gn:admin1_code":"25",
    "gn:asciiname":"Namazgah",
    "gn:country_code":"AZ",
    "gn:dem":1096,
    "gn:feature_class":"P",
    "gn:feature_code":"PPL",
    "gn:name":"Namazgah",
    "gn:population":0,
    "gn:timezone":"Asia/Baku",
    "iso:country":"AZ",
    "name:rus_x_preferred":[
        "\u041d\u0430\u043c\u0430\u0437\u0433\u0430\u0445"
    ],
    "name:tur_x_preferred":[
        "Namazgah"
    ],
    "name:und_x_variant":[
        "Namazgyakh",
        "Namazgakh",
        "Namazgi",
        "Namazgah"
    ],
    "wof:name":"Namazgah",
    "wof:placetype":"locality"
},
  "geometry": {"coordinates":[48.33015,40.83593],"type":"Point"}
}