{
  "type": "Feature",
  "properties": {
    "gn:admin1_code":"06",
    "gn:asciiname":"Nyuydi",
    "gn:country_code":"AZ",
    "gn:dem":812,
    "gn:feature_class":"P",
    "gn:feature_code":"PPL",
    "gn:name":"Nyuydi",
    "gn:population":0,
    "gn:timezone":"Asia/Baku",
    "iso:country":"AZ",
    "name:und_x_variant":[
        "Nyugdi",
        "N\u00fcyd\u00fc"
    ],
    "wof:name":"Nyuydi",
    "wof:placetype":"locality"
},
  "geometry": {"coordinates":[48.39721,40.69372],"type":"Point"}
}