{
  "type": "Feature",
  "properties": {
    "gn:admin1_code":"06",
    "gn:asciiname":"Nyuydi",
    "gn:country_code":"AZ",
    "gn:dem":812,
    "gn:feature_class":"P",
    "gn:feature_code":"PPL",
    "gn:name":"Nyuydi",
    "gn:population":0,
    "gn:timezone":"Asia/Baku",
    "iso:country":"AZ",
    "name:azb_x_preferred":[
        "\u0646\u0648\u06cc\u200c\u062f\u0648"
    ],
    "name:aze_x_preferred":[
        "N\u00fcyd\u00fc"
    ],
    "name:ceb_x_preferred":[
        "Nyuydi"
    ],
    "name:fas_x_preferred":[
        "\u0646\u0648\u06cc\u062f\u0648"
    ],
    "name:ita_x_preferred":[
        "N\u00fcyd\u00fc"
    ],
    "name:kat_x_preferred":[
        "\u10dc\u10d8\u10e3\u10d3\u10d8"
    ],
    "name:msa_x_preferred":[
        "N\u00fcyd\u00fc"
    ],
    "name:und_x_variant":[
        "Nyugdi"
    ],
    "wof:name":"Nyuydi",
    "wof:placetype":"locality"
},
  "geometry": {"coordinates":[48.39721,40.69372],"type":"Point"}
}