{
  "type": "Feature",
  "properties": {
    "gn:admin1_code":"42",
    "gn:asciiname":"Cek",
    "gn:country_code":"AZ",
    "gn:dem":1756,
    "gn:feature_class":"P",
    "gn:feature_code":"PPL",
    "gn:name":"Cek",
    "gn:population":0,
    "gn:timezone":"Asia/Baku",
    "iso:country":"AZ",
    "name:azb_x_preferred":[
        "\u062c\u06a9"
    ],
    "name:aze_x_preferred":[
        "Cek"
    ],
    "name:eus_x_preferred":[
        "Cek"
    ],
    "name:fas_x_preferred":[
        "\u062c\u06a9"
    ],
    "name:ind_x_preferred":[
        "Cek"
    ],
    "name:ita_x_preferred":[
        "Cek"
    ],
    "name:kat_x_preferred":[
        "\u10ef\u10d4\u10d9\u10d8"
    ],
    "name:msa_x_preferred":[
        "Cek"
    ],
    "name:oss_x_preferred":[
        "\u0414\u0436\u0435\u043a"
    ],
    "name:pih_x_preferred":[
        "Dzhek"
    ],
    "name:pol_x_preferred":[
        "Cek"
    ],
    "name:por_x_preferred":[
        "Cek"
    ],
    "name:ron_x_preferred":[
        "Cek"
    ],
    "name:rus_x_preferred":[
        "\u0414\u0436\u0435\u043a"
    ],
    "name:sco_x_preferred":[
        "Cek"
    ],
    "name:tur_x_preferred":[
        "Cek"
    ],
    "name:und_x_variant":[
        "Dzheg"
    ],
    "name:urd_x_preferred":[
        "\u062c\u06cc\u06a9"
    ],
    "wof:name":"Cek",
    "wof:placetype":"locality"
},
  "geometry": {"coordinates":[48.2367,41.19376],"type":"Point"}
}