{
  "type": "Feature",
  "properties": {
    "gn:admin1_code":"42",
    "gn:asciiname":"Cek",
    "gn:country_code":"AZ",
    "gn:dem":1756,
    "gn:feature_class":"P",
    "gn:feature_code":"PPL",
    "gn:name":"Cek",
    "gn:population":0,
    "gn:timezone":"Asia/Baku",
    "iso:country":"AZ",
    "name:und_x_variant":[
        "Dzheg",
        "Dzhek",
        "Cek"
    ],
    "wof:name":"Cek",
    "wof:placetype":"locality"
},
  "geometry": {"coordinates":[48.2367,41.19376],"type":"Point"}
}