{
  "type": "Feature",
  "properties": {
    "gn:admin1_code":"08",
    "gn:asciiname":"Avyarud",
    "gn:country_code":"AZ",
    "gn:dem":774,
    "gn:feature_class":"P",
    "gn:feature_code":"PPL",
    "gn:name":"Avyarud",
    "gn:population":0,
    "gn:timezone":"Asia/Baku",
    "iso:country":"AZ",
    "name:azb_x_preferred":[
        "\u0622\u0648\u06cc\u0627\u0631\u0648\u062f"
    ],
    "name:aze_x_preferred":[
        "Avyarud"
    ],
    "name:fas_x_preferred":[
        "\u0627\u06cc\u0648\u0647\u200c\u0631\u0648\u062f"
    ],
    "name:ita_x_preferred":[
        "Avyarud"
    ],
    "name:kat_x_preferred":[
        "\u10d0\u10d5\u10d8\u10d0\u10e0\u10e3\u10d3\u10d8"
    ],
    "name:kur_x_preferred":[
        "Avyar\u00fbd"
    ],
    "name:msa_x_preferred":[
        "Avyarud"
    ],
    "name:rus_x_preferred":[
        "\u0410\u0432\u044f\u0440\u0443\u0434"
    ],
    "name:und_x_variant":[
        "Aviyarud"
    ],
    "wof:name":"Avyarud",
    "wof:placetype":"locality"
},
  "geometry": {"coordinates":[48.609,38.5052],"type":"Point"}
}