{
  "type": "Feature",
  "properties": {
    "gn:admin1_code":"08",
    "gn:asciiname":"Avyarud",
    "gn:country_code":"AZ",
    "gn:dem":774,
    "gn:feature_class":"P",
    "gn:feature_code":"PPL",
    "gn:name":"Avyarud",
    "gn:population":0,
    "gn:timezone":"Asia/Baku",
    "iso:country":"AZ",
    "name:und_x_variant":[
        "Aviyarud"
    ],
    "wof:name":"Avyarud",
    "wof:placetype":"locality"
},
  "geometry": {"coordinates":[48.609,38.5052],"type":"Point"}
}