{
  "type": "Feature",
  "properties": {
    "gn:admin1_code":"39",
    "gn:asciiname":"Qax Ingiloy",
    "gn:country_code":"AZ",
    "gn:dem":656,
    "gn:feature_class":"P",
    "gn:feature_code":"PPL",
    "gn:name":"Qax \u0130ngiloy",
    "gn:population":2747,
    "gn:timezone":"Asia/Baku",
    "iso:country":"AZ",
    "name:ava_x_preferred":[
        "\u0418\u043d\u0445\u0438\u043b \u041a\u0430\u0445I\u0438\u0431"
    ],
    "name:azb_x_preferred":[
        "\u0642\u0627\u062e \u0627\u06cc\u0646\u06af\u06cc\u0644\u0648\u06cc"
    ],
    "name:aze_x_preferred":[
        "Qaxingiloy"
    ],
    "name:ceb_x_preferred":[
        "Qax \u0130ngiloy"
    ],
    "name:ita_x_preferred":[
        "Qax \u0130ngiloy"
    ],
    "name:kat_x_preferred":[
        "\u10d9\u10d0\u10ee-\u10d8\u10dc\u10d2\u10d8\u10da\u10dd"
    ],
    "name:msa_x_preferred":[
        "Qax \u0130ngiloy"
    ],
    "name:swe_x_preferred":[
        "Qax \u0130ngiloy"
    ],
    "name:und_x_variant":[
        "Kakh Ingilo",
        "Kakh-Bash-Ingiloy",
        "Kakhingiloy",
        "Qax \u0130ngiloy"
    ],
    "wof:name":"Qax Ingiloy",
    "wof:placetype":"locality",
    "wof:population":2747
},
  "geometry": {"coordinates":[46.93859000000001,41.42412],"type":"Point"}
}