{
  "type": "Feature",
  "properties": {
    "gn:admin1_code":"39",
    "gn:asciiname":"Qax Ingiloy",
    "gn:country_code":"AZ",
    "gn:dem":656,
    "gn:feature_class":"P",
    "gn:feature_code":"PPL",
    "gn:name":"Qax \u0130ngiloy",
    "gn:population":2747,
    "gn:timezone":"Asia/Baku",
    "iso:country":"AZ",
    "name:und_x_variant":[
        "Kakh Ingilo",
        "Kakh-Bash-Ingiloy",
        "Kakhingiloy",
        "Qax \u0130ngiloy"
    ],
    "wof:name":"Qax Ingiloy",
    "wof:placetype":"locality",
    "wof:population":2747
},
  "geometry": {"coordinates":[46.93859000000001,41.42412],"type":"Point"}
}