{
  "type": "Feature",
  "properties": {
    "gn:admin1_code":"49",
    "gn:asciiname":"Yetimlyar",
    "gn:country_code":"AZ",
    "gn:dem":-24,
    "gn:feature_class":"P",
    "gn:feature_code":"PPL",
    "gn:name":"Yetimlyar",
    "gn:population":0,
    "gn:timezone":"Asia/Baku",
    "iso:country":"AZ",
    "name:und_x_variant":[
        "Bashirabat",
        "Yetimlar",
        "Yetimlyar",
        "Yenikend",
        "Yenik\u0259nd",
        "Chalovlu"
    ],
    "wof:name":"Yetimlyar",
    "wof:placetype":"locality"
},
  "geometry": {"coordinates":[49.08968,39.71015],"type":"Point"}
}