{
  "type": "Feature",
  "properties": {
    "gn:admin1_code":"15",
    "gn:asciiname":"Novruzalli",
    "gn:country_code":"AZ",
    "gn:dem":245,
    "gn:feature_class":"P",
    "gn:feature_code":"PPL",
    "gn:name":"Novruzall\u0131",
    "gn:population":0,
    "gn:timezone":"Asia/Baku",
    "iso:country":"AZ",
    "name:aze_x_preferred":[
        "Novruzall\u0131"
    ],
    "name:ceb_x_preferred":[
        "Novruzall\u0131"
    ],
    "name:ell_x_preferred":[
        "\u039d\u03bf\u03b2\u03c1\u03bf\u03c5\u03b6\u03ac\u03bb\u03bb\u03b9"
    ],
    "name:ita_x_preferred":[
        "Novruzall\u0131"
    ],
    "name:msa_x_preferred":[
        "Novruzall\u0131"
    ],
    "name:swe_x_preferred":[
        "Novruzall\u0131"
    ],
    "name:und_x_variant":[
        "Naurzali",
        "Novruzally",
        "Novruzalyly"
    ],
    "wof:name":"Novruzalli",
    "wof:placetype":"locality"
},
  "geometry": {"coordinates":[48.26667,39.24391],"type":"Point"}
}