{
  "type": "Feature",
  "properties": {
    "gn:admin1_code":"15",
    "gn:asciiname":"Novruzalli",
    "gn:country_code":"AZ",
    "gn:dem":245,
    "gn:feature_class":"P",
    "gn:feature_code":"PPL",
    "gn:name":"Novruzall\u0131",
    "gn:population":0,
    "gn:timezone":"Asia/Baku",
    "iso:country":"AZ",
    "name:aze_x_preferred":[
        "Novruzall\u0131"
    ],
    "name:und_x_variant":[
        "Naurzali",
        "Novruzally",
        "Novruzalyly"
    ],
    "wof:name":"Novruzalli",
    "wof:placetype":"locality"
},
  "geometry": {"coordinates":[48.26667,39.24391],"type":"Point"}
}