{
  "type": "Feature",
  "properties": {
    "gn:admin1_code":"62",
    "gn:asciiname":"Tulallar",
    "gn:country_code":"AZ",
    "gn:dem":1615,
    "gn:feature_class":"P",
    "gn:feature_code":"PPL",
    "gn:name":"Tulallar",
    "gn:population":0,
    "gn:timezone":"Asia/Baku",
    "iso:country":"AZ",
    "name:und_x_variant":[
        "Tulalar"
    ],
    "wof:name":"Tulallar",
    "wof:placetype":"locality"
},
  "geometry": {"coordinates":[46.2387,40.44239],"type":"Point"}
}