{
  "type": "Feature",
  "properties": {
    "gn:admin1_code":"09",
    "gn:asciiname":"Novaya Bina",
    "gn:country_code":"AZ",
    "gn:dem":18,
    "gn:feature_class":"P",
    "gn:feature_code":"PPL",
    "gn:name":"Novaya Bina",
    "gn:population":0,
    "gn:timezone":"Asia/Baku",
    "iso:country":"AZ",
    "name:und_x_variant":[
        "Imeni Azizbekova",
        "Azizbekov",
        "Novaya Bina",
        "Bina Novaya",
        "\u018fzizb\u0259yov"
    ],
    "wof:name":"Novaya Bina",
    "wof:placetype":"locality"
},
  "geometry": {"coordinates":[50.11556,40.45639],"type":"Point"}
}