{
  "type": "Feature",
  "properties": {
    "gn:admin1_code":"13",
    "gn:asciiname":"Cinarli",
    "gn:country_code":"AZ",
    "gn:dem":-18,
    "gn:feature_class":"P",
    "gn:feature_code":"PPL",
    "gn:name":"Cinarl\u0131",
    "gn:population":0,
    "gn:timezone":"Asia/Baku",
    "iso:country":"AZ",
    "wof:name":"Cinarli",
    "wof:placetype":"locality"
},
  "geometry": {"coordinates":[48.6025,39.50028],"type":"Point"}
}