{
  "type": "Feature",
  "properties": {
    "gn:admin1_code":"08",
    "gn:asciiname":"Shykhympeshta",
    "gn:country_code":"AZ",
    "gn:dem":942,
    "gn:feature_class":"P",
    "gn:feature_code":"PPL",
    "gn:name":"Shykhympeshta",
    "gn:population":0,
    "gn:timezone":"Asia/Baku",
    "iso:country":"AZ",
    "name:und_x_variant":[
        "Shekhin-Peshta",
        "\u015e\u0131x\u0131mpe\u015ft\u0259"
    ],
    "wof:name":"Shykhympeshta",
    "wof:placetype":"locality"
},
  "geometry": {"coordinates":[48.64987,38.60283],"type":"Point"}
}