{
  "type": "Feature",
  "properties": {
    "gn:admin1_code":"08",
    "gn:asciiname":"Shykhympeshta",
    "gn:country_code":"AZ",
    "gn:dem":942,
    "gn:feature_class":"P",
    "gn:feature_code":"PPL",
    "gn:name":"Shykhympeshta",
    "gn:population":0,
    "gn:timezone":"Asia/Baku",
    "iso:country":"AZ",
    "name:azb_x_preferred":[
        "\u0634\u06cc\u062e\u06cc\u0645 \u067e\u0626\u0634\u062a\u0647"
    ],
    "name:aze_x_preferred":[
        "\u015e\u0131x\u0131mpe\u015ft\u0259"
    ],
    "name:ell_x_preferred":[
        "\u03a3\u03b9\u03c7\u03b9\u03bc\u03c0\u03b5\u03c3\u03c4\u03ad"
    ],
    "name:fas_x_preferred":[
        "\u0634\u062e\u0645\u200c\u067e\u0634\u062a\u0647"
    ],
    "name:ita_x_preferred":[
        "\u015e\u0131x\u0131mpe\u015ft\u0259"
    ],
    "name:kat_x_preferred":[
        "\u10e8\u10d8\u10ee\u10d8\u10db\u10e4\u10d4\u10e8\u10d7\u10d0"
    ],
    "name:kur_x_preferred":[
        "\u015eiximp\u00ea\u015fte"
    ],
    "name:msa_x_preferred":[
        "\u015e\u0131x\u0131mpe\u015ft\u0259"
    ],
    "name:und_x_variant":[
        "Shekhin-Peshta"
    ],
    "wof:name":"Shykhympeshta",
    "wof:placetype":"locality"
},
  "geometry": {"coordinates":[48.64987,38.60283],"type":"Point"}
}