{
  "type": "Feature",
  "properties": {
    "gn:admin1_code":"04",
    "gn:asciiname":"Sadavat",
    "gn:country_code":"AZ",
    "gn:dem":39,
    "gn:feature_class":"P",
    "gn:feature_code":"PPL",
    "gn:name":"Sadavat",
    "gn:population":0,
    "gn:timezone":"Asia/Baku",
    "iso:country":"AZ",
    "name:azb_x_preferred":[
        "\u0633\u0627\u062f\u0627\u0648\u0627\u062a"
    ],
    "name:aze_x_preferred":[
        "Sadavat"
    ],
    "name:ell_x_preferred":[
        "\u03a3\u03b1\u03bd\u03c4\u03b1\u03b2\u03ac\u03c4"
    ],
    "name:ita_x_preferred":[
        "Sadavat"
    ],
    "name:kat_x_preferred":[
        "\u10e1\u10d0\u10d3\u10d0\u10d5\u10d0\u10d7\u10d8"
    ],
    "name:msa_x_preferred":[
        "Sadavat"
    ],
    "name:rus_x_preferred":[
        "\u0421\u0430\u0434\u0430\u0432\u0430\u0442"
    ],
    "name:urd_x_preferred":[
        "\u0633\u062f\u0622\u0624\u0679"
    ],
    "wof:name":"Sadavat",
    "wof:placetype":"locality"
},
  "geometry": {"coordinates":[47.57238,40.62686],"type":"Point"}
}