{
  "type": "Feature",
  "properties": {
    "gn:admin1_code":"04",
    "gn:asciiname":"Sadavat",
    "gn:country_code":"AZ",
    "gn:dem":39,
    "gn:feature_class":"P",
    "gn:feature_code":"PPL",
    "gn:name":"Sadavat",
    "gn:population":0,
    "gn:timezone":"Asia/Baku",
    "iso:country":"AZ",
    "wof:name":"Sadavat",
    "wof:placetype":"locality"
},
  "geometry": {"coordinates":[47.57238,40.62686],"type":"Point"}
}