{
  "type": "Feature",
  "properties": {
    "gn:admin1_code":"35",
    "gn:admin2_code":"147365.0",
    "gn:asciiname":"Gilancay",
    "gn:country_code":"AZ",
    "gn:dem":942,
    "gn:feature_class":"P",
    "gn:feature_code":"PPL",
    "gn:name":"Gilan\u00e7ay",
    "gn:population":0,
    "gn:timezone":"Asia/Baku",
    "iso:country":"AZ",
    "name:azb_x_preferred":[
        "\u06af\u06cc\u0644\u0627\u0646\u0686\u0627\u06cc"
    ],
    "name:aze_x_preferred":[
        "Gilan\u00e7ay"
    ],
    "name:ceb_x_preferred":[
        "Gilan\u00e7ay"
    ],
    "name:fas_x_preferred":[
        "\u06af\u06cc\u0644\u0627\u0646\u200c\u0686\u0627\u06cc"
    ],
    "name:hye_x_preferred":[
        "\u0533\u056b\u056c\u0561\u0576\u0579\u0561\u0575"
    ],
    "name:ita_x_preferred":[
        "Gilan\u00e7ay"
    ],
    "name:kat_x_preferred":[
        "\u10d2\u10d8\u10da\u10d0\u10dc\u10e9\u10d0\u10d8"
    ],
    "name:msa_x_preferred":[
        "Gilan\u00e7ay"
    ],
    "name:swe_x_preferred":[
        "Gilan\u00e7ay"
    ],
    "name:und_x_variant":[
        "Kilyanchay",
        "Gilanchay"
    ],
    "wof:name":"Gilancay",
    "wof:placetype":"locality"
},
  "geometry": {"coordinates":[45.81903,39.00718],"type":"Point"}
}