{
  "type": "Feature",
  "properties": {
    "gn:admin1_code":"65",
    "gn:asciiname":"Agdzhakend",
    "gn:country_code":"AZ",
    "gn:dem":1391,
    "gn:feature_class":"P",
    "gn:feature_code":"PPL",
    "gn:name":"Agdzhakend",
    "gn:population":0,
    "gn:timezone":"Asia/Baku",
    "iso:country":"AZ",
    "name:aze_x_preferred":[
        "A\u011fcak\u0259nd"
    ],
    "name:bel_x_preferred":[
        "\u0425\u0430\u043d\u0434\u0437\u0430\u0434\u0437\u043e\u0440"
    ],
    "name:ceb_x_preferred":[
        "Agdzhakend"
    ],
    "name:fra_x_preferred":[
        "Khandzadzor"
    ],
    "name:hye_x_preferred":[
        "Khandzadzor"
    ],
    "name:hye_x_variant":[
        "\u053d\u0561\u0576\u0573\u0561\u0573\u0578\u0580",
        "\u053d\u0561\u0576\u0571\u0561\u0571\u0578\u0580"
    ],
    "name:ita_x_preferred":[
        "Khandzadzor"
    ],
    "name:msa_x_preferred":[
        "A\u011fcak\u0259nd"
    ],
    "name:rus_x_preferred":[
        "\u0410\u0433\u0434\u0436\u0430\u043a\u0435\u043d\u0434"
    ],
    "name:swe_x_preferred":[
        "Agdzhakend"
    ],
    "name:ukr_x_preferred":[
        "\u0425\u0430\u043d\u0434\u0437\u0430\u0434\u0437\u043e\u0440"
    ],
    "name:und_x_variant":[
        "\u0410\u0433\u0434\u0436\u0430\u043a\u0435\u043d\u0434"
    ],
    "wof:name":"Agdzhakend",
    "wof:placetype":"locality"
},
  "geometry": {"coordinates":[46.88449,39.50091],"type":"Point"}
}