{
  "type": "Feature",
  "properties": {
    "gn:admin1_code":"02",
    "gn:asciiname":"Khalfaraddin",
    "gn:country_code":"AZ",
    "gn:dem":7,
    "gn:feature_class":"P",
    "gn:feature_code":"PPL",
    "gn:name":"Khalfaraddin",
    "gn:population":0,
    "gn:timezone":"Asia/Baku",
    "iso:country":"AZ",
    "name:ita_x_preferred":[
        "Khalfaraddin"
    ],
    "name:kat_x_preferred":[
        "\u10ee\u10d0\u10da\u10e4\u10d0\u10e0\u10d0\u10d3\u10d8\u10dc\u10d8"
    ],
    "name:msa_x_preferred":[
        "Khalfaraddin"
    ],
    "name:und_x_variant":[
        "Khalfaradinlu",
        "Khalfaraddin"
    ],
    "wof:name":"Khalfaraddin",
    "wof:placetype":"locality"
},
  "geometry": {"coordinates":[47.47164,40.06442],"type":"Point"}
}