{
  "type": "Feature",
  "properties": {
    "gn:admin1_code":"38",
    "gn:asciiname":"Corlu",
    "gn:country_code":"AZ",
    "gn:dem":485,
    "gn:feature_class":"P",
    "gn:feature_code":"PPL",
    "gn:name":"Corlu",
    "gn:population":0,
    "gn:timezone":"Asia/Baku",
    "iso:country":"AZ",
    "name:aze_x_preferred":[
        "Corlu"
    ],
    "name:ita_x_preferred":[
        "Corlu"
    ],
    "name:kat_x_preferred":[
        "\u10ef\u10dd\u10e0\u10da\u10e3"
    ],
    "name:lez_x_preferred":[
        "\u0416\u043e\u0440\u043b\u0443"
    ],
    "name:msa_x_preferred":[
        "Corlu"
    ],
    "name:und_x_variant":[
        "Dzhorly",
        "Dzhorlu"
    ],
    "wof:name":"Corlu",
    "wof:placetype":"locality"
},
  "geometry": {"coordinates":[47.72587,40.93592],"type":"Point"}
}