{
  "type": "Feature",
  "properties": {
    "gn:admin1_code":"38",
    "gn:asciiname":"Corlu",
    "gn:country_code":"AZ",
    "gn:dem":485,
    "gn:feature_class":"P",
    "gn:feature_code":"PPL",
    "gn:name":"Corlu",
    "gn:population":0,
    "gn:timezone":"Asia/Baku",
    "iso:country":"AZ",
    "name:und_x_variant":[
        "Dzhorly",
        "Dzhorlu",
        "Corlu"
    ],
    "wof:name":"Corlu",
    "wof:placetype":"locality"
},
  "geometry": {"coordinates":[47.72587,40.93592],"type":"Point"}
}