{
  "type": "Feature",
  "properties": {
    "gn:admin1_code":"53",
    "gn:asciiname":"Khandek",
    "gn:country_code":"AZ",
    "gn:dem":445,
    "gn:feature_class":"P",
    "gn:feature_code":"PPLL",
    "gn:name":"Khandek",
    "gn:population":0,
    "gn:timezone":"Asia/Baku",
    "iso:country":"AZ",
    "name:und_x_variant":[
        "Khandag",
        "Khandek",
        "X\u0259nd\u0259k"
    ],
    "wof:name":"Khandek",
    "wof:placetype":"locality"
},
  "geometry": {"coordinates":[48.99661,40.97626],"type":"Point"}
}