{
  "type": "Feature",
  "properties": {
    "gn:admin1_code":"35",
    "gn:admin2_code":"148132.0",
    "gn:asciiname":"Surud",
    "gn:country_code":"AZ",
    "gn:dem":1336,
    "gn:feature_class":"P",
    "gn:feature_code":"PPL",
    "gn:name":"\u015eurud",
    "gn:population":0,
    "gn:timezone":"Asia/Baku",
    "iso:country":"AZ",
    "name:azb_x_preferred":[
        "\u0634\u0648\u0631\u0648\u062f"
    ],
    "name:aze_x_preferred":[
        "\u015eurud"
    ],
    "name:ceb_x_preferred":[
        "\u015eurud"
    ],
    "name:fas_x_preferred":[
        "\u0634\u0648\u0631\u0648\u062f"
    ],
    "name:hye_x_preferred":[
        "\u0547\u0578\u057c\u0578\u0569"
    ],
    "name:ita_x_preferred":[
        "\u015eurud"
    ],
    "name:kat_x_preferred":[
        "\u10e8\u10e3\u10e0\u10e3\u10d3\u10d8"
    ],
    "name:msa_x_preferred":[
        "\u015eurud"
    ],
    "name:swe_x_preferred":[
        "\u015eurud"
    ],
    "name:tur_x_historical":[
        "Shurut"
    ],
    "name:tur_x_preferred":[
        "Shurut"
    ],
    "name:tur_x_variant":[
        "\u015eurud"
    ],
    "name:und_x_variant":[
        "Shurud"
    ],
    "wof:name":"Surud",
    "wof:placetype":"locality"
},
  "geometry": {"coordinates":[45.79992,39.14618],"type":"Point"}
}