{
  "type": "Feature",
  "properties": {
    "gn:admin1_code":"35",
    "gn:admin2_code":"148132.0",
    "gn:asciiname":"Surud",
    "gn:country_code":"AZ",
    "gn:dem":1336,
    "gn:feature_class":"P",
    "gn:feature_code":"PPL",
    "gn:name":"\u015eurud",
    "gn:population":0,
    "gn:timezone":"Asia/Baku",
    "iso:country":"AZ",
    "name:aze_x_preferred":[
        "\u015eurud"
    ],
    "name:tur_x_historical":[
        "Shurut"
    ],
    "name:tur_x_preferred":[
        "Shurut"
    ],
    "name:und_x_variant":[
        "Shurud"
    ],
    "wof:name":"Surud",
    "wof:placetype":"locality"
},
  "geometry": {"coordinates":[45.79992,39.14618],"type":"Point"}
}