{
  "type": "Feature",
  "properties": {
    "gn:admin1_code":"65",
    "gn:asciiname":"Agbulaq",
    "gn:country_code":"AZ",
    "gn:dem":1010,
    "gn:feature_class":"P",
    "gn:feature_code":"PPL",
    "gn:name":"A\u011fbulaq",
    "gn:population":0,
    "gn:timezone":"Asia/Baku",
    "iso:country":"AZ",
    "name:aze_x_preferred":[
        "A\u011fbulaq"
    ],
    "name:aze_x_variant":[
        "M\u0131smna"
    ],
    "name:hye_x_preferred":[
        "\u0544\u057d\u0574\u0576\u0561"
    ],
    "name:hye_x_variant":[
        "Msmna"
    ],
    "name:rus_x_preferred":[
        "\u041c\u044b\u0441\u043c\u043d\u0430"
    ],
    "name:und_x_variant":[
        "Mysmna",
        "Masm\u0131na",
        "Mysmana",
        "Msmna",
        "\u041c\u044b\u0441\u043c\u043d\u0430"
    ],
    "wof:name":"Agbulaq",
    "wof:placetype":"locality"
},
  "geometry": {"coordinates":[46.91432,39.74615],"type":"Point"}
}