{
  "type": "Feature",
  "properties": {
    "gn:admin1_code":"10",
    "gn:asciiname":"Darvazbina",
    "gn:country_code":"AZ",
    "gn:dem":197,
    "gn:feature_class":"P",
    "gn:feature_code":"PPL",
    "gn:name":"Darvazbina",
    "gn:population":0,
    "gn:timezone":"Asia/Baku",
    "iso:country":"AZ",
    "name:aze_x_preferred":[
        "Darbazbin\u0259"
    ],
    "wof:name":"Darvazbina",
    "wof:placetype":"locality"
},
  "geometry": {"coordinates":[46.30869000000001,41.62094],"type":"Point"}
}