{
  "type": "Feature",
  "properties": {
    "gn:admin1_code":"12",
    "gn:asciiname":"Mil",
    "gn:country_code":"AZ",
    "gn:dem":96,
    "gn:feature_class":"P",
    "gn:feature_code":"PPL",
    "gn:name":"Mil",
    "gn:population":0,
    "gn:timezone":"Asia/Baku",
    "iso:country":"AZ",
    "name:aze_x_preferred":[
        "Mil"
    ],
    "name:rus_x_preferred":[
        "Mil\u2019"
    ],
    "wof:name":"Mil",
    "wof:placetype":"locality"
},
  "geometry": {"coordinates":[47.68244,39.63916],"type":"Point"}
}