{
  "type": "Feature",
  "properties": {
    "gn:admin1_code":"60",
    "gn:asciiname":"Keimaraz",
    "gn:country_code":"AZ",
    "gn:dem":-3,
    "gn:feature_class":"P",
    "gn:feature_code":"PPL",
    "gn:name":"Keimaraz",
    "gn:population":0,
    "gn:timezone":"Asia/Baku",
    "iso:country":"AZ",
    "name:und_x_variant":[
        "Keymuraz",
        "Keimaraz",
        "Keym\u0259r\u0259z",
        "Keymaraz"
    ],
    "wof:name":"Keimaraz",
    "wof:placetype":"locality"
},
  "geometry": {"coordinates":[48.92107,41.41828],"type":"Point"}
}