{
  "type": "Feature",
  "properties": {
    "gn:country":"AZ",
    "gn:fcode":"PPL",
    "gn:pop":1760,
    "iso:country":"AZ",
    "name:azb_x_preferred":[
        "\u0633\u0627\u0645\u0648\u0631"
    ],
    "name:aze_x_preferred":[
        "Samur"
    ],
    "name:cat_x_preferred":[
        "Samur"
    ],
    "name:ceb_x_preferred":[
        "Samur"
    ],
    "name:cos_x_preferred":[
        "Samur"
    ],
    "name:eng_x_preferred":[
        "Samur"
    ],
    "name:fur_x_preferred":[
        "Samur"
    ],
    "name:hau_x_preferred":[
        "Samur"
    ],
    "name:ita_x_preferred":[
        "Samur"
    ],
    "name:kal_x_preferred":[
        "Samur"
    ],
    "name:kat_x_preferred":[
        "\u10e1\u10d0\u10db\u10e3\u10e0\u10d8"
    ],
    "name:kik_x_preferred":[
        "Samur"
    ],
    "name:kin_x_preferred":[
        "Samur"
    ],
    "name:kon_x_preferred":[
        "Samur"
    ],
    "name:lez_x_preferred":[
        "\u0421\u0430\u043c\u0443\u0440"
    ],
    "name:msa_x_preferred":[
        "Samur"
    ],
    "name:nld_x_preferred":[
        "Samur"
    ],
    "name:nya_x_preferred":[
        "Samur"
    ],
    "name:roh_x_preferred":[
        "Samur"
    ],
    "name:rus_x_preferred":[
        "\u0421\u0430\u043c\u0443\u0440"
    ],
    "name:sdc_x_preferred":[
        "Samur"
    ],
    "name:smo_x_preferred":[
        "Samur"
    ],
    "name:spa_x_preferred":[
        "Samur"
    ],
    "name:swe_x_preferred":[
        "Samur"
    ],
    "name:vec_x_preferred":[
        "Samur"
    ],
    "qs:name":"Samur",
    "qs:photos_9r":0,
    "qs:photos_sr":0,
    "qs:pop_sr":"3",
    "wd:wordcount":105,
    "wof:name":"Samur",
    "wof:placetype":"locality",
    "wof:population":1760
},
  "geometry": {"coordinates":[48.43025,41.63254],"type":"Point"}
}