{
  "type": "Feature",
  "properties": {
    "gn:admin1_code":"19",
    "gn:asciiname":"Sabatkechmaz",
    "gn:country_code":"AZ",
    "gn:dem":1433,
    "gn:feature_class":"P",
    "gn:feature_code":"PPL",
    "gn:name":"Sabatkechmaz",
    "gn:population":0,
    "gn:timezone":"Asia/Baku",
    "iso:country":"AZ",
    "name:und_x_variant":[
        "Sabetkechmaz",
        "Sabatkechmaz",
        "S\u0259b\u0259tke\u00e7m\u0259z"
    ],
    "wof:name":"Sabatkechmaz",
    "wof:placetype":"locality"
},
  "geometry": {"coordinates":[45.72754000000001,40.50601],"type":"Point"}
}