{
  "type": "Feature",
  "properties": {
    "gn:admin1_code":"19",
    "gn:asciiname":"Sabatkechmaz",
    "gn:country_code":"AZ",
    "gn:dem":1433,
    "gn:feature_class":"P",
    "gn:feature_code":"PPL",
    "gn:name":"Sabatkechmaz",
    "gn:population":0,
    "gn:timezone":"Asia/Baku",
    "iso:country":"AZ",
    "name:aze_x_preferred":[
        "S\u0259b\u0259tke\u00e7m\u0259z"
    ],
    "name:ita_x_preferred":[
        "S\u0259b\u0259tke\u00e7m\u0259z"
    ],
    "name:kat_x_preferred":[
        "\u10e1\u10d0\u10d1\u10d0\u10d7\u10e5\u10d4\u10e9\u10db\u10d0\u10d6\u10d8"
    ],
    "name:msa_x_preferred":[
        "S\u0259b\u0259tke\u00e7m\u0259z"
    ],
    "name:und_x_variant":[
        "Sabetkechmaz",
        "Sabatkechmaz"
    ],
    "wof:name":"Sabatkechmaz",
    "wof:placetype":"locality"
},
  "geometry": {"coordinates":[45.72754000000001,40.50601],"type":"Point"}
}