{
  "type": "Feature",
  "properties": {
    "gn:admin1_code":"17",
    "gn:asciiname":"Sokhbetli",
    "gn:country_code":"AZ",
    "gn:dem":60,
    "gn:feature_class":"P",
    "gn:feature_code":"PPL",
    "gn:name":"Sokhbetli",
    "gn:population":0,
    "gn:timezone":"Asia/Baku",
    "iso:country":"AZ",
    "name:azb_x_preferred":[
        "\u0635\u0648\u062d\u0628\u062a\u200c\u0644\u06cc"
    ],
    "name:aze_x_preferred":[
        "S\u00f6hb\u0259tli"
    ],
    "name:ceb_x_preferred":[
        "Sokhbetli"
    ],
    "name:fas_x_preferred":[
        "\u0635\u062d\u0628\u062a\u200c\u0644\u06cc"
    ],
    "name:ita_x_preferred":[
        "S\u00f6hb\u0259tli"
    ],
    "name:msa_x_preferred":[
        "S\u00f6hb\u0259tli"
    ],
    "name:swe_x_preferred":[
        "Sokhbetli"
    ],
    "name:und_x_variant":[
        "Seybatli"
    ],
    "wof:name":"Sokhbetli",
    "wof:placetype":"locality"
},
  "geometry": {"coordinates":[48.85766,41.36213],"type":"Point"}
}