{
  "type": "Feature",
  "properties": {
    "gn:admin1_code":"62",
    "gn:asciiname":"Zurnabad",
    "gn:country_code":"AZ",
    "gn:dem":898,
    "gn:feature_class":"P",
    "gn:feature_code":"PPL",
    "gn:name":"Zurnabad",
    "gn:population":0,
    "gn:timezone":"Asia/Baku",
    "iso:country":"AZ",
    "name:eng_x_preferred":[
        "Zurnabad"
    ],
    "name:rus_x_preferred":[
        "\u0417\u0443\u0440\u043d\u0430\u0431\u0430\u0434"
    ],
    "name:und_x_variant":[
        "Zhurnadad",
        "Surnabab",
        "Zurnadad",
        "Zurnabad"
    ],
    "wof:name":"Zurnabad",
    "wof:placetype":"locality"
},
  "geometry": {"coordinates":[46.24456,40.50537],"type":"Point"}
}