{
  "type": "Feature",
  "properties": {
    "gn:admin1_code":"15",
    "gn:asciiname":"Khalilli",
    "gn:country_code":"AZ",
    "gn:dem":107,
    "gn:feature_class":"P",
    "gn:feature_code":"PPL",
    "gn:name":"Khalilli",
    "gn:population":0,
    "gn:timezone":"Asia/Baku",
    "iso:country":"AZ",
    "name:aze_x_preferred":[
        "X\u0259lilli"
    ],
    "name:hye_x_preferred":[
        "\u053d\u0561\u056c\u056b\u056c\u056c\u0578\u0582"
    ],
    "name:kat_x_preferred":[
        "\u10ee\u10d0\u10da\u10d8\u10da\u10d8"
    ],
    "wof:name":"Khalilli",
    "wof:placetype":"locality"
},
  "geometry": {"coordinates":[48.44555,39.15823],"type":"Point"}
}