{
  "type": "Feature",
  "properties": {
    "gn:admin1_code":"42",
    "gn:asciiname":"Timiryazev",
    "gn:country_code":"AZ",
    "gn:dem":510,
    "gn:feature_class":"P",
    "gn:feature_code":"PPL",
    "gn:name":"Timiryazev",
    "gn:population":0,
    "gn:timezone":"Asia/Baku",
    "iso:country":"AZ",
    "name:aze_x_preferred":[
        "Timiryazev"
    ],
    "name:rus_x_preferred":[
        "\u0422\u0438\u043c\u0438\u0440\u044f\u0437\u0435\u0432"
    ],
    "wof:name":"Timiryazev",
    "wof:placetype":"locality"
},
  "geometry": {"coordinates":[48.5643,41.36764],"type":"Point"}
}