{
  "type": "Feature",
  "properties": {
    "gn:country":"AZ",
    "gn:fcode":"PPLX",
    "gn:population":11398,
    "iso:country":"AZ",
    "name:ara_x_preferred":[
        "\u0628\u0627\u062f\u0627\u0645\u062f\u0627\u0631"
    ],
    "name:arz_x_preferred":[
        "\u0628\u0627\u062f\u0645\u062f\u0627\u0631"
    ],
    "name:ast_x_preferred":[
        "Badamdar"
    ],
    "name:azb_x_preferred":[
        "\u0628\u0627\u062f\u0627\u0645\u062f\u0627\u0631"
    ],
    "name:aze_x_preferred":[
        "Badamdar"
    ],
    "name:ceb_x_preferred":[
        "Badamdar"
    ],
    "name:che_x_preferred":[
        "\u0411\u0430\u0434\u0430\u043c\u0434\u0430\u0440"
    ],
    "name:eng_x_preferred":[
        "Badamdar"
    ],
    "name:fas_x_preferred":[
        "\u0628\u0627\u062f\u0627\u0645\u200c\u062f\u0627\u0631"
    ],
    "name:fra_x_preferred":[
        "Badamdar"
    ],
    "name:nld_x_preferred":[
        "Badamdar"
    ],
    "name:rus_x_preferred":[
        "\u0411\u0430\u0434\u0430\u043c\u0434\u0430\u0440"
    ],
    "name:swe_x_preferred":[
        "Badamdar"
    ],
    "qs:name":"Badamdar",
    "qs:photos_9r":0,
    "qs:photos_sr":0,
    "qs:pop_sr":"6",
    "wd:wordcount":40,
    "wof:name":"Badamdar",
    "wof:placetype":"neighbourhood",
    "wof:population":11398
},
  "geometry": {"coordinates":[49.80389,40.33944],"type":"Point"}
}