{
  "type": "Feature",
  "properties": {
    "gn:admin1_code":"11",
    "gn:asciiname":"Imamkulubeyli",
    "gn:country_code":"AZ",
    "gn:dem":114,
    "gn:feature_class":"P",
    "gn:feature_code":"PPL",
    "gn:name":"Imamkulubeyli",
    "gn:population":0,
    "gn:timezone":"Asia/Baku",
    "iso:country":"AZ",
    "name:aze_x_preferred":[
        "\u0130mamqulub\u0259yli"
    ],
    "wof:name":"Imamkulubeyli",
    "wof:placetype":"locality"
},
  "geometry": {"coordinates":[47.0694,40.38861],"type":"Point"}
}